Workbook
Name \a: #N/A
Name \HKG: #REF!
Name \HKG: #REF!
Name \o: #REF!
Name \o: #REF!
Name \q: #REF!
Name \q: #REF!
Name \SN: #REF!
Name _: #REF!
Name _: #REF!
Name _: #REF!
Name _: #REF!
Name _: #REF!
Name ________________________EMS753: #REF!
Name ________________________EMS753: #REF!
Name ________________________TM44: #REF!
Name ________________________TM44: #REF!
Name _______________________EMS753: #REF!
Name _______________________EMS753: #REF!
Name _______________________TM44: #REF!
Name _______________________TM44: #REF!
Name ______________________EMS753: #REF!
Name ______________________EMS753: #REF!
Name ______________________TM44: #REF!
Name ______________________TM44: #REF!
Name _____________________EMS753: #REF!
Name _____________________EMS753: #REF!
Name _____________________TM44: #REF!
Name _____________________TM44: #REF!
Name ____________________EMS753: #REF!
Name ____________________EMS753: #REF!
Name ____________________TM44: #REF!
Name ____________________TM44: #REF!
Name ___________________EMS753: #REF!
Name ___________________EMS753: #REF!
Name ___________________TM44: #REF!
Name ___________________TM44: #REF!
Name __________________EMS753: #REF!
Name __________________EMS753: #REF!
Name __________________TM44: #REF!
Name __________________TM44: #REF!
Name _________________EMS753: #REF!
Name _________________EMS753: #REF!
Name _________________TM44: #REF!
Name _________________TM44: #REF!
Name ________________EMS753: #REF!
Name ________________EMS753: #REF!
Name ________________TM44: #REF!
Name ________________TM44: #REF!
Name _______________EMS753: #REF!
Name _______________EMS753: #REF!
Name _______________TM44: #REF!
Name _______________TM44: #REF!
Name ______________EMS753: #REF!
Name ______________EMS753: #REF!
Name ______________TM44: #REF!
Name ______________TM44: #REF!
Name _____________EMS753: #REF!
Name _____________EMS753: #REF!
Name _____________TM44: #REF!

Sheet Instructions
A2: to Supplier | C2: Guidelines for Labor Allocation --- Mass Production labor only
A3: Supplier doesn't need to fill data in the tab "price summary". The BOM cost assumption is listed in this tab. | C3: Operations/Production Manager | F3: Bucket | H3: Equipment Type | J3: Type
A4: Please only fill data in the grey area in the tabs of "SupplierBaseInput" and "Cleansheet". | C4: 1. An operations manager owns the manufacturing of the product. A product line will usually have one operations manager. | F4: SMT | H4: Custom | J4: Equipment
A5: Please provide process flow as required in the tabs | F5: SMT Testing | H5: Standard | J5: MRO
A6: Please provide equipment cost breakdown as required in the tabs | C6: Section Manager | F6: BB Assy
A7: Please provide consumable cost breakdown as required in the tabs | C7: 1. A section manager is a functional head and they are in-charge of the entire division for the whole factory. E.g quality, engineering, materials … etc | F7: BB Testing
F8: Material Management
A9: Program Assumptions: | C9: Engineers | F9: Quality (SMT)
A10: Tier 2 supplies mechanicals… | C10: 1. Only Mass Production engineers should be included in this cleansheet. | F10: Quality (BB)
A11: Tier 1 factory assembles mechanicals into sub-assemblies. Mechanical parts are binned for color Tier 2 and laser engraved with unique part number at Tier 1 for traceability. | C11: Technician
A12: Tier 1 factory produces PCBAs (Motherboard and Touchboard) | C12: 1. Technicians work for the engineers or supervisors to solve problems that arise on the line.
A13: Tier 1 factory performs final assembly and final test operation | C13: 2. Maintenance and regular work on the line will be done by technicians.
A15: Manufacturing Assumptions: | C15: Line Leader
A16: Takt Time: seconds per unit | C16: 1. A line leader owns a line and in some cases more than one line depending on the length and number of stations present in that line.
A17: Factory Labor: 6 day schedule (plan), 7 day (burst) | C17: 2. A single line can only have a maximum of one line leader.
C18: Note: If you need multi-functional operators then they should be designated as “multi-functional operator” which falls in the “DL” category. This should be classified under "Functional DL" in the cleansheet.
A19: Special Manufacturing requirements:
A20: PCBA: Underfill & Depanelization | C20: Supervisor
A21: XXX Assembly: | C21: 1. A supervisor is the operations leader for an entire category such as SMT or Box build.
A22: XXX Assembly: | C22: 2. If new lines are added then line leaders should be added and not supervisors.
A24: Equipment & Consumables: | C24: OBA/IPQC
A25: Equipments and Consumables do not need to be updated on the cleansheet. They should be added onto their respective tabs and they will be populated. | C25: 1. Quality Labor should be designated under Quality(SMT) and Quality(BB), they should not be separately classified.
A27: SMT Process Layout & BB Process Flow Layout
A28: The supplier should provide a layout of the assembly process.

Sheet SupplierBaseInput
A1: Note: Fill in baseline variables before proceeding to other tabs.
B3: CM input required in grey cells
B4: MS input required in white cells
A6: TYPE | B6: Line Item | C6: Rate | D6: Rate
A7: Volume | B7: Annual Demand Assumption | C7: 418000
A9: Direct Labor Wage Rates | B9: Wage per hour per person (DL) (including benefits) | C9: 4.95
C10: Annual Rate | D10: Weekly Rate
A11: Indirect Labor Wage Rates | B11: Operation/Production Manager | C11: 60320 | D11: =C11/50 -> 1206.4
B12: Section Manager (SMT, BB, QA, test, process etc.) | C12: 60320 | D12: =C12/50 -> 1206.4
B13: Engineer (QA,Test, Process, IE) | C13: 24440 | D13: =C13/50 -> 488.8
B14: Lead Engineer | C14: 31200 | D14: =C14/50 -> 624
B15: IT staff | C15: 20150 | D15: =C15/50 -> 403
B16: Administrative Services staff | C16: 20150 | D16: =C16/50 -> 403
B17: Customs/Logistics staff | C17: 20150 | D17: =C17/50 -> 403
B18: Security staff | C18: 20150 | D18: =C18/50 -> 403
B19: HR staff | C19: 20150 | D19: =C19/50 -> 403
B20: Freight/Logistics staff | C20: 20150 | D20: =C20/50 -> 403
B21: Facilities staff | C21: 20150 | D21: =C21/50 -> 403
B22: Planning & Order Fulfillment | C22: 20150 | D22: =C22/50 -> 403
B23: Purchasing | C23: 20150 | D23: =C23/50 -> 403
... B28: Line Leader (SMT, Assy, Test, Pack) | C28: 19760 | D28: =C28/50 -> 395.2
A30: Floor Space | B30: Annual Cost per Square Feet | C30: 14.4276
B31: Annual Cost per Square Feet(Warehouse) | C31: 9.0156
B32: Box Build | C32: 11.088
A33: Machine Depreciation Length | B33: Machine Depreciation years | C33: 6
B34: SMT | C34: 6
B35: SMT Testing | C35: 4
B36: BB Assy | C36: 6
B37: BB Testing | C37: 4
B38: IT Equipment | C38: 6
B39: Material Management | C39: 4
B40: Quality (SMT) | C40: 6
B41: Quality (BB) | C41: 9
A42: PCBA Loss Factor % | B42: Loss Factor | C42: 0.0008
B43: Motherboard Cost | C43: ='Price Summary'!C30 -> 8.683

Sheet Price Summary
A1: Transformation Cost Summary
B4: TC Should-Be Cost Model Summary | C4: Common | D4: SMT Main Board1 | E4: Wave Solder | F4: offine line Router | G4: laser etching | H4: BB Assy | I4: BB Testing | J4: Material Management | K4: Quality (SMT) | L4: Quality (BB) | M4: Total | N4: %
B5: UPH | D5: =Cleansheet!C14 -> 387.91667 | E5: =Cleansheet!D14 -> 279.3 | F5: =Cleansheet!E14 -> 139.65 | G5: =Cleansheet!F14 -> 837.9 | H5: =Cleansheet!G14 -> 176.4 | I5: =Cleansheet!H14 -> 176.4 | J5: =Cleansheet!I14 -> 176.4 | K5: =Cleansheet!J14 -> 387.91667 | L5: =Cleansheet!K14 -> 176.4
B6: UPPH | D6: =D5/Cleansheet!C32 -> 35.265152 | E6: =E5/Cleansheet!D32 -> 14.7 | F6: =F5/Cleansheet!E32 -> 46.55 | G6: =G5/Cleansheet!F32 -> 418.95 | H6: =H5/Cleansheet!G32 -> 7.6695652 | I6: =I5/Cleansheet!H32 -> 27.138462 | J6: =J5/Cleansheet!I32 -> 352.8 | K6: =IF(ISERROR(K5/Cleansheet!J32),0,K5/Cleansheet!J32) -> 775.83333 | L6: =L5/Cleansheet!K32 -> 352.8
B7: DL/IDL ratio | D7: =D9/D10 -> 44.897959 | E7: =E9/E10 -> 870.01293 | F7: =F9/F10 -> #DIV/0! | G7: =G9/G10 -> #DIV/0! | H7: =H9/H10 -> #DIV/0! | I7: =I9/I10 -> #DIV/0! | J7: =J9/J10 -> 1.7857143 | K7: =IF(ISERROR(K9/K10),0,K9/K10) -> 17.643682 | L7: =L9/L10 -> #DIV/0!
B8: Lines and TAKT TIME (seconds) | D8: =Cleansheet!C23 -> 1 | E8: =Cleansheet!D23 -> 1 | F8: =Cleansheet!E23 -> 1 | G8: =Cleansheet!F23 -> 1 | H8: =Cleansheet!G23 -> 1 | I8: =Cleansheet!H23 -> 1 | J8: =Cleansheet!I23 -> 1 | K8: =Cleansheet!J23 -> 1 | L8: =Cleansheet!K23 -> 1
B9: Direct Labors (HC) per day | D9: =Cleansheet!C33 -> 22 | E9: =Cleansheet!D33 -> 38 | F9: =Cleansheet!E33 -> 6 | G9: =Cleansheet!F33 -> 4 | H9: =Cleansheet!G33 -> 23 | I9: =Cleansheet!H33 -> 6.5 | J9: =Cleansheet!I33 -> 0.5 | K9: =Cleansheet!J33 -> 0.5 | L9: =Cleansheet!K33 -> 0.5 | M9: =SUM(C9:L9) -> 101
B10: Indirect Labors (HC) per day | C10: =Cleansheet!I83 -> 0.638 | D10: =Cleansheet!J70 -> 0.49 | E10: =Cleansheet!K70 -> 0.043677512 | F10: =Cleansheet!L70 -> 0 | G10: =Cleansheet!M70 -> 0 | H10: =Cleansheet!L70 -> 0 | I10: =Cleansheet!M70 -> 0 | J10: =Cleansheet!N70 -> 0.28 | K10: =Cleansheet!O70 -> 0.028338756 | L10: =Cleansheet!P70 -> 0 | M10: =SUM(C10:L10) -> 1.4800163
B11: Direct Labors (CPU) | D11: =Cleansheet!C58 -> 0.14820903 | E11: =Cleansheet!D58 -> 0.34926304 | F11: =Cleansheet!E58 -> 0.13139396 | G11: =Cleansheet!F58 -> 0.015991367 | H11: =Cleansheet!G58 -> 0.36237717 | I11: =Cleansheet!H58 -> 0.09119898 | J11: =Cleansheet!I58 -> 0.0070153061 | K11: =Cleansheet!J58 -> 0.0070153061 | L11: =Cleansheet!K58 -> 0.017332766 | M11: =SUM(C11:L11) -> 1.1297969 | N11: =M11/$K$22 -> 0.31934971
B12: Indirect Labors (CPU) | C12: =Cleansheet!J83 -> 0.030755263 | D12: =Cleansheet!K70 -> 0.043677512 | E12: 0 | F12: 0 | G12: 0 | H12: =Cleansheet!O70 -> 0.028338756 | I12: =Cleansheet!Q70 -> 0 | J12: =Cleansheet!S70+Cleansheet!L83 -> 0.017836124 | K12: =Cleansheet!U70 -> 0.0014430622 | L12: =Cleansheet!W70 -> 0 | M12: =SUM(C12:L12) -> 0.12205072 | N12: =M12/$K$22 -> 0.034498997
B13: Equipment Maintenance Spares (MRO) | D13: =Cleansheet!H90 -> 0.0045639161 | E13: =Cleansheet!I90 -> 0 | F13: =Cleansheet!J90 -> 0 | G13: =Cleansheet!K90 -> 0 | H13: =Cleansheet!M90 -> 0.0053652313 | I13: =Cleansheet!O90 -> 0.0034567783 | J13: =Cleansheet!Q90 -> 0 | K13: =Cleansheet!S90 -> 0 | L13: =Cleansheet!U90 -> 0.0030470494 | M13: =SUM(C13:L13) -> 0.016432975 | N13: =M13/$K$22 -> 0.0046449638
B14: Equipment Depreciation | D14: =Cleansheet!H91 -> 0.1362543 | E14: =Cleansheet!I91 -> 0 | F14: =Cleansheet!J91 -> 0 | G14: =Cleansheet!K91 -> 0 | H14: =Cleansheet!M91 -> 0.0046810207 | I14: =Cleansheet!O91 -> 0.016543062 | J14: =Cleansheet!Q91 -> 0 | K14: =Cleansheet!S91 -> 0 | L14: =Cleansheet!U91 -> 0 | M14: =SUM(C14:L14) -> 0.15747839 | N14: =M14/$K$22 -> 0.044513022
B15: Indirect Materials | D15: =Cleansheet!H92 -> 0.3633 | E15: =Cleansheet!I92 -> 0 | F15: =Cleansheet!J92 -> 0 | G15: =Cleansheet!K92 -> 0 | H15: =Cleansheet!M92 -> 0.0078793 | I15: =Cleansheet!O92 -> 0 | J15: =Cleansheet!Q92 -> 0 | K15: =Cleansheet!S92 -> 0 | L15: =Cleansheet!U92 -> 0 | M15: =SUM(C15:L15) -> 0.3711793 | N15: =M15/$K$22 -> 0.10491797
B16: Facility & Utility | D16: =Cleansheet!J103 -> 0.0084834157 | E16: =Cleansheet!K103 -> 0 | F16: =Cleansheet!L103 -> 0 | G16: =Cleansheet!M103 -> 0 | H16: =Cleansheet!N103 -> 0.026990408 | I16: =Cleansheet!P103 -> 0 | J16: =Cleansheet!R103 -> 0.0037967368 | K16: =Cleansheet!T103 -> 0 | L16: =Cleansheet!V103 -> 0.0030373895 | M16: =SUM(C16:L16) -> 0.04230795 | N16: =M16/$K$22 -> 0.011958814
B17: Inbound Frieght | C17: =Cleansheet!J107 -> 0.0059808612 | M17: =SUM(C17:L17) -> 0.0059808612 | N17: =M17/$K$22 -> 0.0016905572
B18: VAT | C18: =Cleansheet!J114 -> 3.5313636e-06 | M18: =SUM(C18:L18) -> 3.5313636e-06 | N18: =M18/$K$22 -> 9.9817933e-07
B19: Loss Factor | C19: =Cleansheet!J110 -> 0.0069464 | M19: =SUM(C19:L19) -> 0.0069464 | N19: =M19/$K$22 -> 0.0019634775
B20: MVA | C20: =SUM(C11:C19) -> 0.043686056 | D20: =SUM(D11:D19) -> 0.70448818 | E20: =SUM(E11:E19) -> 0.34926304 | F20: =SUM(F11:F19) -> 0.13139396 | G20: =SUM(G11:G19) -> 0.015991367 | H20: =SUM(H11:H19) -> 0.43563189 | I20: =SUM(I11:I19) -> 0.11119882 | J20: =SUM(J11:J19) -> 0.028648167 | ... M20: =SUM(M11:M19) -> 1.8521771 | N20: =M20/$K$22 -> 0.52353851 | P20: Assy | Q20: =C20+H20+I20+J20+L20 -> 0.64258214
B21: SG&A & Profit | C21: =Cleansheet!C121+Cleansheet!C120 -> 0.16 | M21: =Cleansheet!J121 -> 1.6856278 | N21: =M21/$K$22 -> 0.47646149 | P21: SMT | Q21: =D20+E20+F20+G20+K20 -> 1.2095949
B22: TC | K22: =SUM(M20:M21) -> 3.5378048 | L22: =K22/$K$22 -> 1
B24: Total Transformation Cost per Unit | C24: =K22 -> 3.5378048
B28: Consignment and Vertical Integration
B30: Total BOM cost | C30: 8.683
C33: 0
B36: Total Vertical Integration | C36: =SUM(C31:C35) -> 0
B37: BOM Less Consigned | C37: =C30-C36 -> 8.683

Sheet Cleansheet
A1: PRODUCT: Rival+ Wired Mouse | H1: CM input required in grey cells
A2: RFQ Date: 20240226 | H2: MS input required in white cells
A4: A. Direct Labor Cost: PCBA + Box Build and Packout + Debug
A6: Category | B6: Line Item | C6: SMT | D6: Wave Solder | E6: offine line Router | F6: laser etching | G6: BB Assy | H6: BB Testing | I6: Material Management | J6: Quality (SMT) | K6: Quality (BB)
A7: Staffed Hours
B8: Working hours per line per day | C8: 23 | D8: 20 | E8: 20 | F8: 20 | G8: 20 | H8: 20 | I8: 20 | J8: 20 | K8: 20
B9: Working days per line per week | C9: 6.67 | D9: 6.67 | E9: 6.67 | F9: 6.67 | G9: 6 | H9: 6 | I9: 6 | J9: 6 | K9: 6
B10: Working hours per line per week | C10: =+C8*C9 -> 153.41 | D10: =+D8*D9 -> 133.4 | E10: =+E8*E9 -> 133.4 | F10: =+F8*F9 -> 133.4 | G10: 120 | H10: 120 | I10: 120 | J10: 120 | K10: 120
B11: Shifts per line per day | C11: 2 | D11: 2 | E11: 2 | F11: 2 | G11: 1 | H11: 1 | I11: 1 | J11: 1 | K11: 1
A12: Throughput
B13: TAKT time (s) | C13: ='SMT Process Flow'!I3 -> 8.64 | D13: ='SMT Process Flow'!I24 -> 12 | E13: ='SMT Process Flow'!I39 -> 24 | F13: ='SMT Process Flow'!E53 -> 4 | G13: 19 | H13: =G13 -> 19 | I13: =G13 -> 19 | J13: =C13 -> 8.64 | K13: =G13 -> 19
B14: UPH | C14: =3600/C13*C15*C16 -> 387.91667 | D14: =3600/D13*D15*D16 -> 279.3 | E14: =3600/E13*E15*E16 -> 139.65 | F14: =3600/F13*F15*F16 -> 837.9 | G14: =3600/G13*G15*G16 -> 176.4 | H14: =3600/H13*H15*H16 -> 176.4 | I14: =3600/I13*I15*I16 -> 176.4 | J14: =3600/J13*J15*J16 -> 387.91667 | K14: =3600/K13*K15*K16 -> 176.4
B15: Yield % | C15: 0.98 | D15: 0.98 | E15: 0.98 | F15: 0.98 | G15: 0.98 | H15: =G15 -> 0.98 | I15: =G15 -> 0.98 | J15: =C15 -> 0.98 | K15: =G15 -> 0.98
B16: Efficiency Rate per line | C16: 0.95 | D16: 0.95 | E16: 0.95 | F16: 0.95 | G16: 0.95 | H16: =G16 -> 0.95 | I16: =G16 -> 0.95 | J16: =C16 -> 0.95 | K16: =G16 -> 0.95
A17: Volume
B18: Annual Demand Assumption | C18: =SupplierBaseInput!$C$7 -> 418000 | D18: =SupplierBaseInput!$C$7 -> 418000 | E18: =SupplierBaseInput!$C$7 -> 418000 | F18: =SupplierBaseInput!$C$7 -> 418000 | G18: =SupplierBaseInput!$C$7 -> 418000 | H18: =SupplierBaseInput!$C$7 -> 418000 | I18: =SupplierBaseInput!$C$7 -> 418000 | J18: =SupplierBaseInput!$C$7 -> 418000 | K18: =SupplierBaseInput!$C$7 -> 418000
B19: Avg weekly demand | C19: =C18/50 -> 8360 | D19: =D18/50 -> 8360 | E19: =E18/50 -> 8360 | F19: =F18/50 -> 8360 | G19: =G18/50 -> 8360 | H19: =H18/50 -> 8360 | I19: =I18/50 -> 8360 | J19: =J18/50 -> 8360 | K19: =K18/50 -> 8360
B20: Maximum demand per week | C20: =C19*1.2 -> 10032 | D20: =D19*1.2 -> 10032 | E20: =E19*1.2 -> 10032 | F20: =F19*1.2 -> 10032 | G20: =G19*1.2 -> 10032 | H20: =H19*1.2 -> 10032 | I20: =I19*1.2 -> 10032 | J20: =J19*1.2 -> 10032 | K20: =K19*1.2 -> 10032
B21: Max Output per line per week | C21: =C10*C14 -> 59510.296 | D21: =D10*D14 -> 37258.62 | E21: =E10*E14 -> 18629.31 | F21: =F10*F14 -> 111775.86 | G21: =G10*G14 -> 21168 | H21: =H10*H14 -> 21168 | I21: =I10*I14 -> 21168 | J21: =J10*J14 -> 46550 | K21: =K10*K14 -> 21168
A22: Production Capacity
B23: Lines installed | C23: =ROUNDUP(+C20/C21,0) -> 1 | D23: =ROUNDUP(+D20/D21,0) -> 1 | E23: =ROUNDUP(+E20/E21,0) -> 1 | F23: =ROUNDUP(+F20/F21,0) -> 1 | G23: =ROUNDUP(+G20/G21,0) -> 1 | H23: =ROUNDUP(+H20/H21,0) -> 1 | I23: =ROUNDUP(+I20/I21,0) -> 1 | J23: =ROUNDUP(+J20/J21,0) -> 1 | K23: =ROUNDUP(+K20/K21,0) -> 1
B24: Weekly output based on installed lines | C24: =C21*C23 -> 59510.296 | D24: =D21*D23 -> 37258.62 | E24: =E21*E23 -> 18629.31 | F24: =F21*F23 -> 111775.86 | G24: =G21*G23 -> 21168 | H24: =H21*H23 -> 21168 | I24: =I21*I23 -> 21168 | J24: =I24 -> 21168 | K24: =J24 -> 21168
B25: Upside potential | C25: =+C24-C20 -> 49478.296 | D25: =+D24-D20 -> 27226.62 | E25: =+E24-E20 -> 8597.31 | F25: =+F24-F20 -> 101743.86 | G25: =+G24-G20 -> 11136 | H25: =+H24-H20 -> 11136 | I25: =+I24-I20 -> 11136 | J25: =+J24-J20 -> 11136 | K25: =+K24-K20 -> 11136 | N25: ·
B26: Debug lines installed | C26: 1 | D26: 1 | E26: 1 | F26: 1 | G26: 0 | H26: 1 | I26: 0 | J26: 0 | K26: 0
A27: Direct Labor Requirements
A28: Per Line per shift | B28: DL per line per shift | C28: 10 | D28: 18 | E28: 2 | F28: 1 | G28: ='BB Process Flow'!M2 -> 22.5 | H28: ='BB Process Flow'!M3 -> 6 | J28: 0.5 | K28: 0.5
B29: Debug DL per line per shift | C29: 0.5 | D29: 0.5 | E29: 0.5 | F29: 0.5 | G29: 0 | H29: 0.5
B30: Functional DL per shift | C30: 0.5 | D30: 0.5 | E30: 0.5 | F30: 0.5 | G30: 0.5
B31: Warehouse DL | I31: 0.5
B32: Total DL per Line per Shift | C32: =SUM(C28:C31) -> 11 | D32: =SUM(D28:D31) -> 19 | E32: =SUM(E28:E31) -> 3 | F32: =SUM(F28:F31) -> 2 | G32: =SUM(G28:G31) -> 23 | H32: =SUM(H28:H31) -> 6.5 | I32: =SUM(I28:I31) -> 0.5 | J32: =SUM(J28:J31) -> 0.5 | K32: =SUM(K28:K31) -> 0.5
B33: Total DL per day | C33: =(C28*C23*C11)+(C29*C26*C11)+(C30*C11)+(C31*C11) -> 22 | D33: =(D28*D23*D11)+(D29*D26*D11)+(D30*D11)+(D31*D11) -> 38 | E33: =(E28*E23*E11)+(E29*E26*E11)+(E30*E11)+(E31*E11) -> 6 | F33: =(F28*F23*F11)+(F29*F26*F11)+(F30*F11)+(F31*F11) -> 4 | G33: =(G28*G23*G11)+(G29*G26*G11)+(G30*G11)+(G31*G11) -> 23 | H33: =(H28*H23*H11)+H29+(H30*H11)+(H31*H11) -> 6.5 | I33: =(I28*I23*I11)+(I29*I26*I11)+(I30*I11)+(I31*I11) -> 0.5 | J33: =(J28*J23*J11)+(J29*J26*J11)+(J30*J11)+(J31*J11) -> 0.5 | K33: =(K28*K23*K11)+(K29*K26*K11)+(K30*K11)+(K31*K11) -> 0.5
A34: In-Direct Labor (Line dependant)
B35: Line Leader Per Line Per Shift | C35: 0.5 | D35: 0.5 | E35: 0.5 | F35: 0.5 | G35: 1 | H35: =H37/H23/H11 -> 0 | I35: =I37/I23/I11 -> 0 | J35: =J37/J23/J11 -> 0 | K35: =K37/K23/K11 -> 0
B36: Technician Per Line Per Shift | C36: 0.5 | D36: 0.5 | E36: 0.5 | F36: 0.5 | G36: 1 | H36: =H38/H23/H11 -> 0 | I36: =I38/I23/I11 -> 0 | J36: =J38/J23/J11 -> 0 | K36: =K38/K23/K11 -> 0.5
B37: Line Leader Per Day | C37: 0.5 | D37: 0.5 | E37: 0.5 | F37: 0.5 | G37: 1 | K37: 0
B38: Technician Per Day | C38: 0.5 | D38: 0.5 | E38: 0.5 | F38: 0.5 | G38: 1 | K38: 0.5
B39: IQC Per Day
B40: Supervisor Per Day | C40: 0.25 | D40: 0.25 | E40: 0.25 | F40: 0.25
B41: Total IDL per day | C41: =SUM(C37:C40) -> 1.25 | D41: =SUM(D37:D40) -> 1.25 | E41: =SUM(E37:E40) -> 1.25 | F41: =SUM(F37:F40) -> 1.25 | G41: =SUM(G37:G40) -> 2 | H41: =SUM(H37:H40) -> 0 | I41: =SUM(I37:I40) -> 0 | J41: =SUM(J37:J40) -> 0 | K41: =SUM(K37:K40) -> 0.5
A42: In-Direct Labor Wage Rates
A43: (Line Dependant) | B43: Line Leader wage per week | C43: =SupplierBaseInput!$D$27 -> 403 | D43: =SupplierBaseInput!$D$27 -> 403 | E43: =SupplierBaseInput!$D$27 -> 403 | F43: =SupplierBaseInput!$D$27 -> 403 | G43: =SupplierBaseInput!$D$27 -> 403 | H43: =SupplierBaseInput!$D$27 -> 403 | I43: =SupplierBaseInput!$D$27 -> 403 | J43: =SupplierBaseInput!$D$27 -> 403 | K43: =SupplierBaseInput!$D$27 -> 403
B44: Technician wage per week | C44: =SupplierBaseInput!$D$26 -> 436.8 | D44: =SupplierBaseInput!$D$26 -> 436.8 | E44: =SupplierBaseInput!$D$26 -> 436.8 | F44: =SupplierBaseInput!$D$26 -> 436.8 | G44: =SupplierBaseInput!$D$26 -> 436.8 | H44: =SupplierBaseInput!$D$26 -> 436.8 | I44: =SupplierBaseInput!$D$26 -> 436.8 | J44: =SupplierBaseInput!$D$26 -> 436.8 | K44: =SupplierBaseInput!$D$26 -> 436.8
B45: IQC wage per week | C45: =SupplierBaseInput!$D$24 -> 403 | D45: =SupplierBaseInput!$D$24 -> 403 | E45: =SupplierBaseInput!$D$24 -> 403 | F45: =SupplierBaseInput!$D$24 -> 403 | G45: =SupplierBaseInput!$D$24 -> 403 | H45: =SupplierBaseInput!$D$24 -> 403 | I45: =SupplierBaseInput!$D$24 -> 403 | J45: =SupplierBaseInput!$D$24 -> 403 | K45: =SupplierBaseInput!$D$24 -> 403
B46: Supervisor wage per week | C46: =SupplierBaseInput!$D$25 -> 403 | D46: =SupplierBaseInput!$D$25 -> 403 | E46: =SupplierBaseInput!$D$25 -> 403 | F46: =SupplierBaseInput!$D$25 -> 403 | G46: =SupplierBaseInput!$D$25 -> 403 | H46: =SupplierBaseInput!$D$25 -> 403 | I46: =SupplierBaseInput!$D$25 -> 403 | J46: =SupplierBaseInput!$D$25 -> 403 | K46: =SupplierBaseInput!$D$25 -> 403
A47: SEA
B48: Per person hours worked per day | C48: 10 | D48: 10 | E48: 10 | F48: 10 | G48: 10 | H48: 10 | I48: 10 | J48: 10 | K48: 10
B49: Per person hours worked per week | C49: 60 | D49: 60 | E49: 60 | F49: 60 | G49: 60 | H49: 60 | I49: 60 | J49: 60 | K49: 60
B50: Multiplier 1 (hours/wk) | C50: =((C8/2)*6)/C49 -> 1.15 | D50: =((D8/2)*6)/D49 -> 1 | E50: =((E8/2)*6)/E49 -> 1 | F50: =((F8/2)*6)/F49 -> 1
B51: Multiplier | C51: =(C48*C9)/C49 -> 1.1116667 | D51: =(D48*D9)/D49 -> 1.1116667 | E51: =(E48*E9)/E49 -> 1.1116667 | F51: =(F48*F9)/F49 -> 1.1116667 | G51: =(G48*G9)/G49 -> 1 | H51: =(H48*H9)/H49 -> 1 | I51: =(I48*I9)/I49 -> 1 | J51: =(J48*J9)/J49 -> 1 | K51: =(K48*K9)/K49 -> 1
A53: Direct Labor Wage Rates
B54: Wage per hour per person (DL) (including benefits) | C54: =IF(ISERROR(VLOOKUP($B54,SupplierBaseInput!$B$6:$C$38,2,FALSE)),"",VLOOKUP($B54,SupplierBaseInput!$B$6:$C$38,2,FALSE)) -> 4.95 | D54: =IF(ISERROR(VLOOKUP($B54,SupplierBaseInput!$B$6:$C$38,2,FALSE)),"",VLOOKUP($B54,SupplierBaseInput!$B$6:$C$38,2,FALSE)) -> 4.95 | E54: =IF(ISERROR(VLOOKUP($B54,SupplierBaseInput!$B$6:$C$38,2,FALSE)),"",VLOOKUP($B54,SupplierBaseInput!$B$6:$C$38,2,FALSE)) -> 4.95 | F54: =IF(ISERROR(VLOOKUP($B54,SupplierBaseInput!$B$6:$C$38,2,FALSE)),"",VLOOKUP($B54,SupplierBaseInput!$B$6:$C$38,2,FALSE)) -> 4.95 | G54: =IF(ISERROR(VLOOKUP($B54,SupplierBaseInput!$B$6:$C$38,2,FALSE)),"",VLOOKUP($B54,SupplierBaseInput!$B$6:$C$38,2,FALSE)) -> 4.95 | H54: =IF(ISERROR(VLOOKUP($B54,SupplierBaseInput!$B$6:$C$38,2,FALSE)),"",VLOOKUP($B54,SupplierBaseInput!$B$6:$C$38,2,FALSE)) -> 4.95 | I54: =IF(ISERROR(VLOOKUP($B54,SupplierBaseInput!$B$6:$C$38,2,FALSE)),"",VLOOKUP($B54,SupplierBaseInput!$B$6:$C$38,2,FALSE)) -> 4.95 | J54: =IF(ISERROR(VLOOKUP($B54,SupplierBaseInput!$B$6:$C$38,2,FALSE)),"",VLOOKUP($B54,SupplierBaseInput!$B$6:$C$38,2,FALSE)) -> 4.95 | K54: =IF(ISERROR(VLOOKUP($B54,SupplierBaseInput!$B$6:$C$38,2,FALSE)),"",VLOOKUP($B54,SupplierBaseInput!$B$6:$C$38,2,FALSE)) -> 4.95
B55: Total IDL Cost per week (demand) | C55: =((C36*C42)+(C37*C43)+(C38*C44)+(C39*C45))*C51 -> 466.78883 | D55: =((D36*D42)+(D37*D43)+(D38*D44)+(D39*D45))*D51 -> 466.78883 | E55: =((E36*E42)+(E37*E43)+(E38*E44)+(E39*E45))*E51 -> 466.78883 | F55: =((F36*F42)+(F37*F43)+(F38*F44)+(F39*F45))*F51 -> 466.78883 | G55: =(G37*G43)+(G38*G44)+(G39*G45)+(G40*G46) -> 839.8 | H55: =(H37*H43)+(H38*H44)+(H39*H45)+(H40*H46) -> 0 | I55: =(I37*I43)+(I38*I44)+(I39*I45)+(I40*I46) -> 0 | J55: =(J37*J43)+(J38*J44)+(J39*J45)+(J40*J46) -> 0 | K55: =(K37*K43)+(K38*K44)+(K39*K45)+(K40*K46) -> 218.4
B56: Total DL Cost per week (demand) | C56: =C54*C49*C33*C51*C50 -> 8353.1745 | D56: =D54*D49*D33*D51*D50 -> 12546.27 | E56: =E54*E49*E33*E51*E50 -> 1980.99 | F56: =F54*F49*F33*F51*F50 -> 1320.66 | G56: =G54*G51*G33*G49 -> 6831 | H56: =H54*H51*H33*H49 -> 1930.5 | I56: =I54*I51*I33*I49 -> 148.5 | J56: =J54*J51*J33*J49 -> 148.5 | K56: =K54*K51*K33*K49 -> 148.5
A57: BB and Packout Cost per Unit | L57: Total
B58: Cost per Unit | C58: =(C56+C55)/C24 -> 0.14820903 | D58: =(D56+D55)/D24 -> 0.34926304 | E58: =(E56+E55)/E24 -> 0.13139396 | F58: =(F56+F55)/F24 -> 0.015991367 | G58: =(G56+G55)/G24 -> 0.36237717 | H58: =(H56+H55)/H24 -> 0.09119898 | I58: =(I56+I55)/I24 -> 0.0070153061 | J58: =(J56+J55)/J24 -> 0.0070153061 | K58: =(K56+K55)/K24 -> 0.017332766 | L58: =SUM(C58:K58) -> 1.1297969
A60: B. Indirect Labor Cost
A62: Category | B62: Line Item | C62: Total H/C | I62: Rate ($) | J62: SMT | L62: SMT De-panel | N62: BB Assy | P62: BB Testing | R62: Material Management | T62: Quality (SMT) | V62: Quality (BB) | X62: "Cost per Unit" calculation
J63: Multiplier | K63: Cost per Unit | L63: Multiplier | M63: Cost per Unit | N63: Multiplier | O63: Cost per Unit | P63: Multiplier | Q63: Cost per Unit | R63: Multiplier | S63: Cost per Unit | T63: Multiplier | U63: Cost per Unit | V63: Multiplier | W63: Cost per Unit
A64: Manufacturing Indirect Labor | B64: Operation/Production Manager | C64: =J64+L64+N64+P64+R64+T64+V64 -> 0.095 | I64: =IF(ISERROR(VLOOKUP($B64,SupplierBaseInput!$B$6:$C$38,2,FALSE)),"",VLOOKUP($B64,SupplierBaseInput!$B$6:$C$38,2,FALSE)) -> 60320 | J64: 0.08 | K64: =$I64*J64/$C$18 -> 0.011544498 | L64: 0 | M64: =$I64*L64/$C$18 -> 0 | N64: 0.005 | O64: =$I64*N64/$G$18 -> 0.0007215311 | Q64: =$I64*P64/$G$18 -> 0 | S64: =$I64*R64/$C$18 -> 0 | T64: 0.01 | U64: =$I64*T64/$G$18 -> 0.0014430622 | W64: =$I64*V64/$G$18 -> 0 | X64: (Annual Wage * Multiplier) / Annual Volume
B65: Section Manager (SMT, BB, QA, test, process etc.) | C65: =J65+L65+N65+P65+R65+T65+V65 -> 0.205 | I65: =IF(ISERROR(VLOOKUP($B65,SupplierBaseInput!$B$6:$C$38,2,FALSE)),"",VLOOKUP($B65,SupplierBaseInput!$B$6:$C$38,2,FALSE)) -> 60320 | J65: 0.08 | K65: =$I65*J65/$C$18 -> 0.011544498 | L65: 0 | M65: =$H65*L65/$C$18 -> 0 | N65: 0.125 | O65: =$I65*N65/$G$18 -> 0.018038278 | Q65: =$I65*P65/$G$18 -> 0 | S65: =$I65*R65/$C$18 -> 0 | U65: =$I65*T65/$G$18 -> 0 | W65: =$I65*V65/$G$18 -> 0 | X65: (Annual Wage * Multiplier) / Annual Volume
B66: Engineer (QA,Test, Process, IE) | C66: =J66+L66+N66+P66+R66+T66+V66 -> 0.35 | I66: =IF(ISERROR(VLOOKUP($B66,SupplierBaseInput!$B$6:$C$38,2,FALSE)),"",VLOOKUP($B66,SupplierBaseInput!$B$6:$C$38,2,FALSE)) -> 24440 | J66: 0.25 | K66: =$I66*J66/$C$18 -> 0.014617225 | L66: 0 | M66: =$H66*L66/$C$18 -> 0 | N66: 0.1 | O66: =$I66*N66/$G$18 -> 0.00584689 | Q66: =$I66*P66/$G$18 -> 0 | S66: =$I66*R66/$C$18 -> 0 | U66: =$I66*T66/$G$18 -> 0 | W66: =$I66*V66/$G$18 -> 0 | X66: (Annual Wage * Multiplier) / Annual Volume
B67: Lead Engineer | C67: =J67+L67+N67+P67+R67+T67+V67 -> 0.13 | I67: =IF(ISERROR(VLOOKUP($B67,SupplierBaseInput!$B$6:$C$38,2,FALSE)),"",VLOOKUP($B67,SupplierBaseInput!$B$6:$C$38,2,FALSE)) -> 31200 | J67: 0.08 | K67: =$I67*J67/$C$18 -> 0.0059712919 | L67: 0 | M67: =$H67*L67/$C$18 -> 0 | N67: 0.05 | O67: =$I67*N67/$G$18 -> 0.0037320574 | Q67: =$I67*P67/$G$18 -> 0 | S67: =$I67*R67/$C$18 -> 0 | U67: =$I67*T67/$G$18 -> 0 | W67: =$I67*V67/$G$18 -> 0 | X67: (Annual Wage * Multiplier) / Annual Volume
K68: =$I68*J68/$C$18 -> 0 | L68: 0 | M68: =$H68*L68/$C$18 -> 0 | O68: =$I68*N68/$G$18 -> 0 | Q68: =$I68*P68/$G$18 -> 0 | S68: =$I68*R68/$C$18 -> 0 | U68: =$I68*T68/$G$18 -> 0 | W68: =$I68*V68/$G$18 -> 0 | X68: (Annual Wage * Multiplier) / Annual Volume
Y69: Total
A70: Total Manufacturing Indirect Labor | J70: =SUM(J64:J68) -> 0.49 | K70: =SUM(K64:K68) -> 0.043677512 | L70: 0 | M70: =SUM(M64:M68) -> 0 | N70: =SUM(N64:N68) -> 0.28 | O70: =SUM(O64:O68) -> 0.028338756 | P70: =SUM(P64:P68) -> 0 | Q70: =SUM(Q64:Q68) -> 0 | R70: =SUM(R64:R68) -> 0 | S70: =SUM(S64:S68) -> 0 | T70: =SUM(T64:T68) -> 0.01 | ... W70: =SUM(W64:W68) -> 0 | Y70: =(U70+S70+Q70+O70+M70+K70+W70) -> 0.07345933
C72: Others | K72: Material Management
A73: Category | B73: Line Item | C73: Rate ($) | I73: Multiplier | J73: Cost per Unit | K73: Multiplier | L73: Cost per Unit
A74: Centralized Services Indirect Labor | B74: IT staff | C74: =IF(ISERROR(VLOOKUP($B74,SupplierBaseInput!$B$6:$C$38,2,FALSE)),"",VLOOKUP($B74,SupplierBaseInput!$B$6:$C$43,2,FALSE)) -> 20150 | I74: 0.04 | J74: =$C74*I74/$C$18 -> 0.0019282297 | L74: =$C74*K74/$C$18 -> 0 | U74: (Annual Wage * Multiplier) / Annual Volume
B75: Administrative Services staff | C75: =IF(ISERROR(VLOOKUP($B75,SupplierBaseInput!$B$6:$C$38,2,FALSE)),"",VLOOKUP($B75,SupplierBaseInput!$B$6:$C$43,2,FALSE)) -> 20150 | I75: 0.08 | J75: =$C75*I75/$C$18 -> 0.0038564593 | K75: 0.05 | L75: =$C75*K75/$C$18 -> 0.0024102871 | U75: (Annual Wage * Multiplier) / Annual Volume
B76: Customs/Logistics staff | C76: =IF(ISERROR(VLOOKUP($B76,SupplierBaseInput!$B$6:$C$38,2,FALSE)),"",VLOOKUP($B76,SupplierBaseInput!$B$6:$C$43,2,FALSE)) -> 20150 | J76: =$C76*I76/$C$18 -> 0 | L76: =$C76*K76/$C$18 -> 0 | U76: (Annual Wage * Multiplier) / Annual Volume
B77: Security staff | C77: =IF(ISERROR(VLOOKUP($B77,SupplierBaseInput!$B$6:$C$38,2,FALSE)),"",VLOOKUP($B77,SupplierBaseInput!$B$6:$C$43,2,FALSE)) -> 20150 | I77: 0.24 | J77: =$C77*I77/$C$18 -> 0.011569378 | L77: =$C77*K77/$C$18 -> 0 | U77: (Annual Wage * Multiplier) / Annual Volume
B78: HR staff | C78: =IF(ISERROR(VLOOKUP($B78,SupplierBaseInput!$B$6:$C$38,2,FALSE)),"",VLOOKUP($B78,SupplierBaseInput!$B$6:$C$43,2,FALSE)) -> 20150 | I78: 0.048 | J78: =$C78*I78/$C$18 -> 0.0023138756 | K78: 0.2 | L78: =$C78*K78/$C$18 -> 0.0096411483 | U78: (Annual Wage * Multiplier) / Annual Volume
B79: Freight/Logistics staff | C79: =IF(ISERROR(VLOOKUP($B79,SupplierBaseInput!$B$6:$C$38,2,FALSE)),"",VLOOKUP($B79,SupplierBaseInput!$B$6:$C$43,2,FALSE)) -> 20150 | J79: =$C79*I79/$C$18 -> 0 | L79: =$C79*K79/$C$18 -> 0 | U79: (Annual Wage * Multiplier) / Annual Volume
B80: Facilities staff | C80: =IF(ISERROR(VLOOKUP($B80,SupplierBaseInput!$B$6:$C$38,2,FALSE)),"",VLOOKUP($B80,SupplierBaseInput!$B$6:$C$43,2,FALSE)) -> 20150 | I80: 0.15 | J80: =$C80*I80/$C$18 -> 0.0072308612 | K80: 0.12 | L80: =$C80*K80/$C$18 -> 0.005784689 | U80: (Annual Wage * Multiplier) / Annual Volume
B81: Planning & Order Fulfillment | C81: =IF(ISERROR(VLOOKUP($B81,SupplierBaseInput!$B$6:$C$38,2,FALSE)),"",VLOOKUP($B81,SupplierBaseInput!$B$6:$C$43,2,FALSE)) -> 20150 | J81: =$C81*I81/$C$18 -> 0 | L81: =$C81*K81/$C$18 -> 0 | U81: (Annual Wage * Multiplier) / Annual Volume
B82: Purchasing | C82: =IF(ISERROR(VLOOKUP($B82,SupplierBaseInput!$B$6:$C$38,2,FALSE)),"",VLOOKUP($B82,SupplierBaseInput!$B$6:$C$43,2,FALSE)) -> 20150 | I82: 0.08 | J82: =$C82*I82/$C$18 -> 0.0038564593 | L82: =$C82*K82/$C$18 -> 0 | U82: (Annual Wage * Multiplier) / Annual Volume | X82: Total
A83: Total Centralized Services Indirect Labor | I83: =SUM(I74:I82) -> 0.638 | J83: =SUM(J74:J82) -> 0.030755263 | K83: =SUM(K74:K82) -> 0.37 | L83: =SUM(L74:L82) -> 0.017836124 | X83: =(J83+L83) -> 0.048591388
A85: C. Equipment & Facilities
N86: 1 | P86: 1 | R86: 1 | T86: 1
A88: Category | B88: Line Item | C88: SMT | J88: SMT Testing | L88: BB Assy | N88: BB Testing | P88: Material Management | R88: Quality (SMT) | T88: Quality (BB) | W88: "Cost per Unit" calculation
C89: Rates ($) | H89: Cost per Unit | J89: Rates ($) | K89: Cost per Unit | L89: Rates ($) | M89: Cost per Unit | N89: Rates ($) | O89: Cost per Unit | P89: Rates ($) | Q89: Cost per Unit | R89: Rates ($) | S89: Cost per Unit | T89: Rates ($) | U89: Cost per Unit
A90: Equipment | B90: Equipment Maintenance Spares (MRO) | C90: =SUM('Equipment List'!O3:O7) -> 9600 | H90: =SUM('Equipment List'!P3:P7)*(C20/C24) -> 0.0045639161 | J90: 0 | L90: =SUM('Equipment List'!O48:O50) -> 6728 | M90: =SUM('Equipment List'!P48:P50) -> 0.0053652313 | N90: =SUM('Equipment List'!O35:O36) -> 8241.6 | O90: =SUM('Equipment List'!P35:P36) -> 0.0034567783 | P90: 0 | Q90: 0 | T90: =SUM('Equipment List'!O55:O57) -> 4458 | U90: =SUM('Equipment List'!P55:P57) -> 0.0030470494 | W90: Annual Spend / Annual Volume
B91: Equipment (Depreciation or Leasing) Costs | C91: =SUM('Equipment List'!O8:O34) -> 1641583.5 | H91: =SUM('Equipment List'!P8:P34)*(C20/C24) -> 0.1362543 | J91: 0 | K91: 0 | L91: =SUM('Equipment List'!O51:O54) -> 2520 | M91: =SUM('Equipment List'!P51:P54) -> 0.0046810207 | N91: =SUM('Equipment List'!O37:O47) -> 24314.2 | O91: =SUM('Equipment List'!P37:P47) -> 0.016543062 | P91: =IF(ISERROR(GETPIVOTDATA("Sum of Extended Cost for all lines",#REF!,"Bucket","Material Management","Type Name","Equipment")),0,GETPIVOTDATA("Sum of Extended Cost for all lines",#REF!,"Bucket","Material Management","Type Name","Equipment")) -> 0 | Q91: =IF(ISERROR(GETPIVOTDATA("Sum of Unit Cost",#REF!,"Bucket","Material Management","Type Name","Equipment")),0,GETPIVOTDATA("Sum of Unit Cost",#REF!,"Bucket","Material Management","Type Name","Equipment"))*P86 -> 0 | R91: =IF(ISERROR(GETPIVOTDATA("Sum of Extended Cost for all lines",#REF!,"Bucket","Quality (SMT)","Type Name","Equipment")),0,GETPIVOTDATA("Sum of Extended Cost for all lines",#REF!,"Bucket","Quality (SMT)","Type Name","Equipment")) -> 0 | S91: =IF(ISERROR(GETPIVOTDATA("Sum of Unit Cost",#REF!,"Bucket","Quality (SMT)","Type Name","Equipment")),0,GETPIVOTDATA("Sum of Unit Cost",#REF!,"Bucket","Quality (SMT)","Type Name","Equipment"))*R86 -> 0 | W91: Total Depreciation Cost / Annual Volume/years
B92: Indirect Material (consumables) | C92: =SUM(Consumables!I2:I7) -> 151859.4 | H92: =SUM(Consumables!J2:J7) -> 0.3633 | K92: =(J92/$C$18)*J86 -> 0 | L92: =SUM(Consumables!I14:I18) -> 3293.5474 | M92: =SUM(Consumables!J14:J18) -> 0.0078793 | Q92: =(P92/C18)*P86 -> 0 | S92: =(R92/I18)*R86 -> 0 | U92: =(T92/K18)*T86 -> 0 | W92: Annual Spend / Annual Volume
X93: Total
A94: Total Equipment | H94: =SUM(H90:H92) -> 0.50411822 | K94: =SUM(K90:K92) -> 0 | M94: =SUM(M90:M92) -> 0.017925552 | O94: =SUM(O90:O92) -> 0.019999841 | Q94: =SUM(Q90:Q92) -> 0 | S94: =SUM(S90:S92) -> 0 | U94: =SUM(U90:U92) -> 0.0030470494 | X94: =SUM(C94:W94) -> 0.54509066
B97: Multiplier | I97: 1 | K97: 1 | M97: 1 | O97: 1 | Q97: 1 | S97: 1 | U97: 1
A98: Category | B98: Line Item | C98: Rate ($) | H98: SMT | K98: SMT Testing | M98: BB Assy | O98: BB Testing | Q98: Material Management | S98: Quality (SMT) | U98: Quality (BB) | W98: "Cost per Unit" calculation
I99: Multiplier | J99: Cost per Unit | K99: Multiplier | L99: Cost per Unit | M99: Multiplier | N99: Cost per Unit | O99: Multiplier | P99: Cost per Unit | Q99: Multiplier | R99: Cost per Unit | S99: Multiplier | T99: Cost per Unit | U99: Multiplier | V99: Cost per Unit
A100: Facilities | B100: Annual Cost per Square Feet | C100: =IF(ISERROR(VLOOKUP($B100,SupplierBaseInput!$B$6:$C$43,2,FALSE)),"",VLOOKUP($B100,SupplierBaseInput!$B$6:$C$43,2,FALSE)) -> 14.4276 | I100: =729*2 -> 1458 | J100: =(I100*$C$100/$C$18)*I97*(C20/C24) -> 0.0084834157 | L100: =(K100*$C$100/$C$18)*K97 -> 0 | M100: =150*11 -> 1650 | N100: =(M100*$C$100/$G$18)*M97*G20/G24 -> 0.026990408 | P100: =(O100*$C$100/$C$18)*O97 -> 0 | Q100: =10*11 -> 110 | R100: =(Q100*SupplierBaseInput!C30/$C$18)*Q97 -> 0.0037967368 | T100: =(S100*$C$100/$G$18)*S97 -> 0 | U100: =8*11 -> 88 | V100: =(U100*$C$100/$G$18)*U97 -> 0.0030373895 | W100: (Total Square Feet * Annual Cost per Square Foot) / Annual Volume
X102: Total
A103: Total Facilities | J103: =SUM(J100:J101) -> 0.0084834157 | L103: =SUM(L100:L101) -> 0 | N103: =SUM(N100:N101) -> 0.026990408 | P103: =SUM(P100:P101) -> 0 | R103: =SUM(R100:R101) -> 0.0037967368 | T103: =SUM(T100:T101) -> 0 | V103: =SUM(V100:V101) -> 0.0030373895 | X103: =SUM(H103:W103) -> 0.04230795
A105: D. Others
A106: Category | B106: Line Item | C106: Rate ($) | I106: Multiplier | J106: Cost per Unit | K106: "Cost per Unit" calculation
A107: Inbound Freight | B107: Shipping Costs (FCA HK) Duties, broker fees, customs fees, insurance | C107: 2500 | I107: =$G$18 -> 418000 | J107: =C107/I107 -> 0.0059808612 | K107: Annual Spend / Annual Volume
A109: Total Inbound Freight | J109: =SUM(J107:J108) -> 0.0059808612
A110: Scrap | B110: Loss Factor | C110: =IF(ISERROR(VLOOKUP($B110,SupplierBaseInput!$B$6:$C$43,2,FALSE)),"",VLOOKUP($B110,SupplierBaseInput!$B$6:$C$43,2,FALSE)) -> 0.0008 | I110: =SupplierBaseInput!C43 -> 8.683 | J110: =I110*C110 -> 0.0069464 | K110: Motherboard Cost * Loss Factor
A112: Total Scrap | J112: =SUM(J110) -> 0.0069464
A114: VAT | B114: Value Add Tax | C114: ='Price Summary'!C30 -> 8.683 | I114: 0.17 | J114: =C114*I114/$C$18 -> 3.5313636e-06 | K114: Material Cost * VAT rate/Annual Volume
A116: E. Transformation Total
...

Sheet Equipment List
R1: Spare | T1: Column Labels
A2: Bucket | B2: Type Name | C2: Equipment type (Custom/Standard) | D2: Description | E2: Manufacturer | F2: Model | G2: P/N | H2: Useful Life | I2: Line Qty | J2: Qty per line | K2: Extended Qty | L2: Spare quanitiy | M2: Equipment Cost | N2: Extended Cost per line | O2: Extended Cost for all lines | P2: Unit Cost | Q2: Comments | T2: (blank) | V2: MRO | X2: Equipment | Z2: Total Sum of Extended Cost for all lines | AA2: Total Sum of Unit Cost
A3: SMT | B3: MRO | C3: Custom | D3: Feeder parts | G3: N/A | H3: 0.5 | I3: 1 | J3: 1 | K3: =J3*I3 -> 1 | M3: 2500 | N3: =Table16[[#This Row],[Equipment Cost]]*Table16[[#This Row],[Qty per line]] -> 2500 | O3: =Table16[[#This Row],[Equipment Cost]]*Table16[[#This Row],[Extended Qty]] -> 2500 | P3: =Table16[[#This Row],[Extended Cost for all lines]]/Table16[[#This Row],[Useful Life]]/SupplierBaseInput!$C$7 -> 0.011961722 | S3: Row Labels | T3: Sum of Extended Cost for all lines | U3: Sum of Unit Cost | V3: Sum of Extended Cost for all lines | W3: Sum of Unit Cost | X3: Sum of Extended Cost for all lines | Y3: Sum of Unit Cost
A4: SMT | B4: MRO | C4: Standard | D4: Nozzle parts | G4: N/A | H4: 0.5 | I4: 1 | J4: 1 | K4: =J4*I4 -> 1 | M4: 1800 | N4: =Table16[[#This Row],[Equipment Cost]]*Table16[[#This Row],[Qty per line]] -> 1800 | O4: =Table16[[#This Row],[Equipment Cost]]*Table16[[#This Row],[Extended Qty]] -> 1800 | P4: =Table16[[#This Row],[Extended Cost for all lines]]/Table16[[#This Row],[Useful Life]]/SupplierBaseInput!$C$7 -> 0.0086124402 | S4: BB Assy | V4: 41193 | W4: 0.025644 | Z4: 41193 | AA4: 0.025644
A5: SMT | B5: MRO | C5: Standard | D5: Equipment Maintenance(SMT) | G5: N/A | H5: 6 | I5: 1 | J5: 1 | K5: =J5*I5 -> 1 | M5: 4300 | N5: =Table16[[#This Row],[Equipment Cost]]*Table16[[#This Row],[Qty per line]] -> 4300 | O5: =Table16[[#This Row],[Equipment Cost]]*Table16[[#This Row],[Extended Qty]] -> 4300 | P5: =Table16[[#This Row],[Extended Cost for all lines]]/Table16[[#This Row],[Useful Life]]/SupplierBaseInput!$C$7 -> 0.0017145136 | S5: BB Testing | V5: 40692 | W5: 0.0106201 | X5: 5100 | Y5: 0.0017 | Z5: 45792 | AA5: 0.0123201
A6: SMT | B6: MRO | C6: Custom | D6: Titanium catch | G6: N/A | H6: 0.5 | I6: 1 | J6: 1 | K6: =J6*I6 -> 1 | M6: 600 | N6: =Table16[[#This Row],[Equipment Cost]]*Table16[[#This Row],[Qty per line]] -> 600 | O6: =Table16[[#This Row],[Equipment Cost]]*Table16[[#This Row],[Extended Qty]] -> 600 | P6: =Table16[[#This Row],[Extended Cost for all lines]]/Table16[[#This Row],[Useful Life]]/SupplierBaseInput!$C$7 -> 0.0028708134 | S6: Quality (BB) | V6: 295355 | W6: 0.1004273 | Z6: 295355 | AA6: 0.1004273
A7: SMT | B7: MRO | C7: Custom | D7: Equipment Maintenance(W/S) | G7: N/A | H7: 0.5 | I7: 1 | J7: 1 | K7: =J7*I7 -> 1 | M7: 400 | N7: =Table16[[#This Row],[Equipment Cost]]*Table16[[#This Row],[Qty per line]] -> 400 | O7: =Table16[[#This Row],[Equipment Cost]]*Table16[[#This Row],[Extended Qty]] -> 400 | P7: =Table16[[#This Row],[Extended Cost for all lines]]/Table16[[#This Row],[Useful Life]]/SupplierBaseInput!$C$7 -> 0.0019138756 | S7: SMT | V7: 26547 | W7: 0.046007 | X7: 150877 | Y7: 0.028131617 | Z7: 177424 | AA7: 0.074138617
A8: SMT | B8: Equipment | C8: Standard | D8: DEK | G8: N/A | H8: 6 | I8: 1 | J8: 1 | K8: =J8*I8 -> 1 | M8: 84000 | N8: =Table16[[#This Row],[Equipment Cost]]*Table16[[#This Row],[Qty per line]] -> 84000 | O8: =Table16[[#This Row],[Equipment Cost]]*Table16[[#This Row],[Extended Qty]] -> 84000 | P8: =Table16[[#This Row],[Extended Cost for all lines]]/Table16[[#This Row],[Useful Life]]/SupplierBaseInput!$C$7 -> 0.033492823 | S8: (blank) | T8: 0 | U8: #DIV/0! | Z8: 0 | AA8: #DIV/0!
A9: SMT | B9: Equipment | C9: Standard | D9: SPI TRI-7007 | G9: N/A | H9: 6 | I9: 1 | J9: 1 | K9: =J9*I9 -> 1 | M9: =420000/6.1 -> 68852.459 | N9: =Table16[[#This Row],[Equipment Cost]]*Table16[[#This Row],[Qty per line]] -> 68852.459 | O9: =Table16[[#This Row],[Equipment Cost]]*Table16[[#This Row],[Extended Qty]] -> 68852.459 | P9: =Table16[[#This Row],[Extended Cost for all lines]]/Table16[[#This Row],[Useful Life]]/SupplierBaseInput!$C$7 -> 0.027453134 | S9: Grand Total | T9: 0 | U9: #DIV/0! | V9: 403787 | W9: 0.1826984 | X9: 155977 | Y9: 0.029831617 | Z9: 559764 | AA9: #DIV/0!
A10: SMT | B10: Equipment | C10: Standard | D10: FUJI NXTⅡM3S*6+FUJI NXTⅡM6S*1 | G10: N/A | H10: 6 | I10: 1 | J10: 1 | K10: =J10*I10 -> 1 | M10: 1013384 | N10: =Table16[[#This Row],[Equipment Cost]]*Table16[[#This Row],[Qty per line]] -> 1013384 | O10: =Table16[[#This Row],[Equipment Cost]]*Table16[[#This Row],[Extended Qty]] -> 1013384 | P10: =Table16[[#This Row],[Extended Cost for all lines]]/Table16[[#This Row],[Useful Life]]/SupplierBaseInput!$C$7 -> 0.40406061
A11: SMT | B11: Equipment | C11: Standard | D11: KWA-1225 | G11: N/A | H11: 6 | I11: 1 | J11: 1 | K11: =J11*I11 -> 1 | M11: 79333 | N11: =Table16[[#This Row],[Equipment Cost]]*Table16[[#This Row],[Qty per line]] -> 79333 | O11: =Table16[[#This Row],[Equipment Cost]]*Table16[[#This Row],[Extended Qty]] -> 79333 | P11: =Table16[[#This Row],[Extended Cost for all lines]]/Table16[[#This Row],[Useful Life]]/SupplierBaseInput!$C$7 -> 0.031631978
A12: SMT | B12: Equipment | C12: Standard | D12: TR7500 (AOI) | G12: N/A | H12: 6 | I12: 1 | J12: 1 | K12: =J12*I12 -> 1 | M12: 67297 | N12: =Table16[[#This Row],[Equipment Cost]]*Table16[[#This Row],[Qty per line]] -> 67297 | O12: =Table16[[#This Row],[Equipment Cost]]*Table16[[#This Row],[Extended Qty]] -> 67297 | P12: =Table16[[#This Row],[Extended Cost for all lines]]/Table16[[#This Row],[Useful Life]]/SupplierBaseInput!$C$7 -> 0.026832935
A13: SMT | B13: Equipment | C13: Standard | D13: Conveyor | G13: N/A | H13: 6 | I13: 1 | J13: 1 | K13: =J13*I13 -> 1 | M13: 2333 | N13: =Table16[[#This Row],[Equipment Cost]]*Table16[[#This Row],[Qty per line]] -> 2333 | O13: =Table16[[#This Row],[Equipment Cost]]*Table16[[#This Row],[Extended Qty]] -> 2333 | P13: =Table16[[#This Row],[Extended Cost for all lines]]/Table16[[#This Row],[Useful Life]]/SupplierBaseInput!$C$7 -> 0.00093022329
A14: SMT | B14: Equipment | C14: Standard | D14: Reject Conveyor | G14: N/A | H14: 6 | I14: 1 | J14: 1 | K14: =J14*I14 -> 1 | M14: 4083 | N14: =Table16[[#This Row],[Equipment Cost]]*Table16[[#This Row],[Qty per line]] -> 4083 | O14: =Table16[[#This Row],[Equipment Cost]]*Table16[[#This Row],[Extended Qty]] -> 4083 | P14: =Table16[[#This Row],[Extended Cost for all lines]]/Table16[[#This Row],[Useful Life]]/SupplierBaseInput!$C$7 -> 0.0016279904
A15: SMT | B15: Equipment | C15: Standard | D15: store conveyor | G15: N/A | H15: 6 | I15: 1 | J15: 1 | K15: =J15*I15 -> 1 | M15: 4083 | N15: =Table16[[#This Row],[Equipment Cost]]*Table16[[#This Row],[Qty per line]] -> 4083 | O15: =Table16[[#This Row],[Equipment Cost]]*Table16[[#This Row],[Extended Qty]] -> 4083 | P15: =Table16[[#This Row],[Extended Cost for all lines]]/Table16[[#This Row],[Useful Life]]/SupplierBaseInput!$C$7 -> 0.0016279904
A16: SMT | B16: Equipment | C16: Standard | D16: Shopfloor computer | G16: N/A | H16: 6 | I16: 1 | J16: 1 | K16: =J16*I16 -> 1 | M16: 808 | N16: =Table16[[#This Row],[Equipment Cost]]*Table16[[#This Row],[Qty per line]] -> 808 | O16: =Table16[[#This Row],[Equipment Cost]]*Table16[[#This Row],[Extended Qty]] -> 808 | P16: =Table16[[#This Row],[Extended Cost for all lines]]/Table16[[#This Row],[Useful Life]]/SupplierBaseInput!$C$7 -> 0.00032216906
A17: SMT | B17: Equipment | C17: Standard | D17: X-ray | G17: N/A | H17: 6 | I17: 1 | J17: 1 | K17: =J17*I17 -> 1 | M17: 143500 | N17: =Table16[[#This Row],[Equipment Cost]]*Table16[[#This Row],[Qty per line]] -> 143500 | O17: =Table16[[#This Row],[Equipment Cost]]*Table16[[#This Row],[Extended Qty]] -> 143500 | P17: =Table16[[#This Row],[Extended Cost for all lines]]/Table16[[#This Row],[Useful Life]]/SupplierBaseInput!$C$7 -> 0.057216906
A18: SMT | B18: Equipment | C18: Standard | D18: Wave solder | G18: N/A | H18: 6 | I18: 1 | J18: 1 | K18: =J18*I18 -> 1 | M18: 56000 | N18: =Table16[[#This Row],[Equipment Cost]]*Table16[[#This Row],[Qty per line]] -> 56000 | O18: =Table16[[#This Row],[Equipment Cost]]*Table16[[#This Row],[Extended Qty]] -> 56000 | P18: =Table16[[#This Row],[Extended Cost for all lines]]/Table16[[#This Row],[Useful Life]]/SupplierBaseInput!$C$7 -> 0.022328549
A19: SMT | B19: Equipment | C19: Standard | D19: Laser ething machine for ID/2D barcode | G19: N/A | H19: 3 | I19: 1 | J19: 1 | K19: =J19*I19 -> 1 | M19: 60000 | N19: =Table16[[#This Row],[Equipment Cost]]*Table16[[#This Row],[Qty per line]] -> 60000 | O19: =Table16[[#This Row],[Equipment Cost]]*Table16[[#This Row],[Extended Qty]] -> 60000 | P19: =Table16[[#This Row],[Extended Cost for all lines]]/Table16[[#This Row],[Useful Life]]/SupplierBaseInput!$C$7 -> 0.04784689
A20: SMT | B20: Equipment | C20: Standard | D20: Sensor IC 剪腳機 | G20: N/A | H20: 1 | I20: 1 | J20: 1 | K20: 1 | M20: 1390 | N20: =Table16[[#This Row],[Equipment Cost]]*Table16[[#This Row],[Qty per line]] -> 1390 | O20: =Table16[[#This Row],[Equipment Cost]]*Table16[[#This Row],[Extended Qty]] -> 1390 | P20: =Table16[[#This Row],[Extended Cost for all lines]]/Table16[[#This Row],[Useful Life]]/SupplierBaseInput!$C$7 -> 0.0033253589
A21: SMT | B21: Equipment | C21: Standard | D21: (Main +LED) Board SMT Paste Stencil_Bot | G21: N/A | H21: 0.25 | I21: 1 | J21: 2 | K21: =J21*I21 -> 2 | M21: 500 | N21: =Table16[[#This Row],[Equipment Cost]]*Table16[[#This Row],[Extended Qty]] -> 1000 | O21: =Table16[[#This Row],[Equipment Cost]]*Table16[[#This Row],[Extended Qty]] -> 1000 | P21: =Table16[[#This Row],[Extended Cost for all lines]]/Table16[[#This Row],[Useful Life]]/SupplierBaseInput!$C$7 -> 0.009569378
A22: SMT | B22: Equipment | C22: Standard | D22: (Main +LED) Board SMT Paste Stencil_Top | G22: N/A | H22: 0.25 | I22: 1 | J22: 2 | K22: =J22*I22 -> 2 | M22: 500 | N22: =Table16[[#This Row],[Equipment Cost]]*Table16[[#This Row],[Extended Qty]] -> 1000 | O22: =Table16[[#This Row],[Equipment Cost]]*Table16[[#This Row],[Extended Qty]] -> 1000 | P22: =Table16[[#This Row],[Extended Cost for all lines]]/Table16[[#This Row],[Useful Life]]/SupplierBaseInput!$C$7 -> 0.009569378
A23: SMT | B23: Equipment | C23: Standard | D23: (Main +LED) Board SMTPCB Carrier_Bot | G23: N/A | H23: 1 | I23: 1 | J23: 70 | K23: =J23*I23 -> 70 | M23: 150 | N23: =Table16[[#This Row],[Equipment Cost]]*Table16[[#This Row],[Extended Qty]] -> 10500 | O23: =Table16[[#This Row],[Equipment Cost]]*Table16[[#This Row],[Extended Qty]] -> 10500 | P23: =Table16[[#This Row],[Extended Cost for all lines]]/Table16[[#This Row],[Useful Life]]/SupplierBaseInput!$C$7 -> 0.025119617
A24: SMT | B24: Equipment | C24: Standard | D24: (Main +LED) Board SMT PCB Carrier_Top | G24: N/A | H24: 1 | I24: 1 | J24: 70 | K24: =J24*I24 -> 70 | M24: 150 | N24: =Table16[[#This Row],[Equipment Cost]]*Table16[[#This Row],[Extended Qty]] -> 10500 | O24: =Table16[[#This Row],[Equipment Cost]]*Table16[[#This Row],[Extended Qty]] -> 10500 | P24: =Table16[[#This Row],[Extended Cost for all lines]]/Table16[[#This Row],[Useful Life]]/SupplierBaseInput!$C$7 -> 0.025119617
A25: SMT | B25: Equipment | C25: Standard | D25: (Main +LED) Board SMT Router Fixture | G25: N/A | H25: 1 | I25: 1 | J25: 2 | K25: =J25*I25 -> 2 | M25: 350 | N25: =Table16[[#This Row],[Equipment Cost]]*Table16[[#This Row],[Extended Qty]] -> 700 | O25: =Table16[[#This Row],[Equipment Cost]]*Table16[[#This Row],[Extended Qty]] -> 700 | P25: =Table16[[#This Row],[Extended Cost for all lines]]/Table16[[#This Row],[Useful Life]]/SupplierBaseInput!$C$7 -> 0.0016746411
A26: SMT | B26: Equipment | C26: Standard | D26: (Main +LED) Board WS PCB Carrier_Bot | G26: N/A | H26: 1 | I26: 1 | J26: 40 | K26: =J26*I26 -> 40 | M26: 100 | N26: =Table16[[#This Row],[Equipment Cost]]*Table16[[#This Row],[Extended Qty]] -> 4000 | O26: =Table16[[#This Row],[Equipment Cost]]*Table16[[#This Row],[Extended Qty]] -> 4000 | P26: =Table16[[#This Row],[Extended Cost for all lines]]/Table16[[#This Row],[Useful Life]]/SupplierBaseInput!$C$7 -> 0.009569378
A27: SMT | B27: Equipment | C27: Standard | D27: (Main +LED) Board WS PCB Carrier_Top | G27: N/A | H27: 1 | I27: 1 | J27: 50 | K27: =J27*I27 -> 50 | M27: 160 | N27: =Table16[[#This Row],[Equipment Cost]]*Table16[[#This Row],[Extended Qty]] -> 8000 | O27: =Table16[[#This Row],[Equipment Cost]]*Table16[[#This Row],[Extended Qty]] -> 8000 | P27: =Table16[[#This Row],[Extended Cost for all lines]]/Table16[[#This Row],[Useful Life]]/SupplierBaseInput!$C$7 -> 0.019138756
A28: SMT | B28: Equipment | C28: Standard | D28: (Main +LED) Board WS WS Touch Up Fixture | G28: N/A | H28: 1 | I28: 1 | J28: 2 | K28: =J28*I28 -> 2 | M28: 150 | N28: =Table16[[#This Row],[Equipment Cost]]*Table16[[#This Row],[Extended Qty]] -> 300 | O28: =Table16[[#This Row],[Equipment Cost]]*Table16[[#This Row],[Extended Qty]] -> 300 | P28: =Table16[[#This Row],[Extended Cost for all lines]]/Table16[[#This Row],[Useful Life]]/SupplierBaseInput!$C$7 -> 0.00071770335
A29: SMT | B29: Equipment | C29: Standard | D29: (Main +LED) Board PCBA ESD Tray | G29: N/A | H29: 1 | I29: 1 | J29: 752 | K29: =J29*I29 -> 752 | M29: 5 | N29: =Table16[[#This Row],[Equipment Cost]]*Table16[[#This Row],[Extended Qty]] -> 3760 | O29: =Table16[[#This Row],[Equipment Cost]]*Table16[[#This Row],[Extended Qty]] -> 3760 | P29: =Table16[[#This Row],[Extended Cost for all lines]]/Table16[[#This Row],[Useful Life]]/SupplierBaseInput!$C$7 -> 0.0089952153
A30: SMT | B30: Equipment | C30: Standard | D30: SWITCH Board Router Fixture | G30: N/A | H30: 1 | I30: 1 | J30: 2 | K30: =J30*I30 -> 2 | M30: 350 | N30: =Table16[[#This Row],[Equipment Cost]]*Table16[[#This Row],[Extended Qty]] -> 700 | O30: =Table16[[#This Row],[Equipment Cost]]*Table16[[#This Row],[Extended Qty]] -> 700 | P30: =Table16[[#This Row],[Extended Cost for all lines]]/Table16[[#This Row],[Useful Life]]/SupplierBaseInput!$C$7 -> 0.0016746411
A31: SMT | B31: Equipment | C31: Standard | D31: SWITCH Board WS PCB Carrier_Bot | G31: N/A | H31: 1 | I31: 1 | J31: 40 | K31: =J31*I31 -> 40 | M31: 100 | N31: =Table16[[#This Row],[Equipment Cost]]*Table16[[#This Row],[Extended Qty]] -> 4000 | O31: =Table16[[#This Row],[Equipment Cost]]*Table16[[#This Row],[Extended Qty]] -> 4000 | P31: =Table16[[#This Row],[Extended Cost for all lines]]/Table16[[#This Row],[Useful Life]]/SupplierBaseInput!$C$7 -> 0.009569378
A32: SMT | B32: Equipment | C32: Standard | D32: SWITCH Board WS PCB Carrier_Top | G32: N/A | H32: 1 | I32: 1 | J32: 50 | K32: =J32*I32 -> 50 | M32: 160 | N32: =Table16[[#This Row],[Equipment Cost]]*Table16[[#This Row],[Extended Qty]] -> 8000 | O32: =Table16[[#This Row],[Equipment Cost]]*Table16[[#This Row],[Extended Qty]] -> 8000 | P32: =Table16[[#This Row],[Extended Cost for all lines]]/Table16[[#This Row],[Useful Life]]/SupplierBaseInput!$C$7 -> 0.019138756
A33: SMT | B33: Equipment | C33: Standard | D33: SWITCH Board WS Touch Up Fixture | G33: N/A | H33: 1 | I33: 1 | J33: 2 | K33: =J33*I33 -> 2 | M33: 150 | N33: =Table16[[#This Row],[Equipment Cost]]*Table16[[#This Row],[Extended Qty]] -> 300 | O33: =Table16[[#This Row],[Equipment Cost]]*Table16[[#This Row],[Extended Qty]] -> 300 | P33: =Table16[[#This Row],[Extended Cost for all lines]]/Table16[[#This Row],[Useful Life]]/SupplierBaseInput!$C$7 -> 0.00071770335
A34: SMT | B34: Equipment | C34: Standard | D34: SWITCH Board PCBA ESD Tray | G34: N/A | H34: 1 | I34: 1 | J34: 752 | K34: 752 | M34: 5 | N34: =Table16[[#This Row],[Equipment Cost]]*Table16[[#This Row],[Extended Qty]] -> 3760 | O34: =Table16[[#This Row],[Equipment Cost]]*Table16[[#This Row],[Extended Qty]] -> 3760 | P34: =Table16[[#This Row],[Extended Cost for all lines]]/Table16[[#This Row],[Useful Life]]/SupplierBaseInput!$C$7 -> 0.0089952153
A35: BB Testing | B35: MRO | C35: Standard | D35: Agilent DAQ973+DAQM901 (Digit Multi-meters) | G35: N/A | H35: 6 | I35: 1 | J35: 2 | K35: =J35*I35 -> 2 | M35: 4078 | N35: =Table16[[#This Row],[Equipment Cost]]*Table16[[#This Row],[Qty per line]] -> 8156 | O35: =Table16[[#This Row],[Equipment Cost]]*Table16[[#This Row],[Extended Qty]] -> 8156 | P35: =Table16[[#This Row],[Extended Cost for all lines]]/Table16[[#This Row],[Useful Life]]/SupplierBaseInput!$C$7 -> 0.0032519936
A36: BB Testing | B36: MRO | C36: Standard | D36: Arduino Board | G36: N/A | H36: 1 | I36: 1 | J36: 2 | K36: =J36*I36 -> 2 | M36: 42.8 | N36: =Table16[[#This Row],[Equipment Cost]]*Table16[[#This Row],[Extended Qty]] -> 85.6 | O36: =Table16[[#This Row],[Equipment Cost]]*Table16[[#This Row],[Extended Qty]] -> 85.6 | P36: =Table16[[#This Row],[Extended Cost for all lines]]/Table16[[#This Row],[Useful Life]]/SupplierBaseInput!$C$7 -> 0.00020478469
A37: BB Testing | B37: Equipment | C37: Standard | D37: Barcode scanner(USB port) | G37: N/A | H37: 3 | I37: 1 | J37: 9 | K37: =J37*I37 -> 9 | M37: 222.9 | N37: =Table16[[#This Row],[Equipment Cost]]*Table16[[#This Row],[Qty per line]] -> 2006.1 | O37: =Table16[[#This Row],[Equipment Cost]]*Table16[[#This Row],[Extended Qty]] -> 2006.1 | P37: =Table16[[#This Row],[Extended Cost for all lines]]/Table16[[#This Row],[Useful Life]]/SupplierBaseInput!$C$7 -> 0.0015997608
A38: BB Testing | B38: Equipment | C38: Standard | D38: Digital Power Supply Agilent E3646A | G38: N/A | H38: 3 | I38: 1 | J38: 2 | K38: =J38*I38 -> 2 | M38: 1710 | N38: =Table16[[#This Row],[Equipment Cost]]*Table16[[#This Row],[Extended Qty]] -> 3420 | O38: =Table16[[#This Row],[Equipment Cost]]*Table16[[#This Row],[Extended Qty]] -> 3420 | P38: =Table16[[#This Row],[Extended Cost for all lines]]/Table16[[#This Row],[Useful Life]]/SupplierBaseInput!$C$7 -> 0.0027272727
A39: BB Testing | B39: Equipment | C39: Standard | D39: Generic desktop PC (KEYBOARD , MOUSE , Monitor ) Win10 | G39: N/A | H39: 3 | I39: 1 | J39: 9 | K39: =J39*I39 -> 9 | M39: 918.3 | N39: =Table16[[#This Row],[Equipment Cost]]*Table16[[#This Row],[Extended Qty]] -> 8264.7 | O39: =Table16[[#This Row],[Equipment Cost]]*Table16[[#This Row],[Extended Qty]] -> 8264.7 | P39: =Table16[[#This Row],[Extended Cost for all lines]]/Table16[[#This Row],[Useful Life]]/SupplierBaseInput!$C$7 -> 0.0065906699
A40: BB Testing | B40: Equipment | C40: Standard | D40: KEYSIGHT 34401A (Digit Multi-meters) | G40: N/A | H40: 6 | I40: 1 | J40: 2 | K40: =J40*I40 -> 2 | M40: 2980 | N40: =Table16[[#This Row],[Equipment Cost]]*Table16[[#This Row],[Qty per line]] -> 5960 | O40: =Table16[[#This Row],[Equipment Cost]]*Table16[[#This Row],[Extended Qty]] -> 5960 | P40: =Table16[[#This Row],[Extended Cost for all lines]]/Table16[[#This Row],[Useful Life]]/SupplierBaseInput!$C$7 -> 0.0023763955
A41: BB Testing | B41: Equipment | C41: Standard | D41: marble or glass (TBD) | G41: N/A | H41: 3 | I41: 1 | J41: 1 | K41: =J41*I41 -> 1 | M41: 198 | N41: =Table16[[#This Row],[Equipment Cost]]*Table16[[#This Row],[Qty per line]] -> 198 | O41: =Table16[[#This Row],[Equipment Cost]]*Table16[[#This Row],[Extended Qty]] -> 198 | P41: =Table16[[#This Row],[Extended Cost for all lines]]/Table16[[#This Row],[Useful Life]]/SupplierBaseInput!$C$7 -> 0.00015789474
A42: BB Testing | B42: Equipment | C42: Standard | D42: NI GPIB card and cable (NI GPIB-USB-HS) | G42: N/A | H42: 6 | I42: 1 | J42: 4 | K42: =J42*I42 -> 4 | M42: 952 | N42: =Table16[[#This Row],[Equipment Cost]]*Table16[[#This Row],[Qty per line]] -> 3808 | O42: =Table16[[#This Row],[Equipment Cost]]*Table16[[#This Row],[Extended Qty]] -> 3808 | P42: =Table16[[#This Row],[Extended Cost for all lines]]/Table16[[#This Row],[Useful Life]]/SupplierBaseInput!$C$7 -> 0.0015183413
A43: BB Testing | B43: Equipment | C43: Standard | D43: Tracking and Wheel Tester | G43: N/A | H43: 1 | I43: 1 | J43: 1 | K43: =J43*I43 -> 1 | M43: 500 | N43: =Table16[[#This Row],[Equipment Cost]]*Table16[[#This Row],[Qty per line]] -> 500 | O43: =Table16[[#This Row],[Equipment Cost]]*Table16[[#This Row],[Extended Qty]] -> 500 | P43: =Table16[[#This Row],[Extended Cost for all lines]]/Table16[[#This Row],[Useful Life]]/SupplierBaseInput!$C$7 -> 0.0011961722 | Q43: 维护费用
A44: BB Testing | B44: Equipment | C44: Standard | D44: USB 2.0 Type A Male to USB 2.0 Type A Female 100cm CABLE | G44: N/A | H44: 1 | I44: 1 | J44: 9 | K44: =J44*I44 -> 9 | M44: 11.4 | N44: =Table16[[#This Row],[Equipment Cost]]*Table16[[#This Row],[Extended Qty]] -> 102.6 | O44: =Table16[[#This Row],[Equipment Cost]]*Table16[[#This Row],[Extended Qty]] -> 102.6 | P44: =Table16[[#This Row],[Extended Cost for all lines]]/Table16[[#This Row],[Useful Life]]/SupplierBaseInput!$C$7 -> 0.00024545455
A45: BB Testing | B45: Equipment | C45: Standard | D45: USB 2.0 Type A Male to USB 2.0 Type A Male 100cm Cable | G45: N/A | H45: 1 | I45: 1 | J45: 2 | K45: =J45*I45 -> 2 | M45: 11.4 | N45: =Table16[[#This Row],[Equipment Cost]]*Table16[[#This Row],[Extended Qty]] -> 22.8 | O45: =Table16[[#This Row],[Equipment Cost]]*Table16[[#This Row],[Extended Qty]] -> 22.8 | P45: =Table16[[#This Row],[Extended Cost for all lines]]/Table16[[#This Row],[Useful Life]]/SupplierBaseInput!$C$7 -> 5.4545455e-05
A46: BB Testing | B46: Equipment | C46: Standard | D46: USB Type A Male to RS-232 100 cm Cable | G46: NA | H46: 1 | I46: 1 | J46: 1 | K46: =J46*I46 -> 1 | M46: 9.2 | N46: =Table16[[#This Row],[Equipment Cost]]*Table16[[#This Row],[Extended Qty]] -> 9.2 | O46: =Table16[[#This Row],[Equipment Cost]]*Table16[[#This Row],[Extended Qty]] -> 9.2 | P46: =Table16[[#This Row],[Extended Cost for all lines]]/Table16[[#This Row],[Useful Life]]/SupplierBaseInput!$C$7 -> 2.2009569e-05
A47: BB Testing | B47: Equipment | C47: Standard | D47: USB 2.0 Type A Male to USB 2.0 Type B Male 100cm Cable | G47: N/A | H47: 1 | I47: 1 | J47: 2 | K47: =J47*I47 -> 2 | M47: 11.4 | N47: =Table16[[#This Row],[Equipment Cost]]*Table16[[#This Row],[Extended Qty]] -> 22.8 | O47: =Table16[[#This Row],[Equipment Cost]]*Table16[[#This Row],[Extended Qty]] -> 22.8 | P47: =Table16[[#This Row],[Extended Cost for all lines]]/Table16[[#This Row],[Useful Life]]/SupplierBaseInput!$C$7 -> 5.4545455e-05
A48: BB ASSY | B48: MRO | C48: Custom | D48: Defect box不良品放置盒 | G48: N/A | H48: 3 | I48: 1 | J48: 26 | K48: =J48*I48 -> 26 | M48: 8 | N48: =Table16[[#This Row],[Equipment Cost]]*Table16[[#This Row],[Qty per line]] -> 208 | O48: =Table16[[#This Row],[Equipment Cost]]*Table16[[#This Row],[Extended Qty]] -> 208 | P48: =Table16[[#This Row],[Extended Cost for all lines]]/Table16[[#This Row],[Useful Life]]/SupplierBaseInput!$C$7 -> 0.00016586922
A49: BB ASSY | B49: MRO | C49: Custom | D49: TPS table | G49: N/A | H49: 3 | I49: 1 | J49: 26 | K49: =J49*I49 -> 26 | M49: 120 | N49: =Table16[[#This Row],[Equipment Cost]]*Table16[[#This Row],[Qty per line]] -> 3120 | O49: =Table16[[#This Row],[Equipment Cost]]*Table16[[#This Row],[Extended Qty]] -> 3120 | P49: =Table16[[#This Row],[Extended Cost for all lines]]/Table16[[#This Row],[Useful Life]]/SupplierBaseInput!$C$7 -> 0.0024880383
A50: BB ASSY | B50: MRO | C50: Custom | D50: Setup line material架線材料 | G50: N/A | H50: 3 | I50: 1 | J50: 1 | K50: =J50*I50 -> 1 | M50: 3400 | N50: =Table16[[#This Row],[Equipment Cost]]*Table16[[#This Row],[Qty per line]] -> 3400 | O50: =Table16[[#This Row],[Equipment Cost]]*Table16[[#This Row],[Extended Qty]] -> 3400 | P50: =Table16[[#This Row],[Extended Cost for all lines]]/Table16[[#This Row],[Useful Life]]/SupplierBaseInput!$C$7 -> 0.0027113238
A51: BB ASSY | B51: Equipment | C51: Standard | D51: Auto screws machine | G51: N/A | H51: 1 | I51: 1 | J51: 3 | K51: =J51*I51 -> 3 | M51: 500 | N51: =Table16[[#This Row],[Equipment Cost]]*Table16[[#This Row],[Extended Qty]] -> 1500 | O51: =Table16[[#This Row],[Equipment Cost]]*Table16[[#This Row],[Extended Qty]] -> 1500 | P51: =Table16[[#This Row],[Extended Cost for all lines]]/Table16[[#This Row],[Useful Life]]/SupplierBaseInput!$C$7 -> 0.0035885167 | Q51: 维护费用
A52: BB ASSY | B52: Equipment | C52: Standard | D52: Electric screwdriver 電批 | G52: N/A | H52: 2 | I52: 1 | J52: 2 | K52: =J52*I52 -> 2 | M52: 200 | N52: =Table16[[#This Row],[Equipment Cost]]*Table16[[#This Row],[Qty per line]] -> 400 | O52: =Table16[[#This Row],[Equipment Cost]]*Table16[[#This Row],[Extended Qty]] -> 400 | P52: =Table16[[#This Row],[Extended Cost for all lines]]/Table16[[#This Row],[Useful Life]]/SupplierBaseInput!$C$7 -> 0.0004784689
A53: BB ASSY | B53: Equipment | C53: Standard | D53: Screw feeder 螺絲機 | G53: N/A | H53: 2 | I53: 1 | J53: 2 | K53: =J53*I53 -> 2 | M53: 150 | N53: =Table16[[#This Row],[Equipment Cost]]*Table16[[#This Row],[Qty per line]] -> 300 | O53: =Table16[[#This Row],[Equipment Cost]]*Table16[[#This Row],[Extended Qty]] -> 300 | P53: =Table16[[#This Row],[Extended Cost for all lines]]/Table16[[#This Row],[Useful Life]]/SupplierBaseInput!$C$7 -> 0.00035885167
A54: BB ASSY | B54: Equipment | C54: Standard | D54: electronic scale電子稱 | G54: N/A | H54: 3 | I54: 1 | J54: 1 | K54: =J54*I54 -> 1 | M54: 320 | N54: =Table16[[#This Row],[Equipment Cost]]*Table16[[#This Row],[Qty per line]] -> 320 | O54: =Table16[[#This Row],[Equipment Cost]]*Table16[[#This Row],[Extended Qty]] -> 320 | P54: =Table16[[#This Row],[Extended Cost for all lines]]/Table16[[#This Row],[Useful Life]]/SupplierBaseInput!$C$7 -> 0.00025518341
A55: Quality (BB) | B55: MRO | C55: Standard | D55: Barcode scanner(USB port,2D) | G55: N/A | H55: 4 | I55: 1 | J55: 2 | K55: =J55*I55 -> 2 | M55: 299 | N55: =Table16[[#This Row],[Equipment Cost]]*Table16[[#This Row],[Qty per line]] -> 598 | O55: =Table16[[#This Row],[Equipment Cost]]*Table16[[#This Row],[Extended Qty]] -> 598 | P55: =Table16[[#This Row],[Extended Cost for all lines]]/Table16[[#This Row],[Useful Life]]/SupplierBaseInput!$C$7 -> 0.0003576555
A56: Quality (BB) | B56: Equipment | C56: Standard | D56: Printer | G56: N/A | H56: 4 | I56: 1 | J56: 1 | K56: =J56*I56 -> 1 | M56: 1950 | N56: =Table16[[#This Row],[Equipment Cost]]*Table16[[#This Row],[Qty per line]] -> 1950 | O56: =Table16[[#This Row],[Equipment Cost]]*Table16[[#This Row],[Extended Qty]] -> 1950 | P56: =Table16[[#This Row],[Extended Cost for all lines]]/Table16[[#This Row],[Useful Life]]/SupplierBaseInput!$C$7 -> 0.0011662679
A57: Quality (BB) | B57: Equipment | C57: Standard | D57: Test PC DELL3010 (Including LCD,Keyboard,Mouse) | G57: N/A | H57: 3 | I57: 1 | J57: 2 | K57: =J57*I57 -> 2 | M57: 955 | N57: =Table16[[#This Row],[Equipment Cost]]*Table16[[#This Row],[Extended Qty]] -> 1910 | O57: =Table16[[#This Row],[Equipment Cost]]*Table16[[#This Row],[Extended Qty]] -> 1910 | P57: =Table16[[#This Row],[Extended Cost for all lines]]/Table16[[#This Row],[Useful Life]]/SupplierBaseInput!$C$7 -> 0.001523126
O58: =SUM(O3:O57) -> 1697445.3 | P58: =SUM(P3:P57) -> 0.86843344

Sheet Consumables
A1: Bucket | B1: Item description | C1: P/N | D1: Spec. | E1: Est Q'ty | F1: Item Cost | G1: Unit Cost | H1: Unit Usage | I1: Total Cost | J1: Unit Cost2 | K1: Remark | L1: 列1
A2: SMT | B2: Solder paste | E2: =SupplierBaseInput!C7 -> 418000 | F2: =Table2[[#This Row],[Unit Cost]]*Table2[[#This Row],[Unit Usage]] -> 0.0473 | G2: 0.11 | H2: 0.43 | I2: =Table2[[#This Row],[Est Q''ty]]*Table2[[#This Row],[Item Cost]] -> 19771.4 | J2: =Table2[[#This Row],[Item Cost]] -> 0.0473
A3: SMT | B3: Solder wire | D3: 1.0 mm | E3: =SupplierBaseInput!C7 -> 418000 | F3: =Table2[[#This Row],[Unit Cost]]*Table2[[#This Row],[Unit Usage]] -> 0.0171 | G3: 0.057 | H3: 0.3 | I3: =Table2[[#This Row],[Est Q''ty]]*Table2[[#This Row],[Item Cost]] -> 7147.8 | J3: =Table2[[#This Row],[Item Cost]] -> 0.0171
A4: SMT | B4: Solder stick | E4: =SupplierBaseInput!C7 -> 418000 | F4: =Table2[[#This Row],[Unit Cost]]*Table2[[#This Row],[Unit Usage]] -> 0.2432 | G4: 0.064 | H4: 3.8 | I4: =Table2[[#This Row],[Est Q''ty]]*Table2[[#This Row],[Item Cost]] -> 101657.6 | J4: =Table2[[#This Row],[Item Cost]] -> 0.2432
A5: SMT | B5: Solder flux | E5: =SupplierBaseInput!C7 -> 418000 | F5: =Table2[[#This Row],[Unit Cost]]*Table2[[#This Row],[Unit Usage]] -> 0.0297 | G5: 0.0066 | H5: 4.5 | I5: =Table2[[#This Row],[Est Q''ty]]*Table2[[#This Row],[Item Cost]] -> 12414.6 | J5: =Table2[[#This Row],[Item Cost]] -> 0.0297
A6: SMT | B6: Cleaning solution | E6: =SupplierBaseInput!C7 -> 418000 | F6: =Table2[[#This Row],[Unit Cost]]*Table2[[#This Row],[Unit Usage]] -> 0.026 | G6: 0.004 | H6: 6.5 | I6: =Table2[[#This Row],[Est Q''ty]]*Table2[[#This Row],[Item Cost]] -> 10868 | J6: =Table2[[#This Row],[Item Cost]] -> 0.026
A8: BB Testing | B8: USB 2.0 Type A Male to USB 2.0 Type A Female 100cm CABLE | E8: =SupplierBaseInput!C7 -> 418000 | F8: =Table2[[#This Row],[Unit Cost]]*Table2[[#This Row],[Unit Usage]] -> 0.012825 | G8: =11.4/8000 -> 0.001425 | H8: 9 | I8: =Table2[[#This Row],[Est Q''ty]]*Table2[[#This Row],[Item Cost]] -> 5360.85 | J8: =Table2[[#This Row],[Item Cost]] -> 0.012825
B9: USB 2.0 Type A Male to USB 2.0 Type A Male 100cm Cable | E9: =SupplierBaseInput!C7 -> 418000 | F9: =Table2[[#This Row],[Unit Cost]]*Table2[[#This Row],[Unit Usage]] -> 0.00285 | G9: =11.4/8000 -> 0.001425 | H9: 2 | I9: =Table2[[#This Row],[Est Q''ty]]*Table2[[#This Row],[Item Cost]] -> 1191.3 | J9: =Table2[[#This Row],[Item Cost]] -> 0.00285
B10: USB 2.0 Type A Male to USB 2.0 Type B Male 100cm Cable | E10: =SupplierBaseInput!C7 -> 418000 | F10: =Table2[[#This Row],[Unit Cost]]*Table2[[#This Row],[Unit Usage]] -> 0.00285 | G10: =11.4/8000 -> 0.001425 | H10: 2 | I10: =Table2[[#This Row],[Est Q''ty]]*Table2[[#This Row],[Item Cost]] -> 1191.3 | J10: =Table2[[#This Row],[Item Cost]] -> 0.00285
B11: USB Type A Male to RS-232 100 cm Cable | E11: =SupplierBaseInput!C7 -> 418000 | F11: =Table2[[#This Row],[Unit Cost]]*Table2[[#This Row],[Unit Usage]] -> 0.00115 | G11: =9.2/8000 -> 0.00115 | H11: 1 | I11: =Table2[[#This Row],[Est Q''ty]]*Table2[[#This Row],[Item Cost]] -> 480.7 | J11: =Table2[[#This Row],[Item Cost]] -> 0.00115
A13: BB Assy
B14: Printer head | E14: =SupplierBaseInput!C7 -> 418000 | F14: =Table2[[#This Row],[Unit Cost]]*Table2[[#This Row],[Unit Usage]] -> 0.004 | G14: 400 | H14: 1e-05 | I14: =Table2[[#This Row],[Est Q''ty]]*Table2[[#This Row],[Item Cost]] -> 1672 | J14: =Table2[[#This Row],[Item Cost]] -> 0.004
B15: Lubrication | E15: =SupplierBaseInput!C7 -> 418000 | F15: =Table2[[#This Row],[Unit Cost]]*Table2[[#This Row],[Unit Usage]] -> 0.003 | G15: 300 | H15: 1e-05 | I15: =Table2[[#This Row],[Est Q''ty]]*Table2[[#This Row],[Item Cost]] -> 1254 | J15: =Table2[[#This Row],[Item Cost]] -> 0.003
B16: INK RIBBON,DEPLETION (0952-0002-00E0) | D16: 60mm | E16: =SupplierBaseInput!C7 -> 418000 | F16: =Table2[[#This Row],[Unit Cost]]*Table2[[#This Row],[Unit Usage]] -> 0.0001851 | G16: 6.17 | H16: 3e-05 | I16: =Table2[[#This Row],[Est Q''ty]]*Table2[[#This Row],[Item Cost]] -> 77.3718 | J16: =Table2[[#This Row],[Item Cost]] -> 0.0001851
B17: INK RIBBON,DEPLETION (0952-0005-00E0) | D17: 110mm | E17: =SupplierBaseInput!C7 -> 418000 | F17: =Table2[[#This Row],[Unit Cost]]*Table2[[#This Row],[Unit Usage]] -> 0.0006942 | G17: 11.57 | H17: 6e-05 | I17: =Table2[[#This Row],[Est Q''ty]]*Table2[[#This Row],[Item Cost]] -> 290.1756 | J17: =Table2[[#This Row],[Item Cost]] -> 0.0006942

Sheet SMT Process Flow
B1: Production Line Layout
B3: ProjectRival 3+ Wired MouseSMT Process Flow | I3: =E7 -> 8.64
B4: (Main+LED) Board
E5: UPH: | F5: =3600/E7 -> 416.66667
B6: Station | C6: Process Flow | E6: C/T | F6: H/C
B7: =96*0.09 -> 8.64 | E7: =MAX(E8:E13)+MAX(E15:E22) -> 8.64 | F7: =SUM(F8:F22) -> 10
B8: Solder printing Bot side | E8: 4 | F8: 1
B9: SPI | E9: 4
B10: Mounting components | E10: 4 | F10: 2
B11: Reflow | E11: 4.04 | F11: 0
B12: AOI | E12: 4 | F12: 1
B13: Visual Inspection | E13: 4.1 | F13: 1
B14: Repair
B15: Solder printing Top side | E15: 4.2 | F15: 1
B16: SPI | E16: 4
B17: Mounting components | E17: 4.54 | F17: 2
B18: Reflow | E18: 4.29 | F18: 0
B19: AOI | E19: 4.2 | F19: 1
B20: Visual Inspection | E20: 4 | F20: 1
B21: Repair
B24: Project Rival 3Wave Solder Process Flow | H24: Total: | I24: =E28+L28 -> 12
B25: Main board Wave Solder | I25: SWITCH board Wave Solder
E26: UPH: | F26: =3600/E28 -> 514.28571 | L26: UPH: | M26: =3600/L28 -> 720
C27: Process Flow | E27: C/T | F27: H/C | J27: Process Flow | L27: C/T | M27: H/C
E28: =MAX(E29:E38) -> 7 | F28: =SUM(F29:F38) -> 18 | L28: =MAX(L29:L38) -> 5 | M28: =SUM(M29:M38) -> 15
B29: Loading PCBA to pallet | E29: 3.3 | F29: 1 | I29: Loading PCBA to pallet | L29: 3.3 | M29: 1
B30: Manual insert components | E30: 7 | F30: 7 | I30: Manual insert components | L30: 5 | M30: 4
B31: Visual ispection | E31: 3.4 | F31: 1 | I31: Visual ispection | L31: 3.4 | M31: 1
B32: Wave soldering | E32: 4.5 | I32: Wave soldering | L32: 4.5
B33: Unloading PCBA | E33: 3 | F33: 1 | I33: Unloading PCBA | L33: 3 | M33: 1
B34: Touch UP | E34: 3.1 | F34: 2 | I34: Touch UP | L34: 3.1 | M34: 2
B36: Repair | I36: Repair
B37: Inspection & packing | E37: 3.4 | F37: 6 | I37: Inspection & packing | L37: 3.4 | M37: 6
B39: Project Rival 3 Out line Process Flow | H39: Total: | I39: =E43+L43 -> 24
B40: Main board Depanel/Router | H40: SWITCH board Depanel/Router
E41: UPH: | F41: 600 | L41: UPH: | M41: 600
B42: Station | C42: Process Flow | E42: C/T | F42: H/C | I42: Station | J42: Process Flow | L42: C/T | M42: H/C
E43: =MAX(E44:E48) -> 12 | F43: 2 | L43: =MAX(L44:L48) -> 12 | M43: 2
B44: Depanel-Router | E44: 12 | F44: 1 | I44: Depanel-Router | L44: 12 | M44: 1
B46: Visual Inspection | E46: 5 | F46: 0.5 | I46: Visual Inspection | L46: 5 | M46: 0.5
B47: Load&unload | E47: 5 | F47: 0.5 | I47: Load&unload | L47: 5 | M47: 0.5
B49: SMT 1D/2D Barcode laser etching | F49: Total: | H49: =E53 -> 4
B50: Main board
E51: UPH: | F51: =3600/E53 -> 900
B52: Station | C52: Process Flow | E52: C/T | F52: H/C
E53: =SUM(MAX(E54:E58)) -> 4 | F53: =SUM(F54:F58) -> 1
B54: Uploading PCB | E54: 1.5 | F54: 0.5
B56: laser etching | E56: 4
B57: unloading | E57: 1.5 | F57: 0.5

Sheet BB Process Flow
A1: Box Build Flow Chart For NPI build
A2: Remark | B2: Station | I2: Flow | J2: H/C | K2: CT | L2: BB assembly HC | M2: =SUM(J4:J37)-M3 -> 22.5
B3: Process | J3: =SUM(J4:J37) -> 28.5 | K3: =MAX(K4:K37) -> 19 | L3: BB test HC | M3: =J9+J21+J22+J23 -> 6
A4: Assembly | B4: LED加工&焊接LED于Main Board/Soldering LED on Main Board | J4: 0.5 | K4: 19 | L4: 模組化,減少0.5人
B5: 組裝Wheel module/Assembly Wheel module | J5: 0.5 | K5: 19 | L5: 模組化,減少0.5人
B6: 焊接4pin排線至Switch board/Soldering the 4pin cable on Switch board | J6: 0.5 | K6: 19 | L6: 模組化,減少0.5人
B7: 組裝CPI Button于Middle housing,然后用1顆螺絲鎖付,組裝side button于Middle housing. | J7: 0.5 | K7: 19 | L7: 模組化,減少0.5人
B8: 組裝Trigger Button LEFT/RIGHT 至Middle housing,然后用兩顆螺絲鎖付,Assemble and screwing Trigger Button LEFT/RIGHT & Middle housing. | J8: 0.5 | K8: 19 | L8: 模組化,減少0.5人
B9: (F1) VOLTAGE / CURRENT & BASIC FUNCTION TEST&組裝Wheel至main Board | J9: 1 | K9: 19 | L9: 模組化,減少1人
B10: 揭去隔熱膠,組裝Wheel至Main board | J10: 1 | K10: 19
B11: 組裝Cable至Bottom Cover/Assembly Cable in Bottom. | J11: 1 | K11: 19
B12: 組裝Sensor Lens 至Bottom Cover & 組裝Main PCB 與Bottom cover/Aseemble sensor Lensin the Main PCB & Assemble main Board and Bottom cover | J12: 1 | K12: 19
B13: 自動鎖付main board/Automatic lock main board | J13: 0 | K13: 19 | L13: Auto screwing machine
B14: 涂潤滑油&插Cable至Main PCB/Lubrication&Insert Cable in the Main PCB | J14: 1 | K14: 19
B15: 組裝側鍵 & Switch PCB于Middle housing/Assembly of Side Keys&Switch PCB in Middle House | J15: 1 | K15: 19
B16: 自動鎖付SWITCH PCB于Middle housing./Auto Screwing Switch PCB & Middle housing | J16: 0 | K16: 19 | L16: Auto screwing machine
B17: 插SW PCB 4pin排線至Main PCB&組裝 Middle housing 與Bottom cover/Insert SW PCB 4pin cable in the Main PCB&Assemble Middle housing and Bottom cover. | J17: 1 | K17: 19
B18: 自動鎖付Middle housing 與Bottom cover/Auto Screwing Middle housing and Bottom cover.. | J18: 0 | K18: 19 | L18: Auto screwing machine
B19: 贴後腳墊&貼S/N/Stick the rear foot pad&stick S/N | J19: 1 | K19: 19
B20: 贴前腳墊並壓緊/Attach the front foot pad and press it tightly | J20: 1 | K20: 19
B21: (F2) KEY FUNCTION AND FEELING & LED CHECK | J21: 2 | K21: 19
B22: (F3) TRACKING & WHEEL TEST | J22: 1 | K22: 19
B23: (F4)IPS&Lift off test /(F4)IPS&Lift off test | J23: 2 | K23: 19
B24: 外觀檢查&產品清潔/Visual inspection&Clean the product | J24: 1 | K24: 19
B25: 異音檢查&按鍵檢查/Voice and button checking | J25: 1 | K25: 19
B26: 打印并貼PID&撕腳墊膜/Scan S/N barcode to print PID and affix it&Tearing up foot pads | J26: 1 | K26: 19
A27: Packaging | B27: Packaging
B28: 裝產品入PE袋/Put the product into a PE bag | J28: 1 | K28: 19
B29: 裝產品入內卡/Loading products into internal cards | J29: 1 | K29: 19
B30: 整理包裝線材/Packaging USB cable | J30: 1 | K30: 19
B31: 加工彩盒Flod color box | J31: 1 | K31: 19
B32: 裝內卡及說明書入彩盒/Put the inner card and manual into color box | J32: 1 | K32: 19
B33: 封盒并貼封口貼/Seal the box and apply sealing tape | J33: 1 | K33: 19
B34: 清潔彩盒&打印并貼彩盒標簽/Cleaning the color box&printing and labeling the color box | J34: 1 | K34: 19
B35: 清潔彩盒&打印并貼彩盒標簽/Cleaning the color box&printing and labeling the color box | J35: 1 | K35: 19
B36: 列印Shipping label，掃描稱重,裝箱,封箱.堆棧板/Scan the retail label and print the shipper label . Affix the shipper label on the color card, seal the box and load pallet | J36: 1 | K36: 19
