Workbook
Name \0: #REF!
Name \0: #REF!
Name \0: #REF!
Name \0: #REF!
Name \0: #REF!
Name \0: #REF!
Name \a: #REF!
Name \a: #REF!
Name \a: #REF!
Name \a: #REF!
Name \a: #REF!
Name \a: #REF!
Name \a: #REF!
Name \aa: #REF!
Name \aa: #REF!
Name \aa: #REF!
Name \aa: #REF!
Name \aa: #REF!
Name \aa: #REF!
Name \aa: #REF!
Name \b: #REF!
Name \b: #REF!
Name \b: #REF!
Name \b: #REF!
Name \b: #REF!
Name \b: #REF!
Name \b: #REF!
Name \c: #REF!
Name \c: #REF!
Name \c: #REF!
Name \c: #REF!
Name \c: #REF!
Name \c: #REF!
Name \c: #REF!
Name \d: #REF!
Name \d: #REF!
Name \d: #REF!
Name \d: #REF!
Name \d: #REF!
Name \d: #REF!
Name \d: #REF!
Name \e: #REF!
Name \e: #REF!
Name \e: #REF!
Name \e: #REF!
Name \e: #REF!
Name \e: #REF!
Name \e: #REF!
Name \f: #REF!
Name \f: #REF!
Name \f: #REF!
Name \f: #REF!
Name \f: #REF!
Name \f: #REF!
Name \f: #REF!
Name \g: #REF!
Name \g: #REF!
Name \g: #REF!
Name \g: #REF!
Name \g: #REF!

Sheet Unit Cost
A1: Project Name: | B1: ELM5 | X1: v0.1 | Z1: True Cost | AA1: True Cost | AC1: True Cost | AD1: True Cost | AF1: True Cost | AG1: True Cost | AI1: True Cost | AJ1: True Cost | AL1: True Cost | AM1: True Cost | AN1: True Cost | AO1: True Cost
A2: Supplier name: | B2: Foxlink | X2: 43467
Z3: 9/18/2023 | AA3: 4/10/2023 | AC3: 9/18/2023 | AD3: 4/10/2023 | AF3: 9/18/2023 | AG3: 4/10/2023 | AI3: 9/18/2023 | AJ3: 4/10/2023 | AL3: 12/2/22 | AM3: 9/13/22 | AN3: 9/5/22 | AO3: 4/12/22
Z4: 350k | AA4: 350k | AC4: 350k | AD4: 350k | AF4: 350k | AG4: 350k | AI4: 350k | AJ4: 350k | AL4: 350k | AM4: 350k | AN4: 350k | AO4: 350k
A5: Retail Packaging | D5: Made In China | E5: Made In Vietnam | F5: Made in Taiwan | G5: Made In China | H5: Made In Vietnam | I5: Made in Taiwan | J5: Made In China | K5: Made In Vietnam | L5: Made in Taiwan | M5: Made In China | N5: Made In Vietnam | O5: Made in Taiwan | P5: Made In China | Q5: Made In Vietnam | R5: Made in Taiwan | T5: Made In China | U5: Made In Myanmar | V5: Made In China | W5: Made In Myanmar | Z5: Made In China | AA5: Made In Vietnam | AB5: Made in Taiwan | AC5: Made In China | AD5: Made In Vietnam | AE5: Made in Taiwan | AF5: Made In China | AG5: Made In Vietnam | AH5: Made in Taiwan | AI5: Made In China | AJ5: Made In Vietnam | AK5: Made in Taiwan
D6: Option A | E6: Option B | F6: Option C | G6: Option A | H6: Option B | I6: Option C | J6: Option A | K6: Option B | L6: Option C | M6: Option A | N6: Option B | O6: Option C | P6: Option A | Q6: Option B | R6: Option C | T6: Option A | U6: Option A | V6: Option A | W6: Option A | Z6: Option A | AA6: Option B | AB6: Opttion C | AC6: Option A | AD6: Option B | AE6: Opttion C | AF6: Option A | AG6: Option B | AH6: Opttion C | AI6: Option A | AJ6: Option B | AK6: Opttion C | AL6: Remark
D7: 45622 | E7: =D7 -> 45622 | F7: =E7 -> 45622 | G7: 45608 | H7: =G7 -> 45608 | I7: =H7 -> 45608 | J7: 45504 | K7: =J7 -> 45504 | L7: =K7 -> 45504 | M7: 45461 | N7: 45461 | O7: 45461 | P7: 45350 | Q7: 45364 | R7: 45364 | T7: 44861 | U7: 44861 | V7: 44413 | W7: 44413 | Z7: 45622 | AA7: 45622 | AB7: 45622 | AC7: 45608 | AD7: 45608 | AE7: 45608 | AF7: 45461 | AG7: 45461 | AH7: 45461 | AI7: 45350 | AJ7: 45364 | AK7: 45364
A8: Rival 3 Gen2 Quote | D8: CMF v1.2, Remove internal LED lens and etch for SS logo, replace with painted logo | E8: CMF v1.2, Remove internal LED lens and etch for SS logo, replace with painted logo | F8: CMF v1.2, Remove internal LED lens and etch for SS logo, replace with painted logo | G8: CMF v1.2, Remove internal LED lens and etch for SS logo, replace with painted logo | H8: CMF v1.2, Remove internal LED lens and etch for SS logo, replace with painted logo | I8: CMF v1.2, Remove internal LED lens and etch for SS logo, replace with painted logo | J8: CMF v1.2, Remove internal LED lens and etch for SS logo, replace with painted logo | K8: CMF v1.2, Remove internal LED lens and etch for SS logo, replace with painted logo | L8: CMF v1.2, Remove internal LED lens and etch for SS logo, replace with painted logo | M8: CMF v1.2, Remove internal LED lens and etch for SS logo, replace with painted logo | N8: CMF v1.2, Remove internal LED lens and etch for SS logo, replace with painted logo | O8: CMF v1.2, Remove internal LED lens and etch for SS logo, replace with painted logo | P8: CMF v1.2, Remove internal LED lens and etch for SS logo, replace with painted logo | Q8: CMF v1.2, Remove internal LED lens and etch for SS logo, replace with painted logo | R8: CMF v1.2, Remove internal LED lens and etch for SS logo, replace with painted logo | T8: CMFv2_6LEDs 3 Zones + Logo LED current control by each one | U8: CMFv2_6LEDs 3 Zones + Logo LED current control by each one | V8: CMFv2_6LEDs 3 Zones + Logo LED current control by each one | W8: CMFv2_6LEDs 3 Zones + Logo LED current control by each one | Z8: CMF v1.2, Remove internal LED lens and etch for SS logo, replace with painted logo | AA8: CMF v1.2, Remove internal LED lens and etch for SS logo, replace with painted logo | AB8: CMF v1.2, Remove internal LED lens and etch for SS logo, replace with painted logo | AC8: CMF v1.2, Remove internal LED lens and etch for SS logo, replace with painted logo | AD8: CMF v1.2, Remove internal LED lens and etch for SS logo, replace with painted logo | AE8: CMF v1.2, Remove internal LED lens and etch for SS logo, replace with painted logo | AF8: CMF v1.2, Remove internal LED lens and etch for SS logo, replace with painted logo | AG8: CMF v1.2, Remove internal LED lens and etch for SS logo, replace with painted logo | AH8: CMF v1.2, Remove internal LED lens and etch for SS logo, replace with painted logo | AI8: CMF v1.2, Remove internal LED lens and etch for SS logo, replace with painted logo | AJ8: CMF v1.2, Remove internal LED lens and etch for SS logo, replace with painted logo | AK8: CMF v1.2, Remove internal LED lens and etch for SS logo, replace with painted logo
D9: Quote Based Quantity : 418Kpcs/year | E9: Quote Based Quantity : 418Kpcs/year | F9: Quote Based Quantity : 150Kpcs/year(only for US) | G9: Quote Based Quantity : 418Kpcs/year | H9: Quote Based Quantity : 418Kpcs/year | I9: Quote Based Quantity : 150Kpcs/year(only for US) | J9: Quote Based Quantity : 418Kpcs/year | K9: Quote Based Quantity : 418Kpcs/year | L9: Quote Based Quantity : 150Kpcs/year(only for US) | M9: Quote Based Quantity : 418Kpcs/year | N9: Quote Based Quantity : 418Kpcs/year | O9: Quote Based Quantity : 150Kpcs/year(only for US) | P9: Quote Based Quantity : 418Kpcs/year | Q9: Quote Based Quantity : 418Kpcs/year | R9: Quote Based Quantity : 150Kpcs/year(only for US) | T9: Quote Based Quantity : 250Kpcs/year | U9: Quote Based Quantity : 250Kpcs/year | V9: Quote Based Quantity : 250Kpcs/year | W9: Quote Based Quantity : 250Kpcs/year | Z9: Quote Based Quantity : 418Kpcs/year | AA9: Quote Based Quantity : 418Kpcs/year | AB9: Quote Based Quantity : 150Kpcs/year(only for US) | AC9: Quote Based Quantity : 418Kpcs/year | AD9: Quote Based Quantity : 418Kpcs/year | AE9: Quote Based Quantity : 150Kpcs/year(only for US) | AF9: Quote Based Quantity : 418Kpcs/year | AG9: Quote Based Quantity : 418Kpcs/year | AH9: Quote Based Quantity : 150Kpcs/year(only for US) | AI9: Quote Based Quantity : 418Kpcs/year | AJ9: Quote Based Quantity : 418Kpcs/year | AK9: Quote Based Quantity : 150Kpcs/year(only for US)
D10: Per Unit Price | E10: Per Unit Price | F10: Per Unit Price | G10: Per Unit Price | H10: Per Unit Price | I10: Per Unit Price | J10: Per Unit Price | K10: Per Unit Price | L10: Per Unit Price | M10: Per Unit Price | N10: Per Unit Price | O10: Per Unit Price | P10: Per Unit Price | Q10: Per Unit Price | R10: Per Unit Price | T10: Per Unit Price | U10: Per Unit Price | V10: Per Unit Price | W10: Per Unit Price | Z10: Per Unit Price | AA10: Per Unit Price | AB10: Per Unit Price | AC10: Per Unit Price | AD10: Per Unit Price | AE10: Per Unit Price | AF10: Per Unit Price | AG10: Per Unit Price | AH10: Per Unit Price | AI10: Per Unit Price | AJ10: Per Unit Price | AK10: Per Unit Price
A11: CDM | D11: SKU Total in US$ | E11: SKU Total in US$ | F11: SKU Total in US$ | G11: SKU Total in US$ | H11: SKU Total in US$ | I11: SKU Total in US$ | J11: SKU Total in US$ | K11: SKU Total in US$ | L11: SKU Total in US$ | M11: SKU Total in US$ | N11: SKU Total in US$ | O11: SKU Total in US$ | P11: SKU Total in US$ | Q11: SKU Total in US$ | R11: SKU Total in US$ | T11: SKU Total in US$ | U11: SKU Total in US$ | V11: SKU Total in US$ | W11: SKU Total in US$ | X11: Remarks
A12: EE (Black) | D12: =G12 -> 6.017395 | E12: =D12*1.0381 -> 6.2466577 | F12: =D12 -> 6.017395 | G12: =J12 -> 6.017395 | H12: =K12 -> 6.2466577 | I12: =H12 -> 6.2466577 | J12: =M12 -> 6.017395 | K12: =N12 -> 6.2466577 | L12: =K12 -> 6.2466577 | M12: =P12 -> 6.017395 | N12: =Q12 -> 6.2466577 | O12: =N12 -> 6.2466577 | P12: ='EE bom 0227'!T168 -> 6.017395 | Q12: =P12*1.0381 -> 6.2466577 | R12: =Q12 -> 6.2466577 | S12: EE | T12: 5.686775 | U12: 5.9034411 | V12: 5.736775 | W12: 5.9553461 | Z12: ='EE bom 0227'!Z168 -> 5.39273 | AA12: =Z12*1.0381 -> 5.598193 | AB12: =Z12 -> 5.39273 | AC12: ='EE bom 0227'!Z168 -> 5.39273 | AD12: =AC12 -> 5.39273 | AE12: =AC12 -> 5.39273 | AF12: =AI12 -> 5.39273 | AG12: =AF12 -> 5.39273 | AH12: =AF12 -> 5.39273 | AI12: ='EE bom 0227'!Z168 -> 5.39273 | AJ12: =AI12 -> 5.39273 | AK12: =AI12 -> 5.39273 | AL12: 031324: for VN & TW, refer to ELM5 quote, added 3%
A13: EE (White) | D13: =G13 -> 6.088895 | E13: =D13*1.0381 -> 6.3208819 | F13: =D13 -> 6.088895 | G13: =J13 -> 6.088895 | H13: =G13*1.0381 -> 6.3208819 | I13: =H13 -> 6.3208819 | J13: =M13 -> 6.088895 | K13: =J13*1.0381 -> 6.3208819 | L13: =K13 -> 6.3208819 | M13: =P13 -> 6.088895 | N13: =M13*1.0381 -> 6.3208819 | O13: =N13 -> 6.3208819 | P13: ='EE bom 0227'!T169 -> 6.088895 | Q13: =P13*1.0381 -> 6.3208819 | R13: =Q13 -> 6.3208819 | S13: ME | T13: 3.3938138 | U13: 3.5231182 | V13: 3.5238138 | W13: 3.6580712 | Z13: ='EE bom 0227'!Z169 -> 5.44973 | AA13: =Z13*1.0381 -> 5.6573647 | AB13: =Z13 -> 5.44973 | AC13: ='EE bom 0227'!Z169 -> 5.44973 | AD13: =AC13 -> 5.44973 | AE13: =AC13 -> 5.44973 | AF13: =AI13 -> 5.44973 | AG13: =AF13 -> 5.44973 | AH13: =AF13 -> 5.44973 | AI13: ='EE bom 0227'!Z169 -> 5.44973 | AJ13: =AI13 -> 5.44973 | AK13: =AI13 -> 5.44973 | AL13: 031324: for VN & TW, refer to ELM5 quote, added 3%
A14: ME (Black) | D14: =G14 -> 1.6713398 | E14: =D14*1.0381 -> 1.7350179 | F14: =D14 -> 1.6713398 | G14: =J14 -> 1.6713398 | H14: =G14*1.0381 -> 1.7350179 | I14: =H14 -> 1.7350179 | J14: =M14 -> 1.6713398 | K14: =J14*1.0381 -> 1.7350179 | L14: =K14 -> 1.7350179 | M14: ='ME bom 0618_Black'!V29 -> 1.6713398 | N14: =M14*1.0381 -> 1.7350179 | O14: =N14 -> 1.7350179 | P14: ='ME bom 0229_Black'!V29 -> 1.5898038 | Q14: =P14*1.0381 -> 1.6503754 | R14: =Q14 -> 1.6503754 | S14: Packaging | T14: 0.67444804 | U14: 0.70014451 | V14: 0.67444804 | W14: 0.70014451 | X14: 6/18 Update light-guide, bottom cover material as Rival3 Gen1 light-guide. | Z14: ='ME bom 0618_Black'!AD29 -> 1.6309795 | AA14: =Z14*1.0381 -> 1.6931198 | AB14: =Z14 -> 1.6309795 | AC14: ='ME bom 0618_Black'!AD29 -> 1.6309795 | AD14: =AC14 -> 1.6309795 | AE14: =AC14 -> 1.6309795 | AF14: ='ME bom 0618_Black'!AD29 -> 1.6309795 | AG14: =AF14 -> 1.6309795 | AH14: =AF14 -> 1.6309795 | AI14: ='ME bom 0229_Black'!AD29 -> 1.4185819 | AJ14: =AI14 -> 1.4185819 | AK14: =AI14 -> 1.4185819 | AL14: 031324: for VN & TW, refer to ELM5 quote, added 3% 022924: w/o the true cost of SIDE BUTTON, CPI BUTTON, WHEEL HUB, SWITCH CUSHION, LED CLIP
A15: ME (White) | D15: =G15 -> 1.815194 | E15: =D15*1.0381 -> 1.8843529 | F15: =D15 -> 1.815194 | G15: =J15 -> 1.815194 | H15: =G15*1.0381 -> 1.8843529 | I15: =H15 -> 1.8843529 | J15: =M15 -> 1.815194 | K15: =J15*1.0381 -> 1.8843529 | L15: =K15 -> 1.8843529 | M15: ='ME bom 0618_White'!V29 -> 1.815194 | N15: =M15*1.0381 -> 1.8843529 | O15: =N15 -> 1.8843529 | P15: ='ME bom 0229_White'!V29 -> 1.6993808 | Q15: =P15*1.0381 -> 1.7641272 | R15: =Q15 -> 1.7641272 | S15: MVA | T15: 1.25 | U15: 1.195 | V15: 1.25 | W15: 1.195 | X15: 6/18 Correction of incorrect price for light-guide. | Z15: ='ME bom 0618_White'!AD29 -> 1.7058044 | AA15: =Z15*1.0381 -> 1.7707955 | AB15: =Z15 -> 1.7058044 | AC15: ='ME bom 0618_White'!AD29 -> 1.7058044 | AD15: =AC15 -> 1.7058044 | AE15: =AC15 -> 1.7058044 | AF15: ='ME bom 0618_White'!AD29 -> 1.7058044 | AG15: =AF15 -> 1.7058044 | AH15: =AF15 -> 1.7058044 | AI15: ='ME bom 0229_White'!AD29 -> 1.5403829 | AJ15: =AI15 -> 1.5403829 | AK15: =AI15 -> 1.5403829 | AL15: 031324: for VN & TW, refer to ELM5 quote, added 3% 022924: w/o the true cost of SWITCH CUSHION, LED CLIP.
A16: Packaging | D16: =G16 -> 0.82809498 | E16: ='PKG BOM 20241119-TW'!M32 -> 0.94416822 | F16: =E16 -> 0.94416822 | G16: ='PKG BOM 20241023_Amber'!M32 -> 0.82809498 | H16: =G16*1.0381 -> 0.8596454 | I16: =H16 -> 0.8596454 | J16: ='PKG BOM 20240731_with FSC&減塑'!L36 -> 0.82839065 | K16: =J16*1.0381 -> 0.85995234 | L16: =K16 -> 0.85995234 | M16: ='PKG BOM 20240618_with FSC&減塑'!L35 -> 1.1086137 | N16: =M16*1.0381 -> 1.1508518 | O16: =N16 -> 1.1508518 | P16: ='PKG BOM 20240308_with FSC'!N35 -> 0.73168367 | Q16: =P16*1.0381 -> 0.75956082 | R16: =Q16 -> 0.75956082 | S16: PRIME COST (Matl + Labor): | T16: 11.005037 | U16: 11.321704 | V16: 11.185037 | W16: 11.508562 | X16: 11/26 Update PKG TW cost for PID & manual. 11/12 Update PKG BOM 7/31 Paper bag chage to Tissue Wrap 6/18 Update PKG price for Plastic Reduction. | Z16: ='PKG BOM 20241023_Amber'!X32 -> 0.70605015 | AA16: ='PKG BOM 20241119-TW'!AA32 -> 0.79625336 | AB16: =AA16 -> 0.79625336 | AC16: ='PKG BOM 20241023_Amber'!X32 -> 0.70605015 | AD16: =AC16 -> 0.70605015 | AE16: =AC16 -> 0.70605015 | AF16: ='PKG BOM 20240618_with FSC&減塑'!T35 -> 0.79299221 | AG16: =AF16 -> 0.79299221 | AH16: =AF16 -> 0.79299221 | AI16: ='PKG BOM 20240308_with FSC'!V35 -> 0.47463541 | AJ16: =AI16 -> 0.47463541 | AK16: =AI16 -> 0.47463541 | AL16: 031324: for VN & TW, refer to ELM5 quote, added 3%
A17: Black Material Cost | D17: =D12+D14+D16 -> 8.5168298 | E17: =E12+E14+E16 -> 8.9258439 | F17: =F12+F14+F16 -> 8.6329031 | G17: =G12+G14+G16 -> 8.5168298 | H17: =H12+H14+H16 -> 8.841321 | I17: =H17 -> 8.841321 | J17: =J12+J14+J16 -> 8.5171255 | K17: =K12+K14+K16 -> 8.841628 | L17: =K17 -> 8.841628 | M17: =M12+M14+M16 -> 8.7973485 | N17: =N12+N14+N16 -> 9.1325275 | O17: =N17 -> 9.1325275 | P17: =P12+P14+P16 -> 8.3388825 | Q17: =Q12+Q14+Q16 -> 8.6565939 | R17: =Q17 -> 8.6565939
A18: White Material Cost | D18: =D13+D15+D16 -> 8.7321839 | E18: =E13+E15+E16 -> 9.149403 | F18: =F13+F15+F16 -> 8.8482572 | G18: =G13+G15+G16 -> 8.7321839 | H18: =H13+H15+H16 -> 9.0648801 | I18: =H18 -> 9.0648801 | J18: =J13+J15+J16 -> 8.7324796 | K18: =K13+K15+K16 -> 9.0651871 | L18: =K18 -> 9.0651871 | M18: =M13+M15+M16 -> 9.0127026 | N18: =N13+N15+N16 -> 9.3560866 | O18: =N18 -> 9.3560866 | P18: =P13+P15+P16 -> 8.5199595 | Q18: =Q13+Q15+Q16 -> 8.8445699 | R18: =Q18 -> 8.8445699
A19: MVA | D19: 1.8558 | E19: 1.43 | F19: 3.207 | G19: 1.8558 | H19: 1.43 | I19: =2.84+0.1634 -> 3.0034 | J19: 1.8558 | K19: 1.43 | L19: =2.84+0.1634 -> 3.0034 | M19: 1.8558 | N19: 1.43 | O19: =2.84+0.1634 -> 3.0034 | P19: 1.8558 | Q19: 1.43 | R19: =2.84+0.1634 -> 3.0034 | S19: SG&A +Profit | T19: 0.75 | U19: 0.75 | V19: 0.75 | W19: 0.75 | Y19: MVA | Z19: 1.8517403 | AA19: =0.5+0.93+0.3 -> 1.73 | AB19: =0.38+1.29+1.17 -> 2.84 | AC19: 1.8517403 | AD19: =0.5+0.93+0.3 -> 1.73 | AE19: =0.38+1.29+1.17 -> 2.84 | AF19: 1.8517403 | AG19: =0.5+0.93+0.3 -> 1.73 | AH19: =0.38+1.29+1.17 -> 2.84 | AI19: 1.8517403 | AJ19: =0.5+0.93+0.3 -> 1.73 | AK19: =0.38+1.29+1.17 -> 2.84 | AL19: 031324: for VN, labor rate is 2.67 for TW, labor rate is 8.64 Produced in TW is based on SMT and pre assemblled in FD then assembly in TW
A20: PRIME COST (Matl + Labor): Black ver. | D20: =D17+D19 -> 10.37263 | E20: =E17+E19 -> 10.355844 | F20: =F17+F19 -> 11.839903 | G20: =G17+G19 -> 10.37263 | H20: =H17+H19 -> 10.271321 | I20: =I17+I19 -> 11.844721 | J20: =J17+J19 -> 10.372925 | K20: =K17+K19 -> 10.271628 | ... R20: =R17+R19 -> 11.659994 | S20: Total Cost (Ex-Factory): | T20: 11.755037 | U20: 12.071704 | V20: 11.935037 | W20: 12.258562 | Y20: Material Black | Z20: =Z12+Z14+Z16 -> 7.7297596 | AA20: =AA12+AA14+AA16 -> 8.0875662 | AB20: =AB12+AB14+AB16 -> 7.8199628 | AC20: =AC12+AC14+AC16 -> 7.7297596 | AD20: =AD12+AD14+AD16 -> 7.7297596 | AE20: =AE12+AE14+AE16 -> 7.7297596 | AF20: =AF12+AF14+AF16 -> 7.8167017 | AG20: =AG12+AG14+AG16 -> 7.8167017 | ... AK20: =AK12+AK14+AK16 -> 7.2859473
A21: PRIME COST (Matl + Labor): White ver. | D21: =D18+D19 -> 10.587984 | E21: =E18+E19 -> 10.579403 | F21: =F18+F19 -> 12.055257 | G21: =G18+G19 -> 10.587984 | H21: =H18+H19 -> 10.49488 | I21: =I18+I19 -> 12.06828 | J21: =J18+J19 -> 10.58828 | K21: =K18+K19 -> 10.495187 | ... R21: =R18+R19 -> 11.84797 | T21: Effective from Nov 1. 2022(new PO) | V21: Effective from Oct 1. 2021 | Y21: Material White | Z21: =Z13+Z15+Z16 -> 7.8615846 | AA21: =AA13+AA15+AA16 -> 8.2244136 | AB21: =AB13+AB15+AB16 -> 7.9517878 | AC21: =AC13+AC15+AC16 -> 7.8615846 | AD21: =AD13+AD15+AD16 -> 7.8615846 | AE21: =AE13+AE15+AE16 -> 7.8615846 | AF21: =AF13+AF15+AF16 -> 7.9485266 | AG21: =AG13+AG15+AG16 -> 7.9485266 | ... AK21: =AK13+AK15+AK16 -> 7.4647483
A22: SG&A +Profit | D22: 0.75 | E22: 0.75 | F22: 0.75 | G22: 0.75 | H22: 0.75 | I22: 0.75 | J22: 0.75 | K22: 0.75 | L22: 0.75 | M22: 0.75 | N22: 0.75 | O22: 0.75 | P22: 0.75 | Q22: 0.75 | R22: 0.75 | Z22: 0.75 | AA22: 0.75 | AB22: 0.75 | AC22: 0.75 | AD22: 0.75 | AE22: 0.75 | AF22: 0.75 | AG22: 0.75 | AH22: 0.75 | AI22: 0.75 | AJ22: 0.75 | AK22: 0.75
A23: Total Cost (Ex-Factory): Black ver. | D23: =SUM(D20,D22) -> 11.12263 | E23: =SUM(E20,E22) -> 11.105844 | F23: =SUM(F20,F22) -> 12.589903 | G23: =SUM(G20,G22) -> 11.12263 | H23: =SUM(H20,H22) -> 11.021321 | I23: =SUM(I20,I22) -> 12.594721 | J23: =SUM(J20,J22) -> 11.122925 | K23: =SUM(K20,K22) -> 11.021628 | ... R23: =SUM(R20,R22) -> 12.409994 | Y23: Material Black + MVA | Z23: =Z20+Z19 -> 9.5814999 | AA23: =AA20+AA19 -> 9.8175662 | AB23: =AB20+AB19 -> 10.659963 | AC23: =AC20+AC19 -> 9.5814999 | AD23: =AD20+AD19 -> 9.4597596 | AE23: =AE20+AE19 -> 10.56976 | AF23: =AF20+AF19 -> 9.668442 | AG23: =AG20+AG19 -> 9.5467017 | ... AK23: =AK20+AK19 -> 10.125947
A24: Total Cost (Ex-Factory): White ver. | D24: =SUM(D21,D22) -> 11.337984 | E24: =SUM(E21,E22) -> 11.329403 | F24: =SUM(F21,F22)-0.055 -> 12.750257 | G24: =SUM(G21,G22) -> 11.337984 | H24: =SUM(H21,H22) -> 11.24488 | I24: =SUM(I21,I22) -> 12.81828 | J24: =SUM(J21,J22) -> 11.33828 | K24: =SUM(K21,K22) -> 11.245187 | L24: =SUM(L21,L22) -> 12.818587 | M24: =SUM(M21,M22) -> 11.618503 | N24: =SUM(N21,N22) -> 11.536087 | ... R24: =SUM(R21,R22) -> 12.59797 | Y24: Material White + MVA | Z24: =Z21+Z19 -> 9.7133249 | AA24: =AA21+AA19 -> 9.9544136 | AB24: =AB21+AB19 -> 10.791788 | AC24: =AC21+AC19 -> 9.7133249 | AD24: =AD21+AD19 -> 9.5915846 | AE24: =AE21+AE19 -> 10.701585 | AF24: =AF21+AF19 -> 9.8002669 | AG24: =AG21+AG19 -> 9.6785266 | ... AK24: =AK21+AK19 -> 10.304748
Y25: Material margin (black) | Z25: =(G23-(Z12+Z14+Z16))/G23 -> 0.30504209 | AA25: =(H23-(AA12+AA14+AA16))/H23 -> 0.26618904 | AB25: =(I23-(AB12+AB14+AB16))/I23 -> 0.3791079 | AC25: =(J23-(AC12+AC14+AC16))/J23 -> 0.30506056 | AD25: =(K23-(AD12+AD14+AD16))/K23 -> 0.29867351 | AE25: =(L23-(AE12+AE14+AE16))/L23 -> 0.38628484 | AF25: =(M23-(AF12+AF14+AF16))/M23 -> 0.31451373 | AG25: =(N23-(AG12+AG14+AG16))/N23 -> 0.30902252 | ... AK25: =(R23-(AK12+AK14+AK16))/R23 -> 0.41289679
Y26: Gross margin (black) | Z26: =(D23-Z23)/D23 -> 0.13855805 | AA26: =(H23-AA23)/H23 -> 0.10922056 | AB26: =(I23-AB23)/I23 -> 0.1536166 | AC26: =(G23-AC23)/G23 -> 0.13855805 | AD26: =(K23-AD23)/K23 -> 0.14170941 | AE26: =(L23-AE23)/L23 -> 0.16079904 | AF26: =(M23-AF23)/M23 -> 0.15212522 | AG26: =(N23-AG23)/N23 -> 0.15609472 | AH26: =(O23-AH23)/O23 -> 0.17299692 | AI26: =(P23-AI23)/P23 -> 0.16510254 | AJ26: =(Q23-AJ23)/Q23 -> 0.16800912 | AK26: =(R23-AK23)/R23 -> 0.18404897
Y27: Material margin (white) | Z27: =(G24-(Z13+Z15+Z16))/G24 -> 0.3066153 | AA27: =(H24-(AA13+AA15+AA16))/H24 -> 0.26860816 | AB27: =(I24-(AB13+AB15+AB16))/I24 -> 0.37965252 | AC27: =(J24-(AC13+AC15+AC16))/J24 -> 0.30663339 | AD27: =(K24-(AD13+AD15+AD16))/K24 -> 0.3008934 | AE27: =(L24-(AE13+AE15+AE16))/L24 -> 0.38670428 | AF27: =(M24-(AF13+AF15+AF16))/M24 -> 0.31587341 | AG27: =(N24-(AG13+AG15+AG16))/N24 -> 0.31098587 | ... AK27: =(R24-(AK13+AK15+AK16))/R24 -> 0.40746419
Y28: Gross margin (white) | Z28: =(D24-Z24)/D24 -> 0.14329347 | AA28: =(H24-AA24)/H24 -> 0.11476036 | AB28: =(I24-AB24)/I24 -> 0.15809394 | AC28: =(G24-AC24)/G24 -> 0.14329347 | AD28: =(K24-AD24)/K24 -> 0.1470498 | AE28: =(L24-AE24)/L24 -> 0.165151 | AF28: =(M24-AF24)/M24 -> 0.15649484 | AG28: =(N24-AG24)/N24 -> 0.16102167 | AH28: =(O24-AH24)/O24 -> 0.17704431 | AI28: =(P24-AI24)/P24 -> 0.16261999 | AJ28: =(Q24-AJ24)/Q24 -> 0.16597669 | AK28: =(R24-AK24)/R24 -> 0.18203104
AC29: =AC20/J23 -> 0.69493944 | AF29: =AF20/M23 -> 0.68548627 | AI29: =AI20/P23 -> 0.66570659
AC30: =AC19/J23 -> 0.16647961 | AF30: =AF19/M23 -> 0.16238851 | AI30: =AI19/P23 -> 0.16919087

Sheet PKG BOM 20241119-TW
R1: 裕同 | S1: 旺盈 | V1: FD | X1: TW
A2: Steelseries Rival3 Gen2 RFQ - Package BOM list | M2: Date: 2024/6/18 | Q2: True Cost | AC2: True Cost | AJ2: 7.1
A3: Model Description: Steelseries Rival 3 Gen2 | K3: Rev.:A | L3: ELM5 Gen2 | P3: Difference between 1015 & 0618 | Q3: 2024/10/14 DV Phase | R3: 報價 in RMB w/ FSC certificate | V3: 報價 in USD w/ FSC certificate | X3: 報價 in USD w/ FSC certificate | AB3: Markup | AC3: EV Phase | AD3: 報價 in RMB w/ FSC certificate | AG3: 報價 in USD w/ FSC certificate | AI3: Markup | AJ3: Remark
A4: No. | B4: Level | C4: Foxlink P/N | D4: Foxlink P/N description | E4: Customer P/N | F4: Customer Description | H4: Image | I4: Description | J4: Chinese Part name | K4: Unit Q'ty (pcs) | L4: Unit Price (USD/pc) ELM5 Gen2 | M4: Amount (USD) ELM5 Gen2 | N4: Remark | Q4: QTY | R4: 單價 RMB | S4: 單價 RMB | T4: MOQ | U4: LT day | V4: 單價 USD | W4: Amount(USD) | X4: MOQ | Y4: LT day | Z4: 單價 USD | AA4: Amount(USD) | AC4: QTY | AD4: 單價 RMB | AE4: MOQ | AF4: LT day | AG4: 單價 USD | AH4: Amount(USD)
A5: 1 | B5: 1 | C5: 584A-1053-00A0 | D5: BOX,ELM5 Gen2/FSG-E1J7,62515 RIVAL3 GEN2 BLACK, 153x86x46mm,300gsm SBS,FSC,RoHS | E5: N/A | F5: black Box | G5: material: 300g artpaper, 4C+1C PMS, printing: matte PP dimension：278x250mm | I5: Box Outside set-up dimensions:(LxWxD):153x86x46mm Flat sheet dimensions:(L)278x(W)250x(T)0.5mm Material:350gsm SBS Print: 4C+1C PMS Surface process: AQ Coating Joint: Glued inside Remark:包装原料需符合FSC认证要求 | J5: 彩盒 | K5: 1 | L5: 0.3033 | M5: =L5*K5 -> 0.3033 | N5: 031324: Paper with FSC certificate was 0.2821 | P5: =W5-AH5 -> 0.053561368 | Q5: 1 | R5: 1.42 | S5: 1.4 | T5: 5000 | U5: =AF5 -> 14 | V5: 0.20285714 | W5: =V5*K5 -> 0.20285714 | X5: 5000 | Z5: =V5 -> 0.20285714 | AA5: =Z5*K5 -> 0.20285714 | AB5: =(M5-W5)/W5 -> 0.49514085 | AC5: 1 | AD5: 1.06 | AE5: 5000 | AF5: 14 | AG5: =AD5/$AJ$2 -> 0.14929577 | AH5: =AG5*K5 -> 0.14929577 | AI5: =(L5-AG5)/AG5 -> 1.0315377 | AJ5: difference between FSC and w/o FSC
A6: 2 | C6: 5831-1053-00A0 | D6: CARD,ELM5 Gen2/FSG-E1J7,HANG TAB,350GSM SBS DOUBLE,AQ COATING,FSC,RoHS | E6: N/A | F6: Hanger | I6: Hang tab Outside dimensions:(LxW):64x38mm Material: 350gsm SBS对裱 Print: 1C (Pantone 1655C) Surface process: AQ Coating Other: Back side with Double sided tape (60x10mm) Remark:包装原料需符合FSC认证要求 | J6: 掛鉤 | K6: 1 | L6: 0.13994366 | M6: =L6*K6 -> 0.13994366 | P6: =W6-AH6 -> 0.0018792757 | Q6: 1 | R6: 0.934 | T6: 5000 | U6: =AF6 -> 14 | V6: 0.13342857 | W6: =V6*K6 -> 0.13342857 | X6: 5000 | Y6: =AJ6 -> 0 | Z6: =V6 -> 0.13342857 | AA6: =Z6*K6 -> 0.13342857 | AB6: =(M6-W6)/W6 -> 0.048828302 | AC6: 1 | AD6: 0.934 | AE6: 5000 | AF6: 14 | AG6: =AD6/$AJ$2 -> 0.1315493 | AH6: =AG6*K6 -> 0.1315493 | AI6: =(L6-AG6)/AG6 -> 0.063811563
A7: 3 | B7: 1 | C7: 5843-1053-00A0 | D7: CARDBOARD,ELM5 Gen2/FSG-E1J7,PAPER INSERT,KRAFT E FLUET,RoHS | E7: N/A | F7: paper insert | G7: material: E flute corrugated paper board, original color extension dimension：296x152mm | I7: Paper insert Outside dimensions:(LxWxD):318x154mm Material:E flute corrugated paper board, original color Process: Die-cut Remark:包装原料需符合FSC认证要求 | J7: 内纸卡 | K7: 1 | L7: 0.088715493 | M7: =L7*K7 -> 0.088715493 | N7: 031324: Paper with FSC certificate 鴻威測試OK | P7: =W7-AH7 -> 0.0017847082 | Q7: 1 | R7: 0.53 | T7: 5000 | U7: =AF7 -> 14 | V7: 0.075714286 | W7: =V7*K7 -> 0.075714286 | X7: 5000 | Z7: =V7 -> 0.075714286 | AA7: =Z7*K7 -> 0.075714286 | AB7: =(M7-W7)/W7 -> 0.17171406 | AC7: 1 | AD7: 0.5249 | AE7: 3000 | AF7: 14 | AG7: =AD7/$AJ$2 -> 0.073929577 | AH7: =AG7*K7 -> 0.073929577 | AI7: =(L7-AG7)/AG7 -> 0.2 | AJ7: difference between FSC and w/o FSC
A8: 4 | B8: 1 | C8: 5849-1053-04A0 | D8: LABEL,ELM5 Gen2/FSG-E1J7,BTS LABEL,RIVAL 3 GEN2,DIAMETER 30mm, TRANSPARENT WOOD PULP PAPER,RoHS | E8: N/A | F8: Seal label | J8: 封口贴 | K8: 1 | L8: 0.02 | M8: =L8*K8 -> 0.02 | P8: =W8-AH8 -> 0.0059 | Q8: 1 | R8: 0.1115 | T8: 10000 | U8: 21-28 | V8: 0.0159 | W8: =V8*K8 -> 0.0159 | X8: 10000 | Y8: 21-28 | Z8: =V8 -> 0.0159 | AA8: =Z8*K8 -> 0.0159 | AB8: =(M8-W8)/W8 -> 0.25786164 | AC8: 2 | AD8: 0.071 | AE8: 5000 | AF8: 14 | AG8: =AD8/$AJ$2 -> 0.01 | AH8: =AG8*K8 -> 0.01 | AI8: =(L8-AG8)/AG8 -> 1 | AJ8: 022724:true cost update
A9: 5 | B9: 1 | C9: 5831-1053-04A0 （global） 5831-1053-05A0（CA) | D9: MANUAL,ELM5 Gen2/FSG-E1J7,RIVAL3 GEN2,100x80mm,80GSM WFUC,FSC,RoHS | E9: N/A | F9: PIG | G9: material: 80g woodfree paper; dimension: 320 x 200 mm, printing: 2C double side printing type: folding paper | I9: Manual Flat sheet dimensions(LxW): (L)320*(W)200mm Fold size: 80*100mm Material : 80gsm WFUC Print: 2C double side printing Process: Folding X 4 Remark:包装原料需符合FSC认证要求 | J9: 说明书 | K9: 1 | L9: 0.12 | M9: =L9*K9 -> 0.12 | N9: 031324: Paper with FSC certificate was 0.0584 | P9: =W9-AH9 -> 0.00058148893 | Q9: 1 | R9: 0.289 | S9: 0.35 | T9: 5000 | U9: =AF9 -> 14 | V9: 0.041285714 | W9: =V9*K9 -> 0.041285714 | X9: 10000 | Y9: 21 | Z9: 0.12 | AA9: =Z9*K9 -> 0.12 | AB9: =(M9-W9)/W9 -> 1.9065744 | AC9: 1 | AD9: 0.289 | AE9: 5000 | AF9: 14 | AG9: =AD9/$AJ$2 -> 0.040704225 | AH9: =AG9*K9 -> 0.040704225 | AI9: =(L9-AG9)/AG9 -> 1.9480969 | AJ9: difference between FSC and w/o FSC
A10: 6 | B10: 1 | C10: 5845-1053-00A0 | D10: BAG,ELM5 Gen2/FSG-E1J7,PAPER SHEET,16GSM MG TISSUE PAPER,FSC,RoHS | E10: N/A | F10: PE bag for mouse | I10: Paper sheet Dimensions(LxW):(L)280x(W)220mm Material : 16gsm 雪梨纸 Print: N/A | J10: 雪梨紙（包鼠標) | K10: 2 | L10: 0.012 | M10: =L10*K10 -> 0.024 | P10: =W10-AH10 -> -0.30905433 | Q10: 2 | R10: 0.2 | T10: 5000 | U10: =AF10 -> 15 | V10: 0.028571429 | W10: =V10*K10 -> 0.057142857 | X10: 5000 | Y10: =AJ10 -> 0 | Z10: =V10 -> 0.028571429 | AA10: =Z10*K10 -> 0.057142857 | AB10: =(M10-W10)/W10 -> -0.58 | AC10: 1 | AD10: 1.3 | AE10: 10000 | AF10: 15 | AG10: =AD10/$AJ$2 -> 0.18309859 | AH10: =AG10*K10 -> 0.36619718 | AI10: =(L10-AG10)/AG10 -> -0.93446154
A11: 7 | B11: 1 | C11: 5842-1047-00AA | D11: CARTON,ELM5/FSG-E1J4,MASTER CARTON,182x149x178mm,KRAFT C FLUET,REMOVE SS LOGO,RoHS | E11: N/A | F11: Master Carton | G11: material: B flute, burst above 12KGF | I11: Carton Outside dimensions:(L)182X(W)149X(H)175mm; Material: A. Material type: Corrugated fibreboard B. Flute: C Flute C. Grade: 200# Mullen Burst OR 32 ECT Print: Black Joint: Glued inside Remark: 纸板原材料需符合FSC认证要求 | J11: 外箱 | K11: =1/6 -> 0.16666667 | L11: 0.32425352 | M11: =L11*K11 -> 0.054042254 | N11: 031324: Paper with FSC certificate | P11: =W11-AH11 -> -0.017654259 | Q11: 0.16666667 | R11: 1.15 | T11: 5000 | U11: =AF11 -> 15 | V11: 0.16428571 | W11: =V11*K11 -> 0.027380952 | X11: 10000 | Y11: 21 | Z11: 0.191 | AA11: =Z11*K11 -> 0.031833333 | AB11: =(M11-W11)/W11 -> 0.97371709 | AC11: 0.16666667 | AD11: 1.9185 | AE11: 500 | AF11: 15 | AG11: =AD11/$AJ$2 -> 0.27021127 | AH11: =AG11*K11 -> 0.045035211 | AI11: =(L11-AG11)/AG11 -> 0.2 | AJ11: difference between FSC and w/o FSC
A12: 8 | B12: 1 | C12: 5843-1047-01A0 | D12: CARDBOARD,ELM5/FSG-E1J4,T/B BOARD,171x138mm,KRAFT B FLUET,RoHS | E12: N/A | F12: carton TB board | G12: B/F, burst above 10KGF(inside the carton top and bottom) | I12: Paper board Dimension(LxW): (L)171x(W)138mm Material: B flute 12kgf Remark: 纸板原材料需符合FSC认证要求 | J12: 天地板 | K12: =2/6 -> 0.33333333 | L12: 0.088235294 | M12: =L12*K12 -> 0.029411765 | P12: =W12-AH12 -> 0.00011401744 | Q12: 0.33333333 | R12: 0.17 | T12: 5000 | U12: =AF12 -> 14 | V12: 0.024285714 | W12: =V12*K12 -> 0.0080952381 | X12: 10000 | Y12: 21 | Z12: 0.027 | AA12: =Z12*K12 -> 0.009 | AB12: =(M12-W12)/W12 -> 2.633218 | AC12: 0.33333333 | AD12: 0.17 | AE12: 500 | AF12: 14 | AG12: =AD12/$AJ$2 -> 0.023943662 | AH12: =AG12*K12 -> 0.0079812207 | AI12: =(L12-AG12)/AG12 -> 2.6851211
A13: 9 | B13: 1 | C13: 5831-1053-01A0 | D13: CARD,ELM5 Gen2/FSG-E1J7,PAPER FILM,16GSM MG TISSUE PAPER,PROTECTIVE FOR BOX,FSC,RoHS | E13: N/A | F13: Protective paper | I13: Protective paper Dimensions(LxW):(L)1092x(W)180mm Material : 16gsm 雪梨纸 Print: N/A | J13: 雪梨紙（包彩盒) | K13: 0.33333333 | L13: 0.0154 | M13: =L13*K13 -> 0.0051333333 | P13: =W13-AH13 -> -0.04167002 | Q13: 0.33333333 | R13: 0.38 | T13: 5000 | U13: =AF13 -> 28 | V13: 0.054285714 | W13: =V13*K13 -> 0.018095238 | X13: 5000 | Z13: =V13 -> 0.054285714 | AA13: =Z13*K13 -> 0.018095238 | AB13: =(M13-W13)/W13 -> -0.71631579 | AC13: 0.33333333 | AD13: 1.273 | AE13: 5000 | AF13: 28 | AG13: =AD13/$AJ$2 -> 0.17929577 | AH13: =AG13*K13 -> 0.059765258 | AI13: =(L13-AG13)/AG13 -> -0.91410841 | AJ13: 022724:true cost update
A14: 10 | B14: 1 | C14: 5849-1051-0AA0 | D14: LABEL,KINGPIN/FCG-3301,4"W x 6"L WHITE,PAPER LABEL,47-00034,RoHS | E14: N/A | F14: Label (for master carton) | G14: material: 80g art paper dimension：100x55 mm printing: 1C with online printing | I14: Master Carton Label Outside dimensions:(L)152X(W)102mm; Material : 80gsm artpaper Print: Black | J14: 外箱标签 | K14: =1/6 -> 0.16666667 | L14: 0.024264706 | M14: =L14*K14 -> 0.0040441176 | P14: =W14-AH14 -> 4.8960429e-05 | Q14: 0.16666667 | R14: 0.146 | T14: 5000 | U14: =AF14 -> 15 | V14: 0.020857143 | W14: =V14*K14 -> 0.0034761905 | X14: 5000 | Y14: =AJ14 -> 0 | Z14: =V14 -> 0.020857143 | AA14: =Z14*K14 -> 0.0034761905 | AB14: =(M14-W14)/W14 -> 0.16337631 | AC14: 0.16666667 | AD14: 0.146 | AE14: 5000 | AF14: 15 | AG14: =AD14/$AJ$2 -> 0.02056338 | AH14: =AG14*K14 -> 0.00342723 | AI14: =(L14-AG14)/AG14 -> 0.17999597
A15: 11 | B15: 1 | C15: 5849-1047-02A0 | D15: LABEL,ELM5/FSG-E1J4,MASTER CARTON SN LABEL,59.67x52mm,80GMS ARTPAPER,RoHS | E15: N/A | F15: S/N label for carton (for master carton) | G15: material: 80g art paper dimension：59.67x52 mm printing: blank with online printing | I15: Carton Label(SN) Outside dimensions: (L)59.67X(W)52mm; Material : 80gsm artpaper | J15: 外箱标签 | K15: =1/6 -> 0.16666667 | L15: 0.0097058824 | M15: =L15*K15 -> 0.0016176471 | P15: =W15-AH15 -> 1.9450034e-05 | Q15: 0.16666667 | R15: 0.058 | T15: 5000 | U15: =AF15 -> 15 | V15: 0.0082857143 | W15: =V15*K15 -> 0.0013809524 | X15: 5000 | Y15: =AJ15 -> 0 | Z15: =V15 -> 0.0082857143 | AA15: =Z15*K15 -> 0.0013809524 | AB15: =(M15-W15)/W15 -> 0.17139959 | AC15: 0.16666667 | AD15: 0.058 | AE15: 5000 | AF15: 15 | AG15: =AD15/$AJ$2 -> 0.0081690141 | AH15: =AG15*K15 -> 0.0013615023 | AI15: =(L15-AG15)/AG15 -> 0.18813387
A16: 12 | B16: 1 | C16: 5849-1047-01A0 | D16: LABEL,NINJA/FSG-E1J0,RETAIL BOX LABEL,38x12mm,80GMS ARTPAPER,BLANK,RoHS | E16: N/A | F16: SN Label (for color box) | G16: material: 80g art paper dimension: 38x12mm printing: blank with online printing | I16: Color box SN Label Outside dimensions: (L)38X(W)12mm; Material : 80gsm artpaper | J16: 彩盒标签 | K16: 1 | L16: 0.0056617647 | M16: =L16*K16 -> 0.0056617647 | P16: =W16-AH16 -> 2.0120724e-05 | Q16: 1 | R16: 0.01 | T16: 5000 | U16: =AF16 -> 15 | V16: 0.0014285714 | W16: =V16*K16 -> 0.0014285714 | X16: 5000 | Y16: =AJ16 -> 0 | Z16: =V16 -> 0.0014285714 | AA16: =Z16*K16 -> 0.0014285714 | AB16: =(M16-W16)/W16 -> 2.9632353 | AC16: 1 | AD16: 0.01 | AE16: 5000 | AF16: 15 | AG16: =AD16/$AJ$2 -> 0.0014084507 | AH16: =AG16*K16 -> 0.0014084507 | AI16: =(L16-AG16)/AG16 -> 3.0198529
A17: 13 | B17: 1 | C17: 5849-1053-02A0 黑色 5849-1053-03A0 白色 | D17: LABEL,ELM5 Gen2/FSG-E1J7,PID LABEL,62515 RIVAL 3 GEN2 BLACK,45.424x23mm, 50 PET WITH MATT PP,RoHS | E17: N/A | F17: PID label (for black product) | G17: material: 80g black PET+ printable matte pp film dimension:45.424x23 mm printing: 2C | I17: PID Label Outside dimensions: (L)45.424X(W)23mm; Material : 50#PET+25# PP film Print: 2C | J17: PID标签 | K17: 1 | L17: 0.08 | M17: =L17*K17 -> 0.08 | P17: =W17-AH17 -> 0.00030181087 | Q17: 1 | R17: 0.15 | T17: 10000 | U17: =AF17 -> 15 | V17: 0.021428571 | W17: =V17*K17 -> 0.021428571 | X17: 10000 | Y17: 21 | Z17: 0.08 | AA17: =Z17*K17 -> 0.08 | AB17: =(M17-W17)/W17 -> 2.7333333 | AC17: 1 | AD17: 0.15 | AE17: 5000 | AF17: 15 | AG17: =AD17/$AJ$2 -> 0.021126761 | AH17: =AG17*K17 -> 0.021126761 | AI17: =(L17-AG17)/AG17 -> 2.7866667 | AJ17: 022724:true cost update
A18: 14 | B18: 1 | C18: 5849-1012-05A0 | D18: LABEL,MICKEY,VK481AA ABA INNER CARTON LABEL 153*102mm,80GSM ARTPAPER,RoHS | E18: N/A | F18: Pallet label | G18: Label,Pallet,AP,153x102mm | H18: N/A | I18: Pallet Label Outside dimensions: (L)153X(W)102mm; Material : 80gsm artpaper | J18: 棧板标签 | K18: 0.001587 | L18: 0.026691176 | M18: =L18*K18 -> 4.2358897e-05 | P18: =W18-AH18 -> 4.3107646e-07 | Q18: 0.001587 | R18: 0.135 | T18: 5000 | U18: =AF18 -> 7 | V18: 0.019285714 | W18: =V18*K18 -> 3.0606429e-05 | X18: 5000 | Y18: =AJ18 -> 0 | Z18: =V18 -> 0.019285714 | AA18: =Z18*K18 -> 3.0606429e-05 | AB18: =(M18-W18)/W18 -> 0.38398693 | AC18: 0.0013333333 | AD18: 0.135 | AE18: 5000 | AF18: 7 | AG18: =AD18/$AJ$2 -> 0.019014085 | AH18: =AG18*K18 -> 3.0175352e-05 | AI18: =(L18-AG18)/AG18 -> 0.40375817
A19: 15 | B19: 1 | C19: 5849-1043-00A0 | D19: LABEL,NINJA/FSG-E1J0,LABEL FOR USB CABLE,66.4x15.3mm,80GMS ARTPAPER WITH MATTE PP FILM TWO SIDE,ADHESIVE,BLANK PRINGING,RoHS | E19: N/A | F19: Cable Tag | G19: material: 80g art paper, matte coating(with glue) dimension：66.073x15 mm printing: blank | I19: Cable tag Outside dimensions: (L)66.4X(W)15.3mm; Material : 80gsm artpaper, matte coating(with glue) | J19: USB標籤 | K19: 1 | L19: 0.0127 | M19: =L19*K19 -> 0.0127 | P19: =W19-AH19 -> 0.00014084507 | Q19: 1 | R19: 0.07 | T19: 5000 | U19: =AF19 -> 14 | V19: 0.01 | W19: =V19*K19 -> 0.01 | X19: 5000 | Y19: =AJ19 -> 0 | Z19: =V19 -> 0.01 | AA19: =Z19*K19 -> 0.01 | AB19: =(M19-W19)/W19 -> 0.27 | AC19: 1 | AD19: 0.07 | AE19: 5000 | AF19: 14 | AG19: =AD19/$AJ$2 -> 0.0098591549 | AH19: =AG19*K19 -> 0.0098591549 | AI19: =(L19-AG19)/AG19 -> 0.28814286
A20: 16 | B20: 1 | C20: 0981-53PN-00A0 | D20: PALLET,Hoist Gen2/FSG-E3J4,FLEX STYLE PALLET,1200x1000x130 mm,PLYWOOD,RoHS | E20: N/A | F20: Pallet & related | G20: pallet packing material Pallet | I20: PALLET,Hoist Gen2/FSG-E3J4,FLEX STYLE PALLET,1200x1000x130 mm,PLYWOOD,RoHS | J20: 膠合棧板 | K20: 0.000794 | L20: 15.71 | M20: =L20*K20 -> 0.01247374 | P20: =W20-AH20 -> -0.0028072773 | Q20: 0.000794 | R20: 76.8 | T20: 100 | U20: =AF20 -> 15 | V20: 10.971429 | W20: =V20*K20 -> 0.0087113143 | X20: 100 | Y20: =AJ20 -> 0 | Z20: =V20 -> 10.971429 | AA20: =Z20*K20 -> 0.0087113143 | AB20: =(M20-W20)/W20 -> 0.43190104 | AC20: 0.0013333333 | AD20: 103 | AE20: 100 | AF20: 15 | AG20: =AD20/$AJ$2 -> 14.507042 | AH20: =AG20*K20 -> 0.011518592 | AI20: =(L20-AG20)/AG20 -> 0.08292233
A21: 17 | B21: 1 | C21: 0984-001E-00A0 | D21: CARDBOARD,SLIP SHEET,CORRUGATED, B/C DOUBLEWALL, 1200MM X 1000MM,BC FLUTE,RoHS | E21: N/A | F21: Card Board | G21: N/A | H21: N/A | I21: Card Board Dimension: 1200x1000mm | J21: 隔板 | K21: =2/1260 -> 0.0015873016 | L21: 1.4041176 | M21: =L21*K21 -> 0.0022287582 | P21: =W21-AH21 -> 2.3186739e-05 | Q21: 0.0015873016 | R21: 7.26 | T21: 5000 | U21: =AF21 -> 14 | V21: 1.0371429 | W21: =V21*K21 -> 0.0016462585 | X21: 10000 | Y21: 21 | Z21: 1.2 | AA21: =Z21*K21 -> 0.0019047619 | AB21: =(M21-W21)/W21 -> 0.35383244 | AC21: 0.0015873016 | AD21: 7.26 | AE21: 100 | AF21: 14 | AG21: =AD21/$AJ$2 -> 1.0225352 | AH21: =AG21*K21 -> 0.0016230718 | AI21: =(L21-AG21)/AG21 -> 0.37317291
A22: 18 | B22: 1 | C22: 0984-1047-00A0 | D22: CARDBOARD,ELM5/FSG-E1J4,CORRUGATED, B FLUTE,1175x993 mm,RoHS | E22: N/A | F22: Card Board | G22: N/A | H22: N/A | I22: Card Board Dimension: 1175x993 mm | J22: 隔板 | K22: =4/1260 -> 0.0031746032 | L22: 0.48028169 | M22: =L22*K22 -> 0.0015247038 | P22: =W22-AH22 -> 2.1781483e-05 | Q22: 0.0031746032 | R22: 3.41 | T22: 1000 | U22: =AF22 -> 15 | V22: 0.48714286 | W22: =V22*K22 -> 0.0015464853 | X22: 10000 | Y22: 21 | Z22: 0.564 | AA22: =Z22*K22 -> 0.0017904762 | AB22: =(M22-W22)/W22 -> -0.014084507 | AC22: 0.0031746032 | AD22: 3.41 | AE22: 100 | AF22: 15 | AG22: =AD22/$AJ$2 -> 0.48028169 | AH22: =AG22*K22 -> 0.0015247038 | AI22: =(L22-AG22)/AG22 -> -2.3116081e-16 | AJ22: 022724:true cost update
A23: 19 | B23: 1 | C23: 0984-001H-00A0 | D23: CARDBOARD,PAPER ANGLE BEAD,1025X50X50mm,THICKNESS 5mm,KRAFT PAPER,RoHS | E23: N/A | F23: Corner Board | G23: N/A | H23: N/A | I23: Corner Board Dimension:1025X50X50mm | J23: 護角 | K23: 0.003175 | L23: 0.32676471 | M23: =L23*K23 -> 0.0010374779 | P23: =W23-AH23 -> 1.2904427e-05 | Q23: 0.003175 | R23: 2.02 | T23: 5000 | U23: =AF23 -> 15 | V23: 0.28857143 | W23: =V23*K23 -> 0.00091621429 | X23: 5000 | Y23: =AJ23 -> 0 | Z23: =V23 -> 0.28857143 | AA23: =Z23*K23 -> 0.00091621429 | AB23: =(M23-W23)/W23 -> 0.13235294 | AC23: 0.0063492063 | AD23: 2.02 | AE23: 1000 | AF23: 15 | AG23: =AD23/$AJ$2 -> 0.28450704 | AH23: =AG23*K23 -> 0.00090330986 | AI23: =(L23-AG23)/AG23 -> 0.14852941
A24: 20 | B24: 1 | C24: 0984-001J-00A0 | D24: CARDBOARD,PAPER ANGLE BEAD,900X50X50mm,THICKNESS 5mm,KRAFT PAPER,RoHS | E24: N/A | F24: Corner Board | G24: N/A | H24: N/A | I24: Corner Board Dimension:900X50X50mm | J24: 護角 | K24: 0.00635 | L24: 0.28632353 | M24: =L24*K24 -> 0.0018181544 | P24: =W24-AH24 -> 2.2614688e-05 | Q24: 0.00635 | R24: 1.77 | T24: 5000 | U24: =AF24 -> 15 | V24: 0.25285714 | W24: =V24*K24 -> 0.0016056429 | X24: 5000 | Y24: =AJ24 -> 0 | Z24: =V24 -> 0.25285714 | AA24: =Z24*K24 -> 0.0016056429 | AB24: =(M24-W24)/W24 -> 0.13235294 | AC24: 0.0031746032 | AD24: 1.77 | AE24: 1000 | AF24: 15 | AG24: =AD24/$AJ$2 -> 0.24929577 | AH24: =AG24*K24 -> 0.0015830282 | AI24: =(L24-AG24)/AG24 -> 0.14852941
A25: 21 | B25: 1 | C25: 0952-0004-0001 | D25: OC,DEPLETION,TAPE,SEAL,48mm*45m, | E25: N/A | F25: Seal tape_Clear | G25: N/A | H25: N/A | I25: OC,DEPLETION,TAPE,SEAL,48mm*45m, | J25: 透明封箱膠帶 | K25: 0.002222 | L25: 6.1352113 | M25: =L25*K25 -> 0.013632439 | P25: =W25-AH25 -> -0.0019116353 | Q25: 0.002222 | R25: 5.02 | T25: 100 | U25: =AF25 -> 15 | V25: 0.71714286 | W25: =V25*K25 -> 0.0015934914 | X25: 100 | Z25: =V25 -> 0.71714286 | AA25: =Z25*K25 -> 0.0015934914 | AB25: =(M25-W25)/W25 -> 7.5550755 | AC25: 0.005 | AD25: 11.2 | AE25: 900 | AF25: 15 | AG25: =AD25/$AJ$2 -> 1.5774648 | AH25: =AG25*K25 -> 0.0035051268 | AI25: =(L25-AG25)/AG25 -> 2.8892857 | AJ25: New
A26: 22 | B26: 1 | C26: 0952-0005-00E0 | D26: INK RIBBON,DEPLETION,B110A,110MM,LF | E26: N/A | F26: INK RIBBON | G26: N/A | H26: N/A | I26: INK RIBBON,DEPLETION,B110A,110MM,LF | J26: 碳带 | K26: 0.00103 | L26: 9.8873239 | M26: =L26*K26 -> 0.010183944 | P26: =W26-AH26 -> 0.00019480885 | Q26: 0.00103 | R26: 59 | T26: 10 | U26: =AF26 -> 7 | V26: 8.4285714 | W26: =V26*K26 -> 0.0086814286 | X26: 10 | Z26: =V26 -> 8.4285714 | AA26: =Z26*K26 -> 0.0086814286 | AB26: =(M26-W26)/W26 -> 0.17307233 | AC26: 0.000217 | AD26: 58.5 | AE26: 10 | AF26: 7 | AG26: =AD26/$AJ$2 -> 8.2394366 | AH26: =AG26*K26 -> 0.0084866197 | AI26: =(L26-AG26)/AG26 -> 0.2 | AJ26: New
A27: 23 | B27: 1 | C27: 0952-0002-00E0 | D27: INK RIBBON,DEPLETION,TW10,60MM,LF | E27: N/A | F27: INK RIBBON | G27: N/A | H27: N/A | I27: INK RIBBON,DEPLETION,TW10,60MM,LF | J27: 碳带 | K27: 0.000118 | L27: 5.3543662 | M27: =L27*K27 -> 0.00063181521 | P27: =W27-AH27 -> 1.2915895e-05 | Q27: 0.000118 | R27: 32 | T27: 10 | U27: =AF27 -> 7 | V27: 4.5714286 | W27: =V27*K27 -> 0.00053942857 | X27: 10 | Z27: =V27 -> 4.5714286 | AA27: =Z27*K27 -> 0.00053942857 | AB27: =(M27-W27)/W27 -> 0.17126761 | AC27: 0.000118 | AD27: 31.68 | AE27: 10 | AF27: 7 | AG27: =AD27/$AJ$2 -> 4.4619718 | AH27: =AG27*K27 -> 0.00052651268 | AI27: =(L27-AG27)/AG27 -> 0.2 | AJ27: New
A28: 24 | B28: 1 | C28: 0952-000N-00A0 | D28: INK RIBBON,DEPLETION,DMX480 BLACK,50MM*300M,RoHS | E28: N/A | F28: INK RIBBON | G28: N/A | H28: N/A | I28: INK RIBBON,DEPLETION,DMX480 BLACK,50MM*300M,RoHS | J28: 碳带 | K28: 0.0001 | L28: 7.6394366 | M28: =L28*K28 -> 0.00076394366 | P28: =W28-AH28 -> 0.00016338028 | Q28: 0.0001 | R28: 56 | T28: 10 | U28: =AF28 -> 7 | V28: 8 | W28: =V28*K28 -> 0.0008 | X28: 10 | Z28: =V28 -> 8 | AA28: =Z28*K28 -> 0.0008 | AB28: =(M28-W28)/W28 -> -0.045070423 | AC28: 0.0001 | AD28: 45.2 | AE28: 50 | AF28: 7 | AG28: =AD28/$AJ$2 -> 6.3661972 | AH28: =AG28*K28 -> 0.00063661972 | AI28: =(L28-AG28)/AG28 -> 0.2 | AJ28: New
A29: 25 | B29: 1 | C29: 0952-000S-00E0 | D29: OC,DEPLETION,TAPE,SEAL(400m*500mm*0.018cm),RoHS | E29: N/A | F29: Tape | G29: N/A | H29: N/A | I29: OC,DEPLETION,TAPE,SEAL(400m*500mm*0.018cm),RoHS | J29: 打包膜 | K29: 0.00045 | L29: 6.1352113 | M29: =L29*K29 -> 0.0027608451 | P29: =W29-AH29 -> 1.3581489e-05 | Q29: 0.00045 | R29: 36 | T29: 100 | U29: =AF29 -> 10 | V29: 5.1428571 | W29: =V29*K29 -> 0.0023142857 | X29: 100 | Z29: =V29 -> 5.1428571 | AA29: =Z29*K29 -> 0.0023142857 | AB29: =(M29-W29)/W29 -> 0.19295775 | AC29: 0.00045 | AD29: 36.3 | AE29: 500 | AF29: 10 | AG29: =AD29/$AJ$2 -> 5.1126761 | AH29: =AG29*K29 -> 0.0023007042 | AI29: =(L29-AG29)/AG29 -> 0.2 | AJ29: New
A30: 26 | B30: 1 | C30: 098C-1053-00A0 | D30: DESICCANT,ELM5 Gen2/FSG-E1J7,45X35MM-2G,RoHS | E30: N/A | F30: DESICCANT | G30: N/A | I30: DESICCANT Outside dimensions: (L)45X(W)35mm; Material : SiO2 乾燥劑, 2g/包 | J30: 乾燥劑 | K30: 1 | L30: 0.0085 | M30: =L30*K30 -> 0.0085 | P30: =W30-AH30 -> 0.007 | Q30: 1 | R30: 0.49 | T30: 15000 | U30: 14 | V30: 0.007 | W30: =V30*K30 -> 0.007 | X30: 15000 | Y30: 14 | Z30: =V30 -> 0.007 | AA30: =Z30*K30 -> 0.007 | AB30: =(M30-W30)/W30 -> 0.21428571 | AC30: 0.00045 | AD30: 36.3 | AE30: 500 | AF30: 10 | AH30: =AG30*K30 -> 0 | AI30: =(L30-AG30)/AG30 -> #DIV/0! | AJ30: New
A31: 27 | B31: 1 | C31: 0952-000T-00E0 | D31: TAPE,12mm*30y,LF | E31: N/A | F31: Tape | G31: N/A | H31: N/A | I31: TAPE,12mm*30y,LF | J31: 小膠帶 | K31: 0.002 | L31: 0 | M31: =L31*K31 -> 0 | P31: =W31-AH31 -> -0.010116781 | Q31: 0.002 | R31: 0.38 | T31: 1000 | U31: =AF31 -> 10 | V31: 0.054285714 | W31: =V31*K31 -> 0.00010857143 | X31: 1000 | Z31: =V31 -> 0.054285714 | AA31: =Z31*K31 -> 0.00010857143 | AB31: =(M31-W31)/W31 -> -1 | AC31: 0.00045 | AD31: 36.3 | AE31: 500 | AF31: 10 | AG31: =AD31/$AJ$2 -> 5.1126761 | AH31: =AG31*K31 -> 0.010225352 | AI31: =(L31-AG31)/AG31 -> -1 | AJ31: New
A32: Subtotal(USD/Unit)： | M32: =SUM(M5:M31) -> 0.94416822 | N32: 022724: ex rate 7.1 ex rate: 6.3 RMB | P32: =SUM(P22:P30) -> 0.0055303518 | W32: =SUM(W5:W31) -> 0.65310801 | AA32: =SUM(AA5:AA31) -> 0.79625336 | AB32: =(M32-W32)/W32 -> 0.44565401 | AG32: =AD32/$AJ$2 -> 0 | AH32: =SUM(AH22:AH29) -> 0.019466625 | AI32: =(M32-AH32)/AH32 -> 47.501896 | AJ32: Margin
A33: Subtotal(USD/Unit)： | N33: New ex rate 7 | AH33: -0.39967817 | AI33: -0.95355632 | AJ33: cost up due to FSC & sustainable material

Sheet PKG BOM 20241023_Amber
S1: 裕同 | T1: 旺盈
A2: Steelseries Rival3 Gen2 RFQ - Package BOM list | M2: Date: 2024/6/18 | R2: True Cost | Z2: True Cost | AG2: 7.1
A3: Model Description: Steelseries Rival 3 Gen2 | K3: Rev.:A | L3: ELM5 Gen2 | Q3: Difference between 1015 & 0618 | R3: 2024/10/14 DV Phase | S3: 報價 in RMB w/ FSC certificate | W3: 報價 in USD w/ FSC certificate | Y3: Markup | Z3: EV Phase | AA3: 報價 in RMB w/ FSC certificate | AD3: 報價 in USD w/ FSC certificate | AF3: Markup | AG3: Remark
A4: No. | B4: Level | C4: Foxlink P/N | D4: Foxlink P/N description | E4: Customer P/N | F4: Customer Description | H4: Image | I4: Description | J4: Chinese Part name | K4: Unit Q'ty (pcs) | L4: Unit Price (USD/pc) ELM5 Gen2 | M4: Amount (USD) ELM5 Gen2 | N4: Remark | R4: QTY | S4: 單價 RMB | T4: 單價 RMB | U4: MOQ | V4: LT day | W4: 單價 USD | X4: Amount(USD) | Z4: QTY | AA4: 單價 RMB | AB4: MOQ | AC4: LT day | AD4: 單價 USD | AE4: Amount(USD)
A5: 1 | B5: 1 | C5: 584A-1053-00A0 | D5: BOX,ELM5 Gen2/FSG-E1J7,62515 RIVAL3 GEN2 BLACK, 153x86x46mm,300gsm SBS,FSC,RoHS | E5: N/A | F5: black Box | G5: material: 300g artpaper, 4C+1C PMS, printing: matte PP dimension：278x250mm | I5: Box Outside set-up dimensions:(LxWxD):153x86x46mm Flat sheet dimensions:(L)278x(W)250x(T)0.5mm Material:350gsm SBS Print: 4C+1C PMS Surface process: AQ Coating Joint: Glued inside Remark:包装原料需符合FSC认证要求 | J5: 彩盒 | K5: 1 | L5: 0.3033 | M5: =L5*K5 -> 0.3033 | N5: 031324: Paper with FSC certificate was 0.2821 | Q5: =X5-AE5 -> 0.050704225 | R5: 1 | S5: 1.42 | T5: 1.4 | U5: 5000 | V5: =AC5 -> 14 | W5: =S5/$AG$2 -> 0.2 | X5: =W5*K5 -> 0.2 | Y5: =(M5-X5)/X5 -> 0.5165 | Z5: 1 | AA5: 1.06 | AB5: 5000 | AC5: 14 | AD5: =AA5/$AG$2 -> 0.14929577 | AE5: =AD5*K5 -> 0.14929577 | AF5: =(L5-AD5)/AD5 -> 1.0315377 | AG5: difference between FSC and w/o FSC
A6: 2 | C6: 5831-1053-00A0 | D6: CARD,ELM5 Gen2/FSG-E1J7,HANG TAB,350GSM SBS DOUBLE,AQ COATING,FSC,RoHS | E6: N/A | F6: Hanger | I6: Hang tab Outside dimensions:(LxW):64x38mm Material: 350gsm SBS对裱 Print: 1C (Pantone 1655C) Surface process: AQ Coating Other: Back side with Double sided tape (60x10mm) Remark:包装原料需符合FSC认证要求 | J6: 掛鉤 | K6: 1 | L6: 0.13994366 | M6: =L6*K6 -> 0.13994366 | Q6: =X6-AE6 -> 0 | R6: 1 | S6: 0.934 | U6: 5000 | V6: =AC6 -> 14 | W6: =S6/$AG$2 -> 0.1315493 | X6: =W6*K6 -> 0.1315493 | Y6: =(M6-X6)/X6 -> 0.063811563 | Z6: 1 | AA6: 0.934 | AB6: 5000 | AC6: 14 | AD6: =AA6/$AG$2 -> 0.1315493 | AE6: =AD6*K6 -> 0.1315493 | AF6: =(L6-AD6)/AD6 -> 0.063811563
A7: 3 | B7: 1 | C7: 5843-1053-00A0 | D7: CARDBOARD,ELM5 Gen2/FSG-E1J7,PAPER INSERT,KRAFT E FLUET,RoHS | E7: N/A | F7: paper insert | G7: material: E flute corrugated paper board, original color extension dimension：296x152mm | I7: Paper insert Outside dimensions:(LxWxD):318x154mm Material:E flute corrugated paper board, original color Process: Die-cut Remark:包装原料需符合FSC认证要求 | J7: 内纸卡 | K7: 1 | L7: =AD7*1.2 -> 0.088715493 | M7: =L7*K7 -> 0.088715493 | N7: 031324: Paper with FSC certificate 鴻威測試OK | Q7: =X7-AE7 -> 0.00071830986 | R7: 1 | S7: 0.53 | U7: 5000 | V7: =AC7 -> 14 | W7: =S7/$AG$2 -> 0.074647887 | X7: =W7*K7 -> 0.074647887 | Y7: =(M7-X7)/X7 -> 0.18845283 | Z7: 1 | AA7: 0.5249 | AB7: 3000 | AC7: 14 | AD7: =AA7/$AG$2 -> 0.073929577 | AE7: =AD7*K7 -> 0.073929577 | AF7: =(L7-AD7)/AD7 -> 0.2 | AG7: difference between FSC and w/o FSC
A8: 4 | B8: 1 | C8: 5849-1053-04A0 | D8: LABEL,ELM5 Gen2/FSG-E1J7,BTS LABEL,RIVAL 3 GEN2,DIAMETER 30mm, TRANSPARENT WOOD PULP PAPER,RoHS | E8: N/A | F8: Seal label | J8: 封口贴 | K8: 1 | L8: 0.02 | M8: =L8*K8 -> 0.02 | Q8: =X8-AE8 -> 0.0057042254 | R8: 1 | S8: 0.1115 | U8: 10000 | V8: 21-28 | W8: =S8/$AG$2 -> 0.015704225 | X8: =W8*K8 -> 0.015704225 | Y8: =(M8-X8)/X8 -> 0.2735426 | Z8: 2 | AA8: 0.071 | AB8: 5000 | AC8: 14 | AD8: =AA8/$AG$2 -> 0.01 | AE8: =AD8*K8 -> 0.01 | AF8: =(L8-AD8)/AD8 -> 1 | AG8: 022724:true cost update
A9: 5 | B9: 1 | C9: 5831-1053-02A0 | D9: MANUAL,ELM5 Gen2/FSG-E1J7,RIVAL3 GEN2,100x80mm,80GSM WFUC,FSC,RoHS | E9: N/A | F9: PIG | G9: material: 80g woodfree paper; dimension: 320 x 200 mm, printing: 2C double side printing type: folding paper | I9: Manual Flat sheet dimensions(LxW): (L)320*(W)200mm Fold size: 80*100mm Material : 80gsm WFUC Print: 2C double side printing Process: Folding X 4 Remark:包装原料需符合FSC认证要求 | J9: 说明书 | K9: 1 | L9: 0.0628 | M9: =L9*K9 -> 0.0628 | N9: 031324: Paper with FSC certificate was 0.0584 | Q9: =X9-AE9 -> 0 | R9: 1 | S9: 0.289 | T9: 0.35 | U9: 5000 | V9: =AC9 -> 14 | W9: =S9/$AG$2 -> 0.040704225 | X9: =W9*K9 -> 0.040704225 | Y9: =(M9-X9)/X9 -> 0.54283737 | Z9: 1 | AA9: 0.289 | AB9: 5000 | AC9: 14 | AD9: =AA9/$AG$2 -> 0.040704225 | AE9: =AD9*K9 -> 0.040704225 | AF9: =(L9-AD9)/AD9 -> 0.54283737 | AG9: difference between FSC and w/o FSC
A10: 6 | B10: 1 | C10: 5845-1053-00A0 | D10: BAG,ELM5 Gen2/FSG-E1J7,PAPER SHEET,16GSM MG TISSUE PAPER,FSC,RoHS | E10: N/A | F10: PE bag for mouse | I10: Paper sheet Dimensions(LxW):(L)280x(W)220mm Material : 16gsm 雪梨纸 Print: N/A | J10: 雪梨紙（包鼠標) | K10: 2 | L10: 0.012 | M10: =L10*K10 -> 0.024 | Q10: =X10-AE10 -> -0.30985915 | R10: 2 | S10: 0.2 | U10: 5000 | V10: =AC10 -> 15 | W10: =S10/$AG$2 -> 0.028169014 | X10: =W10*K10 -> 0.056338028 | Y10: =(M10-X10)/X10 -> -0.574 | Z10: 1 | AA10: 1.3 | AB10: 10000 | AC10: 15 | AD10: =AA10/$AG$2 -> 0.18309859 | AE10: =AD10*K10 -> 0.36619718 | AF10: =(L10-AD10)/AD10 -> -0.93446154
A11: 7 | B11: 1 | C11: 5842-1047-00AA | D11: CARTON,ELM5/FSG-E1J4,MASTER CARTON,182x149x178mm,KRAFT C FLUET,REMOVE SS LOGO,RoHS | E11: N/A | F11: Master Carton | G11: material: B flute, burst above 12KGF | I11: Carton Outside dimensions:(L)182X(W)149X(H)175mm; Material: A. Material type: Corrugated fibreboard B. Flute: C Flute C. Grade: 200# Mullen Burst OR 32 ECT Print: Black Joint: Glued inside Remark: 纸板原材料需符合FSC认证要求 | J11: 外箱 | K11: =1/6 -> 0.16666667 | L11: 0.32425352 | M11: =L11*K11 -> 0.054042254 | N11: 031324: Paper with FSC certificate | Q11: =X11-AE11 -> -0.018039906 | R11: 0.16666667 | S11: 1.15 | U11: 5000 | V11: =AC11 -> 15 | W11: =S11/$AG$2 -> 0.16197183 | X11: =W11*K11 -> 0.026995305 | Y11: =(M11-X11)/X11 -> 1.001913 | Z11: 0.16666667 | AA11: 1.9185 | AB11: 500 | AC11: 15 | AD11: =AA11/$AG$2 -> 0.27021127 | AE11: =AD11*K11 -> 0.045035211 | AF11: =(L11-AD11)/AD11 -> 0.2 | AG11: difference between FSC and w/o FSC
A12: 8 | B12: 1 | C12: 5843-1047-01A0 | D12: CARDBOARD,ELM5/FSG-E1J4,T/B BOARD,171x138mm,KRAFT B FLUET,RoHS | E12: N/A | F12: carton TB board | G12: B/F, burst above 10KGF(inside the carton top and bottom) | I12: Paper board Dimension(LxW): (L)171x(W)138mm Material: B flute 12kgf Remark: 纸板原材料需符合FSC认证要求 | J12: 天地板 | K12: =2/6 -> 0.33333333 | L12: 0.088235294 | M12: =L12*K12 -> 0.029411765 | Q12: =X12-AE12 -> 0 | R12: 0.33333333 | S12: 0.17 | U12: 5000 | V12: =AC12 -> 14 | W12: =S12/$AG$2 -> 0.023943662 | X12: =W12*K12 -> 0.0079812207 | Y12: =(M12-X12)/X12 -> 2.6851211 | Z12: 0.33333333 | AA12: 0.17 | AB12: 500 | AC12: 14 | AD12: =AA12/$AG$2 -> 0.023943662 | AE12: =AD12*K12 -> 0.0079812207 | AF12: =(L12-AD12)/AD12 -> 2.6851211
A13: 9 | B13: 1 | C13: 5831-1053-01A0 | D13: CARD,ELM5 Gen2/FSG-E1J7,PAPER FILM,16GSM MG TISSUE PAPER,PROTECTIVE FOR BOX,FSC,RoHS | E13: N/A | F13: Protective paper | I13: Protective paper Dimensions(LxW):(L)1092x(W)180mm Material : 16gsm 雪梨纸 Print: N/A | J13: 雪梨紙（包彩盒) | K13: 0.33333333 | L13: 0.0154 | M13: =L13*K13 -> 0.0051333333 | Q13: =X13-AE13 -> -0.041924883 | R13: 0.33333333 | S13: 0.38 | U13: 5000 | V13: =AC13 -> 28 | W13: =S13/$AG$2 -> 0.053521127 | X13: =W13*K13 -> 0.017840376 | Y13: =(M13-X13)/X13 -> -0.71226316 | Z13: 0.33333333 | AA13: 1.273 | AB13: 5000 | AC13: 28 | AD13: =AA13/$AG$2 -> 0.17929577 | AE13: =AD13*K13 -> 0.059765258 | AF13: =(L13-AD13)/AD13 -> -0.91410841 | AG13: 022724:true cost update
A14: 10 | B14: 1 | C14: 5849-1051-0AA0 | D14: LABEL,KINGPIN/FCG-3301,4"W x 6"L WHITE,PAPER LABEL,47-00034,RoHS | E14: N/A | F14: Label (for master carton) | G14: material: 80g art paper dimension：100x55 mm printing: 1C with online printing | I14: Master Carton Label Outside dimensions:(L)152X(W)102mm; Material : 80gsm artpaper Print: Black | J14: 外箱标签 | K14: =1/6 -> 0.16666667 | L14: 0.024264706 | M14: =L14*K14 -> 0.0040441176 | Q14: =X14-AE14 -> 0 | R14: 0.16666667 | S14: 0.146 | U14: 5000 | V14: =AC14 -> 15 | W14: =S14/$AG$2 -> 0.02056338 | X14: =W14*K14 -> 0.00342723 | Y14: =(M14-X14)/X14 -> 0.17999597 | Z14: 0.16666667 | AA14: 0.146 | AB14: 5000 | AC14: 15 | AD14: =AA14/$AG$2 -> 0.02056338 | AE14: =AD14*K14 -> 0.00342723 | AF14: =(L14-AD14)/AD14 -> 0.17999597
A15: 11 | B15: 1 | C15: 5849-1047-02A0 | D15: LABEL,ELM5/FSG-E1J4,MASTER CARTON SN LABEL,59.67x52mm,80GMS ARTPAPER,RoHS | E15: N/A | F15: S/N label for carton (for master carton) | G15: material: 80g art paper dimension：59.67x52 mm printing: blank with online printing | I15: Carton Label(SN) Outside dimensions: (L)59.67X(W)52mm; Material : 80gsm artpaper | J15: 外箱标签 | K15: =1/6 -> 0.16666667 | L15: 0.0097058824 | M15: =L15*K15 -> 0.0016176471 | Q15: =X15-AE15 -> 0 | R15: 0.16666667 | S15: 0.058 | U15: 5000 | V15: =AC15 -> 15 | W15: =S15/$AG$2 -> 0.0081690141 | X15: =W15*K15 -> 0.0013615023 | Y15: =(M15-X15)/X15 -> 0.18813387 | Z15: 0.16666667 | AA15: 0.058 | AB15: 5000 | AC15: 15 | AD15: =AA15/$AG$2 -> 0.0081690141 | AE15: =AD15*K15 -> 0.0013615023 | AF15: =(L15-AD15)/AD15 -> 0.18813387
A16: 12 | B16: 1 | C16: 5849-1047-01A0 | D16: LABEL,NINJA/FSG-E1J0,RETAIL BOX LABEL,38x12mm,80GMS ARTPAPER,BLANK,RoHS | E16: N/A | F16: SN Label (for color box) | G16: material: 80g art paper dimension: 38x12mm printing: blank with online printing | I16: Color box SN Label Outside dimensions: (L)38X(W)12mm; Material : 80gsm artpaper | J16: 彩盒标签 | K16: 1 | L16: 0.0056617647 | M16: =L16*K16 -> 0.0056617647 | Q16: =X16-AE16 -> 0 | R16: 1 | S16: 0.01 | U16: 5000 | V16: =AC16 -> 15 | W16: =S16/$AG$2 -> 0.0014084507 | X16: =W16*K16 -> 0.0014084507 | Y16: =(M16-X16)/X16 -> 3.0198529 | Z16: 1 | AA16: 0.01 | AB16: 5000 | AC16: 15 | AD16: =AA16/$AG$2 -> 0.0014084507 | AE16: =AD16*K16 -> 0.0014084507 | AF16: =(L16-AD16)/AD16 -> 3.0198529
A17: 13 | B17: 1 | C17: 5849-1053-00A0 | D17: LABEL,ELM5 Gen2/FSG-E1J7,PID LABEL,62515 RIVAL 3 GEN2 BLACK,45.424x23mm, 50 PET WITH MATT PP,RoHS | E17: N/A | F17: PID label (for black product) | G17: material: 80g black PET+ printable matte pp film dimension:45.424x23 mm printing: 2C | I17: PID Label Outside dimensions: (L)45.424X(W)23mm; Material : 50#PET+25# PP film Print: 2C | J17: PID标签 | K17: 1 | L17: 0.021126761 | M17: =L17*K17 -> 0.021126761 | Q17: =X17-AE17 -> 0 | R17: 1 | S17: 0.15 | U17: 10000 | V17: =AC17 -> 15 | W17: =S17/$AG$2 -> 0.021126761 | X17: =W17*K17 -> 0.021126761 | Y17: =(M17-X17)/X17 -> 8.2110245e-16 | Z17: 1 | AA17: 0.15 | AB17: 5000 | AC17: 15 | AD17: =AA17/$AG$2 -> 0.021126761 | AE17: =AD17*K17 -> 0.021126761 | AF17: =(L17-AD17)/AD17 -> 8.2110245e-16 | AG17: 022724:true cost update
A18: 14 | B18: 1 | C18: 5849-1012-05A0 | D18: LABEL,MICKEY,VK481AA ABA INNER CARTON LABEL 153*102mm,80GSM ARTPAPER,RoHS | E18: N/A | F18: Pallet label | G18: Label,Pallet,AP,153x102mm | H18: N/A | I18: Pallet Label Outside dimensions: (L)153X(W)102mm; Material : 80gsm artpaper | J18: 棧板标签 | K18: 0.001587 | L18: 0.026691176 | M18: =L18*K18 -> 4.2358897e-05 | Q18: =X18-AE18 -> 0 | R18: 0.001587 | S18: 0.135 | U18: 5000 | V18: =AC18 -> 7 | W18: =S18/$AG$2 -> 0.019014085 | X18: =W18*K18 -> 3.0175352e-05 | Y18: =(M18-X18)/X18 -> 0.40375817 | Z18: 0.0013333333 | AA18: 0.135 | AB18: 5000 | AC18: 7 | AD18: =AA18/$AG$2 -> 0.019014085 | AE18: =AD18*K18 -> 3.0175352e-05 | AF18: =(L18-AD18)/AD18 -> 0.40375817
A19: 15 | B19: 1 | C19: 5849-1043-00A0 | D19: LABEL,NINJA/FSG-E1J0,LABEL FOR USB CABLE,66.4x15.3mm,80GMS ARTPAPER WITH MATTE PP FILM TWO SIDE,ADHESIVE,BLANK PRINGING,RoHS | E19: N/A | F19: Cable Tag | G19: material: 80g art paper, matte coating(with glue) dimension：66.073x15 mm printing: blank | I19: Cable tag Outside dimensions: (L)66.4X(W)15.3mm; Material : 80gsm artpaper, matte coating(with glue) | J19: USB標籤 | K19: 1 | L19: 0.0127 | M19: =L19*K19 -> 0.0127 | Q19: =X19-AE19 -> 0 | R19: 1 | S19: 0.07 | U19: 5000 | V19: =AC19 -> 14 | W19: =S19/$AG$2 -> 0.0098591549 | X19: =W19*K19 -> 0.0098591549 | Y19: =(M19-X19)/X19 -> 0.28814286 | Z19: 1 | AA19: 0.07 | AB19: 5000 | AC19: 14 | AD19: =AA19/$AG$2 -> 0.0098591549 | AE19: =AD19*K19 -> 0.0098591549 | AF19: =(L19-AD19)/AD19 -> 0.28814286
A20: 16 | B20: 1 | C20: 0981-53PN-00A0 | D20: PALLET,Hoist Gen2/FSG-E3J4,FLEX STYLE PALLET,1200x1000x130 mm,PLYWOOD,RoHS | E20: N/A | F20: Pallet & related | G20: pallet packing material Pallet | I20: PALLET,Hoist Gen2/FSG-E3J4,FLEX STYLE PALLET,1200x1000x130 mm,PLYWOOD,RoHS | J20: 膠合棧板 | K20: 0.000794 | L20: 15.71 | M20: =L20*K20 -> 0.01247374 | Q20: =X20-AE20 -> -0.0029299718 | R20: 0.000794 | S20: 76.8 | U20: 100 | V20: =AC20 -> 15 | W20: =S20/$AG$2 -> 10.816901 | X20: =W20*K20 -> 0.0085886197 | Y20: =(M20-X20)/X20 -> 0.45235677 | Z20: 0.0013333333 | AA20: 103 | AB20: 100 | AC20: 15 | AD20: =AA20/$AG$2 -> 14.507042 | AE20: =AD20*K20 -> 0.011518592 | AF20: =(L20-AD20)/AD20 -> 0.08292233
A21: 17 | B21: 1 | C21: 0984-001E-00A0 | D21: CARDBOARD,SLIP SHEET,CORRUGATED, B/C DOUBLEWALL, 1200MM X 1000MM,BC FLUTE,RoHS | E21: N/A | F21: Card Board | G21: N/A | H21: N/A | I21: Card Board Dimension: 1200x1000mm | J21: 隔板 | K21: =2/1260 -> 0.0015873016 | L21: 1.4041176 | M21: =L21*K21 -> 0.0022287582 | Q21: =X21-AE21 -> 0 | R21: 0.0015873016 | S21: 7.26 | U21: 5000 | V21: =AC21 -> 14 | W21: =S21/$AG$2 -> 1.0225352 | X21: =W21*K21 -> 0.0016230718 | Y21: =(M21-X21)/X21 -> 0.37317291 | Z21: 0.0015873016 | AA21: 7.26 | AB21: 100 | AC21: 14 | AD21: =AA21/$AG$2 -> 1.0225352 | AE21: =AD21*K21 -> 0.0016230718 | AF21: =(L21-AD21)/AD21 -> 0.37317291
A22: 18 | B22: 1 | C22: 0984-1047-00A0 | D22: CARDBOARD,ELM5/FSG-E1J4,CORRUGATED, B FLUTE,1175x993 mm,RoHS | E22: N/A | F22: Card Board | G22: N/A | H22: N/A | I22: Card Board Dimension: 1175x993 mm | J22: 隔板 | K22: =4/1260 -> 0.0031746032 | L22: 0.48028169 | M22: =L22*K22 -> 0.0015247038 | Q22: =X22-AE22 -> 0 | R22: 0.0031746032 | S22: 3.41 | U22: 5000 | V22: =AC22 -> 15 | W22: =S22/$AG$2 -> 0.48028169 | X22: =W22*K22 -> 0.0015247038 | Y22: =(M22-X22)/X22 -> -2.8443615e-16 | Z22: 0.0031746032 | AA22: 3.41 | AB22: 100 | AC22: 15 | AD22: =AA22/$AG$2 -> 0.48028169 | AE22: =AD22*K22 -> 0.0015247038 | AF22: =(L22-AD22)/AD22 -> -2.3116081e-16 | AG22: 022724:true cost update
A23: 19 | B23: 1 | C23: 0984-001H-00A0 | D23: CARDBOARD,PAPER ANGLE BEAD,1025X50X50mm,THICKNESS 5mm,KRAFT PAPER,RoHS | E23: N/A | F23: Corner Board | G23: N/A | H23: N/A | I23: Corner Board Dimension:1025X50X50mm | J23: 護角 | K23: 0.003175 | L23: 0.32676471 | M23: =L23*K23 -> 0.0010374779 | Q23: =X23-AE23 -> 0 | R23: 0.003175 | S23: 2.02 | U23: 5000 | V23: =AC23 -> 15 | W23: =S23/$AG$2 -> 0.28450704 | X23: =W23*K23 -> 0.00090330986 | Y23: =(M23-X23)/X23 -> 0.14852941 | Z23: 0.0063492063 | AA23: 2.02 | AB23: 1000 | AC23: 15 | AD23: =AA23/$AG$2 -> 0.28450704 | AE23: =AD23*K23 -> 0.00090330986 | AF23: =(L23-AD23)/AD23 -> 0.14852941
A24: 20 | B24: 1 | C24: 0984-001J-00A0 | D24: CARDBOARD,PAPER ANGLE BEAD,900X50X50mm,THICKNESS 5mm,KRAFT PAPER,RoHS | E24: N/A | F24: Corner Board | G24: N/A | H24: N/A | I24: Corner Board Dimension:900X50X50mm | J24: 護角 | K24: 0.00635 | L24: 0.28632353 | M24: =L24*K24 -> 0.0018181544 | Q24: =X24-AE24 -> 0 | R24: 0.00635 | S24: 1.77 | U24: 5000 | V24: =AC24 -> 15 | W24: =S24/$AG$2 -> 0.24929577 | X24: =W24*K24 -> 0.0015830282 | Y24: =(M24-X24)/X24 -> 0.14852941 | Z24: 0.0031746032 | AA24: 1.77 | AB24: 1000 | AC24: 15 | AD24: =AA24/$AG$2 -> 0.24929577 | AE24: =AD24*K24 -> 0.0015830282 | AF24: =(L24-AD24)/AD24 -> 0.14852941
A25: 21 | B25: 1 | C25: 0952-0004-0001 | D25: OC,DEPLETION,TAPE,SEAL,48mm*45m, | E25: N/A | F25: Seal tape_Clear | G25: N/A | H25: N/A | I25: OC,DEPLETION,TAPE,SEAL,48mm*45m, | J25: 透明封箱膠帶 | K25: 0.002222 | L25: 6.1352113 | M25: =L25*K25 -> 0.013632439 | Q25: =X25-AE25 -> -0.0019340789 | R25: 0.002222 | S25: 5.02 | U25: 100 | V25: =AC25 -> 15 | W25: =S25/$AG$2 -> 0.70704225 | X25: =W25*K25 -> 0.0015710479 | Y25: =(M25-X25)/X25 -> 7.6772908 | Z25: 0.005 | AA25: 11.2 | AB25: 900 | AC25: 15 | AD25: =AA25/$AG$2 -> 1.5774648 | AE25: =AD25*K25 -> 0.0035051268 | AF25: =(L25-AD25)/AD25 -> 2.8892857 | AG25: New
A26: 22 | B26: 1 | C26: 0952-0005-00E0 | D26: INK RIBBON,DEPLETION,B110A,110MM,LF | E26: N/A | F26: INK RIBBON | G26: N/A | H26: N/A | I26: INK RIBBON,DEPLETION,B110A,110MM,LF | J26: 碳带 | K26: 0.00103 | L26: 9.8873239 | M26: =L26*K26 -> 0.010183944 | Q26: =X26-AE26 -> 7.2535211e-05 | R26: 0.00103 | S26: 59 | U26: 10 | V26: =AC26 -> 7 | W26: =S26/$AG$2 -> 8.3098592 | X26: =W26*K26 -> 0.0085591549 | Y26: =(M26-X26)/X26 -> 0.18983051 | Z26: 0.000217 | AA26: 58.5 | AB26: 10 | AC26: 7 | AD26: =AA26/$AG$2 -> 8.2394366 | AE26: =AD26*K26 -> 0.0084866197 | AF26: =(L26-AD26)/AD26 -> 0.2 | AG26: New
A27: 23 | B27: 1 | C27: 0952-0002-00E0 | D27: INK RIBBON,DEPLETION,TW10,60MM,LF | E27: N/A | F27: INK RIBBON | G27: N/A | H27: N/A | I27: INK RIBBON,DEPLETION,TW10,60MM,LF | J27: 碳带 | K27: 0.000118 | L27: 5.3543662 | M27: =L27*K27 -> 0.00063181521 | Q27: =X27-AE27 -> 5.3183099e-06 | R27: 0.000118 | S27: 32 | U27: 10 | V27: =AC27 -> 7 | W27: =S27/$AG$2 -> 4.5070423 | X27: =W27*K27 -> 0.00053183099 | Y27: =(M27-X27)/X27 -> 0.188 | Z27: 0.000118 | AA27: 31.68 | AB27: 10 | AC27: 7 | AD27: =AA27/$AG$2 -> 4.4619718 | AE27: =AD27*K27 -> 0.00052651268 | AF27: =(L27-AD27)/AD27 -> 0.2 | AG27: New
A28: 24 | B28: 1 | C28: 0952-000N-00A0 | D28: INK RIBBON,DEPLETION,DMX480 BLACK,50MM*300M,RoHS | E28: N/A | F28: INK RIBBON | G28: N/A | H28: N/A | I28: INK RIBBON,DEPLETION,DMX480 BLACK,50MM*300M,RoHS | J28: 碳带 | K28: 0.0001 | L28: 7.6394366 | M28: =L28*K28 -> 0.00076394366 | Q28: =X28-AE28 -> 0.00015211268 | R28: 0.0001 | S28: 56 | U28: 10 | V28: =AC28 -> 7 | W28: =S28/$AG$2 -> 7.8873239 | X28: =W28*K28 -> 0.00078873239 | Y28: =(M28-X28)/X28 -> -0.031428571 | Z28: 0.0001 | AA28: 45.2 | AB28: 50 | AC28: 7 | AD28: =AA28/$AG$2 -> 6.3661972 | AE28: =AD28*K28 -> 0.00063661972 | AF28: =(L28-AD28)/AD28 -> 0.2 | AG28: New
A29: 25 | B29: 1 | C29: 0952-000S-00E0 | D29: OC,DEPLETION,TAPE,SEAL(400m*500mm*0.018cm),RoHS | E29: N/A | F29: Tape | G29: N/A | H29: N/A | I29: OC,DEPLETION,TAPE,SEAL(400m*500mm*0.018cm),RoHS | J29: 打包膜 | K29: 0.00045 | L29: 6.1352113 | M29: =L29*K29 -> 0.0027608451 | Q29: =X29-AE29 -> -1.9014085e-05 | R29: 0.00045 | S29: 36 | U29: 100 | V29: =AC29 -> 10 | W29: =S29/$AG$2 -> 5.0704225 | X29: =W29*K29 -> 0.0022816901 | Y29: =(M29-X29)/X29 -> 0.21 | Z29: 0.00045 | AA29: 36.3 | AB29: 500 | AC29: 10 | AD29: =AA29/$AG$2 -> 5.1126761 | AE29: =AD29*K29 -> 0.0023007042 | AF29: =(L29-AD29)/AD29 -> 0.2 | AG29: New
A30: 26 | B30: 1 | C30: 098C-1053-00A0 | D30: DESICCANT,ELM5 Gen2/FSG-E1J7,45X35MM-2G,RoHS | E30: N/A | F30: DESICCANT | G30: N/A | I30: DESICCANT Outside dimensions: (L)45X(W)35mm; Material : SiO2 乾燥劑, 2g/包 | J30: 乾燥劑 | K30: 1 | L30: 0.0085 | M30: =L30*K30 -> 0.0085 | Q30: =X30-AE30 -> 0.069014085 | R30: 1 | S30: 0.49 | U30: 15000 | V30: 14 | W30: =S30/$AG$2 -> 0.069014085 | X30: =W30*K30 -> 0.069014085 | Y30: =(M30-X30)/X30 -> -0.87683673 | Z30: 0.00045 | AA30: 36.3 | AB30: 500 | AC30: 10 | AE30: =AD30*K30 -> 0 | AF30: =(L30-AD30)/AD30 -> #DIV/0! | AG30: New
A31: 27 | B31: 1 | C31: 0952-000T-00E0 | D31: TAPE,12mm*30y,LF | E31: N/A | F31: Tape | G31: N/A | H31: N/A | I31: TAPE,12mm*30y,LF | J31: 小膠帶 | K31: 0.002 | L31: 0 | M31: =L31*K31 -> 0 | Q31: =X31-AE31 -> -0.01011831 | R31: 0.002 | S31: 0.38 | U31: 1000 | V31: =AC31 -> 10 | W31: =S31/$AG$2 -> 0.053521127 | X31: =W31*K31 -> 0.00010704225 | Y31: =(M31-X31)/X31 -> -1 | Z31: 0.00045 | AA31: 36.3 | AB31: 500 | AC31: 10 | AD31: =AA31/$AG$2 -> 5.1126761 | AE31: =AD31*K31 -> 0.010225352 | AF31: =(L31-AD31)/AD31 -> -1 | AG31: New
A32: Subtotal(USD/Unit)： | M32: =SUM(M5:M31) -> 0.82809498 | N32: 022724: ex rate 7.1 ex rate: 6.3 RMB | Q32: =SUM(Q5:Q30) -> -0.2483362 | X32: =SUM(X5:X31) -> 0.70605015 | Y32: =(M32-X32)/X32 -> 0.17285574 | AD32: =AA32/$AG$2 -> 0 | AE32: =SUM(AE5:AE29) -> 0.95427931 | AF32: =(M32-AE32)/AE32 -> -0.13222998 | AG32: Margin
A33: Subtotal(USD/Unit)： | N33: New ex rate 7 | AE33: 0.53513451 | AF33: 1.2767295 | AG33: cost up due to FSC & sustainable material

Sheet ME bom 0618_Black
A2: Project Name: | B2: ELM5 Gen2
A3: Prepared By: | B3: Alvin
A4: Last Updated:
A5: Forecast: | B5: 418K*0.8
A7: Item | B7: Component Type | C7: Level 1 System Part Name (by RD) | D7: Level 2 Parts Name (by RD) | E7: Part Picture | F7: Part Description (by PLM) | G7: Foxlink P/N | H7: Customer P/N | I7: Level 1 Q'ty | J7: Level 2 Q'ty | K7: Part Size /mm | L7: Part Weight /g | M7: Material | N7: Color | O7: 2nd Process (Incl. Finish) | P7: T2 Supplier (Vendor Name) | Q7: Component Catergory (Part Type) | R7: Customized / Standard | S7: 2D Version | T7: Remarks | U7: U/P | V7: Sub-Total | W7: Tool Q'ty | X7: Tool Cav. | Y7: Tooling Cost Per Tool (USD/set) | Z7: Jig Cost | AA7: Total Tooling Cost | AC7: True U/P (USD/pcs) | AD7: True Sub-Total | AE7: Mark up % | AG7: Tooling True Cost | AH7: Jig Cost | AI7: True Sub-Total | AJ7: Mark Up %
A8: P1 | B8: 1. Plastic | C8: MIDDLE HOUSING B | F8: PLASTIC ASSY,ELM5/FSG-E1J4,MIDDLE HOUSING B,BLACK,RoHS | G8: 5881-1047-0HA0 | I8: 1 | J8: 0 | L8: 22 | M8: ABS Chimei PA 757 | N8: Black | O8: Black /ABS /VDI 27 印刷Logo,Color:Metallic Pantone 10390C /Silkscreen Print /Matte | P8: 廠內-塑件 | U8: 0.3675 | V8: =U8*I8 -> 0.3675 | W8: 1 | X8: 2 | Y8: 2000 | AA8: =W8*(Y8+Z8) -> 2000 | AC8: 0.33837654 | AD8: =I8*AC8 -> 0.33837654 | AE8: =(U8-AC8)/AC8 -> 0.086068191 | AG8: 1600 | AI8: =W8*(AG8+AH8) -> 1600 | AJ8: =(Y8-AG8)/AG8 -> 0.25
A9: P2 | B9: 1. Plastic | C9: TRIGGER BUTTON LEFT B | F9: PLASTIC ASSY,ELM5/FSG-E1J4,TRIGGER BUTTON LEFT B,BLACK,RoHS | G9: 5881-1047-0JA0 | I9: 1 | L9: 2.6 | M9: ABS+PC WY-A240 | N9: Black | O9: Black /ABS + PC /VDI 27 | P9: 廠內-塑件 | U9: 0.0945 | V9: =U9*I9 -> 0.0945 | W9: 1 | X9: 2 | Y9: 1000 | AA9: =W9*(Y9+Z9) -> 1000 | AC9: 0.092883333 | AD9: =I9*AC9 -> 0.092883333 | AE9: =(U9-AC9)/AC9 -> 0.017405347 | AG9: 800 | AI9: =W9*(AG9+AH9) -> 800 | AJ9: =(AA9-AI9)/AI9 -> 0.25
A10: P3 | B10: 1. Plastic | C10: TRIGGER BUTTON RIGHT B | F10: PLASTIC ASSY,ELM5/FSG-E1J4,TRIGGER BUTTON RIGHT B,BLACK,RoHS | G10: 5881-1047-0KA0 | I10: 1 | L10: 2.6 | M10: ABS+PC WY-A240 | N10: Black | O10: Black /ABS + PC /VDI 27 | P10: 廠內-塑件 | U10: 0.0945 | V10: =U10*I10 -> 0.0945 | X10: 2 | AC10: 0.092883333 | AD10: =I10*AC10 -> 0.092883333 | AE10: =(U10-AC10)/AC10 -> 0.017405347 | AJ10: =(AA10-AI10)/AI10 -> #DIV/0!
A11: P4 | B11: 1. Plastic | C11: BOTTOM COVER W | F11: PLASTIC ASSY,ELM5/FSG-E1J4,BOTTOM COVER B,Smokey BLACK,RoHS | G11: 5881-1047-0CA0 | I11: 1 | L11: 11 | M11: PC141R | N11: Milky White Diffusing 1/1000 | O11: Smokey Black /Translucent PC /VDI 27 | P11: 廠內-塑件 | T11: 黑/白機種共用 相同Lightguide原料 | U11: 0.275 | V11: =U11*I11 -> 0.275 | W11: 1 | X11: 2 | AA11: =W11*(Y11+Z11) -> 0 | AC11: 0.2729 | AD11: =I11*AC11 -> 0.2729 | AE11: =(U11-AC11)/AC11 -> 0.0076951264 | AI11: =W11*(AG11+AH11) -> 0 | AJ11: =(AA11-AI11)/AI11 -> #DIV/0!
A12: P5 | B12: 1. Plastic | C12: LIGHTGUIDE | F12: PLASTIC ASSY,ELM5/FSG-E1J4,LIGHTGUIDE B,Smokey BLACK,RoHS | G12: 5881-1047-04A0 | I12: 1 | L12: 4.4 | M12: PC141R | N12: Milky White Diffusing 1/1000 | O12: Smokey Black /Translucent PC /VDI 24 | P12: 廠內-塑件 | T12: 沿用ELM5物料 | U12: 0.135885 | V12: =U12*I12 -> 0.135885 | W12: 1 | X12: 2 | AA12: =W12*(Y12+Z12) -> 0 | AC12: 0.1837 | AD12: =I12*AC12 -> 0.1837 | AE12: =(U12-AC12)/AC12 -> -0.26028851 | AI12: =W12*(AG12+AH12) -> 0 | AJ12: =(AA12-AI12)/AI12 -> #DIV/0!
A13: P6 | B13: 1. Plastic | C13: SIDE BUTTON | F13: PLASTIC ASSY,ELM5/FSG-E1J4,SIDE BUTTON,ABS,BLACK,RoHS | G13: 5881-1047-05A0 | I13: 1 | L13: 0.6 | M13: ABS Chimei PA 757 | N13: Black | O13: Black /ABS /VDI 24 | P13: 廠內-塑件 | T13: 沿用ELM5物料 | U13: 0.062521 | V13: =U13*I13 -> 0.062521 | W13: 1 | X13: 4 | AA13: =W13*(Y13+Z13) -> 0 | AC13: 0.063665704 | AD13: =I13*AC13 -> 0.063665704 | AE13: =(U13-AC13)/AC13 -> -0.017979911 | AI13: =W13*(AG13+AH13) -> 0 | AJ13: =(AA13-AI13)/AI13 -> #DIV/0!
A14: P7 | B14: 1. Plastic | C14: CPI BUTTON | F14: PLASTIC ASSY,ELM5/FSG-E1J4,CPI BUTTON,ABS,BLACK,RoHS | G14: 5881-1047-06A0 | I14: 1 | L14: 0.2 | M14: ABS Chimei PA 757 | N14: Black | O14: Black /ABS /VDI 24 | P14: 廠內-塑件 | T14: 沿用ELM5物料 | U14: 0.05768 | V14: =U14*I14 -> 0.05768 | W14: 1 | X14: 4 | AA14: =W14*(Y14+Z14) -> 0 | AC14: 0.057167704 | AD14: =I14*AC14 -> 0.057167704 | AE14: =(U14-AC14)/AC14 -> 0.0089612887 | AI14: =W14*(AG14+AH14) -> 0 | AJ14: =(AA14-AI14)/AI14 -> #DIV/0!
A15: P8 | B15: 1. Plastic | C15: WHEEL HUB | F15: PLASTIC ASSY,ELM5/FSG-E1J4,WHEEL HUB,PC,BLACK,RoHS | G15: 5881-1047-07A0 | I15: 1 | L15: 1.8 | M15: PC 141R | N15: Black | O15: Black /PC /VDI 21 | P15: 廠內-塑件 | T15: 沿用ELM5物料 | U15: 0.089198 | V15: =U15*I15 -> 0.089198 | W15: 1 | X15: 8 | AA15: =W15*(Y15+Z15) -> 0 | AC15: 0.0866 | AD15: =I15*AC15 -> 0.0866 | AE15: =(U15-AC15)/AC15 -> 0.03 | AI15: =W15*(AG15+AH15) -> 0 | AJ15: =(AA15-AI15)/AI15 -> #DIV/0!
A16: P9 | B16: 1. Plastic | C16: SWITCH CUSHION | F16: PLASTIC,NINJA/FSG-E1J0,SWITCH CUSHION,PA66,RoHS | G16: 5811-1043-08A0 | I16: 1 | L16: 0.05 | M16: PA66 | N16: Black | P16: 頂鈞 | T16: 沿用ELM5物料 | U16: 0.031522844 | V16: =U16*I16 -> 0.031522844 | W16: 1 | X16: 8 | AA16: =W16*(Y16+Z16) -> 0 | AC16: 0.0287 | AD16: =I16*AC16 -> 0.0287 | AE16: =(U16-AC16)/AC16 -> 0.098356945 | AI16: =W16*(AG16+AH16) -> 0 | AJ16: =(AA16-AI16)/AI16 -> #DIV/0!
A17: P10 | B17: 1. Plastic | C17: LED CLIP | F17: PLASTIC ASSY,ELM5/FSG-E1J4,LED CLIP,LCP,BLACK,RoHS | G17: 5881-1047-08A0 | I17: 1 | L17: 0.2 | M17: ABS | N17: Black | P17: 廠內-塑件 | T17: 沿用ELM5物料 | U17: 0.104133 | V17: =U17*I17 -> 0.104133 | W17: 1 | X17: 8 | AA17: =W17*(Y17+Z17) -> 0 | AC17: 0.1011 | AD17: =I17*AC17 -> 0.1011 | AE17: =(U17-AC17)/AC17 -> 0.03 | AI17: =W17*(AG17+AH17) -> 0 | AJ17: =(AA17-AI17)/AI17 -> #DIV/0!
A18: R1 | B18: 3. Rubber | C18: WHEEL GRIP B1 | F18: RUBBER,ELM5/FSG-E1J4,WHEEL GRIP B1,BLACK,RoHS | G18: 5813-1047-01A0 | I18: 0 | M18: Silicon rubber | N18: Black | O18: Black /Silicon Rubber /VDI 24 (Arrow) | U18: 0.081 | V18: =U18*I18 -> 0 | W18: 1 | X18: 36 | AA18: =W18*(Y18+Z18) -> 0 | AC18: 0.0732 | AD18: =I18*AC18 -> 0 | AE18: =(U18-AC18)/AC18 -> 0.10655738 | AI18: =W18*(AG18+AH18) -> 0 | AJ18: =(AA18-AI18)/AI18 -> #DIV/0!
A19: R2 | B19: 3. Rubber | C19: WHEEL GRIP B2 | F19: RUBBER,ELM5/FSG-E1J4,WHEEL GRIP B2,BLACK,RoHS | G19: 5813-1047-02A0 | I19: 1 | M19: Silicon rubber | N19: Black | O19: Black /Silicon Rubber /VDI 24 (Horizontal V2) | P19: 鑫永成 | U19: 0.081 | V19: =U19*I19 -> 0.081 | AA19: =W19*(Y19+Z19) -> 0 | AC19: =0.47/7 -> 0.067142857 | AD19: =I19*AC19 -> 0.067142857 | AE19: =(U19-AC19)/AC19 -> 0.20638298 | AI19: =W19*(AG19+AH19) -> 0 | AJ19: =(AA19-AI19)/AI19 -> #DIV/0!
A20: R3 | B20: 3. Rubber | C20: WHEEL GRIP B3 | F20: RUBBER,ELM5/FSG-E1J4,WHEEL GRIP B3,BLACK,RoHS | G20: 5813-1047-03A0 | I20: 0 | M20: Silicon rubber | N20: Black | O20: Black /Silicon Rubber /VDI 24 (Topographic) | U20: 0.081 | V20: =U20*I20 -> 0 | AA20: =W20*(Y20+Z20) -> 0 | AC20: 0.0732 | AD20: =I20*AC20 -> 0 | AE20: =(U20-AC20)/AC20 -> 0.10655738 | AI20: =W20*(AG20+AH20) -> 0 | AJ20: =(AA20-AI20)/AI20 -> #DIV/0!
A21: O1 | B21: 4. Others | C21: PTFE FEET PAD UP W | F21: MYLAR,ELM5/FSG-E1J4,PTFE FEET PAD UP WHITE,RoHS | G21: 581C-1047-05A0 | I21: 2 | M21: PTFE (TEFLON) | N21: White (電暈) 鈉化 | O21: White /Virgin Grade PTFE /High Gloss 含保護膜(透明) | P21: 德暉 | U21: 0.03 | V21: =U21*I21 -> 0.06 | AA21: =W21*(Y21+Z21) -> 0 | AC21: 0.028 | AD21: =I21*AC21 -> 0.056 | AE21: =(U21-AC21)/AC21 -> 0.071428571 | AI21: =W21*(AG21+AH21) -> 0 | AJ21: =(AA21-AI21)/AI21 -> #DIV/0!
A22: O2 | B22: 4. Others | C22: PTFE FEET PAD DOWN W | F22: MYLAR,ELM5/FSG-E1J4,PTFE FEET PAD DOWN WHITE,RoHS | G22: 581C-1047-06A0 | I22: 1 | M22: PTFE (TEFLON) | N22: White (電暈) 鈉化 | O22: White /Virgin Grade PTFE /High Gloss 含保護膜(透明) | P22: 德暉 | U22: 0.153 | V22: =U22*I22 -> 0.153 | AA22: =W22*(Y22+Z22) -> 0 | AC22: 0.145 | AD22: =I22*AC22 -> 0.145 | AE22: =(U22-AC22)/AC22 -> 0.055172414 | AI22: =W22*(AG22+AH22) -> 0 | AJ22: =(AA22-AI22)/AI22 -> #DIV/0!
A23: O3 | B23: 4. Others | C23: SCREW T2x6mm | F23: SCREW,MILD STEEL,ZINC BLACK,NINJA/FSG-E1J0,T2x6mm,CROSS,1018A BLACK,ZN,RoHS | G23: 0961-0003-83A0 | I23: 4 | M23: A1018 | N23: Sliver | O23: 自攻,十字槽,鍍鎳,D3.5*頭厚1.3*L6 | P23: 高億/or 2nd source | T23: 沿用ELM5物料 | U23: 0.00385 | V23: =U23*I23 -> 0.0154 | AA23: =W23*(Y23+Z23) -> 0 | AC23: 0.00309 | AD23: =I23*AC23 -> 0.01236 | AE23: =(U23-AC23)/AC23 -> 0.24595469 | AI23: =W23*(AG23+AH23) -> 0 | AJ23: =(AA23-AI23)/AI23 -> #DIV/0!
A24: O4 | B24: 4. Others | C24: SCREW P2x4mm | F24: SCREW,MILD STEEL,ZINC BLACK,NINJA/FSG-E1J0, P2x4mm,CROSS,1018A BLACK,ZN,RoHS | G24: 0961-0004-83A0 | I24: 9 | M24: A1018 | N24: Black | O24: 自攻,十字槽,鍍黑鎳,D3.5*頭厚1.3*L4 | P24: 高億/or 2nd source | T24: 沿用ELM5物料 | U24: 0.00495 | V24: =U24*I24 -> 0.04455 | AA24: =W24*(Y24+Z24) -> 0 | AC24: 0.003 | AD24: =I24*AC24 -> 0.027 | AE24: =(U24-AC24)/AC24 -> 0.65 | AI24: =W24*(AG24+AH24) -> 0 | AJ24: =(AA24-AI24)/AI24 -> #DIV/0!
A25: O5 | B25: 4. Others | C25: SCREW P2x4mm | F25: SCREW,MILD STEEL,ZINC WHITE, P2x4mm,CROSS,1018A WHITE,ZN,RoHS,LEFT-HAND THREAD | G25: 0961-0006-81A0 | I25: 1 | M25: A1018 | N25: White | O25: 自攻,十字槽,鍍白鋅,D3.5*頭厚1.3*L4, 左旋螺絲 | P25: 力工 | T25: 沿用ELM5物料 | U25: 0.00495 | V25: =U25*I25 -> 0.00495 | AA25: =W25*(Y25+Z25) -> 0 | AC25: =0.0385/7 -> 0.0055 | AD25: =I25*AC25 -> 0.0055 | AE25: =(U25-AC25)/AC25 -> -0.1 | AI25: =W25*(AG25+AH25) -> 0 | AJ25: =(AA25-AI25)/AI25 -> #DIV/0!
V26: =U26*I26 -> 0 | AA26: =W26*(Y26+Z26) -> 0 | AD26: =I26*AC26 -> 0 | AE26: =(U26-AC26)/AC26 -> #DIV/0! | AI26: =W26*(AG26+AH26) -> 0 | AJ26: =(AA26-AI26)/AI26 -> #DIV/0!
V27: =U27*I27 -> 0 | AA27: =W27*(Y27+Z27) -> 0 | AD27: =I27*AC27 -> 0 | AE27: =(U27-AC27)/AC27 -> #DIV/0! | AI27: =W27*(AG27+AH27) -> 0 | AJ27: =(AA27-AI27)/AI27 -> #DIV/0!
U29: Total cost | V29: =SUM(V8:V27) -> 1.6713398 | AA29: =SUM(AA8:AA27) -> 3000 | AD29: =SUM(AD8:AD27) -> 1.6309795 | AE29: =(V29-AD29)/AD29 -> 0.024746093 | AI29: =SUM(AI8:AI27) -> 2400 | AJ29: =(AA29-AI29)/AI29 -> 0.25

Sheet ME bom 0618_White
A2: Project Name: | B2: ELM5 Gen2
A3: Prepared By: | B3: Alvin
A4: Last Updated:
A5: Forecast: | B5: 418K*0.2
A7: Item | B7: Component Type | C7: Level 1 System Part Name (by RD) | D7: Level 2 Parts Name (by RD) | E7: Part Picture | F7: Part Description (by PLM) | G7: Foxlink P/N | H7: Customer P/N | I7: Level 1 Q'ty | J7: Level 2 Q'ty | K7: Part Size /mm | L7: Part Weight /g | M7: Material | N7: Color | O7: 2nd Process (Incl. Finish) | P7: T2 Supplier (Vendor Name) | Q7: Component Catergory (Part Type) | R7: Customized / Standard | S7: 2D Version | T7: Remarks | U7: U/P | V7: Sub-Total | W7: Tool Q'ty | X7: Tool Cav. | Y7: Tooling Cost Per Tool (USD/set) | Z7: Jig Cost | AA7: Total Tooling Cost | AC7: True U/P (USD/pcs) | AD7: True Sub-Total | AE7: Mark up % | AG7: Tooling True Cost | AH7: Jig Cost | AI7: True Sub-Total | AJ7: Mark Up %
A8: P1 | B8: 1. Plastic | C8: MIDDLE HOUSING W | F8: PLASTIC ASSY,ELM5/FSG-E1J4,MIDDLE HOUSING W,Pantone PQ-11-0601 TCX,RoHS | G8: 5881-1047-09A0 | I8: 1 | J8: 0 | L8: 22 | M8: ABS Chimei PA 757 | N8: Pantone PQ-11-0601 TCX | O8: Pantone PQ-11-0601 TCX /ABS /VDI 27 印刷Logo,Color:Pantone Cool Grey 6C /Silkscreen Print /Matte | P8: 廠內-塑件 | U8: 0.39048495 | V8: =U8*I8 -> 0.39048495 | W8: 1 | X8: 2 | AA8: =W8*(Y8+Z8) -> 0 | AC8: 0.37189043 | AD8: =I8*AC8 -> 0.37189043 | AE8: =(V8-AD8)/AD8 -> 0.05 | AI8: =W8*(AG8+AH8) -> 0 | AJ8: =(AA8-AI8)/AI8 -> #DIV/0!
A9: P2 | B9: 1. Plastic | C9: TRIGGER BUTTON LEFT W | F9: PLASTIC ASSY,ELM5/FSG-E1J4,TRIGGER BUTTON LEFT W,Pantone PQ-11-0601 TCX,RoHS | G9: 5881-1047-0AA0 | I9: 1 | L9: 2.6 | M9: ABS+PC WY-A240 | N9: Pantone PQ-11-0601 TCX | O9: Pantone PQ-11-0601 TCX /ABS + PC /VDI 27 | P9: 廠內-塑件 | U9: 0.11372083 | V9: =U9*I9 -> 0.11372083 | W9: 1 | X9: 2 | AA9: =W9*(Y9+Z9) -> 0 | AC9: 0.10830556 | AD9: =I9*AC9 -> 0.10830556 | AE9: =(V9-AD9)/AD9 -> 0.05 | AI9: =W9*(AG9+AH9) -> 0 | AJ9: =(AA9-AI9)/AI9 -> #DIV/0!
A10: P3 | B10: 1. Plastic | C10: TRIGGER BUTTON RIGHT W | F10: PLASTIC ASSY,ELM5/FSG-E1J4,TRIGGER BUTTON RIGHT W,Pantone PQ-11-0601 TCX,RoHS | G10: 5881-1047-0BA0 | I10: 1 | L10: 2.6 | M10: ABS+PC WY-A240 | N10: Pantone PQ-11-0601 TCX | O10: Pantone PQ-11-0601 TCX /ABS + PC /VDI 27 | P10: 廠內-塑件 | U10: 0.11372083 | V10: =U10*I10 -> 0.11372083 | X10: 2 | AA10: =W10*(Y10+Z10) -> 0 | AC10: 0.10830556 | AD10: =I10*AC10 -> 0.10830556 | AE10: =(V10-AD10)/AD10 -> 0.05 | AI10: =W10*(AG10+AH10) -> 0 | AJ10: =(AA10-AI10)/AI10 -> #DIV/0!
A11: P4 | B11: 1. Plastic | C11: BOTTOM COVER W | F11: PLASTIC ASSY,ELM5/FSG-E1J4,BOTTOM COVER W,Milky WHITE,RoHS | G11: 5881-1047-0CA0 | I11: 1 | L11: 11 | M11: PC 141R | N11: Milky White Diffusing 1/1000 | O11: Milky White /Translucent PC /VDI 27 | P11: 廠內-塑件 | T11: 黑/白機種共用 | U11: 0.275 | V11: =U11*I11 -> 0.275 | W11: 1 | X11: 2 | AA11: =W11*(Y11+Z11) -> 0 | AC11: 0.2729 | AD11: =I11*AC11 -> 0.2729 | AE11: =(V11-AD11)/AD11 -> 0.0076951264 | AI11: =W11*(AG11+AH11) -> 0 | AJ11: =(AA11-AI11)/AI11 -> #DIV/0!
A12: P5 | B12: 1. Plastic | C12: LIGHTGUIDE | F12: PLASTIC ASSY,ELM5/FSG-E1J4,LIGHTGUIDE W,Milky WHITE,RoHS | G12: 5881-1047-04A0 | I12: 1 | L12: 4.4 | M12: PC 141R | N12: Milky White Diffusing 1/1000 | O12: Milky White /Translucent PC /VDI 24 | P12: 廠內-塑件 | T12: 沿用ELM5物料 | U12: 0.1929 | V12: =U12*I12 -> 0.1929 | W12: 1 | X12: 2 | AA12: =W12*(Y12+Z12) -> 0 | AC12: 0.1837 | AD12: =I12*AC12 -> 0.1837 | AE12: =(V12-AD12)/AD12 -> 0.050081655 | AI12: =W12*(AG12+AH12) -> 0 | AJ12: =(AA12-AI12)/AI12 -> #DIV/0!
A13: P6 | B13: 1. Plastic | C13: SIDE BUTTON W | F13: PLASTIC ASSY,ELM5/FSG-E1J4,SIDE BUTTON W, Pantone Cool Grey 6C,RoHS | G13: 5881-1047-0EA0 | I13: 1 | L13: 0.6 | M13: ABS Chimei PA 757 | N13: Pantone Cool Grey 6C | O13: Pantone Cool Grey 6C /ABS /VDI 24 | P13: 廠內-塑件 | U13: 0.0701085 | V13: =U13*I13 -> 0.0701085 | W13: 1 | X13: 4 | AA13: =W13*(Y13+Z13) -> 0 | AC13: 0.0734 | AD13: =I13*AC13 -> 0.0734 | AE13: =(V13-AD13)/AD13 -> -0.044843324 | AI13: =W13*(AG13+AH13) -> 0 | AJ13: =(AA13-AI13)/AI13 -> #DIV/0!
A14: P7 | B14: 1. Plastic | C14: CPI BUTTON W | F14: PLASTIC ASSY,ELM5/FSG-E1J4,CPI BUTTON W,Pantone Cool Grey 6C,RoHS | G14: 5881-1047-0FA0 | I14: 1 | L14: 0.2 | M14: ABS Chimei PA 757 | N14: Pantone Cool Grey 6C | O14: Pantone Cool Grey 6C /ABS /VDI 24 | P14: 廠內-塑件 | U14: 0.06468 | V14: =U14*I14 -> 0.06468 | W14: 1 | X14: 4 | AA14: =W14*(Y14+Z14) -> 0 | AC14: 0.0652 | AD14: =I14*AC14 -> 0.0652 | AE14: =(V14-AD14)/AD14 -> -0.0079754601 | AI14: =W14*(AG14+AH14) -> 0 | AJ14: =(AA14-AI14)/AI14 -> #DIV/0!
A15: P8 | B15: 1. Plastic | C15: WHEEL HUB W | F15: PLASTIC ASSY,ELM5/FSG-E1J4,WHEEL HUB W,Pantone Cool Grey 6C,RoHS | G15: 5881-1047-0GA0 | I15: 1 | L15: 1.8 | M15: PC 141R | N15: Pantone Cool Grey 6C | O15: Pantone Cool Grey 6C /PC /VDI 21 | P15: 廠內-塑件 | U15: 0.100023 | V15: =U15*I15 -> 0.100023 | W15: 1 | X15: 8 | AA15: =W15*(Y15+Z15) -> 0 | AC15: 0.0793 | AD15: =I15*AC15 -> 0.0793 | AE15: =(V15-AD15)/AD15 -> 0.26132409 | AI15: =W15*(AG15+AH15) -> 0 | AJ15: =(AA15-AI15)/AI15 -> #DIV/0!
A16: P9 | B16: 1. Plastic | C16: SWITCH CUSHION | F16: PLASTIC,NINJA/FSG-E1J0,SWITCH CUSHION,PA66,RoHS | G16: 5811-1043-08A0 | I16: 1 | L16: 0.05 | M16: PA66 | N16: Black | P16: 頂鈞 | T16: 沿用ELM5物料 | U16: 0.031522844 | V16: =U16*I16 -> 0.031522844 | W16: 1 | X16: 8 | AA16: =W16*(Y16+Z16) -> 0 | AC16: 0.0287 | AD16: =I16*AC16 -> 0.0287 | AE16: =(V16-AD16)/AD16 -> 0.098356945 | AI16: =W16*(AG16+AH16) -> 0 | AJ16: =(AA16-AI16)/AI16 -> #DIV/0!
A17: P10 | B17: 1. Plastic | C17: LED CLIP | F17: PLASTIC ASSY,ELM5/FSG-E1J4,LED CLIP,LCP,BLACK,RoHS | G17: 5881-1047-08A0 | I17: 1 | L17: 0.2 | M17: ABS | N17: Black | P17: 廠內-塑件 | T17: 沿用ELM5物料 | U17: 0.104133 | V17: =U17*I17 -> 0.104133 | W17: 1 | X17: 8 | AA17: =W17*(Y17+Z17) -> 0 | AC17: 0.1011 | AD17: =I17*AC17 -> 0.1011 | AE17: =(V17-AD17)/AD17 -> 0.03 | AI17: =W17*(AG17+AH17) -> 0 | AJ17: =(AA17-AI17)/AI17 -> #DIV/0!
A18: R1 | B18: 3. Rubber | C18: WHEEL GRIP W1 | F18: RUBBER,ELM5/FSG-E1J4,WHEEL GRIP W1,Pantone Cool Grey 6C,RoHS | G18: 5813-1047-04A0 | I18: 0 | M18: Silicon rubber | N18: Pantone Cool Grey 6C | O18: Pantone Cool Grey 6C /Silicon Rubber /VDI 24 (Arrow) | U18: 0.081 | V18: =U18*I18 -> 0 | W18: 1 | X18: 36 | AA18: =W18*(Y18+Z18) -> 0 | AC18: 0.0732 | AD18: =I18*AC18 -> 0 | AE18: =(V18-AD18)/AD18 -> #DIV/0! | AI18: =W18*(AG18+AH18) -> 0 | AJ18: =(AA18-AI18)/AI18 -> #DIV/0!
A19: R2 | B19: 3. Rubber | C19: WHEEL GRIP W2 | F19: RUBBER,ELM5/FSG-E1J4,WHEEL GRIP W2,Pantone Cool Grey 6C,RoHS | G19: 5813-1047-05A0 | I19: 1 | M19: Silicon rubber | N19: Pantone Cool Grey 6C | O19: Pantone Cool Grey 6C /Silicon Rubber /VDI 24 (Horizontal V2) | P19: 鑫永成 | U19: 0.081 | V19: =U19*I19 -> 0.081 | AA19: =W19*(Y19+Z19) -> 0 | AC19: =0.47/7 -> 0.067142857 | AD19: =I19*AC19 -> 0.067142857 | AE19: =(V19-AD19)/AD19 -> 0.20638298 | AI19: =W19*(AG19+AH19) -> 0 | AJ19: =(AA19-AI19)/AI19 -> #DIV/0!
A20: R3 | B20: 3. Rubber | C20: WHEEL GRIP W3 | F20: RUBBER,ELM5/FSG-E1J4,WHEEL GRIP W3,Pantone Cool Grey 6C,RoHS | G20: 5813-1047-06A0 | I20: 0 | M20: Silicon rubber | N20: Pantone Cool Grey 6C | O20: Pantone Cool Grey 6C /Silicon Rubber /VDI 24 (Topographic) | U20: 0.081 | V20: =U20*I20 -> 0 | AA20: =W20*(Y20+Z20) -> 0 | AC20: 0.0732 | AD20: =I20*AC20 -> 0 | AE20: =(V20-AD20)/AD20 -> #DIV/0! | AI20: =W20*(AG20+AH20) -> 0 | AJ20: =(AA20-AI20)/AI20 -> #DIV/0!
A21: O1 | B21: 4. Others | C21: PTFE FEET PAD UP W | F21: MYLAR,ELM5/FSG-E1J4,PTFE FEET PAD UP WHITE,RoHS | G21: 581C-1047-05A0 | I21: 2 | M21: PTFE (TEFLON) | N21: White (電暈) 鈉化 | O21: White /Virgin Grade PTFE /High Gloss 含保護膜(透明) | P21: 德暉 | U21: 0.03 | V21: =U21*I21 -> 0.06 | AA21: =W21*(Y21+Z21) -> 0 | AC21: 0.028 | AD21: =I21*AC21 -> 0.056 | AE21: =(V21-AD21)/AD21 -> 0.071428571 | AI21: =W21*(AG21+AH21) -> 0 | AJ21: =(AA21-AI21)/AI21 -> #DIV/0!
A22: O2 | B22: 4. Others | C22: PTFE FEET PAD DOWN W | F22: MYLAR,ELM5/FSG-E1J4,PTFE FEET PAD DOWN WHITE,RoHS | G22: 581C-1047-06A0 | I22: 1 | M22: PTFE (TEFLON) | N22: White (電暈) 鈉化 | O22: White /Virgin Grade PTFE /High Gloss 含保護膜(透明) | P22: 德暉 | U22: 0.153 | V22: =U22*I22 -> 0.153 | AA22: =W22*(Y22+Z22) -> 0 | AC22: 0.145 | AD22: =I22*AC22 -> 0.145 | AE22: =(V22-AD22)/AD22 -> 0.055172414 | AI22: =W22*(AG22+AH22) -> 0 | AJ22: =(AA22-AI22)/AI22 -> #DIV/0!
A23: O3 | B23: 4. Others | C23: SCREW T2x6mm | F23: SCREW,MILD STEEL,ZINC BLACK,NINJA/FSG-E1J0,T2x6mm,CROSS,1018A BLACK,ZN,RoHS | G23: 0961-0003-83A0 | I23: 4 | M23: A1018 | N23: Sliver | O23: 自攻,十字槽,鍍鎳,D3.5*頭厚1.3*L6 | P23: 高億/or 2nd source | T23: 沿用ELM5物料 | U23: 0.00385 | V23: =U23*I23 -> 0.0154 | AA23: =W23*(Y23+Z23) -> 0 | AC23: 0.00309 | AD23: =I23*AC23 -> 0.01236 | AE23: =(V23-AD23)/AD23 -> 0.24595469 | AI23: =W23*(AG23+AH23) -> 0 | AJ23: =(AA23-AI23)/AI23 -> #DIV/0!
A24: O4 | B24: 4. Others | C24: SCREW P2x4mm | F24: SCREW,MILD STEEL,ZINC BLACK,NINJA/FSG-E1J0, P2x4mm,CROSS,1018A BLACK,ZN,RoHS | G24: 0961-0004-83A0 | I24: 9 | M24: A1018 | N24: Black | O24: 自攻,十字槽,鍍黑鎳,D3.5*頭厚1.3*L4 | P24: 高億/or 2nd source | T24: 沿用ELM5物料 | U24: 0.00495 | V24: =U24*I24 -> 0.04455 | AA24: =W24*(Y24+Z24) -> 0 | AC24: 0.003 | AD24: =I24*AC24 -> 0.027 | AE24: =(V24-AD24)/AD24 -> 0.65 | AI24: =W24*(AG24+AH24) -> 0 | AJ24: =(AA24-AI24)/AI24 -> #DIV/0!
A25: O5 | B25: 4. Others | C25: SCREW P2x4mm | F25: SCREW,MILD STEEL,ZINC WHITE, P2x4mm,CROSS,1018A WHITE,ZN,RoHS,LEFT-HAND THREAD | G25: 0961-0006-81A0 | I25: 1 | M25: A1018 | N25: White | O25: 自攻,十字槽,鍍白鋅,D3.5*頭厚1.3*L4, 左旋螺絲 | P25: 力工 | T25: 沿用ELM5物料 | U25: 0.00495 | V25: =U25*I25 -> 0.00495 | AA25: =W25*(Y25+Z25) -> 0 | AC25: =0.0385/7 -> 0.0055 | AD25: =I25*AC25 -> 0.0055 | AE25: =(V25-AD25)/AD25 -> -0.1 | AI25: =W25*(AG25+AH25) -> 0 | AJ25: =(AA25-AI25)/AI25 -> #DIV/0!
V26: =U26*I26 -> 0 | AA26: =W26*(Y26+Z26) -> 0 | AD26: =I26*AC26 -> 0 | AE26: =(V26-AD26)/AD26 -> #DIV/0! | AI26: =W26*(AG26+AH26) -> 0 | AJ26: =(AA26-AI26)/AI26 -> #DIV/0!
V27: =U27*I27 -> 0 | AA27: =W27*(Y27+Z27) -> 0 | AD27: =I27*AC27 -> 0 | AE27: =(V27-AD27)/AD27 -> #DIV/0! | AI27: =W27*(AG27+AH27) -> 0 | AJ27: =(AA27-AI27)/AI27 -> #DIV/0!
U29: Total cost | V29: =SUM(V8:V27) -> 1.815194 | AA29: =SUM(AA8:AA27) -> 0 | AD29: =SUM(AD8:AD27) -> 1.7058044 | AE29: =(V29-AD29)/AD29 -> 0.064127847 | AI29: =SUM(AI8:AI27) -> 0 | AJ29: =(AA29-AI29)/AI29 -> #DIV/0!

Sheet EE bom 0227
C1: A | D1: A_8/5 | E1: ELM5 Gen2 2024/02/23 | Q1: ELM5 A | R1: ELM5 A_8/5 | S1: ELM5 Gen2 022724 | T1: ELM5 Gen2 022724
B2: Main Board | W2: True Cost
B3: Item | C3: Qt'y | D3: Qt'y | E3: Qt'y | F3: FLK P/N | G3: Type | H3: SMD/DIP/ASSEMBLY | I3: Description | J3: Reference | K3: Vendor | L3: Part number | M3: MOQ/SPQ | N3: L/T(WKS) | O3: L/T(WKS) | P3: U/P (USD) | Q3: Sub-Total | R3: Sub-Total | S3: U/P (USD) | T3: Sub-Total | U3: Remark | W3: 022624 EV phase (to China) | X3: 022624 EV phase (out of China) | Y3: MAX (USD) | Z3: 022624 sub-total (USD) | AA3: Mark up % | AB3: 重量 | AC3: 中文品名 | AD3: 20221117 U/P True | AE3: 20221021 U/P True | AF3: 202200812 U/P True | AG3: Max | AH3: 20221201 poc3 Total | AI3: Mark up % | AJ3: 20220812 poc2 Total | AK3: Mark up % | AL3: Difference | AM3: Customer | AN3: Project | AO3: PO to | AP3: PIC | AQ3: Sourcing Remarks | AR3: DPM Remarks | AS3: Value
B4: Capacitor
B5: 1 | C5: 0 | D5: 0 | E5: 0 | G5: Capacitor | H5: SMD | I5: C-SMD,CERAMIC,16V,10uF,±10%,0603,X5R,RoHS | K5: Murata | L5: GRM188R60J106ME47D | M5: 4K | N5: 32WK | O5: DV2 | P5: 0.018 | Q5: =$P5*C5 -> 0 | R5: =P5*D5 -> 0 | S5: 0.018 | U5: 1/2 From 4 to 0
K6: Semco | L6: CL21A106KOQNNNE | M6: 4K | N6: 32WK | O6: 32WK | Q6: =$P6*C6 -> 0
B7: 1 | C7: 3 | D7: 3 | E7: 3 | F7: 07CA-106M-A3A0 | G7: Capacitor | H7: SMD | I7: C-SMD,CERAMIC,10V,10uF,±20%,0603,X5R,RoHS | K7: Semco | L7: CL10A106MP8NNNC | M7: 4K | N7: 19WK | O7: 8/13 Update | P7: 0.01125 | Q7: =$P7*C7 -> 0.03375 | R7: =P7*D7 -> 0.03375 | S7: 0.01125 | T7: =S7*E7 -> 0.03375 | U7: 1/2 From 0 to 3 | W7: 0.0035 | Z7: =W7*E7 -> 0.0105 | AA7: =(P7-W7)/W7 -> 2.2142857
K8: WALSIN | L8: 0603X106M100CT
K9: YAGEO | L9: CC0603MRX5R6BB106
K10: Murata | L10: GRM188R61A106KE69D | M10: 4K | N10: 25WK | O10: 25WK | Q10: =$P10*C10 -> 0
B11: 2 | C11: 1 | D11: 1 | E11: 1 | F11: 07CB-106K-B3A1 | G11: Capacitor | H11: SMD | I11: C-SMD,CERAMIC,16V,10uF,±10%,0805,X5R,RoHS | K11: Semco | L11: CL21A106KOQNNNE | M11: 2k | N11: 19WK | O11: 19WK | P11: 0.00759 | Q11: =$P11*C11 -> 0.00759 | R11: =P11*D11 -> 0.00759 | S11: 0.00759 | T11: =S11*E11 -> 0.00759 | U11: 1/2 From 0 to 1 | W11: 0.0076 | Z11: =W11*E11 -> 0.0076 | AA11: =(P11-W11)/W11 -> -0.0013157895
K12: Murata | L12: GRM21BR61C106KE15L
B13: 3 | C13: 11 | D13: 11 | E13: 11 | F13: 07CA-104K-73A1 | G13: Capacitor | H13: SMD | I13: C-SMD,CERAMIC,10V,0.1uF,±10%,0402,X5R,RoHS | J13: Carton Outside dimensions: (L)213X(W)165X(H)185mm(L)321X(W)106X(H)182mm; (L)182X(W)149X(H)175mm; Material: A. Material type: Corrugated fibreboard B. Flute: C Flute C. Grade: 200# Mullen Burst OR 32 ECT Print: Black Joint: Glued inside | K13: WALSIN | L13: 0402X104K100CT | M13: 10k | N13: 36wk | O13: 36wk | P13: 0.00525 | Q13: =$P13*C13 -> 0.05775 | R13: =P13*D13 -> 0.05775 | S13: 0.00525 | T13: =S13*E13 -> 0.05775 | U13: ` | W13: 0.00035 | Z13: =W13*E13 -> 0.00385 | AA13: =(P13-W13)/W13 -> 14
K14: YAGEO | L14: CC0402KRX5R6BB104 | M14: 10k | N14: 28wk | O14: 28wk | Q14: =$P14*C14 -> 0
K15: DARFON | L15: C1005X5R104KDTS | M15: 10K | N15: 32WK | O15: =RC[-1] | Q15: =$P15*C15 -> 0
K16: Murata | L16: GRM155R61A104KA01D
K17: Semco | L17: CL05A104KP5NNNC | M17: 10k | N17: 28wk | O17: =RC[-1] | Q17: =$P17*C17 -> 0
B18: 4 | C18: 4 | D18: 4 | E18: 4 | F18: 07CA-105K-73A1 | G18: Capacitor | H18: SMD | I18: C-SMD,CERAMIC,10V,1uF,±10%,0402,X5R,RoHS | K18: YAGEO | L18: CC0402KRX5R6BB105 | M18: 10K | N18: 28WK | O18: 28WK | P18: 0.018 | Q18: =$P18*C18 -> 0.072 | R18: =P18*D18 -> 0.072 | S18: 0.018 | T18: =S18*E18 -> 0.072 | W18: 0.00081 | Z18: =W18*E18 -> 0.00324 | AA18: =(P18-W18)/W18 -> 21.222222
K19: WALSIN | L19: 0402X105K100CT | M19: X | N19: X | O19: X | Q19: =$P19*C19 -> 0
K20: DARFON | L20: C1005X5R105KDTS | M20: X | N20: X | O20: X | Q20: =$P20*C20 -> 0
K21: SAMSUNG | L21: CL05A105KP5NNNC | M21: X | N21: X | O21: X | Q21: =$P21*C21 -> 0
K22: Murata | L22: GRM155R61A105KE15D
K23: Kyocera | L23: CM05X5R105K35AH-MF | M23: X | N23: X | O23: X | Q23: =$P23*C23 -> 0
B24: 5 | C24: 1 | D24: 1 | E24: 1 | F24: 07CA-475M-73A0 | G24: Capacitor | H24: SMD | I24: C-SMD,CERAMIC,10V,4.7uF,±20%,0402,X5R,RoHS | K24: Murata | L24: GRM155R61A475MEAAD | M24: 10k | N24: 31wk | O24: 31wk | P24: 0.0237 | Q24: =$P24*C24 -> 0.0237 | R24: =P24*D24 -> 0.0237 | S24: 0.0237 | T24: =S24*E24 -> 0.0237 | W24: 0.0028 | Z24: =W24*E24 -> 0.0028 | AA24: =(P24-W24)/W24 -> 7.4642857
K25: YAGEO | L25: CC0402MRX5R6BB475 | M25: x | N25: x | O25: x | Q25: =$P25*C25 -> 0
K26: SAMSUNG | L26: CL05A475MP5NRNC | M26: 10k | N26: 21wk | O26: 21wk | Q26: =$P26*C26 -> 0
K27: DARFON | L27: C1005X5R475MDTS | M27: 10k | N27: 33wk | O27: 33wk | Q27: =$P27*C27 -> 0
B28: 6 | C28: 2 | D28: 2 | E28: 2 | F28: 07CG-270J-71A0 | G28: Capacitor | H28: SMD | I28: C-SMD,CERMAIC,50V,27pF,±5%,0402,NPO,RoHS | K28: YAGEO | L28: CC0402JRNPO9BN270 | M28: 10k | N28: 28wk | O28: 28wk | P28: 0.003 | Q28: =$P28*C28 -> 0.006 | R28: =P28*D28 -> 0.006 | S28: 0.003 | T28: =S28*E28 -> 0.006 | W28: 0.00045 | Z28: =W28*E28 -> 0.0009 | AA28: =(P28-W28)/W28 -> 5.6666667
K29: WALSIN | L29: 0402N270J500CT | M29: 10k | N29: 36wk | O29: 36wk | Q29: =$P29*C29 -> 0
K30: DARFON | L30: C1005NPO270JGTS | M30: 10k | N30: 36wk | O30: 36wk | Q30: =$P30*C30 -> 0
K31: MURATA | L31: GRM1555C1H270JA01D | M31: X | N31: X | O31: X | Q31: =$P31*C31 -> 0
B32: 7 | C32: 3 | D32: 3 | E32: 3 | F32: 07CA-225M-73A0 | G32: Capacitor | H32: SMD | I32: C-SMD,CERAMIC,10V,2.2uF,±20%,0402,X5R,RoHS | K32: Murata | L32: GRM155R61A225KE95D | M32: 10K | N32: 33WKS | O32: 33WKS | P32: 0.0072 | Q32: =$P32*C32 -> 0.0216 | R32: =P32*D32 -> 0.0216 | S32: 0.0072 | T32: =S32*E32 -> 0.0216 | W32: 0.00245 | Z32: =W32*E32 -> 0.00735 | AA32: =(P32-W32)/W32 -> 1.9387755
K33: Semco | L33: CL05A225MP5NSNC | M33: 10K | N33: 17WKS | O33: 17WKS | Q33: =$P33*C33 -> 0
B34: 8 | C34: 1 | D34: 1 | E34: 1 | F34: 07CD-822K-74A0 | G34: Capacitor | H34: SMD | I34: C-SMD,CERAMIC,25V,8.2nF,±10%,0402,X7R,RoHS | K34: YAGEO | L34: CC0402KRX7R8BB822 | M34: 10K | N34: 8WKS | O34: 8WKS | P34: 0.0048 | Q34: =$P34*C34 -> 0.0048 | R34: =P34*D34 -> 0.0048 | S34: 0.0048 | T34: =S34*E34 -> 0.0048 | U34: 7/9 add new parts from 0 to 1 | W34: 0.00096 | Z34: =W34*E34 -> 0.00096 | AA34: =(P34-W34)/W34 -> 4
K35: WALSIN | L35: 0402B822K250CT | M35: 10K | N35: 8WKS | O35: 8WKS
K36: Murata | L36: GRM155R71E822KA01D | M36: 10K | N36: 10WKS | O36: 10WKS
B37: Resistor
B38: 7 | C38: 0 | D38: 0 | E38: 0 | G38: Resistor | H38: SMD | I38: R-SMD,CERAMIC,0402,1.5KΩ,1/16W,1%,RoHS | K38: WALSIN | L38: WR04X1501FTL | M38: 10k | N38: 17wk | O38: 17wk | P38: 0.001125 | Q38: =$P38*C38 -> 0 | R38: =P38*D38 -> 0 | S38: 0.001125
K39: YAGEO | L39: RC0402FR-071K5L | M39: 10k | N39: 17wk | O39: 17wk | Q39: =$P39*C39 -> 0
K40: TA-I | L40: RM04FTN1501 | M40: 10k | N40: 17wk | O40: 17wk | Q40: =$P40*C40 -> 0
B41: 9 | C41: 1 | D41: 1 | E41: 1 | F41: 0023-1002-33A0 | G41: Resistor | H41: SMD | I41: R-SMD,CERAMIC,0402,10KΩ,1/16W,5%,RoHS | K41: WALSIN | L41: WR04X103JTL | M41: 10k | N41: 17wk | O41: 17wk | P41: 0.0009 | Q41: =$P41*C41 -> 0.0009 | R41: =P41*D41 -> 0.0009 | S41: 0.0009 | T41: =S41*E41 -> 0.0009 | U41: 7/9 From 2 to 1 | W41: 0.00015 | Z41: =W41*E41 -> 0.00015 | AA41: =(P41-W41)/W41 -> 5
K42: YAGEO | L42: RC0402JR-0710KL | M42: 10k | N42: 17wk | O42: 17wk | Q42: =$P42*C42 -> 0
K43: TA-I | L43: RM04JTN103 | M43: 10k | N43: 17wk | O43: 17wk | Q43: =$P43*C43 -> 0
B44: 9 | C44: 0 | D44: 0 | E44: 0 | G44: Resistor | H44: SMD | I44: R-SMD,CERAMIC,0402,82Ω,1/16W,1%,RoHS | K44: WALSIN | L44: WR04X82R0FTL | M44: 10k | N44: 17wk | O44: 17wk | P44: 0.001125 | Q44: =$P44*C44 -> 0 | R44: =P44*D44 -> 0 | S44: 0.001125 | U44: 7/9 From 1 to 0
K45: YAGEO | L45: RC0402FR-0782RL | M45: 10k | N45: 17wk | O45: 17wk | Q45: =$P45*C45 -> 0
K46: TA-I | L46: RM04FTN82R0 | M46: 10k | N46: 17wk | O46: 17wk | Q46: =$P46*C46 -> 0
B47: 10 | C47: 1 | D47: 1 | E47: 1 | F47: 0023-0430-31A0 | G47: Resistor | H47: SMD | I47: R-SMD,CERAMIC,0402,43Ω,1/16W,1%,RoHS | K47: WALSIN | L47: WR04X43R0FTL | M47: 10k | N47: 17wk | O47: 17wk | P47: 0.00069 | Q47: =$P47*C47 -> 0.00069 | R47: =P47*D47 -> 0.00069 | S47: 0.00069 | T47: =S47*E47 -> 0.00069 | U47: 7/9 add new parts from 0 to 1 | W47: 0.00017 | Z47: =W47*E47 -> 0.00017 | AA47: =(P47-W47)/W47 -> 3.0588235
K48: YAGEO | L48: RC0402FR-0743RL | M48: 10k | N48: 17wk | O48: 17wk
K49: TA-I | L49: RM04FTN43R0 | M49: 10k | N49: 17wk | O49: 17wk
K50: ROYALOHM | L50: 0402WGF430JTCE
B51: 11 | C51: 7 | D51: 7 | E51: 7 | F51: 0023-0000-33A1 | G51: Resistor | H51: SMD | I51: R-SMD,CERAMIC,0402,0Ω,1/16W,RoHS | K51: WALSIN | L51: WR04X000 PTL | M51: 10k | N51: 17wk | O51: 17wk | P51: 0.001035 | Q51: =$P51*C51 -> 0.007245 | R51: =P51*D51 -> 0.007245 | S51: 0.001035 | T51: =S51*E51 -> 0.007245 | U51: 7/9 From 6 to 7 | W51: 0.00015 | Z51: =W51*E51 -> 0.00105 | AA51: =(P51-W51)/W51 -> 5.9
K52: YAGEO | L52: RC0402FR-070RL | M52: 10k | N52: 17wk | O52: 17wk | Q52: =$P52*C52 -> 0
K53: TA-I | L53: RM04JTN0 | M53: 10k | N53: 17wk | O53: 17wk | Q53: =$P53*C53 -> 0
B54: 12 | C54: 2 | D54: 2 | E54: 2 | F54: 0023-0270-31A0 | G54: Resistor | H54: SMD | I54: R-SMD,CERAMIC,0402,27Ω,1/16W,1%,RoHS | K54: WALSIN | L54: WR04X27R0FTL | M54: 10k | N54: 17wk | O54: 17wk | P54: 0.00069 | Q54: =$P54*C54 -> 0.00138 | R54: =P54*D54 -> 0.00138 | S54: 0.00069 | T54: =S54*E54 -> 0.00138 | U54: 7/9 add new parts from 0 to 2 | W54: 0.00017 | Z54: =W54*E54 -> 0.00034 | AA54: =(P54-W54)/W54 -> 3.0588235
K55: YAGEO | L55: RC0402FR-0727RL | M55: 10k | N55: 17wk | O55: 17wk
B56: 13 | C56: 1 | D56: 1 | E56: 1 | F56: 0023-3003-33A1 | G56: Resistor | H56: SMD | I56: R-SMD,CERAMIC,0402,300KΩ,1/16W,5%,RoHS | K56: WALSIN | L56: WR04X304JTL | M56: 10k | N56: 17wk | O56: 17wk | W56: 0.00015
K57: YAGEO | L57: RC0402JR-07300KL | M57: 10k | N57: 17wk | O57: 17wk | P57: 0.0006 | Q57: =P57*C56 -> 0.0006 | R57: =P57*D56 -> 0.0006 | S57: 0.0006 | T57: =S57*E56 -> 0.0006 | U57: 7/9 add new parts from 0 to 1 | W57: 0.00015 | Y57: =MAX(Z56:Z57) -> 0.00015 | Z57: =W57*E56 -> 0.00015 | AA57: =(S57-Y57)/Y57 -> 3
B58: 12 | C58: 0 | D58: 0 | E58: 0 | G58: Resistor | H58: SMD | I58: R-SMD,CERAMIC,0402,3.3KΩ,1/16W,5%,RoHS | K58: WALSIN | L58: WR04X332 JTL | M58: 10k | N58: 17wk | O58: 17wk | P58: 0.0009 | Q58: =$P58*C58 -> 0 | R58: =P58*D57 -> 0 | S58: 0.0009 | U58: 7/9 Remove parts form 1 to 0
K59: YAGEO | L59: RC0402JR-073K3L | M59: 10k | N59: 17wk | O59: 17wk | Q59: =$P59*C59 -> 0
K60: TA-I | L60: RM04JTN332 | M60: 10k | N60: 17wk | O60: 17wk | Q60: =$P60*C60 -> 0
B61: RGB LEDs circuit : 3 Zones +1 LOGO ( 6 LEDs)
B62: 12 | C62: 0 | D62: 0 | E62: 0 | G62: Diode/LED | H62: SMD | I62: LED,RGB COLOR,3.5mm*2.8mm*1.45mm,SMD,6 PIN | K62: LITEON | L62: LTST-G683GEBW-FL | M62: 2K | N62: 8wks | O62: 8wks | P62: 0.098 | Q62: =$P62*C62 -> 0 | R62: =P62*D62 -> 0 | S62: 0.098 | U62: 7/9 Remove parts form 6 to 0
B63: 14 | C63: 6 | D63: 6 | E63: 5 | F63: 0602-000U-S0A0 | G63: Diode/LED | H63: SMD | I63: LED,RGB COLOR,3.5mm*2.8mm*1.45mm,SMD,6 PIN ( BIN：A5, A6, B5, B6, B7) | K63: Lite-on | L63: LTST-G683GEBW-FL1 | M63: 2K | N63: 8wks | O63: 8wks | P63: 0.098 | Q63: =$P63*C63 -> 0.588 | R63: =P63*D63 -> 0.588 | S63: 0.098 | T63: =S63*E63 -> 0.49 | U63: 7/9 add new parts from 0 to 6 | W63: 0.089 | Z63: =W63*E63 -> 0.445 | AA63: =(P63-W63)/W63 -> 0.1011236
B64: 13 | C64: 0 | D64: 0 | E64: 0 | G64: Capacitor | H64: SMD | I64: C-SMD,CERAMIC,10V,4.7uF,±20%,0402,X5R,RoHS | K64: Murata | L64: GRM155R61A475MEAAD | M64: 10k | N64: 31wk | O64: 31wk | P64: 0.01485 | Q64: =$P64*C64 -> 0 | R64: =P64*D64 -> 0 | S64: 0.01485
K65: YAGEO | L65: CC0402MRX5R6BB475 | M65: x | N65: x | O65: x | Q65: =$P65*C65 -> 0
K66: SAMSUNG | L66: CL05A475MP5NRNC | M66: 10k | N66: 21wk | O66: 21wk | Q66: =$P66*C66 -> 0
K67: DARFON | L67: C1005X5R475MDTS | M67: 10k | N67: 33wk | O67: 33wk | Q67: =$P67*C67 -> 0
B68: 15 | C68: 18 | D68: 18 | E68: 15 | F68: 0023-1002-33A0 | G68: Resistor | H68: SMD | I68: R-SMD,CERAMIC,0402,10KΩ,1/16W,5%,RoHS | K68: WALSIN | L68: WR04X103JTL | M68: 10k | N68: 17wk | O68: 17wk | P68: 0.00066 | Q68: =$P68*C68 -> 0.01188 | R68: =P68*D68 -> 0.01188 | S68: 0.00066 | T68: =S68*E68 -> 0.0099 | U68: 1/2 9 to 18pcs | W68: 0.00015 | Z68: =W68*E68 -> 0.00225 | AA68: =(P68-W68)/W68 -> 3.4
K69: YAGEO | L69: RC0402JR-0710KL | M69: 10k | N69: 17wk | O69: 17wk | Q69: =$P69*C69 -> 0
K70: TA-I | L70: RM04JTN103 | M70: 10k | N70: 17wk | O70: 17wk | Q70: =$P70*C70 -> 0
B71: 16 | C71: 6 | D71: 6 | E71: 0 | G71: Resistor | H71: SMD | I71: R-SMD,CERAMIC,0402,95.3Ω,1/16W,1%,RoHS | K71: YAGEO | L71: RC0402FR-0795R3L | M71: 10k | N71: 17wk | O71: 17wk | P71: 0.000825 | Q71: =$P71*C71 -> 0.00495 | R71: =P71*D71 -> 0.00495 | S71: 0.000825 | U71: 1/2 3 to 6pcs
K72: WALSIN | L72: WR04X95R3FTL | M72: 10k | N72: 17wk | O72: 17wk | Q72: =$P72*C72 -> 0
K73: TA-I | L73: RM04FTN95R3 | M73: 10k | N73: 17wk | O73: 17wk | Q73: =$P73*C73 -> 0
C74: 0 | D74: 0 | E74: 4 | F74: 0023-0910-31A0 | G74: Resistor | I74: R-SMD,CERAMIC,0402,91Ω,1/16W,1%,RoHS | K74: YAGEO | L74: RC0402FR-0791RL | S74: =W74*2 -> 0.00034 | T74: =S74*E74 -> 0.00136 | W74: 0.00017 | Z74: =W74*E74 -> 0.00068 | AA74: =(S74-W74)/W74 -> 1
K75: WALSIN | L75: WR04X91R0FTL
K76: ROYALOHM | L76: 0402WGF910JTCE
B77: 17 | C77: 6 | D77: 6 | E77: 0 | G77: Resistor | H77: SMD | I77: R-SMD,CERAMIC,0402,162Ω,1/16W,1%,RoHS | K77: YAGEO | L77: RC0402FR-07162RL | M77: 10k | N77: 17wk | O77: 17wk | P77: 0.00825 | Q77: =$P77*C77 -> 0.0495 | R77: =P77*D77 -> 0.0495 | S77: 0.00825 | U77: 1/2 3 to 6pcs
K78: WALSIN | L78: WR04X1620FTL | M78: 10k | N78: 17wk | O78: 17wk | Q78: =$P78*C78 -> 0
K79: TA-I | L79: RM04FTN1620 | M79: 10K | N79: 17WK | O79: 17WK | Q79: =$P79*C79 -> 0
C80: 0 | D80: 0 | E80: 4 | F80: 0023-0620-31A0 | G80: Resistor | I80: R-SMD,CERAMIC,0402,62Ω,1/16W,1%,RoHS | K80: YAGEO | L80: RC0402FR-0762RL | S80: =W80*2 -> 0.00034 | T80: =S80*E80 -> 0.00136 | W80: 0.00017 | Z80: =W80*E80 -> 0.00068 | AA80: =(S80-W80)/W80 -> 1
K81: WALSIN | L81: WR04X62R0FTL
K82: ROYALOHM | L82: 0402WGF620JTCE
B83: 18 | C83: 6 | D83: 6 | E83: 0 | G83: Resistor | H83: SMD | I83: R-SMD,CERAMIC,0402,93.1Ω,1/16W,1%,RoHS | K83: YAGEO | L83: RC0402FR-0793R1L | M83: 10k | N83: 17wk | O83: 17wk | P83: 0.000825 | Q83: =$P83*C83 -> 0.00495 | R83: =P83*D83 -> 0.00495 | S83: 0.000825 | U83: 1/2 3 to 6pcs
K84: WALSIN | L84: WR04X93R1FTL | M84: 10k | N84: 17wk | O84: 17wk | Q84: =$P84*C84 -> 0
K85: TA-I | L85: RM04FTN93R1 | M85: 10K | N85: 17wk | O85: 17wk | Q85: =$P85*C85 -> 0
C86: 0 | D86: 0 | E86: 4 | F86: 0023-0820-31A1 | G86: Resistor | I86: R-SMD,CERAMIC,0402,82Ω,1/16W,1%,RoHS | K86: YAGEO | L86: RC0402FR-0782RL | S86: =W86*2 -> 0.00034 | T86: =S86*E86 -> 0.00136 | W86: 0.00017 | Z86: =W86*E86 -> 0.00068 | AA86: =(S86-W86)/W86 -> 1
K87: WALSIN | L87: WR04X82R0FTL
K88: ROYALOHM | L88: 0402WGF820JTCE
B89: 18 | C89: 0 | D89: 0 | E89: 0 | G89: Resistor | H89: SMD | I89: R-SMD,CERAMIC,0603,2R7Ω,1/10W,5%,RoHS | K89: WALSIN | L89: WR06W2R70FTL | M89: 10k | N89: 17wk | O89: 17wk | P89: 0.001848 | Q89: =$P89*C89 -> 0 | R89: =P89*D89 -> 0 | S89: 0.001848
K90: YAGEO | L90: RC0603JR-072R7L | M90: 10k | N90: 17wk | O90: 17wk | Q90: =$P90*C90 -> 0
K91: TA-I | L91: RM06JTN2R7 | M91: 10K | N91: 17wk | O91: 17wk | Q91: =$P91*C91 -> 0
B92: 19 | C92: 0 | D92: 0 | E92: 1 | F92: 0023-0750-31A2 | G92: Resistor | I92: R-SMD,CERAMIC,0402,75Ω,1/16W,1%,RoHS | K92: YAGEO | L92: RC0402FR-0775RL | S92: =W92*2 -> 0.00034 | T92: =S92*E92 -> 0.00034 | W92: 0.00017 | Z92: =W92*E92 -> 0.00017 | AA92: =(S92-W92)/W92 -> 1
K93: WALSIN | L93: WR04X75R0FTL
K94: ROYALOHM | L94: 0402WGF750JTCE
B95: 20 | C95: 0 | D95: 0 | E95: 1 | F95: 0023-0430-31A0 | G95: Resistor | I95: R-SMD,CERAMIC,0402,43Ω,1/16W,1%,RoHS | K95: WALSIN | L95: WR04X43R0FTL | S95: =W95*2 -> 0.00034 | T95: =S95*E95 -> 0.00034 | W95: 0.00017 | Z95: =W95*E95 -> 0.00017 | AA95: =(S95-W95)/W95 -> 1
K96: YAGEO | L96: RC0402FR-0743RL
K97: TA-I | L97: RM04FTN43R0
K98: ROYALOHM | L98: 0402WGF430JTCE
B99: 21 | C99: 0 | D99: 0 | E99: 1 | F99: 0023-0680-31A1 | G99: Resistor | I99: R-SMD,CERAMIC,0402,68Ω,1/16W,1%,RoHS | K99: YAGEO | L99: RC0402FR-0768RL | S99: =W99*2 -> 0.00034 | T99: =S99*E99 -> 0.00034 | W99: 0.00017 | Z99: =W99*E99 -> 0.00017 | AA99: =(S99-W99)/W99 -> 1
K100: WALSIN | L100: WR04X68R0FTL
...

Sheet NRE Summary
A1: Project: Rival 3+
A2: Summary of all NREs | C2: 02/27/24 | I2: 02/27/2024
A3: Item # | B3: Description | C3: Qty | D3: U/P (USD) | E3: Sub- Total (USD) | F3: Delta | G3: Remark | I3: Qty | J3: U/P (USD) | K3: Sub- Total (USD) | L3: Remark
A4: 1 | B4: Build Cost | C4: 1 | D4: ='Build Cost'!E35 -> 13600 | E4: =D4*C4 -> 13600 | G4: 3/13 Update build qty from 300 to 200 for each color. | I4: 1 | J4: ='Build Cost'!M35 -> 33900.278 | K4: =J4*I4 -> 33900.278
A5: 2 | B5: EMC Test + EMC/Safety Certification | C5: 0 | D5: 0 | E5: 0 | G5: SS own | I5: 0 | J5: 0 | K5: 0
A6: 3 | B6: Budget for EMC Debugging Fee (hrs) | C6: 30 | D6: 125 | E6: =D6*C6 -> 3750 | G6: assume it will be needed due to new certificate | I6: 30 | J6: 125 | K6: =J6*I6 -> 3750
A7: 4 | B7: Compatibility Test | C7: 0 | D7: 0 | E7: =D7*C7 -> 0 | G7: FLK internal test. | I7: 0 | J7: 0 | K7: =J7*I7 -> 0
A8: 6 | B8: DVE NRE - Chromebook | C8: 1 | D8: 165 | E8: =D8*C8 -> 165 | I8: 1 | J8: 165 | K8: =J8*I8 -> 165
A9: 7 | B9: Travel Expense | C9: 2 | D9: ='Travel Expense'!E8 -> 6000 | E9: 0 | I9: 0 | J9: 0 | K9: =J9*I9 -> 0
A10: 8 | B10: Dev. + NPI Labor Cost | C10: 1 | D10: ='Dev+NPI Labor'!G45 -> 93299.4 | E10: 10000 | G10: 3/13 Reduced price from US$30,000 to US$10,000 for maintain long-term partnership. | I10: 1 | J10: 0 | K10: =J10*I10 -> 0
A11: 9 | B11: Reliability Test | C11: 1 | D11: ='RET (option2)'!Q30 -> 9158.9338 | E11: 1500 | G11: 031324: Updated if SS chose Option2. included EV+DV | I11: 1 | J11: ='RET (option2)'!U30 -> 824.22535 | K11: =J11*I11 -> 824.22535
B12: Package RET | C12: 1 | D12: ='PKG RET'!M13+'PKG RET'!N13 -> 2222.5352 | E12: 500 | G12: included EV+DV | I12: 1 | J12: ='PKG RET'!Q13 -> 346.12676 | K12: =J12*I12 -> 346.12676
B13: ORT | C13: 1 | D13: =ORT!I12+ORT!J12 -> 7530.2179 | E13: 361 | G13: 031024:Only charge sample fee first 2years ORT cost and samples cost (incl. EV+DV) | I13: 1 | J13: =ORT!M6+ORT!M7 -> 1994.6424 | K13: =J13*I13 -> 1994.6424
A14: 10 | B14: Unique Fixtures Cost (MTE) | C14: 1 | D14: ='MTE NRE'!G7+'MTE NRE'!I7+'MTE NRE'!G27+'MTE NRE'!I68 -> 80184.641 | E14: 5000 | G14: 031024:Only charge NPI phase fixture cost, FLK own MP fixture cost. | I14: 1 | J14: =D14 -> 80184.641 | K14: =J14*I14 -> 80184.641
A15: 11 | B15: Tooling | C15: 1 | D15: ='ME bom 0229_Black'!AA29+'ME bom 0229_White'!AA29 -> 3000 | E15: =D15*C15 -> 3000 | G15: 031024: Middle Housing & Trigger button tooling modify texture fee. | I15: 1 | J15: ='ME bom 0229_Black'!AI29+'ME bom 0229_White'!AD29 -> 2401.5404 | K15: =J15*I15 -> 2401.5404
D16: Total | E16: =SUM(E4:E15) -> 37876 | J16: Total | K16: =SUM(K4:K15) -> 123566.45

Sheet Build Cost
A1: Program name: Rival 3+ | K1: True cost
C2: Quotation | F2: Actual | I2: Comments | K2: Quotation : Hoist Gen2 | N2: Remark
D3: Unit | E3: Extended | G3: Unit | H3: Extended | L3: Unit | M3: Extended
A4: Phase | B4: Description | C4: Quantity | D4: Cost | E4: Cost | F4: Quantity | G4: Cost | H4: Cost | K4: Quantity | L4: Cost | M4: Cost
B5: Date of Run:
A6: EV | B6: Line Charges (with SMT and W/S) | C6: 2 | D6: 3000 | E6: 0 | I6: Assume 2line , 4days with both Black and White version. | K6: =C6 -> 2 | L6: =D6 -> 3000 | M6: =L6*K6 -> 6000
B7: Line Labor Charges | C7: 4 | D7: 2000 | E7: 0 | I7: with both for Balck and White ver. | K7: =C7 -> 4 | L7: =D7 -> 2000 | M7: =L7*K7 -> 8000
B8: EE + ME + PKG Material (Black) | C8: 200 | D8: 17 | E8: =D8*C8 -> 3400 | K8: =C8 -> 200 | L8: ='Unit Cost'!AI20 -> 7.2859473 | M8: =L8*K8 -> 1457.1895
B9: EE + ME + PKG Material (White) | C9: 200 | D9: 17 | E9: =D9*C9 -> 3400 | K9: =C9 -> 200 | L9: ='Unit Cost'!AI21 -> 7.4647483 | M9: =L9*K9 -> 1492.9497
E10: =D10*C10 -> 0 | K10: =C10 -> 0 | L10: ='PKG BOM 20240223'!V30 -> 0.4191448 | M10: =L10*K10 -> 0
B11: Shipping | C11: 0 | D11: 1 | E11: =D11*C11 -> 0 | I11: Use SS's account | K11: =C11 -> 0 | L11: 0 | M11: =L11*K11 -> 0
B12: Sub-Total | E12: =SUM(E6:E11) -> 6800 | M12: =SUM(M6:M10) -> 16950.139
B13: Date of Run:
A14: DV | B14: Line Charges (with SMT and W/S) | C14: 2 | D14: 3000 | E14: 0 | H14: =F14*G14 -> 0 | I14: Assume 2line , 4days with both Black and White version. | K14: =C14 -> 2 | L14: =D14 -> 3000 | M14: =L14*K14 -> 6000
B15: Line Labor Charges | C15: 4 | D15: 2000 | E15: 0 | H15: =F15*G15 -> 0 | I15: with both for Balck and White ver. | K15: =C15 -> 4 | L15: =D15 -> 2000 | M15: =L15*K15 -> 8000
B16: EE + ME Material (Black) | C16: 200 | D16: =D8 -> 17 | E16: =C16*D16 -> 3400 | H16: =F16*G16 -> 0 | K16: =C16 -> 200 | L16: =L8 -> 7.2859473 | M16: =L16*K16 -> 1457.1895
B17: EE + ME Material (White) | C17: 200 | D17: =D9 -> 17 | E17: =C17*D17 -> 3400 | K17: =C17 -> 200 | L17: =L9 -> 7.4647483 | M17: =L17*K17 -> 1492.9497
D18: =D10 -> 0 | E18: =C18*D18 -> 0 | K18: =C18 -> 0 | L18: =L10 -> 0.4191448 | M18: =L18*K18 -> 0
B19: Shipping | C19: 0 | D19: 1 | E19: =C19*D19 -> 0 | H19: =F19*G19 -> 0 | I19: Use SS's account | K19: =C19 -> 0 | L19: 0 | M19: =L19*K19 -> 0
B20: Sub-Total | E20: =SUM(E14:E19) -> 6800 | H20: =SUM(H14:H19) -> 0 | M20: =SUM(M14:M18) -> 16950.139
B21: Date of Run:
A22: PV | B22: Line Charges (with SMT and W/S) | E22: =C22*D22 -> 0 | H22: =F22*G22 -> 0
B23: Line Labor Charges | E23: =C23*D23 -> 0 | H23: =F23*G23 -> 0
B24: EE + ME Material | E24: =C24*D24 -> 0 | H24: =F24*G24 -> 0
B25: Shipping | E25: =C25*D25 -> 0 | H25: =F25*G25 -> 0
B26: Sample to SS | E26: =C26*D26 -> 0 | H26: =F26*G26 -> 0
B27: Sub-Total | E27: =SUM(E22:E26) -> 0 | H27: =SUM(H22:H26) -> 0
B28: Date of Run:
A29: MP | B29: Line Charges (with SMT and W/S) | E29: =C29*D29 -> 0 | H29: =F29*G29 -> 0
B30: Line Labor Charges | E30: =C30*D30 -> 0 | H30: =F30*G30 -> 0
B31: EE + ME Material | E31: =C31*D31 -> 0 | H31: =F31*G31 -> 0
B32: Shipping | E32: =C32*D32 -> 0 | H32: =F32*G32 -> 0
B33: Sample to SS | E33: =C33*D33 -> 0 | H33: =F33*G33 -> 0
B34: Sub-Total | E34: =SUM(E29:E33) -> 0 | H34: =SUM(H29:H33) -> 0
D35: Total Development Cost Request: | E35: =E12+E20+E27+E34 -> 13600 | H35: =SUM(H12+H20+H27+H34) -> 0 | L35: Total Development Cost Request: | M35: =SUM(M12,M20) -> 33900.278
M37: =(E35-M35)/M35 -> -0.59882335

Sheet PKG BOM 20240731_with FSC&減塑
A2: Steelseries Rival3 Gen2 RFQ - Package BOM list | L2: Date: 2024/6/18 | O2: True Cost | V2: 7.1
A3: Model Description: Steelseries Rival 3 Gen2 | J3: Rev.:A | K3: ELM5 Gen2 | O3: EV Phase | P3: 報價 in RMB w/ FSC certificate | S3: 報價 in USD w/ FSC certificate | U3: Markup | V3: Remark
A4: No. | B4: Level | C4: Foxlink P/N | D4: Customer P/N | E4: Customer Description | G4: Image | H4: Description | I4: Chinese Part name | J4: Unit Q'ty (pcs) | K4: Unit Price (USD/pc) ELM5 Gen2 | L4: Amount (USD) ELM5 Gen2 | M4: Remark | O4: QTY | P4: 單價 RMB | Q4: MOQ | R4: LT day | S4: 單價 USD | T4: Amount(USD)
A5: 1-1 | B5: 1 | C5: 584A-1047-00AC | D5: N/A | E5: Box | F5: material: 300g artpaper, 4C+1C PMS, printing: matte PP dimension：278x250mm | H5: Box Outside set-up dimensions:(LxWxD):153x86x46mm Flat sheet dimensions:(L)278x(W)250x(T)0.5mm Material:300gsm SBS Print: 4C+1C PMS Surface process: Matte PP film Joint: Glued inside Remark:包装原料需符合FSC认证要求 | I5: 彩盒 | J5: 1 | K5: 0.3033 | L5: =K5*J5 -> 0.3033 | M5: 031324: Paper with FSC certificate was 0.2821 | O5: 1 | P5: 1.06 | Q5: 5000 | R5: 14 | S5: =P5/$V$2 -> 0.14929577 | T5: =S5*J5 -> 0.14929577 | U5: =(K5-S5)/S5 -> 1.0315377 | V5: difference between FSC and w/o FSC | W5: =P5-'PKG BOM 20240223'!R4 -> 0.02 | X5: =(P5-'PKG BOM 20240223'!R4)/'PKG BOM 20240223'!R4 -> 0.019230769
A6: 2 | C6: 5811-1047-00A0 | D6: N/A | E6: Hanger | F6: material: 0.5T clear PET dimension：70x36.5mm | H6: Hang tab Outside dimensions:(LxW):60x40mm70x36.5mm Material: 0.5T PET (Clear) Other: Back side with Double sided tape (70x10mm) | I6: 掛鉤 | J6: 0 | K6: 0.062117647 | L6: =K6*J6 -> 0 | M6: MOQ:10K | O6: 1 | P6: 0.352 | Q6: 5000 | R6: 14 | S6: =P6/$V$2 -> 0.049577465 | T6: =S6*J6 -> 0 | U6: =(K6-S6)/S6 -> 0.25294118
A7: 2 | C7: TBD | D7: N/A | E7: Hanger | H7: Hang tab Outside dimensions:(LxW):70x36.5mm Material: 350gsm SBS对裱 Print: 1C (Pantone 1655C) Other: Back side with Double sided tape (70x10mm) | I7: 掛鉤 | J7: 1 | K7: 0.13994366 | L7: =K7*J7 -> 0.13994366 | O7: 1 | P7: 0.934 | Q7: 5000 | R7: 14 | S7: =P7/$V$2 -> 0.1315493 | T7: =S7*J7 -> 0.1315493 | U7: =(K7-S7)/S7 -> 0.063811563 | W7: =S7-S6 -> 0.081971831 | X7: =(S7-S6)/S6 -> 1.6534091
A8: 3 | B8: 1 | C8: 5843-1047-00A0 | D8: N/A | E8: paper insert | F8: material: E flute corrugated paper board, original color extension dimension：296x152mm | H8: Paper insert Outside dimensions:(LxWxD):380x164mm 296x152mm Material:E flute corrugated paper board, original color Process: Die-cut Remark:包装原料需符合FSC认证要求 | I8: 内纸卡 | J8: 1 | K8: =S8*1.2 -> 0.088715493 | L8: =K8*J8 -> 0.088715493 | M8: 031324: Paper with FSC certificate | O8: 1 | P8: 0.5249 | Q8: 3000 | R8: 14 | S8: =P8/$V$2 -> 0.073929577 | T8: =S8*J8 -> 0.073929577 | U8: =(K8-S8)/S8 -> 0.2 | V8: difference between FSC and w/o FSC | W8: =P8-'PKG BOM 20240223'!R6 -> 0.2199 | X8: =(P8-'PKG BOM 20240223'!R6)/'PKG BOM 20240223'!R6 -> 0.72098361
A9: 4 | B9: 1 | C9: 5649-1001-0LE0 5849-1020-00E0 | D9: N/A | E9: Seal label | F9: material: 19#PET, dimension: 25x25mm | H9: Seal label Outside dimensions:Φ=40mm25mm Material:Acrylic 25#19#TRANSPARENCY Can be use foxlink existing part P/N 5649-1020-00E0 | I9: 封口贴 | J9: 0 | K9: 0.0056338028 | L9: =K9*J9 -> 0 | M9: Can be use foxlink existing part P/N 5649-1001-0LE0 | O9: 2 | P9: 0.04 | Q9: 5000 | R9: 14 | S9: =P9/$V$2 -> 0.0056338028 | T9: =S9*J9 -> 0 | U9: =(K9-S9)/S9 -> 0 | V9: 022724:true cost update
A10: 4 | B10: 1 | C10: TBD | D10: N/A | E10: Seal label | H10: Seal label Outside dimensions:Φ25mm Material:53gsm 透明木浆纸+丙烯酸胶 &背80gsm格拉辛离型纸 Thickness: 50um +/-2 | I10: 封口贴 | J10: 2 | K10: =S10*1.2 -> 0.012 | L10: =K10*J10 -> 0.024 | O10: 2 | P10: 0.071 | Q10: 5000 | R10: 14 | S10: =P10/$V$2 -> 0.01 | T10: =S10*J10 -> 0.02 | U10: =(K10-S10)/S10 -> 0.2 | V10: 022724:true cost update | W10: =S10-S9 -> 0.0043661972 | X10: =(S10-S9)/S9 -> 0.775
A11: 5 | B11: 1 | C11: 5831-1047-00AB | D11: N/A | E11: PIG | F11: material: 80g woodfree paper; dimension: 320 x 200 mm, printing: 2C double side printing type: folding paper | H11: Manual Flat sheet dimensions(LxW): (L)320*(W)200mm Fold size: 80*100mm Material : 80gsm WFUC Print: 2C double side printing Process: Folding X 4 Remark:包装原料需符合FSC认证要求 | I11: 说明书 | J11: 1 | K11: 0.0628 | L11: =K11*J11 -> 0.0628 | M11: 031324: Paper with FSC certificate was 0.0584 | O11: 1 | P11: 0.289 | Q11: 5000 | R11: 14 | S11: =P11/$V$2 -> 0.040704225 | T11: =S11*J11 -> 0.040704225 | U11: =(K11-S11)/S11 -> 0.54283737 | V11: difference between FSC and w/o FSC | W11: =P11-'PKG BOM 20240223'!R8 -> 0.026 | X11: =(P11-'PKG BOM 20240223'!R8)/'PKG BOM 20240223'!R8 -> 0.098859316
A12: 6 | B12: 1 | C12: 5845-1047-00A0 | D12: N/A | E12: PE bag for mouse | F12: material:0.03T HDPE,1C printing dimension: 280x100mm | H12: PE Bag Dimensions(LxW): (L)215x(W)100mm (L)280x(W)100mm Material : 0.05mm LDPE Material : 0.03mm HDPE Print: Black only Process:Hole x1 | I12: 胶袋 | J12: 0 | K12: 0.017205882 | L12: =K12*J12 -> 0 | O12: 1 | P12: 0.067 | Q12: 10000 | R12: 15 | S12: =P12/$V$2 -> 0.0094366197 | T12: =S12*J12 -> 0 | U12: =(K12-S12)/S12 -> 0.82330992
A13: 6 | B13: 1 | C13: TBD | D13: N/A | E13: PE bag for mouse | H13: PE Bag Dimensions(LxW):(L)280x(W)100mm Material : 70%CPE+30%GMX Thickness: 0.05mm Print: Black only Process:Hole x1 厂商：新东颖 | I13: 胶袋 | J13: 0 | K13: =S13*1.2 -> 0.21971831 | L13: =K13*J13 -> 0 | O13: 1 | P13: 1.3 | Q13: 10000 | R13: 15 | S13: =P13/$V$2 -> 0.18309859 | T13: =S13*J13 -> 0 | U13: =(K13-S13)/S13 -> 0.2 | W13: =S13-S12 -> 0.17366197 | X13: =(S13-S12)/S12 -> 18.402985
A14: 6 | B14: 1 | C14: TBD | D14: N/A | E14: PE bag for mouse | H14: 雪梨紙 230*240mm 17g 雪梨紙 免印+切 | I14: 紙 | J14: 2 | K14: 0.012 | L14: =K14*J14 -> 0.024 | O14: 1 | P14: 0.07 | Q14: 5000 | R14: 15 | S14: =P14/$V$2 -> 0.0098591549 | T14: =S14*J14 -> 0.01971831 | U14: =(K14-S14)/S14 -> 0.21714286 | W14: =S14-S13 -> -0.17323944 | X14: =(S14-S13)/S13 -> -0.94615385
A15: 7 | B15: 1 | C15: 5842-1047-00A0 | D15: N/A | E15: Master Carton | F15: material: B flute, burst above 12KGF | H15: ‘Carton Outside dimensions: (L)213X(W)165X(H)185mm(L)321X(W)106X(H)182mm; (L)182X(W)149X(H)175mm; Material: A. Material type: Corrugated fibreboard B. Flute: C Flute C. Grade: 200# Mullen Burst OR 32 ECT Print: Black Joint: Glued inside Remark: 纸板原材料需符合FSC认证要求 | I15: 外箱 | J15: =1/6 -> 0.16666667 | K15: =S15*1.2 -> 0.32425352 | L15: =K15*J15 -> 0.054042254 | M15: 031324: Paper with FSC certificate | O15: 0.16666667 | P15: 1.9185 | Q15: 500 | R15: 15 | S15: =P15/$V$2 -> 0.27021127 | T15: =S15*J15 -> 0.045035211 | U15: =(K15-S15)/S15 -> 0.2 | V15: difference between FSC and w/o FSC | W15: =P15-'PKG BOM 20240223'!R10 -> 0.7685 | X15: =(P15-'PKG BOM 20240223'!R10)/'PKG BOM 20240223'!R10 -> 0.66826087
A16: 8 | B16: 1 | C16: 5843-1047-01A0 | D16: N/A | E16: carton TB board | F16: B/F, burst above 10KGF(inside the carton top and bottom) | H16: Paper board Material: B flute 12kgf Dimension(LxW): (L)171x(W)138mm Remark: 纸板原材料需符合FSC认证要求 | I16: 天地板 | J16: =2/6 -> 0.33333333 | K16: 0.088235294 | L16: =K16*J16 -> 0.029411765 | O16: 0.33333333 | P16: 0.17 | Q16: 500 | R16: 14 | S16: =P16/$V$2 -> 0.023943662 | T16: =S16*J16 -> 0.0079812207 | U16: =(K16-S16)/S16 -> 2.6851211
A17: 9 | B17: 1 | C17: 0952-0035-00E0 0952-1047-00A0 | D17: N/A | E17: PE bag for box | F17: PE-LD :1219x230x0.015mm1840x230x0.015mm | G17: N/A | H17: HDPE film (protect retail box) Material: HDPE (T=0.015mm) Dimension: (L)1219x(W)230mm(L)1840x(W)230mm Can be use foxlink existing part P/N 0952-0035-00E0 | I17: 隔膜 | K17: 0.017323944 | L17: =K17*J17 -> 0 | M17: Can be use foxlink existing part P/N 0952-0035-00E0 | O17: 0.33333333 | P17: 0.123 | Q17: 20000 | R17: 14 | S17: =P17/$V$2 -> 0.017323944 | T17: =S17*J17 -> 0 | U17: =(K17-S17)/S17 -> 0 | V17: 022724:true cost update
A18: 9 | B18: 1 | C18: TBD | D18: N/A | E18: Protective paper | G18: N/A | H18: Protective paper Material: 17gsm 雪梨纸 Thickness: 0.02mm Dimension:L700*W170mm | I18: 隔膜纸 | J18: 0.33333333 | K18: 0.015387324 | L18: =K18*J18 -> 0.005129108 | O18: 0.33333333 | P18: 0.095 | Q18: 5000 | R18: 28 | S18: =P18/$V$2 -> 0.013380282 | T18: =S18*J18 -> 0.0044600939 | U18: =(K18-S18)/S18 -> 0.15 | V18: 022724:true cost update | W18: =S18-S17 -> -0.003943662 | X18: =(S18-S17)/S17 -> -0.22764228
A19: 10 | B19: 1 | C19: 5849-1047-03A0 | D19: N/A | E19: Label (for master carton) | F19: material: 80g art paper dimension：100x55 mm printing: 1C with online printing | H19: Master Carton Label Outside dimensions:(L)119X(W)78mm (L)88.3X(W)59.48mm(L)100X(W)55mm; Material : 80gsm artpaper Print: Black | I19: 外箱标签 | J19: =1/6 -> 0.16666667 | K19: 0.024264706 | L19: =K19*J19 -> 0.0040441176 | O19: 0.16666667 | P19: 0.146 | Q19: 5000 | R19: 15 | S19: =P19/$V$2 -> 0.02056338 | T19: =S19*J19 -> 0.00342723 | U19: =(K19-S19)/S19 -> 0.17999597
A20: 11 | B20: 1 | C20: 5849-1047-02A0 | D20: N/A | E20: S/N label for carton (for master carton) | F20: material: 80g art paper dimension：59.67x52 mm printing: blank with online printing | H20: Carton Label(SN) Outside dimensions: (L)40x(W)38mm(L)59.67X(W)52mm; Material : 80gsm artpaper | I20: 外箱标签 | J20: =1/6 -> 0.16666667 | K20: 0.0097058824 | L20: =K20*J20 -> 0.0016176471 | O20: 0.16666667 | P20: 0.058 | Q20: 5000 | R20: 15 | S20: =P20/$V$2 -> 0.0081690141 | T20: =S20*J20 -> 0.0013615023 | U20: =(K20-S20)/S20 -> 0.18813387
A21: 12 | B21: 1 | C21: 5849-1043-02A0 | D21: N/A | E21: SN Label (for color box) | F21: material: 80g art paper dimension: 38x12mm printing: blank with online printing | G21: N/A | H21: Color box SN Label Outside dimensions:(L)38X(W)8mm (L)38X(W)12mm; Material : 80gsm artpaper Can be use foxlink existing part P/N 5849-1043-02A0 | I21: 彩盒标签 | J21: 1 | K21: 0.0056617647 | L21: =K21*J21 -> 0.0056617647 | M21: Can be use foxlink existing part P/N 5849-1043-02A0 | O21: 1 | P21: 0.01 | Q21: 5000 | R21: 15 | S21: =P21/$V$2 -> 0.0014084507 | T21: =S21*J21 -> 0.0014084507 | U21: =(K21-S21)/S21 -> 3.0198529
A22: 13 | B22: 1 | C22: 5849-1047-00AA | D22: N/A | E22: PID label (for product) | F22: material: 80g black PET+ printable matte pp film dimension:45.424x23 mm printing: 2C | H22: PID Label Outside dimensions: (L)37.3X(W)33.7mm (L)45.424X(W)23mm; Material : 50#PET+25# PP film Print: 2C | I22: PID标签 | J22: 1 | K22: 0.021126761 | L22: =K22*J22 -> 0.021126761 | O22: 1 | P22: 0.15 | Q22: 5000 | R22: 15 | S22: =P22/$V$2 -> 0.021126761 | T22: =S22*J22 -> 0.021126761 | U22: =(K22-S22)/S22 -> 0 | V22: 022724:true cost update
A23: 14 | B23: 1 | C23: 5849-1012-05A0 | D23: N/A | E23: Pallet label | F23: Label,Pallet,AP,153x102mm | G23: N/A | H23: Pallet Label Outside dimensions: (L)165X(W)102mm (L)153X(W)102mm; Material : 80gsm artpaper Can be use foxlink existing part P/N 5849-1012-05A0 | I23: 棧板标签 | J23: =1/750 -> 0.0013333333 | K23: 0.026691176 | L23: =K23*J23 -> 3.5588235e-05 | M23: Can be use foxlink existing part P/N 5849-1012-05A0 | O23: 0.0013333333 | P23: 0.135 | Q23: 5000 | R23: 7 | S23: =P23/$V$2 -> 0.019014085 | T23: =S23*J23 -> 2.5352113e-05 | U23: =(K23-S23)/S23 -> 0.40375817
A24: 15 | B24: 1 | C24: 5849-1043-05A0 | D24: N/A | E24: PCBA Tracking Label | F24: material: 80g art paper dimension：35x7 mm printing: blank with online printing | G24: N/A | H24: PCBA Tracking Label Outside dimensions: (L)35X(W)7mm; Material : 80gsm artpaper Can be use foxlink existing part P/N 5849-1043-05A0 | I24: 追蹤標籤 | J24: 1 | K24: 0.0084117647 | L24: =K24*J24 -> 0.0084117647 | M24: Can be use foxlink existing part P/N 5849-1043-05A0 | O24: 1 | P24: 0.044 | Q24: 10000 | R24: 14 | S24: =P24/$V$2 -> 0.0061971831 | T24: =S24*J24 -> 0.0061971831 | U24: =(K24-S24)/S24 -> 0.35735294
A25: 16 | B25: 1 | C25: 5849-1043-00A0 | D25: N/A | E25: Cable Tag | F25: material: 80g art paper, matte coating(with glue) dimension：66.073x15 mm printing: blank | H25: Cable tag Outside dimensions: (L)66X(W)15mm; Material : 80gsm artpaper, matte coating(with glue) Can be use foxlink existing part P/N 5849-1043-00A0 | I25: 下載標籤 | J25: 1 | K25: 0.0127 | L25: =K25*J25 -> 0.0127 | M25: Can be use foxlink existing part P/N 0981-1914-00A0 | O25: 1 | P25: 0.07 | Q25: 5000 | R25: 14 | S25: =P25/$V$2 -> 0.0098591549 | T25: =S25*J25 -> 0.0098591549 | U25: =(K25-S25)/S25 -> 0.28814286
A26: 16 | B26: 1 | C26: 0981-1918-00A0 | D26: N/A | E26: Pallet & related | F26: pallet packing material Pallet | H26: PALLET,OMAHA/FVV-E5K2,GMA STYLE PALLET,1200x1000 mm,RoHS | I26: 棧板 | J26: =1/750 -> 0.0013333333 | K26: 15.71 | L26: =K26*J26 -> 0.020946667 | M26: 2020/06/08 Change to GMA pallet | O26: 0.0013333333 | P26: 103 | Q26: 100 | R26: 15 | S26: =P26/$V$2 -> 14.507042 | T26: =S26*J26 -> 0.019342723 | U26: =(K26-S26)/S26 -> 0.08292233
A27: 17 | B27: 1 | C27: 0984-001E-00A0 | D27: N/A | E27: Card Board | F27: N/A | G27: N/A | H27: Card Board Dimension: 1200x1000mm | I27: 隔板 | J27: =2/1260 -> 0.0015873016 | K27: 1.4041176 | L27: =K27*J27 -> 0.0022287582 | O27: 0.0015873016 | P27: 7.26 | Q27: 100 | R27: 14 | S27: =P27/$V$2 -> 1.0225352 | T27: =S27*J27 -> 0.0016230718 | U27: =(K27-S27)/S27 -> 0.37317291
A28: 18 | B28: 1 | C28: 0984-1047-00A0 | D28: N/A | E28: Card Board | F28: N/A | G28: N/A | H28: Card Board Dimension: 1175x993 mm | I28: 隔板 | J28: =4/1260 -> 0.0031746032 | K28: 0.48028169 | L28: =K28*J28 -> 0.0015247038 | O28: 0.0031746032 | P28: 3.41 | Q28: 100 | R28: 15 | S28: =P28/$V$2 -> 0.48028169 | T28: =S28*J28 -> 0.0015247038 | U28: =(K28-S28)/S28 -> 0 | V28: 022724:true cost update
A29: 19 | B29: 1 | C29: 0984-001H-00A0 | D29: N/A | E29: Corner Board | F29: N/A | G29: N/A | H29: Corner Board Dimension:1025X50X50mm Can be use Foxlink existing P/N: 0984-000W-00E0 | I29: 護角 | J29: =8/1260 -> 0.0063492063 | K29: 0.32676471 | L29: =K29*J29 -> 0.0020746965 | M29: Can be use Foxlink existing P/N: 0984-000W-00E0 | O29: 0.0063492063 | P29: 2.02 | Q29: 1000 | R29: 15 | S29: =P29/$V$2 -> 0.28450704 | T29: =S29*J29 -> 0.0018063939 | U29: =(K29-S29)/S29 -> 0.14852941
A30: 20 | B30: 1 | C30: 0984-001J-00A0 | D30: N/A | E30: Corner Board | F30: N/A | G30: N/A | H30: Corner Board Dimension:,900X50X50mm Can be use Foxlink existing P/N: 0984-000x-00E0 | I30: 護角 | J30: =4/1260 -> 0.0031746032 | K30: 0.28632353 | L30: =K30*J30 -> 0.00090896359 | M30: Can be use Foxlink existing P/N: 0984-000x-00E0 | O30: 0.0031746032 | P30: 1.77 | Q30: 1000 | R30: 15 | S30: =P30/$V$2 -> 0.24929577 | T30: =S30*J30 -> 0.00079141516 | U30: =(K30-S30)/S30 -> 0.14852941
A31: 21 | B31: 1 | C31: 0952-000T-00A0 | D31: N/A | E31: SS Logo seal tape | F31: N/A | G31: N/A | H31: Corner Board Dimension:60mm X 100m Color: 2C Print | I31: SS標誌封箱膠帶 | J31: 0.005 | K31: 1.8929577 | L31: =K31*J31 -> 0.0094647887 | O31: 0.005 | P31: 11.2 | Q31: 900 | R31: 15 | S31: =P31/$V$2 -> 1.5774648 | T31: =S31*J31 -> 0.0078873239 | U31: =(K31-S31)/S31 -> 0.2 | V31: New
A32: 22 | B32: 1 | C32: 0952-0005-00E0 | D32: N/A | E32: INK RIBBON | F32: N/A | G32: N/A | H32: INK RIBBON,DEPLETION,B110A,110MM,LF | I32: 碳带 | J32: 0.000217 | K32: 9.8873239 | L32: =K32*J32 -> 0.0021455493 | O32: 0.000217 | P32: 58.5 | Q32: 10 | R32: 7 | S32: =P32/$V$2 -> 8.2394366 | T32: =S32*J32 -> 0.0017879577 | U32: =(K32-S32)/S32 -> 0.2 | V32: New
A33: 23 | B33: 1 | C33: 0952-0002-00E0 | D33: N/A | E33: INK RIBBON | F33: N/A | G33: N/A | H33: INK RIBBON,DEPLETION,TW10,60MM,LF | I33: 碳带 | J33: 0.000118 | K33: 5.3543662 | L33: =K33*J33 -> 0.00063181521 | O33: 0.000118 | P33: 31.68 | Q33: 10 | R33: 7 | S33: =P33/$V$2 -> 4.4619718 | T33: =S33*J33 -> 0.00052651268 | U33: =(K33-S33)/S33 -> 0.2 | V33: New
A34: 24 | B34: 1 | C34: 0952-000C-00E0 | D34: N/A | E34: INK RIBBON | F34: N/A | G34: N/A | H34: INK RIBBON,DEPLETION,TRC32, 40MM,LF | I34: 碳带 | J34: 0.0001 | K34: 7.6394366 | L34: =K34*J34 -> 0.00076394366 | O34: 0.0001 | P34: 45.2 | Q34: 50 | R34: 7 | S34: =P34/$V$2 -> 6.3661972 | T34: =S34*J34 -> 0.00063661972 | U34: =(K34-S34)/S34 -> 0.2 | V34: New
A35: 25 | B35: 1 | C35: 0952-000S-00E0 | D35: N/A | E35: Tape | F35: N/A | G35: N/A | H35: OC,DEPLETION,TAPE,SEAL(400m*500mm*0.018cm),RoHS | I35: 打包膜 | J35: 0.00045 | K35: 6.1352113 | L35: =K35*J35 -> 0.0027608451 | O35: 0.00045 | P35: 36.3 | Q35: 500 | R35: 10 | S35: =P35/$V$2 -> 5.1126761 | T35: =S35*J35 -> 0.0023007042 | U35: =(K35-S35)/S35 -> 0.2 | V35: New
A36: Subtotal(USD/Unit)： | L36: =SUM(L5:L35) -> 0.82839065 | M36: 022724: ex rate 7.1 ex rate: 6.3 RMB | S36: =P36/$V$2 -> 0 | T36: =SUM(T5:T35) -> 0.57430677 | U36: =(L36-T36)/T36 -> 0.44241841 | V36: Margin
A37: Subtotal(USD/Unit)： | M37: New ex rate 7 | N37: =>update on Oct 27, 2022 | T37: =T36-'PKG BOM 20240223'!V30 -> 0.15516197 | U37: =(T36-'PKG BOM 20240223'!V30)/'PKG BOM 20240223'!V30 -> 0.37018704 | V37: cost up due to FSC & sustainable material

Sheet PKG BOM 20240618_with FSC&減塑
A2: Steelseries Rival3 Gen2 RFQ - Package BOM list | L2: Date: 2024/6/18 | O2: True Cost | V2: 7.1
A3: Model Description: Steelseries Rival 3 Gen2 | J3: Rev.:A | K3: ELM5 Gen2 | O3: EV Phase | P3: 報價 in RMB w/ FSC certificate | S3: 報價 in USD w/ FSC certificate | U3: Markup | V3: Remark
A4: No. | B4: Level | C4: Foxlink P/N | D4: Customer P/N | E4: Customer Description | G4: Image | H4: Description | I4: Chinese Part name | J4: Unit Q'ty (pcs) | K4: Unit Price (USD/pc) ELM5 Gen2 | L4: Amount (USD) ELM5 Gen2 | M4: Remark | O4: QTY | P4: 單價 RMB | Q4: MOQ | R4: LT day | S4: 單價 USD | T4: Amount(USD)
A5: 1-1 | B5: 1 | C5: 584A-1047-00AC | D5: N/A | E5: Box | F5: material: 300g artpaper, 4C+1C PMS, printing: matte PP dimension：278x250mm | H5: Box Outside set-up dimensions:(LxWxD):153x86x46mm Flat sheet dimensions:(L)278x(W)250x(T)0.5mm Material:300gsm SBS Print: 4C+1C PMS Surface process: Matte PP film Joint: Glued inside Remark:包装原料需符合FSC认证要求 | I5: 彩盒 | J5: 1 | K5: 0.3033 | L5: =K5*J5 -> 0.3033 | M5: 031324: Paper with FSC certificate was 0.2821 | O5: 1 | P5: 1.06 | Q5: 5000 | R5: 14 | S5: =P5/$V$2 -> 0.14929577 | T5: =S5*J5 -> 0.14929577 | U5: =(K5-S5)/S5 -> 1.0315377 | V5: difference between FSC and w/o FSC | W5: =P5-'PKG BOM 20240223'!R4 -> 0.02 | X5: =(P5-'PKG BOM 20240223'!R4)/'PKG BOM 20240223'!R4 -> 0.019230769
A6: 2 | C6: 5811-1047-00A0 | D6: N/A | E6: Hanger | F6: material: 0.5T clear PET dimension：70x36.5mm | H6: Hang tab Outside dimensions:(LxW):60x40mm70x36.5mm Material: 0.5T PET (Clear) Other: Back side with Double sided tape (70x10mm) | I6: 掛鉤 | J6: 0 | K6: 0.062117647 | L6: =K6*J6 -> 0 | M6: MOQ:10K | O6: 1 | P6: 0.352 | Q6: 5000 | R6: 14 | S6: =P6/$V$2 -> 0.049577465 | T6: =S6*J6 -> 0 | U6: =(K6-S6)/S6 -> 0.25294118
A7: 2 | C7: TBD | D7: N/A | E7: Hanger | H7: Hang tab Outside dimensions:(LxW):70x36.5mm Material: 350gsm SBS对裱 Print: 1C (Pantone 1655C) Other: Back side with Double sided tape (70x10mm) | I7: 掛鉤 | J7: 1 | K7: =S7*1.2 -> 0.15785915 | L7: =K7*J7 -> 0.15785915 | O7: 1 | P7: 0.934 | Q7: 5000 | R7: 14 | S7: =P7/$V$2 -> 0.1315493 | T7: =S7*J7 -> 0.1315493 | U7: =(K7-S7)/S7 -> 0.2 | W7: =S7-S6 -> 0.081971831 | X7: =(S7-S6)/S6 -> 1.6534091
A8: 3 | B8: 1 | C8: 5843-1047-00A0 | D8: N/A | E8: paper insert | F8: material: E flute corrugated paper board, original color extension dimension：296x152mm | H8: Paper insert Outside dimensions:(LxWxD):380x164mm 296x152mm Material:E flute corrugated paper board, original color Process: Die-cut Remark:包装原料需符合FSC认证要求 | I8: 内纸卡 | J8: 1 | K8: =S8*1.2 -> 0.088715493 | L8: =K8*J8 -> 0.088715493 | M8: 031324: Paper with FSC certificate | O8: 1 | P8: 0.5249 | Q8: 3000 | R8: 14 | S8: =P8/$V$2 -> 0.073929577 | T8: =S8*J8 -> 0.073929577 | U8: =(K8-S8)/S8 -> 0.2 | V8: difference between FSC and w/o FSC | W8: =P8-'PKG BOM 20240223'!R6 -> 0.2199 | X8: =(P8-'PKG BOM 20240223'!R6)/'PKG BOM 20240223'!R6 -> 0.72098361
A9: 4 | B9: 1 | C9: 5649-1001-0LE0 5849-1020-00E0 | D9: N/A | E9: Seal label | F9: material: 19#PET, dimension: 25x25mm | H9: Seal label Outside dimensions:Φ=40mm25mm Material:Acrylic 25#19#TRANSPARENCY Can be use foxlink existing part P/N 5649-1020-00E0 | I9: 封口贴 | J9: 0 | K9: 0.0056338028 | L9: =K9*J9 -> 0 | M9: Can be use foxlink existing part P/N 5649-1001-0LE0 | O9: 2 | P9: 0.04 | Q9: 5000 | R9: 14 | S9: =P9/$V$2 -> 0.0056338028 | T9: =S9*J9 -> 0 | U9: =(K9-S9)/S9 -> 0 | V9: 022724:true cost update
A10: 4 | B10: 1 | C10: TBD | D10: N/A | E10: Seal label | H10: Seal label Outside dimensions:Φ25mm Material:53gsm 透明木浆纸+丙烯酸胶 &背80gsm格拉辛离型纸 Thickness: 50um +/-2 | I10: 封口贴 | J10: 2 | K10: =S10*1.2 -> 0.012 | L10: =K10*J10 -> 0.024 | O10: 2 | P10: 0.071 | Q10: 5000 | R10: 14 | S10: =P10/$V$2 -> 0.01 | T10: =S10*J10 -> 0.02 | U10: =(K10-S10)/S10 -> 0.2 | V10: 022724:true cost update | W10: =S10-S9 -> 0.0043661972 | X10: =(S10-S9)/S9 -> 0.775
A11: 5 | B11: 1 | C11: 5831-1047-00AB | D11: N/A | E11: PIG | F11: material: 80g woodfree paper; dimension: 320 x 200 mm, printing: 2C double side printing type: folding paper | H11: Manual Flat sheet dimensions(LxW): (L)320*(W)200mm Fold size: 80*100mm Material : 80gsm WFUC Print: 2C double side printing Process: Folding X 4 Remark:包装原料需符合FSC认证要求 | I11: 说明书 | J11: 1 | K11: 0.0628 | L11: =K11*J11 -> 0.0628 | M11: 031324: Paper with FSC certificate was 0.0584 | O11: 1 | P11: 0.289 | Q11: 5000 | R11: 14 | S11: =P11/$V$2 -> 0.040704225 | T11: =S11*J11 -> 0.040704225 | U11: =(K11-S11)/S11 -> 0.54283737 | V11: difference between FSC and w/o FSC | W11: =P11-'PKG BOM 20240223'!R8 -> 0.026 | X11: =(P11-'PKG BOM 20240223'!R8)/'PKG BOM 20240223'!R8 -> 0.098859316
A12: 6 | B12: 1 | C12: 5845-1047-00A0 | D12: N/A | E12: PE bag for mouse | F12: material:0.03T HDPE,1C printing dimension: 280x100mm | H12: PE Bag Dimensions(LxW): (L)215x(W)100mm (L)280x(W)100mm Material : 0.05mm LDPE Material : 0.03mm HDPE Print: Black only Process:Hole x1 | I12: 胶袋 | J12: 0 | K12: 0.017205882 | L12: =K12*J12 -> 0 | O12: 1 | P12: 0.067 | Q12: 10000 | R12: 15 | S12: =P12/$V$2 -> 0.0094366197 | T12: =S12*J12 -> 0 | U12: =(K12-S12)/S12 -> 0.82330992
A13: 6 | B13: 1 | C13: TBD | D13: N/A | E13: PE bag for mouse | H13: PE Bag Dimensions(LxW):(L)280x(W)100mm Material : 70%CPE+30%GMX Thickness: 0.05mm Print: Black only Process:Hole x1 厂商：新东颖 | I13: 胶袋 | J13: 1 | K13: =S13*1.2 -> 0.21971831 | L13: =K13*J13 -> 0.21971831 | O13: 1 | P13: 1.3 | Q13: 10000 | R13: 15 | S13: =P13/$V$2 -> 0.18309859 | T13: =S13*J13 -> 0.18309859 | U13: =(K13-S13)/S13 -> 0.2 | W13: =S13-S12 -> 0.17366197 | X13: =(S13-S12)/S12 -> 18.402985
A14: 7 | B14: 1 | C14: 5842-1047-00A0 | D14: N/A | E14: Master Carton | F14: material: B flute, burst above 12KGF | H14: ‘Carton Outside dimensions: (L)213X(W)165X(H)185mm(L)321X(W)106X(H)182mm; (L)182X(W)149X(H)175mm; Material: A. Material type: Corrugated fibreboard B. Flute: C Flute C. Grade: 200# Mullen Burst OR 32 ECT Print: Black Joint: Glued inside Remark: 纸板原材料需符合FSC认证要求 | I14: 外箱 | J14: =1/6 -> 0.16666667 | K14: =S14*1.2 -> 0.32425352 | L14: =K14*J14 -> 0.054042254 | M14: 031324: Paper with FSC certificate | O14: 0.16666667 | P14: 1.9185 | Q14: 500 | R14: 15 | S14: =P14/$V$2 -> 0.27021127 | T14: =S14*J14 -> 0.045035211 | U14: =(K14-S14)/S14 -> 0.2 | V14: difference between FSC and w/o FSC | W14: =P14-'PKG BOM 20240223'!R10 -> 0.7685 | X14: =(P14-'PKG BOM 20240223'!R10)/'PKG BOM 20240223'!R10 -> 0.66826087
A15: 8 | B15: 1 | C15: 5843-1047-01A0 | D15: N/A | E15: carton TB board | F15: B/F, burst above 10KGF(inside the carton top and bottom) | H15: Paper board Material: B flute 12kgf Dimension(LxW): (L)171x(W)138mm Remark: 纸板原材料需符合FSC认证要求 | I15: 天地板 | J15: =2/6 -> 0.33333333 | K15: 0.088235294 | L15: =K15*J15 -> 0.029411765 | O15: 0.33333333 | P15: 0.17 | Q15: 500 | R15: 14 | S15: =P15/$V$2 -> 0.023943662 | T15: =S15*J15 -> 0.0079812207 | U15: =(K15-S15)/S15 -> 2.6851211
A16: 9 | B16: 1 | C16: 0952-0035-00E0 0952-1047-00A0 | D16: N/A | E16: PE bag for box | F16: PE-LD :1219x230x0.015mm1840x230x0.015mm | G16: N/A | H16: HDPE film (protect retail box) Material: HDPE (T=0.015mm) Dimension: (L)1219x(W)230mm(L)1840x(W)230mm Can be use foxlink existing part P/N 0952-0035-00E0 | I16: 隔膜 | K16: 0.017323944 | L16: =K16*J16 -> 0 | M16: Can be use foxlink existing part P/N 0952-0035-00E0 | O16: 0.33333333 | P16: 0.123 | Q16: 20000 | R16: 14 | S16: =P16/$V$2 -> 0.017323944 | T16: =S16*J16 -> 0 | U16: =(K16-S16)/S16 -> 0 | V16: 022724:true cost update
A17: 9 | B17: 1 | C17: TBD | D17: N/A | E17: Protective paper | G17: N/A | H17: Protective paper Material: 40gsm 雪梨纸 Thickness: 0.02mm Dimension:(L)1840x(W)230mm | I17: 隔膜纸 | J17: 0.33333333 | K17: =S17*1.2 -> 0.21515493 | L17: =K17*J17 -> 0.07171831 | O17: 0.33333333 | P17: 1.273 | Q17: 5000 | R17: 28 | S17: =P17/$V$2 -> 0.17929577 | T17: =S17*J17 -> 0.059765258 | U17: =(K17-S17)/S17 -> 0.2 | V17: 022724:true cost update | W17: =S17-S16 -> 0.16197183 | X17: =(S17-S16)/S16 -> 9.3495935
A18: 10 | B18: 1 | C18: 5849-1047-03A0 | D18: N/A | E18: Label (for master carton) | F18: material: 80g art paper dimension：100x55 mm printing: 1C with online printing | H18: Master Carton Label Outside dimensions:(L)119X(W)78mm (L)88.3X(W)59.48mm(L)100X(W)55mm; Material : 80gsm artpaper Print: Black | I18: 外箱标签 | J18: =1/6 -> 0.16666667 | K18: 0.024264706 | L18: =K18*J18 -> 0.0040441176 | O18: 0.16666667 | P18: 0.146 | Q18: 5000 | R18: 15 | S18: =P18/$V$2 -> 0.02056338 | T18: =S18*J18 -> 0.00342723 | U18: =(K18-S18)/S18 -> 0.17999597
A19: 11 | B19: 1 | C19: 5849-1047-02A0 | D19: N/A | E19: S/N label for carton (for master carton) | F19: material: 80g art paper dimension：59.67x52 mm printing: blank with online printing | H19: Carton Label(SN) Outside dimensions: (L)40x(W)38mm(L)59.67X(W)52mm; Material : 80gsm artpaper | I19: 外箱标签 | J19: =1/6 -> 0.16666667 | K19: 0.0097058824 | L19: =K19*J19 -> 0.0016176471 | O19: 0.16666667 | P19: 0.058 | Q19: 5000 | R19: 15 | S19: =P19/$V$2 -> 0.0081690141 | T19: =S19*J19 -> 0.0013615023 | U19: =(K19-S19)/S19 -> 0.18813387
A20: 12 | B20: 1 | C20: 5849-1043-02A0 | D20: N/A | E20: SN Label (for color box) | F20: material: 80g art paper dimension: 38x12mm printing: blank with online printing | G20: N/A | H20: Color box SN Label Outside dimensions:(L)38X(W)8mm (L)38X(W)12mm; Material : 80gsm artpaper Can be use foxlink existing part P/N 5849-1043-02A0 | I20: 彩盒标签 | J20: 1 | K20: 0.0056617647 | L20: =K20*J20 -> 0.0056617647 | M20: Can be use foxlink existing part P/N 5849-1043-02A0 | O20: 1 | P20: 0.01 | Q20: 5000 | R20: 15 | S20: =P20/$V$2 -> 0.0014084507 | T20: =S20*J20 -> 0.0014084507 | U20: =(K20-S20)/S20 -> 3.0198529
A21: 13 | B21: 1 | C21: 5849-1047-00AA | D21: N/A | E21: PID label (for product) | F21: material: 80g black PET+ printable matte pp film dimension:45.424x23 mm printing: 2C | H21: PID Label Outside dimensions: (L)37.3X(W)33.7mm (L)45.424X(W)23mm; Material : 50#PET+25# PP film Print: 2C | I21: PID标签 | J21: 1 | K21: 0.021126761 | L21: =K21*J21 -> 0.021126761 | O21: 1 | P21: 0.15 | Q21: 5000 | R21: 15 | S21: =P21/$V$2 -> 0.021126761 | T21: =S21*J21 -> 0.021126761 | U21: =(K21-S21)/S21 -> 0 | V21: 022724:true cost update
A22: 14 | B22: 1 | C22: 5849-1012-05A0 | D22: N/A | E22: Pallet label | F22: Label,Pallet,AP,153x102mm | G22: N/A | H22: Pallet Label Outside dimensions: (L)165X(W)102mm (L)153X(W)102mm; Material : 80gsm artpaper Can be use foxlink existing part P/N 5849-1012-05A0 | I22: 棧板标签 | J22: =1/750 -> 0.0013333333 | K22: 0.026691176 | L22: =K22*J22 -> 3.5588235e-05 | M22: Can be use foxlink existing part P/N 5849-1012-05A0 | O22: 0.0013333333 | P22: 0.135 | Q22: 5000 | R22: 7 | S22: =P22/$V$2 -> 0.019014085 | T22: =S22*J22 -> 2.5352113e-05 | U22: =(K22-S22)/S22 -> 0.40375817
A23: 15 | B23: 1 | C23: 5849-1043-05A0 | D23: N/A | E23: PCBA Tracking Label | F23: material: 80g art paper dimension：35x7 mm printing: blank with online printing | G23: N/A | H23: PCBA Tracking Label Outside dimensions: (L)35X(W)7mm; Material : 80gsm artpaper Can be use foxlink existing part P/N 5849-1043-05A0 | I23: 追蹤標籤 | J23: 1 | K23: 0.0084117647 | L23: =K23*J23 -> 0.0084117647 | M23: Can be use foxlink existing part P/N 5849-1043-05A0 | O23: 1 | P23: 0.044 | Q23: 10000 | R23: 14 | S23: =P23/$V$2 -> 0.0061971831 | T23: =S23*J23 -> 0.0061971831 | U23: =(K23-S23)/S23 -> 0.35735294
A24: 16 | B24: 1 | C24: 5849-1043-00A0 | D24: N/A | E24: Cable Tag | F24: material: 80g art paper, matte coating(with glue) dimension：66.073x15 mm printing: blank | H24: Cable tag Outside dimensions: (L)66X(W)15mm; Material : 80gsm artpaper, matte coating(with glue) Can be use foxlink existing part P/N 5849-1043-00A0 | I24: 下載標籤 | J24: 1 | K24: 0.0127 | L24: =K24*J24 -> 0.0127 | M24: Can be use foxlink existing part P/N 0981-1914-00A0 | O24: 1 | P24: 0.07 | Q24: 5000 | R24: 14 | S24: =P24/$V$2 -> 0.0098591549 | T24: =S24*J24 -> 0.0098591549 | U24: =(K24-S24)/S24 -> 0.28814286
A25: 16 | B25: 1 | C25: 0981-1918-00A0 | D25: N/A | E25: Pallet & related | F25: pallet packing material Pallet | H25: PALLET,OMAHA/FVV-E5K2,GMA STYLE PALLET,1200x1000 mm,RoHS | I25: 棧板 | J25: =1/750 -> 0.0013333333 | K25: 15.71 | L25: =K25*J25 -> 0.020946667 | M25: 2020/06/08 Change to GMA pallet | O25: 0.0013333333 | P25: 103 | Q25: 100 | R25: 15 | S25: =P25/$V$2 -> 14.507042 | T25: =S25*J25 -> 0.019342723 | U25: =(K25-S25)/S25 -> 0.08292233
A26: 17 | B26: 1 | C26: 0984-001E-00A0 | D26: N/A | E26: Card Board | F26: N/A | G26: N/A | H26: Card Board Dimension: 1200x1000mm | I26: 隔板 | J26: =2/1260 -> 0.0015873016 | K26: 1.4041176 | L26: =K26*J26 -> 0.0022287582 | O26: 0.0015873016 | P26: 7.26 | Q26: 100 | R26: 14 | S26: =P26/$V$2 -> 1.0225352 | T26: =S26*J26 -> 0.0016230718 | U26: =(K26-S26)/S26 -> 0.37317291
A27: 18 | B27: 1 | C27: 0984-1047-00A0 | D27: N/A | E27: Card Board | F27: N/A | G27: N/A | H27: Card Board Dimension: 1175x993 mm | I27: 隔板 | J27: =4/1260 -> 0.0031746032 | K27: 0.48028169 | L27: =K27*J27 -> 0.0015247038 | O27: 0.0031746032 | P27: 3.41 | Q27: 100 | R27: 15 | S27: =P27/$V$2 -> 0.48028169 | T27: =S27*J27 -> 0.0015247038 | U27: =(K27-S27)/S27 -> 0 | V27: 022724:true cost update
A28: 19 | B28: 1 | C28: 0984-001H-00A0 | D28: N/A | E28: Corner Board | F28: N/A | G28: N/A | H28: Corner Board Dimension:1025X50X50mm Can be use Foxlink existing P/N: 0984-000W-00E0 | I28: 護角 | J28: =8/1260 -> 0.0063492063 | K28: 0.32676471 | L28: =K28*J28 -> 0.0020746965 | M28: Can be use Foxlink existing P/N: 0984-000W-00E0 | O28: 0.0063492063 | P28: 2.02 | Q28: 1000 | R28: 15 | S28: =P28/$V$2 -> 0.28450704 | T28: =S28*J28 -> 0.0018063939 | U28: =(K28-S28)/S28 -> 0.14852941
A29: 20 | B29: 1 | C29: 0984-001J-00A0 | D29: N/A | E29: Corner Board | F29: N/A | G29: N/A | H29: Corner Board Dimension:,900X50X50mm Can be use Foxlink existing P/N: 0984-000x-00E0 | I29: 護角 | J29: =4/1260 -> 0.0031746032 | K29: 0.28632353 | L29: =K29*J29 -> 0.00090896359 | M29: Can be use Foxlink existing P/N: 0984-000x-00E0 | O29: 0.0031746032 | P29: 1.77 | Q29: 1000 | R29: 15 | S29: =P29/$V$2 -> 0.24929577 | T29: =S29*J29 -> 0.00079141516 | U29: =(K29-S29)/S29 -> 0.14852941
A30: 21 | B30: 1 | C30: 0952-000T-00A0 | D30: N/A | E30: SS Logo seal tape | F30: N/A | G30: N/A | H30: Corner Board Dimension:60mm X 100m Color: 2C Print | I30: SS標誌封箱膠帶 | J30: 0.005 | K30: 1.8929577 | L30: =K30*J30 -> 0.0094647887 | O30: 0.005 | P30: 11.2 | Q30: 900 | R30: 15 | S30: =P30/$V$2 -> 1.5774648 | T30: =S30*J30 -> 0.0078873239 | U30: =(K30-S30)/S30 -> 0.2 | V30: New
A31: 22 | B31: 1 | C31: 0952-0005-00E0 | D31: N/A | E31: INK RIBBON | F31: N/A | G31: N/A | H31: INK RIBBON,DEPLETION,B110A,110MM,LF | I31: 碳带 | J31: 0.000217 | K31: 9.8873239 | L31: =K31*J31 -> 0.0021455493 | O31: 0.000217 | P31: 58.5 | Q31: 10 | R31: 7 | S31: =P31/$V$2 -> 8.2394366 | T31: =S31*J31 -> 0.0017879577 | U31: =(K31-S31)/S31 -> 0.2 | V31: New
A32: 23 | B32: 1 | C32: 0952-0002-00E0 | D32: N/A | E32: INK RIBBON | F32: N/A | G32: N/A | H32: INK RIBBON,DEPLETION,TW10,60MM,LF | I32: 碳带 | J32: 0.000118 | K32: 5.3543662 | L32: =K32*J32 -> 0.00063181521 | O32: 0.000118 | P32: 31.68 | Q32: 10 | R32: 7 | S32: =P32/$V$2 -> 4.4619718 | T32: =S32*J32 -> 0.00052651268 | U32: =(K32-S32)/S32 -> 0.2 | V32: New
A33: 24 | B33: 1 | C33: 0952-000C-00E0 | D33: N/A | E33: INK RIBBON | F33: N/A | G33: N/A | H33: INK RIBBON,DEPLETION,TRC32, 40MM,LF | I33: 碳带 | J33: 0.0001 | K33: 7.6394366 | L33: =K33*J33 -> 0.00076394366 | O33: 0.0001 | P33: 45.2 | Q33: 50 | R33: 7 | S33: =P33/$V$2 -> 6.3661972 | T33: =S33*J33 -> 0.00063661972 | U33: =(K33-S33)/S33 -> 0.2 | V33: New
A34: 25 | B34: 1 | C34: 0952-000S-00E0 | D34: N/A | E34: Tape | F34: N/A | G34: N/A | H34: OC,DEPLETION,TAPE,SEAL(400m*500mm*0.018cm),RoHS | I34: 打包膜 | J34: 0.00045 | K34: 6.1352113 | L34: =K34*J34 -> 0.0027608451 | O34: 0.00045 | P34: 36.3 | Q34: 500 | R34: 10 | S34: =P34/$V$2 -> 5.1126761 | T34: =S34*J34 -> 0.0023007042 | U34: =(K34-S34)/S34 -> 0.2 | V34: New
A35: Subtotal(USD/Unit)： | L35: =SUM(L5:L34) -> 1.1086137 | M35: 022724: ex rate 7.1 ex rate: 6.3 RMB | S35: =P35/$V$2 -> 0 | T35: =SUM(T5:T34) -> 0.79299221 | U35: =(L35-T35)/T35 -> 0.3980133 | V35: Margin
A36: Subtotal(USD/Unit)： | M36: New ex rate 7 | N36: =>update on Oct 27, 2022 | T36: =T35-'PKG BOM 20240223'!V30 -> 0.37384742 | U36: =(T35-'PKG BOM 20240223'!V30)/'PKG BOM 20240223'!V30 -> 0.89192904 | V36: cost up due to FSC & sustainable material

Sheet ME bom 0229_Black
A2: Project Name: | B2: ELM5 Gen2
A3: Prepared By: | B3: Alvin
A4: Last Updated:
A5: Forecast: | B5: 418K*0.8
A7: Item | B7: Component Type | C7: Level 1 System Part Name (by RD) | D7: Level 2 Parts Name (by RD) | E7: Part Picture | F7: Part Description (by PLM) | G7: Foxlink P/N | H7: Customer P/N | I7: Level 1 Q'ty | J7: Level 2 Q'ty | K7: Part Size /mm | L7: Part Weight /g | M7: Material | N7: Color | O7: 2nd Process (Incl. Finish) | P7: T2 Supplier (Vendor Name) | Q7: Component Catergory (Part Type) | R7: Customized / Standard | S7: 2D Version | T7: Remarks | U7: U/P | V7: Sub-Total | W7: Tool Q'ty | X7: Tool Cav. | Y7: Tooling Cost Per Tool (USD/set) | Z7: Jig Cost | AA7: Total Tooling Cost | AC7: True U/P (USD/pcs) | AD7: True Sub-Total | AE7: Mark up % | AG7: Tooling True Cost | AH7: Jig Cost | AI7: True Sub-Total | AJ7: Mark Up %
A8: P1 | B8: 1. Plastic | C8: MIDDLE HOUSING B | I8: 1 | J8: 0 | L8: 22 | M8: ABS | N8: Black | O8: Black /ABS /VDI 27 印刷Logo,Color:Metallic Pantone 10390C /Silkscreen Print /Matte | U8: 0.3675 | V8: =U8*I8 -> 0.3675 | W8: 1 | X8: 2 | Y8: 2000 | AA8: =W8*(Y8+Z8) -> 2000 | AC8: 0.33837654 | AD8: =I8*AC8 -> 0.33837654 | AE8: =(U8-AC8)/AC8 -> 0.086068191 | AG8: 1600 | AI8: =W8*(AG8+AH8) -> 1600 | AJ8: =(Y8-AG8)/AG8 -> 0.25
A9: P2 | B9: 1. Plastic | C9: TRIGGER BUTTON LEFT B | I9: 1 | L9: 2.6 | M9: ABS+PC | N9: Black | O9: Black /ABS + PC /VDI 27 | U9: 0.0945 | V9: =U9*I9 -> 0.0945 | W9: 1 | X9: 2 | Y9: 1000 | AA9: =W9*(Y9+Z9) -> 1000 | AC9: 0.092883333 | AD9: =I9*AC9 -> 0.092883333 | AE9: =(U9-AC9)/AC9 -> 0.017405347 | AG9: 800 | AI9: =W9*(AG9+AH9) -> 800 | AJ9: =(AA9-AI9)/AI9 -> 0.25
A10: P3 | B10: 1. Plastic | C10: TRIGGER BUTTON RIGHT B | I10: 1 | L10: 2.6 | M10: ABS+PC | N10: Black | O10: Black /ABS + PC /VDI 27 | U10: 0.0945 | V10: =U10*I10 -> 0.0945 | X10: 2 | AC10: 0.092883333 | AD10: =I10*AC10 -> 0.092883333 | AE10: =(U10-AC10)/AC10 -> 0.017405347 | AJ10: =(AA10-AI10)/AI10 -> #DIV/0!
A11: P4 | B11: 1. Plastic | C11: BOTTOM COVER B | I11: 1 | L11: 11 | M11: PC | N11: Smokey Black | O11: Smokey Black /Translucent PC /VDI 27 | U11: 0.2625 | V11: =U11*I11 -> 0.2625 | W11: 1 | X11: 2 | AA11: =W11*(Y11+Z11) -> 0 | AC11: 0.17861296 | AD11: =I11*AC11 -> 0.17861296 | AE11: =(U11-AC11)/AC11 -> 0.46965817 | AI11: =W11*(AG11+AH11) -> 0 | AJ11: =(AA11-AI11)/AI11 -> #DIV/0!
A12: P5 | B12: 1. Plastic | C12: LIGHTGUIDE B | I12: 1 | L12: 4.4 | M12: PC | N12: Smokey Black | O12: Smokey Black /Translucent PC /VDI 24 | U12: 0.066848989 | V12: =U12*I12 -> 0.066848989 | W12: 1 | X12: 2 | AA12: =W12*(Y12+Z12) -> 0 | AC12: 0.063665704 | AD12: =I12*AC12 -> 0.063665704 | AE12: =(U12-AC12)/AC12 -> 0.05 | AI12: =W12*(AG12+AH12) -> 0 | AJ12: =(AA12-AI12)/AI12 -> #DIV/0!
A13: P6 | B13: 1. Plastic | C13: SIDE BUTTON | F13: PLASTIC ASSY,ELM5/FSG-E1J4,SIDE BUTTON,ABS,BLACK,RoHS | G13: 5881-1047-05A0 | I13: 1 | L13: 0.6 | M13: ABS | N13: Black | O13: Black /ABS /VDI 24 | U13: 0.062521 | V13: =U13*I13 -> 0.062521 | W13: 1 | X13: 4 | AA13: =W13*(Y13+Z13) -> 0 | AC13: 0.0607 | AD13: =I13*AC13 -> 0.0607 | AE13: =(U13-AC13)/AC13 -> 0.03 | AI13: =W13*(AG13+AH13) -> 0 | AJ13: =(AA13-AI13)/AI13 -> #DIV/0!
A14: P7 | B14: 1. Plastic | C14: CPI BUTTON | F14: PLASTIC ASSY,ELM5/FSG-E1J4,CPI BUTTON,ABS,BLACK,RoHS | G14: 5881-1047-06A0 | I14: 1 | L14: 0.2 | M14: ABS | N14: Black | O14: Black /ABS /VDI 24 | U14: 0.05768 | V14: =U14*I14 -> 0.05768 | W14: 1 | X14: 4 | AA14: =W14*(Y14+Z14) -> 0 | AC14: 0.056 | AD14: =I14*AC14 -> 0.056 | AE14: =(U14-AC14)/AC14 -> 0.03 | AI14: =W14*(AG14+AH14) -> 0 | AJ14: =(AA14-AI14)/AI14 -> #DIV/0!
A15: P8 | B15: 1. Plastic | C15: WHEEL HUB | F15: PLASTIC ASSY,ELM5/FSG-E1J4,WHEEL HUB,PC,BLACK,RoHS | G15: 5881-1047-07A0 | I15: 1 | L15: 1.8 | M15: PC | N15: Black | O15: Black /PC /VDI 21 | U15: 0.089198 | V15: =U15*I15 -> 0.089198 | W15: 1 | X15: 8 | AA15: =W15*(Y15+Z15) -> 0 | AC15: 0.0866 | AD15: =I15*AC15 -> 0.0866 | AE15: =(U15-AC15)/AC15 -> 0.03 | AI15: =W15*(AG15+AH15) -> 0 | AJ15: =(AA15-AI15)/AI15 -> #DIV/0!
A16: P9 | B16: 1. Plastic | C16: SWITCH CUSHION | F16: PLASTIC,NINJA/FSG-E1J0,SWITCH CUSHION,PA66,RoHS | G16: 5811-1043-08A0 | I16: 1 | L16: 0.05 | M16: PA66 | N16: Black | U16: 0.031522844 | V16: =U16*I16 -> 0.031522844 | W16: 1 | X16: 8 | AA16: =W16*(Y16+Z16) -> 0 | AC16: 0.0287 | AD16: =I16*AC16 -> 0.0287 | AE16: =(U16-AC16)/AC16 -> 0.098356945 | AI16: =W16*(AG16+AH16) -> 0 | AJ16: =(AA16-AI16)/AI16 -> #DIV/0!
A17: P10 | B17: 1. Plastic | C17: LED CLIP | F17: PLASTIC ASSY,ELM5/FSG-E1J4,LED CLIP,LCP,BLACK,RoHS | G17: 5881-1047-08A0 | I17: 1 | L17: 0.2 | M17: ABS | N17: Black | U17: 0.104133 | V17: =U17*I17 -> 0.104133 | W17: 1 | X17: 8 | AA17: =W17*(Y17+Z17) -> 0 | AC17: 0.1011 | AD17: =I17*AC17 -> 0.1011 | AE17: =(U17-AC17)/AC17 -> 0.03 | AI17: =W17*(AG17+AH17) -> 0 | AJ17: =(AA17-AI17)/AI17 -> #DIV/0!
A18: R1 | B18: 3. Rubber | C18: WHEEL GRIP B1 | I18: 1 | M18: Silicon rubber | N18: Black | O18: Black /Silicon Rubber /VDI 24 (Arrow) | U18: 0.081 | V18: =U18*I18 -> 0.081 | W18: 1 | X18: 36 | AA18: =W18*(Y18+Z18) -> 0 | AC18: 0.0732 | AD18: =I18*AC18 -> 0.0732 | AE18: =(U18-AC18)/AC18 -> 0.10655738 | AI18: =W18*(AG18+AH18) -> 0 | AJ18: =(AA18-AI18)/AI18 -> #DIV/0!
A19: R2 | B19: 3. Rubber | C19: WHEEL GRIP B2 | I19: 0 | M19: Silicon rubber | N19: Black | O19: Black /Silicon Rubber /VDI 24 (Horizontal) | U19: 0.081 | V19: =U19*I19 -> 0 | AA19: =W19*(Y19+Z19) -> 0 | AC19: 0.0732 | AD19: =I19*AC19 -> 0 | AE19: =(U19-AC19)/AC19 -> 0.10655738 | AI19: =W19*(AG19+AH19) -> 0 | AJ19: =(AA19-AI19)/AI19 -> #DIV/0!
A20: R3 | B20: 3. Rubber | C20: WHEEL GRIP B3 | I20: 0 | M20: Silicon rubber | N20: Black | O20: Black /Silicon Rubber /VDI 24 (Topographic) | U20: 0.081 | V20: =U20*I20 -> 0 | AA20: =W20*(Y20+Z20) -> 0 | AC20: 0.0732 | AD20: =I20*AC20 -> 0 | AE20: =(U20-AC20)/AC20 -> 0.10655738 | AI20: =W20*(AG20+AH20) -> 0 | AJ20: =(AA20-AI20)/AI20 -> #DIV/0!
A21: O1 | B21: 4. Others | C21: PTFE FEET PAD UP W | I21: 2 | M21: PTFE (TEFLON) | N21: White | O21: White /Virgin Grade PTFE /High Gloss 含保護膜(透明) | U21: 0.03 | V21: =U21*I21 -> 0.06 | AA21: =W21*(Y21+Z21) -> 0 | AC21: 0.028 | AD21: =I21*AC21 -> 0.056 | AE21: =(U21-AC21)/AC21 -> 0.071428571 | AI21: =W21*(AG21+AH21) -> 0 | AJ21: =(AA21-AI21)/AI21 -> #DIV/0!
A22: O2 | B22: 4. Others | C22: PTFE FEET PAD DOWN W | I22: 1 | M22: PTFE (TEFLON) | N22: White | O22: White /Virgin Grade PTFE /High Gloss 含保護膜(透明) | U22: 0.153 | V22: =U22*I22 -> 0.153 | AA22: =W22*(Y22+Z22) -> 0 | AC22: 0.145 | AD22: =I22*AC22 -> 0.145 | AE22: =(U22-AC22)/AC22 -> 0.055172414 | AI22: =W22*(AG22+AH22) -> 0 | AJ22: =(AA22-AI22)/AI22 -> #DIV/0!
A23: O3 | B23: 4. Others | C23: SCREW T2x6mm | F23: SCREW,MILD STEEL,ZINC BLACK,NINJA/FSG-E1J0,T2x6mm,CROSS,1018A BLACK,ZN,RoHS | G23: 0961-0003-83A0 | I23: 4 | M23: A1018 | N23: Sliver | O23: 自攻,十字槽,鍍鎳,D3.5*頭厚1.3*L6 | U23: 0.00385 | V23: =U23*I23 -> 0.0154 | AA23: =W23*(Y23+Z23) -> 0 | AC23: 0.00309 | AD23: =I23*AC23 -> 0.01236 | AE23: =(U23-AC23)/AC23 -> 0.24595469 | AI23: =W23*(AG23+AH23) -> 0 | AJ23: =(AA23-AI23)/AI23 -> #DIV/0!
A24: O4 | B24: 4. Others | C24: SCREW P2x4mm | F24: SCREW,MILD STEEL,ZINC BLACK,NINJA/FSG-E1J0, P2x4mm,CROSS,1018A BLACK,ZN,RoHS | G24: 0961-0004-83A0 | I24: 9 | M24: A1018 | N24: Black | O24: 自攻,十字槽,鍍黑鎳,D3.5*頭厚1.3*L4 | U24: 0.00495 | V24: =U24*I24 -> 0.04455 | AA24: =W24*(Y24+Z24) -> 0 | AC24: 0.003 | AD24: =I24*AC24 -> 0.027 | AE24: =(U24-AC24)/AC24 -> 0.65 | AI24: =W24*(AG24+AH24) -> 0 | AJ24: =(AA24-AI24)/AI24 -> #DIV/0!
A25: O5 | B25: 4. Others | C25: SCREW P2x4mm | F25: SCREW,MILD STEEL,ZINC WHITE, P2x4mm,CROSS,1018A WHITE,ZN,RoHS,LEFT-HAND THREAD | G25: 0961-0006-81A0 | I25: 1 | M25: A1018 | N25: White | O25: 自攻,十字槽,鍍白鋅,D3.5*頭厚1.3*L4, 左旋螺絲 | U25: 0.00495 | V25: =U25*I25 -> 0.00495 | AA25: =W25*(Y25+Z25) -> 0 | AC25: =0.0385/7 -> 0.0055 | AD25: =I25*AC25 -> 0.0055 | AE25: =(U25-AC25)/AC25 -> -0.1 | AI25: =W25*(AG25+AH25) -> 0 | AJ25: =(AA25-AI25)/AI25 -> #DIV/0!
V26: =U26*I26 -> 0 | AA26: =W26*(Y26+Z26) -> 0 | AD26: =I26*AC26 -> 0 | AE26: =(U26-AC26)/AC26 -> #DIV/0! | AI26: =W26*(AG26+AH26) -> 0 | AJ26: =(AA26-AI26)/AI26 -> #DIV/0!
V27: =U27*I27 -> 0 | AA27: =W27*(Y27+Z27) -> 0 | AD27: =I27*AC27 -> 0 | AE27: =(U27-AC27)/AC27 -> #DIV/0! | AI27: =W27*(AG27+AH27) -> 0 | AJ27: =(AA27-AI27)/AI27 -> #DIV/0!
U29: Total cost | V29: =SUM(V8:V27) -> 1.5898038 | AA29: =SUM(AA8:AA27) -> 3000 | AD29: =SUM(AD8:AD27) -> 1.4185819 | AE29: =(V29-AD29)/AD29 -> 0.12069938 | AI29: =SUM(AI8:AI27) -> 2400 | AJ29: =(AA29-AI29)/AI29 -> 0.25

Sheet ME bom 0229_White
A2: Project Name: | B2: ELM5 Gen2
A3: Prepared By: | B3: Alvin
A4: Last Updated:
A5: Forecast: | B5: 418K*0.2
A7: Item | B7: Component Type | C7: Level 1 System Part Name (by RD) | D7: Level 2 Parts Name (by RD) | E7: Part Picture | F7: Part Description (by PLM) | G7: Foxlink P/N | H7: Customer P/N | I7: Level 1 Q'ty | J7: Level 2 Q'ty | K7: Part Size /mm | L7: Part Weight /g | M7: Material | N7: Color | O7: 2nd Process (Incl. Finish) | P7: T2 Supplier (Vendor Name) | Q7: Component Catergory (Part Type) | R7: Customized / Standard | S7: 2D Version | T7: Remarks | U7: U/P | V7: Sub-Total | W7: Tool Q'ty | X7: Tool Cav. | Y7: Tooling Cost Per Tool (USD/set) | Z7: Jig Cost | AA7: Total Tooling Cost | AC7: True U/P (USD/pcs) | AD7: True Sub-Total | AE7: Mark up % | AG7: Tooling True Cost | AH7: Jig Cost | AI7: True Sub-Total | AJ7: Mark Up %
A8: P1 | B8: 1. Plastic | C8: MIDDLE HOUSING W | I8: 1 | J8: 0 | L8: 22 | M8: ABS | N8: Pantone PQ-11-0601 TCX | O8: Pantone PQ-11-0601 TCX /ABS /VDI 27 印刷Logo,Color:Pantone Cool Grey 6C /Silkscreen Print /Matte | U8: 0.39048495 | V8: =U8*I8 -> 0.39048495 | W8: 1 | X8: 2 | AA8: =W8*(Y8+Z8) -> 0 | AC8: 0.37189043 | AD8: =I8*AC8 -> 0.37189043 | AE8: =(V8-AD8)/AD8 -> 0.05 | AI8: =W8*(AG8+AH8) -> 0 | AJ8: =(AA8-AI8)/AI8 -> #DIV/0!
A9: P2 | B9: 1. Plastic | C9: TRIGGER BUTTON LEFT W | I9: 1 | L9: 2.6 | M9: ABS+PC | N9: Pantone PQ-11-0601 TCX | O9: Pantone PQ-11-0601 TCX /ABS + PC /VDI 27 | U9: 0.11372083 | V9: =U9*I9 -> 0.11372083 | W9: 1 | X9: 2 | AA9: =W9*(Y9+Z9) -> 0 | AC9: 0.10830556 | AD9: =I9*AC9 -> 0.10830556 | AE9: =(V9-AD9)/AD9 -> 0.05 | AI9: =W9*(AG9+AH9) -> 0 | AJ9: =(AA9-AI9)/AI9 -> #DIV/0!
A10: P3 | B10: 1. Plastic | C10: TRIGGER BUTTON RIGHT W | I10: 1 | L10: 2.6 | M10: ABS+PC | N10: Pantone PQ-11-0601 TCX | O10: Pantone PQ-11-0601 TCX /ABS + PC /VDI 27 | U10: 0.11372083 | V10: =U10*I10 -> 0.11372083 | X10: 2 | AA10: =W10*(Y10+Z10) -> 0 | AC10: 0.10830556 | AD10: =I10*AC10 -> 0.10830556 | AE10: =(V10-AD10)/AD10 -> 0.05 | AI10: =W10*(AG10+AH10) -> 0 | AJ10: =(AA10-AI10)/AI10 -> #DIV/0!
A11: P4 | B11: 1. Plastic | C11: BOTTOM COVER W | I11: 1 | L11: 11 | M11: PC | N11: Milky White | O11: Milky White /Translucent PC /VDI 27 | U11: 0.275 | V11: =U11*I11 -> 0.275 | W11: 1 | X11: 2 | AA11: =W11*(Y11+Z11) -> 0 | AC11: 0.20597531 | AD11: =I11*AC11 -> 0.20597531 | AE11: =(V11-AD11)/AD11 -> 0.33511148 | AI11: =W11*(AG11+AH11) -> 0 | AJ11: =(AA11-AI11)/AI11 -> #DIV/0!
A12: P5 | B12: 1. Plastic | C12: LIGHTGUIDE W | I12: 1 | L12: 4.4 | M12: PC | N12: Milky White | O12: Milky White /Translucent PC /VDI 24 | U12: 0.077086852 | V12: =U12*I12 -> 0.077086852 | W12: 1 | X12: 2 | AA12: =W12*(Y12+Z12) -> 0 | AC12: 0.073416049 | AD12: =I12*AC12 -> 0.073416049 | AE12: =(V12-AD12)/AD12 -> 0.05 | AI12: =W12*(AG12+AH12) -> 0 | AJ12: =(AA12-AI12)/AI12 -> #DIV/0!
A13: P6 | B13: 1. Plastic | C13: SIDE BUTTON W | I13: 1 | L13: 0.6 | M13: ABS | N13: Pantone Cool Grey 6C | O13: Pantone Cool Grey 6C /ABS /VDI 24 | U13: 0.0701085 | V13: =U13*I13 -> 0.0701085 | W13: 1 | X13: 4 | AA13: =W13*(Y13+Z13) -> 0 | AC13: =0.0607*1.1 -> 0.06677 | AD13: =I13*AC13 -> 0.06677 | AE13: =(V13-AD13)/AD13 -> 0.05 | AI13: =W13*(AG13+AH13) -> 0 | AJ13: =(AA13-AI13)/AI13 -> #DIV/0!
A14: P7 | B14: 1. Plastic | C14: CPI BUTTON W | I14: 1 | L14: 0.2 | M14: ABS | N14: Pantone Cool Grey 6C | O14: Pantone Cool Grey 6C /ABS /VDI 24 | U14: 0.06468 | V14: =U14*I14 -> 0.06468 | W14: 1 | X14: 4 | AA14: =W14*(Y14+Z14) -> 0 | AC14: =0.056*1.1 -> 0.0616 | AD14: =I14*AC14 -> 0.0616 | AE14: =(V14-AD14)/AD14 -> 0.05 | AI14: =W14*(AG14+AH14) -> 0 | AJ14: =(AA14-AI14)/AI14 -> #DIV/0!
A15: P8 | B15: 1. Plastic | C15: WHEEL HUB W | I15: 1 | L15: 1.8 | M15: PC | N15: Pantone Cool Grey 6C | O15: Pantone Cool Grey 6C /PC /VDI 21 | U15: 0.100023 | V15: =U15*I15 -> 0.100023 | W15: 1 | X15: 8 | AA15: =W15*(Y15+Z15) -> 0 | AC15: =0.0866*1.1 -> 0.09526 | AD15: =I15*AC15 -> 0.09526 | AE15: =(V15-AD15)/AD15 -> 0.05 | AI15: =W15*(AG15+AH15) -> 0 | AJ15: =(AA15-AI15)/AI15 -> #DIV/0!
A16: P9 | B16: 1. Plastic | C16: SWITCH CUSHION | F16: PLASTIC,NINJA/FSG-E1J0,SWITCH CUSHION,PA66,RoHS | G16: 5811-1043-08A0 | I16: 1 | L16: 0.05 | M16: PA66 | N16: Black | U16: 0.031522844 | V16: =U16*I16 -> 0.031522844 | W16: 1 | X16: 8 | AA16: =W16*(Y16+Z16) -> 0 | AC16: 0.0287 | AD16: =I16*AC16 -> 0.0287 | AE16: =(V16-AD16)/AD16 -> 0.098356945 | AI16: =W16*(AG16+AH16) -> 0 | AJ16: =(AA16-AI16)/AI16 -> #DIV/0!
A17: P10 | B17: 1. Plastic | C17: LED CLIP | F17: PLASTIC ASSY,ELM5/FSG-E1J4,LED CLIP,LCP,BLACK,RoHS | G17: 5881-1047-08A0 | I17: 1 | L17: 0.2 | M17: ABS | N17: Black | U17: 0.104133 | V17: =U17*I17 -> 0.104133 | W17: 1 | X17: 8 | AA17: =W17*(Y17+Z17) -> 0 | AC17: 0.1011 | AD17: =I17*AC17 -> 0.1011 | AE17: =(V17-AD17)/AD17 -> 0.03 | AI17: =W17*(AG17+AH17) -> 0 | AJ17: =(AA17-AI17)/AI17 -> #DIV/0!
A18: R1 | B18: 3. Rubber | C18: WHEEL GRIP W1 | I18: 1 | M18: Silicon rubber | N18: Pantone Cool Grey 6C | O18: Pantone Cool Grey 6C /Silicon Rubber /VDI 24 (Arrow) | U18: 0.081 | V18: =U18*I18 -> 0.081 | W18: 1 | X18: 36 | AA18: =W18*(Y18+Z18) -> 0 | AC18: 0.0732 | AD18: =I18*AC18 -> 0.0732 | AE18: =(V18-AD18)/AD18 -> 0.10655738 | AI18: =W18*(AG18+AH18) -> 0 | AJ18: =(AA18-AI18)/AI18 -> #DIV/0!
A19: R2 | B19: 3. Rubber | C19: WHEEL GRIP W2 | I19: 0 | M19: Silicon rubber | N19: Pantone Cool Grey 6C | O19: Pantone Cool Grey 6C /Silicon Rubber /VDI 24 (Horizontal) | U19: 0.081 | V19: =U19*I19 -> 0 | AA19: =W19*(Y19+Z19) -> 0 | AC19: 0.0732 | AD19: =I19*AC19 -> 0 | AE19: =(V19-AD19)/AD19 -> #DIV/0! | AI19: =W19*(AG19+AH19) -> 0 | AJ19: =(AA19-AI19)/AI19 -> #DIV/0!
A20: R3 | B20: 3. Rubber | C20: WHEEL GRIP W3 | I20: 0 | M20: Silicon rubber | N20: Pantone Cool Grey 6C | O20: Pantone Cool Grey 6C /Silicon Rubber /VDI 24 (Topographic) | U20: 0.081 | V20: =U20*I20 -> 0 | AA20: =W20*(Y20+Z20) -> 0 | AC20: 0.0732 | AD20: =I20*AC20 -> 0 | AE20: =(V20-AD20)/AD20 -> #DIV/0! | AI20: =W20*(AG20+AH20) -> 0 | AJ20: =(AA20-AI20)/AI20 -> #DIV/0!
A21: O1 | B21: 4. Others | C21: PTFE FEET PAD UP W | I21: 2 | M21: PTFE (TEFLON) | N21: White | O21: White /Virgin Grade PTFE /High Gloss 含保護膜(透明) | U21: 0.03 | V21: =U21*I21 -> 0.06 | AA21: =W21*(Y21+Z21) -> 0 | AC21: 0.028 | AD21: =I21*AC21 -> 0.056 | AE21: =(V21-AD21)/AD21 -> 0.071428571 | AI21: =W21*(AG21+AH21) -> 0 | AJ21: =(AA21-AI21)/AI21 -> #DIV/0!
A22: O2 | B22: 4. Others | C22: PTFE FEET PAD DOWN W | I22: 1 | M22: PTFE (TEFLON) | N22: White | O22: White /Virgin Grade PTFE /High Gloss 含保護膜(透明) | U22: 0.153 | V22: =U22*I22 -> 0.153 | AA22: =W22*(Y22+Z22) -> 0 | AC22: 0.145 | AD22: =I22*AC22 -> 0.145 | AE22: =(V22-AD22)/AD22 -> 0.055172414 | AI22: =W22*(AG22+AH22) -> 0 | AJ22: =(AA22-AI22)/AI22 -> #DIV/0!
A23: O3 | B23: 4. Others | C23: SCREW T2x6mm | F23: SCREW,MILD STEEL,ZINC BLACK,NINJA/FSG-E1J0,T2x6mm,CROSS,1018A BLACK,ZN,RoHS | G23: 0961-0003-83A0 | I23: 4 | M23: A1018 | N23: Sliver | O23: 自攻,十字槽,鍍鎳,D3.5*頭厚1.3*L6 | U23: 0.00385 | V23: =U23*I23 -> 0.0154 | AA23: =W23*(Y23+Z23) -> 0 | AC23: 0.00309 | AD23: =I23*AC23 -> 0.01236 | AE23: =(V23-AD23)/AD23 -> 0.24595469 | AI23: =W23*(AG23+AH23) -> 0 | AJ23: =(AA23-AI23)/AI23 -> #DIV/0!
A24: O4 | B24: 4. Others | C24: SCREW P2x4mm | F24: SCREW,MILD STEEL,ZINC BLACK,NINJA/FSG-E1J0, P2x4mm,CROSS,1018A BLACK,ZN,RoHS | G24: 0961-0004-83A0 | I24: 9 | M24: A1018 | N24: Black | O24: 自攻,十字槽,鍍黑鎳,D3.5*頭厚1.3*L4 | U24: 0.00495 | V24: =U24*I24 -> 0.04455 | AA24: =W24*(Y24+Z24) -> 0 | AC24: 0.003 | AD24: =I24*AC24 -> 0.027 | AE24: =(V24-AD24)/AD24 -> 0.65 | AI24: =W24*(AG24+AH24) -> 0 | AJ24: =(AA24-AI24)/AI24 -> #DIV/0!
A25: O5 | B25: 4. Others | C25: SCREW P2x4mm | F25: SCREW,MILD STEEL,ZINC WHITE, P2x4mm,CROSS,1018A WHITE,ZN,RoHS,LEFT-HAND THREAD | G25: 0961-0006-81A0 | I25: 1 | M25: A1018 | N25: White | O25: 自攻,十字槽,鍍白鋅,D3.5*頭厚1.3*L4, 左旋螺絲 | U25: 0.00495 | V25: =U25*I25 -> 0.00495 | AA25: =W25*(Y25+Z25) -> 0 | AC25: =0.0385/7 -> 0.0055 | AD25: =I25*AC25 -> 0.0055 | AE25: =(V25-AD25)/AD25 -> -0.1 | AI25: =W25*(AG25+AH25) -> 0 | AJ25: =(AA25-AI25)/AI25 -> #DIV/0!
V26: =U26*I26 -> 0 | AA26: =W26*(Y26+Z26) -> 0 | AD26: =I26*AC26 -> 0 | AE26: =(V26-AD26)/AD26 -> #DIV/0! | AI26: =W26*(AG26+AH26) -> 0 | AJ26: =(AA26-AI26)/AI26 -> #DIV/0!
V27: =U27*I27 -> 0 | AA27: =W27*(Y27+Z27) -> 0 | AD27: =I27*AC27 -> 0 | AE27: =(V27-AD27)/AD27 -> #DIV/0! | AI27: =W27*(AG27+AH27) -> 0 | AJ27: =(AA27-AI27)/AI27 -> #DIV/0!
U29: Total cost | V29: =SUM(V8:V27) -> 1.6993808 | AA29: =SUM(AA8:AA27) -> 0 | AD29: =SUM(AD8:AD27) -> 1.5403829 | AE29: =(V29-AD29)/AD29 -> 0.10321974 | AI29: =SUM(AI8:AI27) -> 0 | AJ29: =(AA29-AI29)/AI29 -> #DIV/0!

Sheet PKG BOM 20240308_with FSC
A2: Steelseries Rival3 Gen2 RFQ - Package BOM list | N2: Date: 2024/3/13 | Q2: True Cost | X2: 7.1
A3: Model Description: Steelseries Rival 3 Gen2 | J3: Rev.:A | K3: ELM5 | M3: ELM5 Gen2 | Q3: EV Phase | R3: 報價 in RMB w/ FSC certificate | U3: 報價 in USD w/ FSC certificate | W3: Markup | X3: Remark
A4: No. | B4: Level | C4: Foxlink P/N | D4: Customer P/N | E4: Customer Description | G4: Image | H4: Description | I4: Chinese Part name | J4: Unit Q'ty (pcs) | K4: Unit Price (USD/pc) ELM5 | L4: Amount (USD) ELM5 | M4: Unit Price (USD/pc) ELM5 Gen2 | N4: Amount (USD) ELM5 Gen2 | O4: Remark | Q4: QTY | R4: 單價 RMB | S4: MOQ | T4: LT day | U4: 單價 USD | V4: Amount(USD)
A5: 1-1 | B5: 1 | C5: 584A-1047-00AC | D5: N/A | E5: Box | F5: material: 300g artpaper, 4C+1C PMS, printing: matte PP dimension：278x250mm | H5: Box Outside set-up dimensions:(LxWxD):153x86x46mm Flat sheet dimensions:(L)278x(W)250x(T)0.5mm Material:300gsm SBS Print: 4C+1C PMS Surface process: Matte PP film Joint: Glued inside Remark:包装原料需符合FSC认证要求 | I5: 彩盒 | J5: 1 | K5: 0.3033 | L5: =J5*K5 -> 0.3033 | M5: 0.3033 | N5: =M5*J5 -> 0.3033 | O5: 031324: Paper with FSC certificate was 0.2821 | Q5: 1 | R5: 1.06 | S5: 5000 | T5: 14 | U5: =R5/$X$2 -> 0.14929577 | V5: =U5*J5 -> 0.14929577 | W5: =(M5-U5)/U5 -> 1.0315377 | X5: difference between FSC and w/o FSC | Y5: =R5-'PKG BOM 20240223'!R4 -> 0.02 | Z5: =(R5-'PKG BOM 20240223'!R4)/'PKG BOM 20240223'!R4 -> 0.019230769
A6: 2 | C6: 5811-1047-00A0 | D6: N/A | E6: Hanger | F6: material: 0.5T clear PET dimension：70x36.5mm | H6: Hang tab Outside dimensions:(LxW):60x40mm70x36.5mm Material: 0.5T PET (Clear) Other: Back side with Double sided tape (70x10mm) | I6: 掛鉤 | J6: 1 | K6: 0.062117647 | L6: =K6*J6 -> 0.062117647 | M6: 0.062117647 | N6: =M6*J6 -> 0.062117647 | O6: MOQ:10K | Q6: 1 | R6: 0.352 | S6: 5000 | T6: 14 | U6: =R6/$X$2 -> 0.049577465 | V6: =U6*J6 -> 0.049577465 | W6: =(M6-U6)/U6 -> 0.25294118
A7: 2 | C7: TBD | D7: N/A | E7: Hanger | H7: Hang tab Outside dimensions:(LxW):70x36.5mm Material: 350gsm SBS对裱 Print: 1C (Pantone 1655C) Other: Back side with Double sided tape (70x10mm) | I7: 掛鉤 | J7: 0 | M7: =U7*1.2 -> 0.15785915 | N7: =M7*J7 -> 0 | Q7: 1 | R7: 0.934 | S7: 5000 | T7: 14 | U7: =R7/$X$2 -> 0.1315493 | V7: =U7*J7 -> 0 | W7: =(M7-U7)/U7 -> 0.2 | Y7: =U7-U6 -> 0.081971831 | Z7: =(U7-U6)/U6 -> 1.6534091
A8: 3 | B8: 1 | C8: 5843-1047-00A0 | D8: N/A | E8: paper insert | F8: material: E flute corrugated paper board, original color extension dimension：296x152mm | H8: Paper insert Outside dimensions:(LxWxD):380x164mm 296x152mm Material:E flute corrugated paper board, original color Process: Die-cut Remark:包装原料需符合FSC认证要求 | I8: 内纸卡 | J8: 1 | K8: 0.071764706 | L8: =K8*J8 -> 0.071764706 | M8: =U8*1.2 -> 0.088715493 | N8: =M8*J8 -> 0.088715493 | O8: 031324: Paper with FSC certificate | Q8: 1 | R8: 0.5249 | S8: 3000 | T8: 14 | U8: =R8/$X$2 -> 0.073929577 | V8: =U8*J8 -> 0.073929577 | W8: =(M8-U8)/U8 -> 0.2 | X8: difference between FSC and w/o FSC | Y8: =R8-'PKG BOM 20240223'!R6 -> 0.2199 | Z8: =(R8-'PKG BOM 20240223'!R6)/'PKG BOM 20240223'!R6 -> 0.72098361
A9: 4 | B9: 1 | C9: 5649-1001-0LE0 5849-1020-00E0 | D9: N/A | E9: Seal label | F9: material: 19#PET, dimension: 25x25mm | H9: Seal label Outside dimensions:Φ=40mm25mm Material:Acrylic 25#19#TRANSPARENCY Can be use foxlink existing part P/N 5649-1020-00E0 | I9: 封口贴 | J9: 2 | K9: 0.0040683824 | L9: =K9*J9 -> 0.0081367647 | M9: 0.0056338028 | N9: =M9*J9 -> 0.011267606 | O9: Can be use foxlink existing part P/N 5649-1001-0LE0 | Q9: 2 | R9: 0.04 | S9: 5000 | T9: 14 | U9: =R9/$X$2 -> 0.0056338028 | V9: =U9*J9 -> 0.011267606 | W9: =(M9-U9)/U9 -> 0 | X9: 022724:true cost update
A10: 4 | B10: 1 | C10: TBD | D10: N/A | E10: Seal label | H10: Seal label Outside dimensions:Φ25mm Material:53gsm 透明木浆纸+丙烯酸胶 &背80gsm格拉辛离型纸 Thickness: 50um +/-2 | I10: 封口贴 | J10: 0 | M10: =U10*1.2 -> 0.012 | N10: =M10*J10 -> 0 | Q10: 2 | R10: 0.071 | S10: 5000 | T10: 14 | U10: =R10/$X$2 -> 0.01 | V10: =U10*J10 -> 0 | W10: =(M10-U10)/U10 -> 0.2 | X10: 022724:true cost update | Y10: =U10-U9 -> 0.0043661972 | Z10: =(U10-U9)/U9 -> 0.775
A11: 5 | B11: 1 | C11: 5831-1047-00AB | D11: N/A | E11: PIG | F11: material: 80g woodfree paper; dimension: 320 x 200 mm, printing: 2C double side printing type: folding paper | H11: Manual Flat sheet dimensions(LxW): (L)320*(W)200mm Fold size: 80*100mm Material : 80gsm WFUC Print: 2C double side printing Process: Folding X 4 Remark:包装原料需符合FSC认证要求 | I11: 说明书 | J11: 1 | K11: 0.0628 | L11: =K11*J11 -> 0.0628 | M11: 0.0628 | N11: =M11*J11 -> 0.0628 | O11: 031324: Paper with FSC certificate was 0.0584 | Q11: 1 | R11: 0.289 | S11: 5000 | T11: 14 | U11: =R11/$X$2 -> 0.040704225 | V11: =U11*J11 -> 0.040704225 | W11: =(M11-U11)/U11 -> 0.54283737 | X11: difference between FSC and w/o FSC | Y11: =R11-'PKG BOM 20240223'!R8 -> 0.026 | Z11: =(R11-'PKG BOM 20240223'!R8)/'PKG BOM 20240223'!R8 -> 0.098859316
A12: 6 | B12: 1 | C12: 5845-1047-00A0 | D12: N/A | E12: PE bag for mouse | F12: material:0.03T HDPE,1C printing dimension: 280x100mm | H12: PE Bag Dimensions(LxW): (L)215x(W)100mm (L)280x(W)100mm Material : 0.05mm LDPE Material : 0.03mm HDPE Print: Black only Process:Hole x1 | I12: 胶袋 | J12: 1 | K12: 0.017205882 | L12: =K12*J12 -> 0.017205882 | M12: 0.017205882 | N12: =M12*J12 -> 0.017205882 | O12: =M13/M12 -> 12.769953 | Q12: 1 | R12: 0.067 | S12: 10000 | T12: 15 | U12: =R12/$X$2 -> 0.0094366197 | V12: =U12*J12 -> 0.0094366197 | W12: =(M12-U12)/U12 -> 0.82330992
A13: 6 | B13: 1 | C13: TBD | D13: N/A | E13: PE bag for mouse | H13: PE Bag Dimensions(LxW):(L)280x(W)100mm Material : 70%CPE+30%GMX Thickness: 0.05mm Print: Black only Process:Hole x1 厂商：新东颖 | I13: 胶袋 | J13: 0 | M13: =U13*1.2 -> 0.21971831 | N13: =M13*J13 -> 0 | Q13: 1 | R13: 1.3 | S13: 10000 | T13: 15 | U13: =R13/$X$2 -> 0.18309859 | V13: =U13*J13 -> 0 | W13: =(M13-U13)/U13 -> 0.2 | Y13: =U13-U12 -> 0.17366197 | Z13: =(U13-U12)/U12 -> 18.402985
A14: 7 | B14: 1 | C14: 5842-1047-00A0 | D14: N/A | E14: Master Carton | F14: material: B flute, burst above 12KGF | H14: ‘Carton Outside dimensions: (L)213X(W)165X(H)185mm(L)321X(W)106X(H)182mm; (L)182X(W)149X(H)175mm; Material: A. Material type: Corrugated fibreboard B. Flute: C Flute C. Grade: 200# Mullen Burst OR 32 ECT Print: Black Joint: Glued inside Remark: 纸板原材料需符合FSC认证要求 | I14: 外箱 | J14: =1/6 -> 0.16666667 | K14: 0.25808824 | L14: =K14*J14 -> 0.043014706 | M14: =U14*1.2 -> 0.32425352 | N14: =M14*J14 -> 0.054042254 | O14: 031324: Paper with FSC certificate | Q14: 0.16666667 | R14: 1.9185 | S14: 500 | T14: 15 | U14: =R14/$X$2 -> 0.27021127 | V14: =U14*J14 -> 0.045035211 | W14: =(M14-U14)/U14 -> 0.2 | X14: difference between FSC and w/o FSC | Y14: =R14-'PKG BOM 20240223'!R10 -> 0.7685 | Z14: =(R14-'PKG BOM 20240223'!R10)/'PKG BOM 20240223'!R10 -> 0.66826087
A15: 8 | B15: 1 | C15: 5843-1047-01A0 | D15: N/A | E15: carton TB board | F15: B/F, burst above 10KGF(inside the carton top and bottom) | H15: Paper board Material: B flute 12kgf Dimension(LxW): (L)171x(W)138mm Remark: 纸板原材料需符合FSC认证要求 | I15: 天地板 | J15: =2/6 -> 0.33333333 | K15: 0.088235294 | L15: =K15*J15 -> 0.029411765 | M15: 0.088235294 | N15: =M15*J15 -> 0.029411765 | Q15: 0.33333333 | R15: 0.17 | S15: 500 | T15: 14 | U15: =R15/$X$2 -> 0.023943662 | V15: =U15*J15 -> 0.0079812207 | W15: =(M15-U15)/U15 -> 2.6851211
A16: 9 | B16: 1 | C16: 0952-0035-00E0 0952-1047-00A0 | D16: N/A | E16: PE bag for box | F16: PE-LD :1219x230x0.015mm1840x230x0.015mm | G16: N/A | H16: HDPE film (protect retail box) Material: HDPE (T=0.015mm) Dimension: (L)1219x(W)230mm(L)1840x(W)230mm Can be use foxlink existing part P/N 0952-0035-00E0 | I16: 隔膜 | J16: 0.33333333 | K16: 0.012617647 | L16: =K16*J16 -> 0.0042058824 | M16: 0.017323944 | N16: =M16*J16 -> 0.0057746479 | O16: Can be use foxlink existing part P/N 0952-0035-00E0 | Q16: 0.33333333 | R16: 0.123 | S16: 20000 | T16: 14 | U16: =R16/$X$2 -> 0.017323944 | V16: =U16*J16 -> 0.0057746479 | W16: =(M16-U16)/U16 -> 0 | X16: 022724:true cost update
A17: 9 | B17: 1 | C17: TBD | D17: N/A | E17: Protective paper | G17: N/A | H17: Protective paper Material: 40gsm 雪梨纸 Thickness: 0.02mm Dimension:(L)1840x(W)230mm | I17: 隔膜纸 | J17: 0 | M17: =U17*1.2 -> 0.21515493 | N17: =M17*J17 -> 0 | Q17: 0.33333333 | R17: 1.273 | S17: 5000 | T17: 28 | U17: =R17/$X$2 -> 0.17929577 | V17: =U17*J17 -> 0 | W17: =(M17-U17)/U17 -> 0.2 | X17: 022724:true cost update | Y17: =U17-U16 -> 0.16197183 | Z17: =(U17-U16)/U16 -> 9.3495935
A18: 10 | B18: 1 | C18: 5849-1047-03A0 | D18: N/A | E18: Label (for master carton) | F18: material: 80g art paper dimension：100x55 mm printing: 1C with online printing | H18: Master Carton Label Outside dimensions:(L)119X(W)78mm (L)88.3X(W)59.48mm(L)100X(W)55mm; Material : 80gsm artpaper Print: Black | I18: 外箱标签 | J18: =1/6 -> 0.16666667 | K18: 0.024264706 | L18: =K18*J18 -> 0.0040441176 | M18: 0.024264706 | N18: =M18*J18 -> 0.0040441176 | Q18: 0.16666667 | R18: 0.146 | S18: 5000 | T18: 15 | U18: =R18/$X$2 -> 0.02056338 | V18: =U18*J18 -> 0.00342723 | W18: =(M18-U18)/U18 -> 0.17999597
A19: 11 | B19: 1 | C19: 5849-1047-02A0 | D19: N/A | E19: S/N label for carton (for master carton) | F19: material: 80g art paper dimension：59.67x52 mm printing: blank with online printing | H19: Carton Label(SN) Outside dimensions: (L)40x(W)38mm(L)59.67X(W)52mm; Material : 80gsm artpaper | I19: 外箱标签 | J19: =1/6 -> 0.16666667 | K19: 0.0097058824 | L19: =K19*J19 -> 0.0016176471 | M19: 0.0097058824 | N19: =M19*J19 -> 0.0016176471 | Q19: 0.16666667 | R19: 0.058 | S19: 5000 | T19: 15 | U19: =R19/$X$2 -> 0.0081690141 | V19: =U19*J19 -> 0.0013615023 | W19: =(M19-U19)/U19 -> 0.18813387
A20: 12 | B20: 1 | C20: 5849-1043-02A0 | D20: N/A | E20: SN Label (for color box) | F20: material: 80g art paper dimension: 38x12mm printing: blank with online printing | G20: N/A | H20: Color box SN Label Outside dimensions:(L)38X(W)8mm (L)38X(W)12mm; Material : 80gsm artpaper Can be use foxlink existing part P/N 5849-1043-02A0 | I20: 彩盒标签 | J20: 1 | K20: 0.0056617647 | L20: =K20*J20 -> 0.0056617647 | M20: 0.0056617647 | N20: =M20*J20 -> 0.0056617647 | O20: Can be use foxlink existing part P/N 5849-1043-02A0 | Q20: 1 | R20: 0.01 | S20: 5000 | T20: 15 | U20: =R20/$X$2 -> 0.0014084507 | V20: =U20*J20 -> 0.0014084507 | W20: =(M20-U20)/U20 -> 3.0198529
A21: 13 | B21: 1 | C21: 5849-1047-00AA | D21: N/A | E21: PID label (for product) | F21: material: 80g black PET+ printable matte pp film dimension:45.424x23 mm printing: 2C | H21: PID Label Outside dimensions: (L)37.3X(W)33.7mm (L)45.424X(W)23mm; Material : 50#PET+25# PP film Print: 2C | I21: PID标签 | J21: 1 | K21: 0.016985294 | L21: =K21*J21 -> 0.016985294 | M21: 0.021126761 | N21: =M21*J21 -> 0.021126761 | Q21: 1 | R21: 0.15 | S21: 5000 | T21: 15 | U21: =R21/$X$2 -> 0.021126761 | V21: =U21*J21 -> 0.021126761 | W21: =(M21-U21)/U21 -> 0 | X21: 022724:true cost update
A22: 14 | B22: 1 | C22: 5849-1012-05A0 | D22: N/A | E22: Pallet label | F22: Label,Pallet,AP,153x102mm | G22: N/A | H22: Pallet Label Outside dimensions: (L)165X(W)102mm (L)153X(W)102mm; Material : 80gsm artpaper Can be use foxlink existing part P/N 5849-1012-05A0 | I22: 棧板标签 | J22: =1/750 -> 0.0013333333 | K22: 0.026691176 | L22: =K22*J22 -> 3.5588235e-05 | M22: 0.026691176 | N22: =M22*J22 -> 3.5588235e-05 | O22: Can be use foxlink existing part P/N 5849-1012-05A0 | Q22: 0.0013333333 | R22: 0.135 | S22: 5000 | T22: 7 | U22: =R22/$X$2 -> 0.019014085 | V22: =U22*J22 -> 2.5352113e-05 | W22: =(M22-U22)/U22 -> 0.40375817
A23: 15 | B23: 1 | C23: 5849-1043-05A0 | D23: N/A | E23: PCBA Tracking Label | F23: material: 80g art paper dimension：35x7 mm printing: blank with online printing | G23: N/A | H23: PCBA Tracking Label Outside dimensions: (L)35X(W)7mm; Material : 80gsm artpaper Can be use foxlink existing part P/N 5849-1043-05A0 | I23: 追蹤標籤 | J23: 1 | K23: 0.0084117647 | L23: =K23*J23 -> 0.0084117647 | M23: 0.0084117647 | N23: =M23*J23 -> 0.0084117647 | O23: Can be use foxlink existing part P/N 5849-1043-05A0 | Q23: 1 | R23: 0.044 | S23: 10000 | T23: 14 | U23: =R23/$X$2 -> 0.0061971831 | V23: =U23*J23 -> 0.0061971831 | W23: =(M23-U23)/U23 -> 0.35735294
A24: 16 | B24: 1 | C24: 5849-1043-00A0 | D24: N/A | E24: Cable Tag | F24: material: 80g art paper, matte coating(with glue) dimension：66.073x15 mm printing: blank | H24: Cable tag Outside dimensions: (L)66X(W)15mm; Material : 80gsm artpaper, matte coating(with glue) Can be use foxlink existing part P/N 5849-1043-00A0 | I24: 下載標籤 | J24: 1 | K24: 0.0127 | L24: =K24*J24 -> 0.0127 | M24: 0.0127 | N24: =M24*J24 -> 0.0127 | O24: Can be use foxlink existing part P/N 0981-1914-00A0 | Q24: 1 | R24: 0.07 | S24: 5000 | T24: 14 | U24: =R24/$X$2 -> 0.0098591549 | V24: =U24*J24 -> 0.0098591549 | W24: =(M24-U24)/U24 -> 0.28814286
A25: 16 | B25: 1 | C25: 0981-1918-00A0 | D25: N/A | E25: Pallet & related | F25: pallet packing material Pallet | H25: PALLET,OMAHA/FVV-E5K2,GMA STYLE PALLET,1200x1000 mm,RoHS | I25: 棧板 | J25: =1/750 -> 0.0013333333 | K25: 15.71 | L25: =K25*J25 -> 0.020946667 | M25: 15.71 | N25: =M25*J25 -> 0.020946667 | O25: 2020/06/08 Change to GMA pallet | Q25: 0.0013333333 | R25: 103 | S25: 100 | T25: 15 | U25: =R25/$X$2 -> 14.507042 | V25: =U25*J25 -> 0.019342723 | W25: =(M25-U25)/U25 -> 0.08292233
A26: 17 | B26: 1 | C26: 0984-001E-00A0 | D26: N/A | E26: Card Board | F26: N/A | G26: N/A | H26: Card Board Dimension: 1200x1000mm | I26: 隔板 | J26: =2/1260 -> 0.0015873016 | K26: 1.4041176 | L26: =K26*J26 -> 0.0022287582 | M26: 1.4041176 | N26: =M26*J26 -> 0.0022287582 | Q26: 0.0015873016 | R26: 7.26 | S26: 100 | T26: 14 | U26: =R26/$X$2 -> 1.0225352 | V26: =U26*J26 -> 0.0016230718 | W26: =(M26-U26)/U26 -> 0.37317291
A27: 18 | B27: 1 | C27: 0984-1047-00A0 | D27: N/A | E27: Card Board | F27: N/A | G27: N/A | H27: Card Board Dimension: 1175x993 mm | I27: 隔板 | J27: =4/1260 -> 0.0031746032 | K27: 0.32676471 | L27: =K27*J27 -> 0.0010373483 | M27: 0.48028169 | N27: =M27*J27 -> 0.0015247038 | Q27: 0.0031746032 | R27: 3.41 | S27: 100 | T27: 15 | U27: =R27/$X$2 -> 0.48028169 | V27: =U27*J27 -> 0.0015247038 | W27: =(M27-U27)/U27 -> 0 | X27: 022724:true cost update
A28: 19 | B28: 1 | C28: 0984-001H-00A0 | D28: N/A | E28: Corner Board | F28: N/A | G28: N/A | H28: Corner Board Dimension:1025X50X50mm Can be use Foxlink existing P/N: 0984-000W-00E0 | I28: 護角 | J28: =8/1260 -> 0.0063492063 | K28: 0.32676471 | L28: =K28*J28 -> 0.0020746965 | M28: 0.32676471 | N28: =M28*J28 -> 0.0020746965 | O28: Can be use Foxlink existing P/N: 0984-000W-00E0 | Q28: 0.0063492063 | R28: 2.02 | S28: 1000 | T28: 15 | U28: =R28/$X$2 -> 0.28450704 | V28: =U28*J28 -> 0.0018063939 | W28: =(M28-U28)/U28 -> 0.14852941
A29: 20 | B29: 1 | C29: 0984-001J-00A0 | D29: N/A | E29: Corner Board | F29: N/A | G29: N/A | H29: Corner Board Dimension:,900X50X50mm Can be use Foxlink existing P/N: 0984-000x-00E0 | I29: 護角 | J29: =4/1260 -> 0.0031746032 | K29: 0.28632353 | L29: =K29*J29 -> 0.00090896359 | M29: 0.28632353 | N29: =M29*J29 -> 0.00090896359 | O29: Can be use Foxlink existing P/N: 0984-000x-00E0 | Q29: 0.0031746032 | R29: 1.77 | S29: 1000 | T29: 15 | U29: =R29/$X$2 -> 0.24929577 | V29: =U29*J29 -> 0.00079141516 | W29: =(M29-U29)/U29 -> 0.14852941
A30: 21 | B30: 1 | C30: 0952-000T-00A0 | D30: N/A | E30: SS Logo seal tape | F30: N/A | G30: N/A | H30: Corner Board Dimension:60mm X 100m Color: 2C Print | I30: SS標誌封箱膠帶 | J30: 0.005 | K30: 0 | L30: =K30*J30 -> 0 | M30: 1.8929577 | N30: =M30*J30 -> 0.0094647887 | Q30: 0.005 | R30: 11.2 | S30: 900 | T30: 15 | U30: =R30/$X$2 -> 1.5774648 | V30: =U30*J30 -> 0.0078873239 | W30: =(M30-U30)/U30 -> 0.2 | X30: New
A31: 22 | B31: 1 | C31: 0952-0005-00E0 | D31: N/A | E31: INK RIBBON | F31: N/A | G31: N/A | H31: INK RIBBON,DEPLETION,B110A,110MM,LF | I31: 碳带 | J31: 0.000217 | K31: 0 | L31: =K31*J31 -> 0 | M31: 9.8873239 | N31: =M31*J31 -> 0.0021455493 | Q31: 0.000217 | R31: 58.5 | S31: 10 | T31: 7 | U31: =R31/$X$2 -> 8.2394366 | V31: =U31*J31 -> 0.0017879577 | W31: =(M31-U31)/U31 -> 0.2 | X31: New
A32: 23 | B32: 1 | C32: 0952-0002-00E0 | D32: N/A | E32: INK RIBBON | F32: N/A | G32: N/A | H32: INK RIBBON,DEPLETION,TW10,60MM,LF | I32: 碳带 | J32: 0.000118 | K32: 0 | L32: =K32*J32 -> 0 | M32: 5.3543662 | N32: =M32*J32 -> 0.00063181521 | Q32: 0.000118 | R32: 31.68 | S32: 10 | T32: 7 | U32: =R32/$X$2 -> 4.4619718 | V32: =U32*J32 -> 0.00052651268 | W32: =(M32-U32)/U32 -> 0.2 | X32: New
A33: 24 | B33: 1 | C33: 0952-000C-00E0 | D33: N/A | E33: INK RIBBON | F33: N/A | G33: N/A | H33: INK RIBBON,DEPLETION,TRC32, 40MM,LF | I33: 碳带 | J33: 0.0001 | K33: 0 | L33: =K33*J33 -> 0 | M33: 7.6394366 | N33: =M33*J33 -> 0.00076394366 | Q33: 0.0001 | R33: 45.2 | S33: 50 | T33: 7 | U33: =R33/$X$2 -> 6.3661972 | V33: =U33*J33 -> 0.00063661972 | W33: =(M33-U33)/U33 -> 0.2 | X33: New
A34: 25 | B34: 1 | C34: 0952-000S-00E0 | D34: N/A | E34: Tape | F34: N/A | G34: N/A | H34: OC,DEPLETION,TAPE,SEAL(400m*500mm*0.018cm),RoHS | I34: 打包膜 | J34: 0.00045 | K34: 0 | L34: =K34*J34 -> 0 | M34: 6.1352113 | N34: =M34*J34 -> 0.0027608451 | Q34: 0.00045 | R34: 36.3 | S34: 500 | T34: 10 | U34: =R34/$X$2 -> 5.1126761 | V34: =U34*J34 -> 0.0023007042 | W34: =(M34-U34)/U34 -> 0.2 | X34: New
A35: Subtotal(USD/Unit)： | L35: =SUM(L5:L29) -> 0.67860996 | N35: =SUM(N5:N34) -> 0.73168367 | O35: 022724: ex rate 7.1 ex rate: 6.3 RMB | U35: =R35/$X$2 -> 0 | V35: =SUM(V5:V34) -> 0.47463541 | W35: =(N35-V35)/V35 -> 0.54156992 | X35: Margin
A36: Subtotal(USD/Unit)： | L36: =L35*6.3/7 -> 0.61074897 | O36: New ex rate 7 | P36: =>update on Oct 27, 2022 | V36: =V35-'PKG BOM 20240223'!V30 -> 0.05549061 | W36: =(V35-'PKG BOM 20240223'!V30)/'PKG BOM 20240223'!V30 -> 0.13239007 | X36: cost up due to FSC & sustainable material
M38: Rival 3 vs Rvial 3 Gen2 difference | N38: =N35-L35 -> 0.053073705 | O38: =(N35-L35)/L35 -> 0.07820944

Sheet PKG BOM 20240223
A1: Steelseries Rival3+ RFQ - Package BOM list | N1: Date: 2024/2/23 | Q1: True Cost | X1: 7.1
A2: Model Description: Steelseries Rival 3 + | J2: Rev.:A | K2: ELM5 | M2: Rival3+ | Q2: EV Phase | R2: 報價 in RMB w/o FSC certificate | U2: 報價 in USD w/o FSC certificate | W2: Markup | X2: Remark
A3: No. | B3: Level | C3: Foxlink P/N | D3: Customer P/N | E3: Customer Description | G3: Image | H3: Description | I3: Chinese Part name | J3: Unit Q'ty (pcs) | K3: Unit Price (USD/pc) ELM5 | L3: Amount (USD) ELM5 | M3: Unit Price (USD/pc) Rivlal 3+ | N3: Amount (USD) Rival 3+ | O3: Remark | Q3: QTY | R3: 單價 RMB | S3: MOQ | T3: LT day | U3: 單價 USD | V3: Amount(USD)
A4: 1-1 | B4: 1 | C4: 584A-1047-00AC | D4: N/A | E4: Box | F4: material: 300g artpaper, 4C+1C PMS, printing: matte PP dimension：278x250mm | H4: Box Outside set-up dimensions:(LxWxD):153x86x46mm Flat sheet dimensions:(L)278x(W)250x(T)0.5mm Material:300gsm SBS Print: 4C+1C PMS Surface process: Matte PP film Joint: Glued inside | I4: 彩盒 | J4: 1 | K4: 0.3033 | L4: =J4*K4 -> 0.3033 | M4: 0.3033 | N4: =M4*J4 -> 0.3033 | O4: was 0.2821 | Q4: 1 | R4: 1.04 | S4: 5000 | T4: 14 | U4: =R4/$X$1 -> 0.14647887 | V4: =U4*J4 -> 0.14647887 | W4: =(M4-U4)/U4 -> 1.0706058
A5: 2 | C5: 5811-1047-00A0 | D5: N/A | E5: Hanger | F5: material: 0.5T clear PET dimension：70x36.5mm | H5: Hang tab Outside dimensions:(LxW):60x40mm70x36.5mm Material: 0.5T PET (Clear) Other: Back side with Double sided tape (70x10mm) | I5: 掛鉤 | J5: 1 | K5: 0.062117647 | L5: =K5*J5 -> 0.062117647 | M5: 0.062117647 | N5: =M5*J5 -> 0.062117647 | O5: MOQ:10K | Q5: 1 | R5: 0.352 | S5: 5000 | T5: 14 | U5: =R5/$X$1 -> 0.049577465 | V5: =U5*J5 -> 0.049577465 | W5: =(M5-U5)/U5 -> 0.25294118
A6: 3 | B6: 1 | C6: 5843-1047-00A0 | D6: N/A | E6: paper insert | F6: material: E flute corrugated paper board, original color extension dimension：380x164mm | H6: Paper insert Outside dimensions:(LxWxD):380x164mm 296x152mm Material:E flute corrugated paper board, original color Process: Die-cut | I6: 内纸卡 | J6: 1 | K6: 0.071764706 | L6: =K6*J6 -> 0.071764706 | M6: 0.071764706 | N6: =M6*J6 -> 0.071764706 | Q6: 1 | R6: 0.305 | S6: 3000 | T6: 14 | U6: =R6/$X$1 -> 0.042957746 | V6: =U6*J6 -> 0.042957746 | W6: =(M6-U6)/U6 -> 0.67058824
A7: 4 | B7: 1 | C7: 5649-1001-0LE0 5849-1020-00E0 | D7: N/A | E7: Seal label | F7: material: 19#PET, dimension: 25x25mm | H7: Seal label Outside dimensions:D=40mm25mm Material:Acrylic 25#19#TRANSPARENCY Can be use foxlink existing part P/N 5649-1020-00E0 | I7: 封口贴 | J7: 2 | K7: 0.0040683824 | L7: =K7*J7 -> 0.0081367647 | M7: 0.0056338028 | N7: =M7*J7 -> 0.011267606 | O7: Can be use foxlink existing part P/N 5649-1001-0LE0 | Q7: 2 | R7: 0.04 | S7: 5000 | T7: 14 | U7: =R7/$X$1 -> 0.0056338028 | V7: =U7*J7 -> 0.011267606 | W7: =(M7-U7)/U7 -> 0 | X7: 022724:true cost update
A8: 5 | B8: 1 | C8: 5831-1047-00AB | D8: N/A | E8: PIG | F8: material: 80g woodfree paper; dimension: 320 x 200 mm, printing: 2C double side printing type: folding paper | H8: Manual Flat sheet dimensions(LxW): (L)320*(W)200mm Fold size: 80*100mm Material : 80gsm WFUC Print: 2C double side printing Process: Folding X 4 | I8: 说明书 | J8: 1 | K8: 0.0628 | L8: =K8*J8 -> 0.0628 | M8: 0.0628 | N8: =M8*J8 -> 0.0628 | O8: was 0.0584 | Q8: 1 | R8: 0.263 | S8: 5000 | T8: 14 | U8: =R8/$X$1 -> 0.037042254 | V8: =U8*J8 -> 0.037042254 | W8: =(M8-U8)/U8 -> 0.69536122
A9: 6 | B9: 1 | C9: 5845-1047-00A0 | D9: N/A | E9: PE bag for mouse | F9: material:0.03T HDPE,1C printing dimension: 280x100mm | H9: PE Bag Dimensions(LxW): (L)215x(W)100mm (L)280x(W)100mm Material : 0.05mm LDPE Material : 0.03mm HDPE Print: Black only Process:Hole x1 | I9: 胶袋 | J9: 1 | K9: 0.017205882 | L9: =K9*J9 -> 0.017205882 | M9: 0.017205882 | N9: =M9*J9 -> 0.017205882 | Q9: 1 | R9: 0.067 | S9: 10000 | T9: 15 | U9: =R9/$X$1 -> 0.0094366197 | V9: =U9*J9 -> 0.0094366197 | W9: =(M9-U9)/U9 -> 0.82330992
A10: 7 | B10: 1 | C10: 5842-1047-00A0 | D10: N/A | E10: Master Carton | F10: material: B flute, burst above 12KGF | H10: Carton Outside dimensions: (L)213X(W)165X(H)185mm(L)321X(W)106X(H)182mm; (L)182X(W)149X(H)175mm; Material: A. Material type: Corrugated fibreboard B. Flute: C Flute C. Grade: 200# Mullen Burst OR 32 ECT Print: Black Joint: Glued inside | I10: 外箱 | J10: =1/6 -> 0.16666667 | K10: 0.25808824 | L10: =K10*J10 -> 0.043014706 | M10: 0.25808824 | N10: =M10*J10 -> 0.043014706 | Q10: 0.16666667 | R10: 1.15 | S10: 500 | T10: 15 | U10: =R10/$X$1 -> 0.16197183 | V10: =U10*J10 -> 0.026995305 | W10: =(M10-U10)/U10 -> 0.59341432
A11: 8 | B11: 1 | C11: 5843-1047-01A0 | D11: N/A | E11: carton TB board | F11: B/F, burst above 10KGF(inside the carton top and bottom) | H11: Paper board Material: B flute 12kgf Dimension(LxW):(L)205x(W)157mm (L)312x(W)97mm (L)171x(W)138mm | I11: 天地板 | J11: =2/6 -> 0.33333333 | K11: 0.088235294 | L11: =K11*J11 -> 0.029411765 | M11: 0.088235294 | N11: =M11*J11 -> 0.029411765 | Q11: 0.33333333 | R11: 0.17 | S11: 500 | T11: 14 | U11: =R11/$X$1 -> 0.023943662 | V11: =U11*J11 -> 0.0079812207 | W11: =(M11-U11)/U11 -> 2.6851211
A12: 9 | B12: 1 | C12: 0952-0035-00E0 0952-1047-00A0 | D12: N/A | E12: PE bag for box | F12: PE-LD :1219x230x0.015mm1840x230x0.015mm | G12: N/A | H12: HDPE film (protect retail box) Material: HDPE (T=0.015mm) Dimension: (L)1219x(W)230mm(L)1840x(W)230mm Can be use foxlink existing part P/N 0952-0035-00E0 | I12: 隔膜纸 | J12: =2/6 -> 0.33333333 | K12: 0.012617647 | L12: =K12*J12 -> 0.0042058824 | M12: 0.017323944 | N12: =M12*J12 -> 0.0057746479 | O12: Can be use foxlink existing part P/N 0952-0035-00E0 | Q12: 0.33333333 | R12: 0.123 | S12: 20000 | T12: 14 | U12: =R12/$X$1 -> 0.017323944 | V12: =U12*J12 -> 0.0057746479 | W12: =(M12-U12)/U12 -> 0 | X12: 022724:true cost update
A13: 10 | B13: 1 | C13: 5849-1047-03A0 | D13: N/A | E13: Label (for master carton) | F13: material: 80g art paper dimension：100x55 mm printing: 1C with online printing | H13: Master Carton Label Outside dimensions:(L)119X(W)78mm (L)88.3X(W)59.48mm(L)100X(W)55mm; Material : 80gsm artpaper Print: Black | I13: 外箱标签 | J13: =1/6 -> 0.16666667 | K13: 0.024264706 | L13: =K13*J13 -> 0.0040441176 | M13: 0.024264706 | N13: =M13*J13 -> 0.0040441176 | Q13: 0.16666667 | R13: 0.146 | S13: 5000 | T13: 15 | U13: =R13/$X$1 -> 0.02056338 | V13: =U13*J13 -> 0.00342723 | W13: =(M13-U13)/U13 -> 0.17999597
A14: 11 | B14: 1 | C14: 5849-1047-02A0 | D14: N/A | E14: S/N label for carton (for master carton) | F14: material: 80g art paper dimension：59.67x52 mm printing: blank with online printing | H14: Carton Label(SN) Outside dimensions: (L)40x(W)38mm(L)59.67X(W)52mm; Material : 80gsm artpaper | I14: 外箱标签 | J14: =1/6 -> 0.16666667 | K14: 0.0097058824 | L14: =K14*J14 -> 0.0016176471 | M14: 0.0097058824 | N14: =M14*J14 -> 0.0016176471 | Q14: 0.16666667 | R14: 0.058 | S14: 5000 | T14: 15 | U14: =R14/$X$1 -> 0.0081690141 | V14: =U14*J14 -> 0.0013615023 | W14: =(M14-U14)/U14 -> 0.18813387
A15: 12 | B15: 1 | C15: 5849-1043-02A0 | D15: N/A | E15: SN Label (for color box) | F15: material: 80g art paper dimension: 38x12mm printing: blank with online printing | G15: N/A | H15: Color box SN Label Outside dimensions:(L)38X(W)8mm (L)38X(W)12mm; Material : 80gsm artpaper Can be use foxlink existing part P/N 5849-1043-02A0 | I15: 彩盒标签 | J15: 1 | K15: 0.0056617647 | L15: =K15*J15 -> 0.0056617647 | M15: 0.0056617647 | N15: =M15*J15 -> 0.0056617647 | O15: Can be use foxlink existing part P/N 5849-1043-02A0 | Q15: 1 | R15: 0.01 | S15: 5000 | T15: 15 | U15: =R15/$X$1 -> 0.0014084507 | V15: =U15*J15 -> 0.0014084507 | W15: =(M15-U15)/U15 -> 3.0198529
A16: 13 | B16: 1 | C16: 5849-1047-00AA | D16: N/A | E16: PID label (for product) | F16: material: 80g black PET+ printable matte pp film dimension:45.424x23 mm printing: 2C | H16: PID Label Outside dimensions: (L)37.3X(W)33.7mm (L)45.424X(W)23mm; Material : 50#PET+25# PP film Print: 2C | I16: PID标签 | J16: 1 | K16: 0.016985294 | L16: =K16*J16 -> 0.016985294 | M16: 0.021126761 | N16: =M16*J16 -> 0.021126761 | Q16: 1 | R16: 0.15 | S16: 5000 | T16: 15 | U16: =R16/$X$1 -> 0.021126761 | V16: =U16*J16 -> 0.021126761 | W16: =(M16-U16)/U16 -> 0 | X16: 022724:true cost update
A17: 14 | B17: 1 | C17: 5849-1012-05A0 | D17: N/A | E17: Pallet label | F17: Label,Pallet,AP,153x102mm | G17: N/A | H17: Pallet Label Outside dimensions: (L)165X(W)102mm (L)153X(W)102mm; Material : 80gsm artpaper Can be use foxlink existing part P/N 5849-1012-05A0 | I17: 棧板标签 | J17: =1/750 -> 0.0013333333 | K17: 0.026691176 | L17: =K17*J17 -> 3.5588235e-05 | M17: 0.026691176 | N17: =M17*J17 -> 3.5588235e-05 | O17: Can be use foxlink existing part P/N 5849-1012-05A0 | Q17: 0.0013333333 | R17: 0.135 | S17: 5000 | T17: 7 | U17: =R17/$X$1 -> 0.019014085 | V17: =U17*J17 -> 2.5352113e-05 | W17: =(M17-U17)/U17 -> 0.40375817
A18: 15 | B18: 1 | C18: 5849-1043-05A0 | D18: N/A | E18: PCBA Tracking Label | F18: material: 80g art paper dimension：35x7 mm printing: blank with online printing | G18: N/A | H18: PCBA Tracking Label Outside dimensions: (L)35X(W)7mm; Material : 80gsm artpaper Can be use foxlink existing part P/N 5849-1043-05A0 | I18: 追蹤標籤 | J18: 1 | K18: 0.0084117647 | L18: =K18*J18 -> 0.0084117647 | M18: 0.0084117647 | N18: =M18*J18 -> 0.0084117647 | O18: Can be use foxlink existing part P/N 5849-1043-05A0 | Q18: 1 | R18: 0.044 | S18: 10000 | T18: 14 | U18: =R18/$X$1 -> 0.0061971831 | V18: =U18*J18 -> 0.0061971831 | W18: =(M18-U18)/U18 -> 0.35735294
A19: 16 | B19: 1 | C19: 5849-1043-00A0 | D19: N/A | E19: Cable Tag | F19: material: 80g art paper, matte coating(with glue) dimension：66.073x15 mm printing: blank | H19: Cable tag Outside dimensions: (L)66X(W)15mm; Material : 80gsm artpaper, matte coating(with glue) Can be use foxlink existing part P/N 5849-1043-00A0 | I19: 下載標籤 | J19: 1 | K19: 0.0127 | L19: =K19*J19 -> 0.0127 | M19: 0.0127 | N19: =M19*J19 -> 0.0127 | O19: Can be use foxlink existing part P/N 0981-1914-00A0 | Q19: 1 | R19: 0.07 | S19: 5000 | T19: 14 | U19: =R19/$X$1 -> 0.0098591549 | V19: =U19*J19 -> 0.0098591549 | W19: =(M19-U19)/U19 -> 0.28814286
A20: 16 | B20: 1 | C20: 0981-1918-00A0 | D20: N/A | E20: Pallet & related | F20: pallet packing material Pallet | H20: PALLET,OMAHA/FVV-E5K2,GMA STYLE PALLET,1200x1000 mm,RoHS | I20: 棧板 | J20: =1/750 -> 0.0013333333 | K20: 15.71 | L20: =K20*J20 -> 0.020946667 | M20: 15.71 | N20: =M20*J20 -> 0.020946667 | O20: 2020/06/08 Change to GMA pallet | Q20: 0.0013333333 | R20: 103 | S20: 100 | T20: 15 | U20: =R20/$X$1 -> 14.507042 | V20: =U20*J20 -> 0.019342723 | W20: =(M20-U20)/U20 -> 0.08292233
A21: 17 | B21: 1 | C21: 0984-001E-00A0 | D21: N/A | E21: Card Board | F21: N/A | G21: N/A | H21: Card Board Dimension: 1200x1000mm | I21: 隔板 | J21: =2/1260 -> 0.0015873016 | K21: 1.4041176 | L21: =K21*J21 -> 0.0022287582 | M21: 1.4041176 | N21: =M21*J21 -> 0.0022287582 | Q21: 0.0015873016 | R21: 7.26 | S21: 100 | T21: 14 | U21: =R21/$X$1 -> 1.0225352 | V21: =U21*J21 -> 0.0016230718 | W21: =(M21-U21)/U21 -> 0.37317291
A22: 18 | B22: 1 | C22: 0984-1047-00A0 | D22: N/A | E22: Card Board | F22: N/A | G22: N/A | H22: Card Board Dimension: 1175x993 mm | I22: 隔板 | J22: =4/1260 -> 0.0031746032 | K22: 0.32676471 | L22: =K22*J22 -> 0.0010373483 | M22: 0.48028169 | N22: =M22*J22 -> 0.0015247038 | Q22: 0.0031746032 | R22: 3.41 | S22: 100 | T22: 15 | U22: =R22/$X$1 -> 0.48028169 | V22: =U22*J22 -> 0.0015247038 | W22: =(M22-U22)/U22 -> 0 | X22: 022724:true cost update
A23: 19 | B23: 1 | C23: 0984-001H-00A0 | D23: N/A | E23: Corner Board | F23: N/A | G23: N/A | H23: Corner Board Dimension:1025X50X50mm Can be use Foxlink existing P/N: 0984-000W-00E0 | I23: 護角 | J23: =8/1260 -> 0.0063492063 | K23: 0.32676471 | L23: =K23*J23 -> 0.0020746965 | M23: 0.32676471 | N23: =M23*J23 -> 0.0020746965 | O23: Can be use Foxlink existing P/N: 0984-000W-00E0 | Q23: 0.0063492063 | R23: 2.02 | S23: 1000 | T23: 15 | U23: =R23/$X$1 -> 0.28450704 | V23: =U23*J23 -> 0.0018063939 | W23: =(M23-U23)/U23 -> 0.14852941
A24: 20 | B24: 1 | C24: 0984-001J-00A0 | D24: N/A | E24: Corner Board | F24: N/A | G24: N/A | H24: Corner Board Dimension:,900X50X50mm Can be use Foxlink existing P/N: 0984-000x-00E0 | I24: 護角 | J24: =4/1260 -> 0.0031746032 | K24: 0.28632353 | L24: =K24*J24 -> 0.00090896359 | M24: 0.28632353 | N24: =M24*J24 -> 0.00090896359 | O24: Can be use Foxlink existing P/N: 0984-000x-00E0 | Q24: 0.0031746032 | R24: 1.77 | S24: 1000 | T24: 15 | U24: =R24/$X$1 -> 0.24929577 | V24: =U24*J24 -> 0.00079141516 | W24: =(M24-U24)/U24 -> 0.14852941
A25: 21 | B25: 1 | C25: 0952-000T-00A0 | D25: N/A | E25: SS Logo seal tape | F25: N/A | G25: N/A | H25: Corner Board Dimension:60mm X 100m Color: 2C Print | I25: SS標誌封箱膠帶 | J25: 0.005 | K25: 0 | L25: =K25*J25 -> 0 | M25: 1.8929577 | N25: =M25*J25 -> 0.0094647887 | Q25: 0.005 | R25: 11.2 | S25: 900 | T25: 15 | U25: =R25/$X$1 -> 1.5774648 | V25: =U25*J25 -> 0.0078873239 | W25: =(M25-U25)/U25 -> 0.2 | X25: New
A26: 22 | B26: 1 | C26: 0952-0005-00E0 | D26: N/A | E26: INK RIBBON | F26: N/A | G26: N/A | H26: INK RIBBON,DEPLETION,B110A,110MM,LF | I26: 碳带 | J26: 0.000217 | K26: 0 | L26: =K26*J26 -> 0 | M26: 9.8873239 | N26: =M26*J26 -> 0.0021455493 | Q26: 0.000217 | R26: 58.5 | S26: 10 | T26: 7 | U26: =R26/$X$1 -> 8.2394366 | V26: =U26*J26 -> 0.0017879577 | W26: =(M26-U26)/U26 -> 0.2 | X26: New
A27: 23 | B27: 1 | C27: 0952-0002-00E0 | D27: N/A | E27: INK RIBBON | F27: N/A | G27: N/A | H27: INK RIBBON,DEPLETION,TW10,60MM,LF | I27: 碳带 | J27: 0.000118 | K27: 0 | L27: =K27*J27 -> 0 | M27: 5.3543662 | N27: =M27*J27 -> 0.00063181521 | Q27: 0.000118 | R27: 31.68 | S27: 10 | T27: 7 | U27: =R27/$X$1 -> 4.4619718 | V27: =U27*J27 -> 0.00052651268 | W27: =(M27-U27)/U27 -> 0.2 | X27: New
A28: 24 | B28: 1 | C28: 0952-000C-00E0 | D28: N/A | E28: INK RIBBON | F28: N/A | G28: N/A | H28: INK RIBBON,DEPLETION,TRC32, 40MM,LF | I28: 碳带 | J28: 0.0001 | K28: 0 | L28: =K28*J28 -> 0 | M28: 7.6394366 | N28: =M28*J28 -> 0.00076394366 | Q28: 0.0001 | R28: 45.2 | S28: 50 | T28: 7 | U28: =R28/$X$1 -> 6.3661972 | V28: =U28*J28 -> 0.00063661972 | W28: =(M28-U28)/U28 -> 0.2 | X28: New
A29: 25 | B29: 1 | C29: 0952-000S-00E0 | D29: N/A | E29: Tape | F29: N/A | G29: N/A | H29: OC,DEPLETION,TAPE,SEAL(400m*500mm*0.018cm),RoHS | I29: 打包膜 | J29: 0.00045 | K29: 0 | L29: =K29*J29 -> 0 | M29: 6.1352113 | N29: =M29*J29 -> 0.0027608451 | Q29: 0.00045 | R29: 36.3 | S29: 500 | T29: 10 | U29: =R29/$X$1 -> 5.1126761 | V29: =U29*J29 -> 0.0023007042 | W29: =(M29-U29)/U29 -> 0.2 | X29: New
A30: Subtotal(USD/Unit)： | L30: =SUM(L4:L24) -> 0.67860996 | N30: =SUM(N4:N29) -> 0.70370533 | O30: 022724: ex rate 7.1 ex rate: 6.3 RMB | U30: =R30/$X$1 -> 0 | V30: =SUM(V4:V29) -> 0.4191448 | W30: =(N30-V30)/V30 -> 0.67890748
A31: Subtotal(USD/Unit)： | L31: =L30*6.3/7 -> 0.61074897 | O31: New ex rate 7 | P31: =>update on Oct 27, 2022
M33: Rival 3 vs Rvial 3+ difference | N33: =N30-L30 -> 0.02509537

Sheet ME BOM 0228_draft
A2: Project Name: | C2: Rival 3+ | X2: E + | AC2: ELM5
A3: Prepared By: | C3: Alvin K | I3: 紅字 修改 | L3: ELM5 | N3: E +
A4: Last Updated: | C4: 45350 | E4: Forecast: 418k /year | I4: 藍字 新增 | X4: 45350 | Z4: 45350 | AB4: 45350 | AC4: 43826 | AE4: 43826
D5: V1 | L5: V1 | M5: V1 | N5: 2/28 | O5: 2/28 | P5: 2/28 | Q5: 2/28
A6: Item | B6: Part picture | C6: Part Name | D6: Qty | E6: Part size/mm | F6: Part Weight/g | G6: Material | H6: Density | I6: Finish/2nd Process | J6: CAV | K6: Note | L6: U/P | M6: Sub-total | N6: U/P Black | O6: U/P White | P6: Subtotal | Q6: Subtol | R6: Set | S6: per tool (USD/set) | T6: Jig cost | U6: Total tooling cost | V6: Remark | X6: Unit price | Y6: U/P subtotal | Z6: Tooling True cost | AA6: Jig cost | AB6: True Total tooling cost | AC6: Tooling True cost | AD6: Jig cost | AE6: True Total tooling cost
A7: A>.Plastic part
A8: P1-3 | C8: MIDDLE HOUSING | D8: 1 | F8: 22 | G8: ABS PA758 | H8: 1.06 | I8: <氣輔成型> VDI 27, MATTE ABS: 透明(奇美ABS PA-758) (噴漆雷雕製程) | J8: 2 | K8: 噴漆+雷雕LOGO(雷雕露出LOGO)+面漆 (製程同NK機種 COVER做法) | L8: 1.588 | M8: =L8*D8 -> 1.588 | N8: =X8*1.05 -> 0.3675 | O8: =X8*1.1 -> 0.385 | P8: =N8*D8 -> 0.3675 | Q8: =O8*D8 -> 0.385 | R8: 1 | S8: 23100 | T8: 0 | U8: =(S8+T8)*R8 -> 23100 | V8: 2020/12/14 change to Waterborne paint | X8: 0.35 | Z8: 21000 | AA8: 2500 | AB8: 23500 | AC8: 21000 | AD8: 2500 | AE8: =(AC8+AD8)*R8 -> 23500
A9: P2-1 | C9: TRIGGER BUTTON LEFT | D9: 1 | F9: 2.6 | G9: ABS+PC Sabic C6200 | H9: 1.18 | I9: 噴漆+面漆 (製程同NK機種 COVER做法) | J9: 2+2 | L9: 0.4472 | M9: =L9*D9 -> 0.4472 | N9: =X9*1.05 -> 0.0945 | O9: =X9*1.1 -> 0.099 | P9: =N9*D9 -> 0.0945 | Q9: =O9*D9 -> 0.099 | R9: 1 | S9: 10710 | T9: 2500 | U9: =(S9*R9)+T9 -> 13210 | V9: 2020/12/14 change to Waterborne paint | X9: 0.09 | Z9: 10200 | AA9: 2500 | AB9: 12700 | AC9: 10200 | AD9: 2500 | AE9: =(AC9+AD9)*R9 -> 12700
A10: P3-1 | C10: TRIGGER BUTTON RIGHT | D10: 1 | F10: 2.6 | G10: ABS+PC Sabic C6200 | H10: 1.18 | I10: 噴漆+面漆 (製程同NK機種 COVER做法) | L10: 0.4472 | M10: =L10*D10 -> 0.4472 | N10: =X10*1.05 -> 0.0945 | O10: =X10*1.1 -> 0.099 | P10: =N10*D10 -> 0.0945 | Q10: =O10*D10 -> 0.099 | X10: 0.09
A11: P5 | C11: LIGHTGUIDE_V2 | D11: 1 | F11: 4.4 | G11: PC | H11: =VLOOKUP(G11,$A$34:$B$53,2,FALSE) -> 1.2 | I11: VDI 24,MATTE, MILKY WHITE TRANSPARENT 钛白粉:5.5g/Kg | J11: 2 | K11: OPTION-2 光學評估鋐特,非光學單價如註解 | L11: 0.192885 | M11: =L11*D11 -> 0.192885 | N11: 0.192885 | O11: =0.192885*1.05 -> 0.20252925 | P11: =N11*D11 -> 0.192885 | Q11: =O11*D11 -> 0.20252925 | R11: 1 | S11: 13230 | T11: 0 | U11: =(S11*R11)+T11 -> 13230 | Z11: 12600 | AA11: 0 | AB11: 12600 | AC11: 12600 | AD11: 0 | AE11: =(AC11+AD11)*R11 -> 12600
A12: P5-1 | C12: 光學廠費用 待確認 (美光達 or Liteon) | D12: 0 | F12: 4.4 | G12: PC | H12: =VLOOKUP(G12,$A$34:$B$53,2,FALSE) -> 1.2 | I12: VDI 24,MATTE, MILKY WHITE TRANSPARENT | K12: OPTION-2 | L12: 0.554655 | M12: =L12*D12 -> 0 | N12: 0.554655 | O12: 0.554655 | P12: =N12*D12 -> 0 | Q12: Only Middle Housing & Trigger button texture fee. | R12: 0 | S12: 12117 | T12: 0 | U12: =(S12*R12)+T12 -> 0 | Z12: 11540 | AA12: 0 | AB12: 0 | AC12: 11540 | AD12: 0 | AE12: =(AC12+AD12)*R12 -> 0
A13: P6 | C13: SIDE BUTTON | D13: 1 | F13: 0.6 | G13: ABS | H13: =VLOOKUP(G13,$A$34:$B$53,2,FALSE) -> 1.06 | I13: VDI 24,MATTE,BLACK | J13: 4 | L13: 0.062521 | M13: =L13*D13 -> 0.062521 | N13: 0.062521 | O13: =0.062521*1.05 -> 0.06564705 | P13: =N13*D13 -> 0.062521 | Q13: =O13*D13 -> 0.06564705 | R13: 1 | S13: 9975 | T13: 0 | U13: =(S13*R13)+T13 -> 9975 | Z13: 9500 | AA13: 0 | AB13: 9500 | AC13: 9500 | AD13: 0 | AE13: =(AC13+AD13)*R13 -> 9500
A14: P7 | C14: CPI BUTTON | D14: 1 | F14: 0.2 | G14: ABS | H14: =VLOOKUP(G14,$A$34:$B$53,2,FALSE) -> 1.06 | I14: VDI 24,MATTE,BLACK | J14: 4 | L14: 0.05768 | M14: =L14*D14 -> 0.05768 | N14: 0.05768 | O14: =0.05768*1.05 -> 0.060564 | P14: =N14*D14 -> 0.05768 | Q14: =O14*D14 -> 0.060564 | R14: 1 | S14: 8925 | T14: 0 | U14: =(S14*R14)+T14 -> 8925 | Z14: 8500 | AA14: 0 | AB14: 8500 | AC14: 8500 | AD14: 0 | AE14: =(AC14+AD14)*R14 -> 8500
A15: P8 | C15: WHEEL HUB | D15: 1 | F15: 1.8 | G15: PC | H15: =VLOOKUP(G15,$A$34:$B$53,2,FALSE) -> 1.2 | I15: VDI 21,,BLACK | J15: 4 | L15: 0.089198 | M15: =L15*D15 -> 0.089198 | N15: 0.089198 | O15: =0.089198*1.05 -> 0.0936579 | P15: =N15*D15 -> 0.089198 | Q15: =O15*D15 -> 0.0936579 | R15: 1 | S15: 9450 | T15: 0 | U15: =(S15*R15)+T15 -> 9450 | Z15: 9000 | AA15: 0 | AB15: 9000 | AC15: 9000 | AD15: 0 | AE15: =(AC15+AD15)*R15 -> 9000
A16: P9 | C16: BOTTOM COVER | D16: 1 | F16: 11 | G16: ABS | H16: =VLOOKUP(G16,$A$34:$B$53,2,FALSE) -> 1.06 | I16: VDI 27,MATTE,BLACK | J16: 2 | L16: 0.226394 | M16: =L16*D16 -> 0.226394 | N16: =X16*1.05 -> 0.2625 | O16: =X16*1.1 -> 0.275 | P16: =N16*D16 -> 0.2625 | Q16: =O16*D16 -> 0.275 | R16: 1 | S16: 13650 | T16: 0 | U16: =(S16*R16)+T16 -> 13650 | X16: 0.25 | Z16: 13000 | AA16: 0 | AB16: 13000 | AC16: 13000 | AD16: 0 | AE16: =(AC16+AD16)*R16 -> 13000
A17: P11 | C17: SWITCH CUSHION | D17: 1 | G17: PA66 | H17: =VLOOKUP(G17,$A$34:$B$53,2,FALSE) -> #N/A | J17: 8 | K17: 沿用NK機種, | L17: 0.031522844 | M17: =L17*D17 -> 0.031522844 | N17: 0.031522844 | O17: 0.031522844 | P17: =N17*D17 -> 0.031522844 | Q17: =O17*D17 -> 0.031522844 | R17: 0 | S17: 0 | T17: 0 | U17: =(S17*R17)+T17 -> 0 | Z17: 0 | AA17: 0 | AB17: 0 | AC17: 0 | AD17: 0 | AE17: =(AC17+AD17)*R17 -> 0
A18: P13 | C18: LED CLIP | D18: 1 | F18: 0.2 | G18: LCP | H18: =VLOOKUP(G18,$A$34:$B$53,2,FALSE) -> #N/A | I18: BLACK | J18: 8 | K18: 新開模單價與模具費 | L18: 0.104133 | M18: =L18*D18 -> 0.104133 | N18: 0.104133 | O18: 0.104133 | P18: =N18*D18 -> 0.104133 | Q18: =O18*D18 -> 0.104133 | R18: 1 | S18: 12390 | T18: 0 | U18: =(S18*R18)+T18 -> 12390 | Z18: 11800 | AA18: 0 | AB18: 11800 | AC18: 11800 | AD18: 0 | AE18: =(AC18+AD18)*R18 -> 11800
A19: B> Metal Part
A20: M1 | M20: =L20*D20 -> 0 | U20: =(S20+T20)*D20 -> 0 | X20: 0 | Z20: 0 | AA20: 0 | AC20: 0 | AD20: 0
A21: C>.Rubber parts
A22: R1 | C22: WHEEL GRIP | D22: 1 | G22: Silicon rubber | I22: VDI 24,MATTE,BLACK | L22: 0.06798 | M22: =L22*D22 -> 0.06798 | N22: 0.06798 | O22: =0.06798*1.05 -> 0.071379 | P22: =N22*D22 -> 0.06798 | Q22: =O22*D22 -> 0.071379 | R22: 1 | S22: 5775 | T22: 0 | U22: =(S22*R22)+T22 -> 5775 | Z22: 5500 | AA22: 0 | AB22: 5500 | AC22: 5500 | AD22: 0 | AE22: =(AC22+AD22)*R22 -> 5500
A23: D>.Other parts
A24: O3 | C24: PTFE FEET PAD UP | D24: 2 | G24: PTFE (TEFLON) | I24: BLACK, PTFE 0.5mm+桦宇-3718 0.1mm | L24: 0.0206 | M24: =L24*D24 -> 0.0412 | N24: 0.0206 | O24: =0.0206*1.05 -> 0.02163 | P24: =N24*D24 -> 0.0412 | Q24: =O24*D24 -> 0.04326 | R24: 0 | S24: 0 | T24: 0 | U24: =(S24*R24)+T24 -> 0 | Z24: 0 | AA24: 0 | AB24: 0 | AC24: 0 | AD24: 0 | AE24: =(AC24+AD24)*R24 -> 0
A25: O6 | C25: PTFE FEET PAD DOWN | D25: 1 | G25: PTFE (TEFLON) | I25: BLACK, PTFE 0.5mm+桦宇-3718 0.1mm | L25: 0.103 | M25: =L25*D25 -> 0.103 | N25: 0.103 | O25: =0.103*1.05 -> 0.10815 | P25: =N25*D25 -> 0.103 | Q25: =O25*D25 -> 0.10815 | R25: 0 | S25: 0 | T25: 0 | U25: =(S25*R25)+T25 -> 0 | Z25: 0 | AA25: 0 | AB25: 0 | AC25: 0 | AD25: 0 | AE25: =(AC25+AD25)*R25 -> 0
A26: O7 | C26: SCREW T2x6mm | D26: 4 | G26: A1018 | I26: 自攻,十字槽,鍍鎳,D3.5*頭厚1.3*L6 | K26: 0961-0003-83A0 | L26: 0.00385 | M26: =L26*D26 -> 0.0154 | N26: 0.00385 | O26: 0.00385 | P26: =N26*D26 -> 0.0154 | Q26: =O26*D26 -> 0.0154 | R26: 0 | S26: 0 | T26: 0 | U26: =(S26*R26)+T26 -> 0 | Z26: 0 | AA26: 0 | AB26: 0 | AC26: 0 | AD26: 0 | AE26: =(AC26+AD26)*R26 -> 0
A27: O8 | C27: SCREW P2x4mm | D27: 9 | G27: A1018 | I27: 自攻,十字槽,鍍黑鎳,D3.5*頭厚1.3*L4 | K27: 0961-0004-83A0 | L27: 0.00495 | M27: =L27*D27 -> 0.04455 | N27: 0.00495 | O27: 0.00495 | P27: =N27*D27 -> 0.04455 | Q27: =O27*D27 -> 0.04455 | R27: 0 | S27: 0 | T27: 0 | U27: =(S27*R27)+T27 -> 0 | Z27: 0 | AA27: 0 | AB27: 0 | AC27: 0 | AD27: 0 | AE27: =(AC27+AD27)*R27 -> 0
A28: O9 | C28: Screw P2x4mm | D28: 1 | G28: A1018 | I28: SCREW,MILD STEEL,ZINC WHITE, P2x4mm,CROSS,1018A WHITE,ZN,RoHS,LEFT-HAND THREAD 1 | K28: 0961-0006-81A0 | L28: =L27 -> 0.00495 | M28: =L28*D28 -> 0.00495 | N28: 0.00495 | O28: 0.00495 | P28: =N28*D28 -> 0.00495 | Q28: =O28*D28 -> 0.00495 | R28: 0 | S28: 0 | T28: 0 | U28: =(S28*R28)+T28 -> 0 | AB28: 0 | AE28: =(AC28+AD28)*R28 -> 0
L29: Total Cost | M29: =SUM(M8:M28) -> 3.5238138 | P29: =SUM(P8:P28) -> 1.6340198 | Q29: =SUM(Q8:Q28) -> 1.703743 | U29: =SUM(U8:U27) -> 109705 | Y29: =SUM(Y8:Y28) -> 0 | AB29: =SUM(AB8:AB28) -> 106100 | AE29: =SUM(AE8:AE28) -> 106100
P30: Black | Q30: White
AC32: 21000 | AD32: 6500 | AE32: 27500
A33: 材料 | B33: 密度 | C33: 金屬材料 | D33: 密度 | AC33: 9800 | AD33: 0 | AE33: 9800
A34: ABS | B34: 1.06 | C34: SUS 301 | D34: 7.8 | AC34: 0 | AD34: 0 | AE34: =(AC34*F34)+AD34 -> 0
A35: PC | B35: 1.2 | C35: SUS 304 | D35: 7.8 | AC35: 0 | AD35: 0 | AE35: =(AC35*F35)+AD35 -> 0
A36: ABS+PC | B36: 1.18 | C36: Zinc Alloy | D36: 6.8 | AC36: 0 | AD36: 0 | AE36: 0
A37: ABS+PMMA | B37: 1.19 | C37: Aluminum | D37: 2.7 | AC37: 0 | AD37: 0 | AE37: 0
A38: PMMA | B38: 1.05 | C38: Au | D38: 19.3
A39: PP | B39: 0.9 | C39: Pb | D39: 11.3
A40: HIPS | B40: 1.05 | C40: Ag | D40: 10.5
A41: POM | B41: 1.4 | C41: Cu | D41: 8.9 | AC41: 2800 | AD41: 0 | AE41: =(AC41*F41)+AD41 -> 0
A42: TPE | B42: 1.3 | C42: SPCC | D42: 7.8 | AC42: 0 | AD42: 0 | AE42: =(AC42*F42)+AD42 -> 0
A43: TPU | B43: 1.5 | C43: SECC | D43: 7.8 | AC43: 0 | AD43: 0 | AE43: =(AC43*F43)+AD43 -> 0
A44: PVC | B44: 1.38 | C44: A1018 | D44: 7.8 | AC44: 0 | AD44: 0 | AE44: =(AC44*F44)+AD44 -> 0
A45: PA | B45: 1.15 | C45: SGCC | D45: 7.8 | AC45: 42000 | AD45: 0 | AE45: =(AC45*F45)+(AD45*F45) -> 0
A46: PE | B46: 0.95 | AC46: 42000 | AD46: 0 | AE46: =(AC46*F46)+(AD46*F46) -> 0
A47: PPS | B47: 1.36 | AC47: 21000 | AD47: 0 | AE47: =(AC47*F47)+(AD47*F47) -> 0
A48: TPV | B48: 0.95 | AC48: 10200 | AD48: 0 | AE48: =(AC48*F48)+(AD48*F48) -> 0
A49: PS | B49: 1.05
A50: TPE | B50: 1.05 | AC50: 9720 | AD50: 0 | AE50: =(AC50*F50)+(AD50*F50) -> 0
AC51: 33000 | AD51: 0 | AE51: =(AC51*F51)+(AD51*F51) -> 0
AC52: 9500 | AD52: 0 | AE52: =(AC52*F52)+(AD52*F52) -> 0
AC53: 0 | AD53: 0 | AE53: =(AC53*F53)+(AD53*F53) -> 0
AC54: 0 | AD54: 0 | AE54: =(AC54*F54)+AD54 -> 0
AC55: 0 | AD55: 0 | AE55: =(W55+AC55)*E55 -> 0

Sheet MTE NRE
B1: Supplier: Foxlink
B2: Project: Rival 3 Gen2
F4: EV/DV | H4: PV/MP
C5: Assume box build lines | F5: 1 Line
A6: No. | B6: Item | C6: Share in C/S | D6: LT (WK) | E6: U/P (USD) | F6: Need Qty | G6: Pay (USD) | H6: Need Qty | I6: Pay (USD) | J6: Remarks
G7: =SUM(G8:G22) -> 19700 | I7: =SUM(I8:I22) -> 56524 | J7: =G7+I7 -> 76224
A8: SMT
A9: =ROW()-8 -> 1 | B9: (Main +LED) Board SMT Paste Stencil_Bot | D9: 2 | E9: 500 | F9: 2 | G9: =F9*E9 -> 1000 | H9: 2 | I9: =H9*E9 -> 1000
A10: =ROW()-8 -> 2 | B10: (Main +LED) Board SMT Paste Stencil_Top | D10: 2 | E10: 500 | F10: 2 | G10: =F10*E10 -> 1000 | H10: 2 | I10: =H10*E10 -> 1000
A11: =ROW()-8 -> 3 | B11: (Main +LED) Board SMTPCB Carrier_Bot | D11: 2 | E11: 150 | F11: 20 | G11: =F11*E11 -> 3000 | H11: 70 | I11: =H11*E11 -> 10500
A12: =ROW()-8 -> 4 | B12: (Main +LED) Board SMT PCB Carrier_Top | D12: 2 | E12: 150 | F12: 20 | G12: =F12*E12 -> 3000 | H12: 70 | I12: =H12*E12 -> 10500
